Workbook

Sheet 6月
A2: 科 目 | B2: 本部 | F2: 本社営業本部 | AD2: 東京支店 | AP2: 全社合計 | AT2: 前期実績 | AX2: 前期比較
F3: 営業本部 | J3: 東大阪 | N3: 南港工場 | R3: 南港事務 | V3: 南港合計 | Z3: 本社営業合計 | AD3: 東京営業 | AH3: 東京工場 | AL3: 東京合計
B4: 45838 | D4: 累計 | F4: 45838 | H4: 累計 | J4: 45838 | L4: 累計 | N4: 45838 | P4: 累計 | R4: 45838 | T4: 累計 | V4: 45838 | X4: 累計 | Z4: 45838 | AB4: 累計 | AD4: 45838 | AF4: 累計 | AH4: 45838 | AJ4: 累計 | AL4: 45838 | AN4: 累計 | AP4: 45838 | AR4: 累計 | AT4: 45473 | AV4: 累計 | AX4: 月中比較 | AZ4: 累計比較
B5: 金 額 | C5: 比率 | D5: 金 額 | E5: 比率 | F5: 金 額 | G5: 比率 | H5: 金 額 | I5: 比率 | J5: 金 額 | K5: 比率 | L5: 金 額 | M5: 比率 | N5: 金 額 | O5: 比率 | P5: 金 額 | Q5: 比率 | R5: 金 額 | S5: 比率 | T5: 金 額 | U5: 比率 | V5: 金 額 | W5: 比率 | X5: 金 額 | Y5: 比率 | Z5: 金 額 | AA5: 比率 | AB5: 金 額 | AC5: 比率 | AD5: 金 額 | AE5: 比率 | AF5: 金 額 | AG5: 比率 | AH5: 金 額 | AI5: 比率 | AJ5: 金 額 | AK5: 比率 | AL5: 金 額 | AM5: 比率 | AN5: 金 額 | AO5: 比率 | AP5: 金 額 | AQ5: 比率 | AR5: 金 額 | AS5: 比率 | AT5: 金 額 | AU5: 比率 | AV5: 金 額 | AW5: 比率 | AX5: 金 額 | AY5: 比率 | AZ5: 金 額 | BA5: 比率
A6: 売上高 | C6: =IF(ISERR(B6/$B$11),"",B6/$B$11) | D6: =B6 -> 0 | E6: =IF(ISERR(D6/$D$11),"",D6/$D$11) | F6: =[1]本社営業!$L$5 -> 433671542 | G6: =IF(ISERR(F6/$F$11),"",F6/$F$11) -> 0.81097613 | H6: =F6 -> 433671542 | I6: =IF(ISERR(H6/$H$11),"",H6/$H$11) -> 0.81097613 | J6: =[1]東大阪!$L$5 -> 512935 | K6: =IF(ISERR(J6/$J$11),"",J6/$J$11) -> 0.057776874 | L6: =J6 -> 512935 | M6: =IF(ISERR(L6/$L$11),"",L6/$L$11) -> 0.057776874 | N6: =[1]南港工場!$L$5 -> 3687510 | O6: =IF(ISERR(N6/$N$11),"",N6/$N$11) -> 0.13065865 | P6: =N6 -> 3687510 | Q6: =IF(ISERR(P6/$P$11),"",P6/$P$11) -> 0.13065865 | S6: =IF(ISERR(R6/$R$11),"",R6/$R$11) | T6: =R6 -> 0 | U6: =IF(ISERR(T6/$T$11),"",T6/$T$11) | V6: =N6+R6 -> 3687510 | W6: =IF(ISERR(V6/$V$11),"",V6/$V$11) -> 0.13065865 | X6: =P6+T6 -> 3687510 | Y6: =IF(ISERR(X6/$X$11),"",X6/$X$11) -> 0.13065865 | Z6: =F6+J6+N6+R6 -> 437871987 | AA6: =IF(ISERR(Z6/$Z$11),"",Z6/$Z$11) -> 0.76570743 | AB6: =H6+L6+P6+T6 -> 437871987 | AC6: =IF(ISERR(AB6/$AB$11),"",AB6/$AB$11) -> 0.76570743 | AD6: =[1]東京事務!$L$5 -> 157743585 | AE6: =IF(ISERR(AD6/$AD$11),"",AD6/$AD$11) -> 0.64044995 | AF6: =AD6 -> 157743585 | AG6: =IF(ISERR(AF6/$AF$11),"",AF6/$AF$11) -> 0.64044995 | AH6: =[1]東京工場!$L$5 -> 0 | AI6: =IF(ISERR(AH6/$AH$11),"",AH6/$AH$11) -> 0 | AJ6: =AH6 -> 0 | AK6: =IF(ISERR(AJ6/$AJ$11),"",AJ6/$AJ$11) -> 0 | AL6: =AD6+AH6 -> 157743585 | AM6: =IF(ISERR(AL6/$AL$11),"",AL6/AL$11) -> 0.61591828 | AN6: =AF6+AJ6 -> 157743585 | AO6: =IF(ISERR(AN6/$AN$11),"",AN6/$AN$11) -> 0.61591828 | AP6: =B6+Z6+AL6 -> 595615572 | AQ6: =IF(ISERR(AP6/$AP$11),"",AP6/$AP$11) -> 0.71937368 | AR6: =D6+AB6+AN6 -> 595615572 | AS6: =IF(ISERR(AR6/$AR$11),"",AR6/$AR$11) -> 0.71937368 | AT6: =[1]全社合計!$N$5 -> 655350010 | AU6: =IF(ISERR(AT6/$AT$11),"",AT6/$AT$11) -> 0.67763905 | AV6: =AT6 -> 655350010 | AW6: =IF(ISERR(AV6/$AV$11),"",AV6/$AV$11) -> 0.67763905 | AX6: =AP6-AT6 -> -59734438 | AY6: =IF(ISERROR(AP6/AT6),"",AP6/AT6) -> 0.90885109 | AZ6: =AR6-AV6 -> -59734438 | BA6: =IF(ISERROR(AR6/AV6),"",AR6/AV6) -> 0.90885109
A7: 輸出売上高 | C7: =IF(ISERR(B7/$B$11),"",B7/$B$11) | D7: =B7 -> 0 | E7: =IF(ISERR(D7/$D$11),"",D7/$D$11) | F7: =[1]本社営業!$L$6 -> 34430373 | G7: =IF(ISERR(F7/$F$11),"",F7/$F$11) -> 0.064385619 | H7: =F7 -> 34430373 | I7: =IF(ISERR(H7/$H$11),"",H7/$H$11) -> 0.064385619 | J7: =[1]東大阪!$L$6 -> 0 | K7: =IF(ISERR(J7/$J$11),"",J7/$J$11) -> 0 | L7: =J7 -> 0 | M7: =IF(ISERR(L7/$L$11),"",L7/$L$11) -> 0 | N7: =[1]南港工場!$L$6 -> 0 | O7: =IF(ISERR(N7/$N$11),"",N7/$N$11) -> 0 | P7: =N7 -> 0 | Q7: =IF(ISERR(P7/$P$11),"",P7/$P$11) -> 0 | S7: =IF(ISERR(R7/$R$11),"",R7/$R$11) | T7: =R7 -> 0 | U7: =IF(ISERR(T7/$T$11),"",T7/$T$11) | V7: =N7+R7 -> 0 | W7: =IF(ISERR(V7/$V$11),"",V7/$V$11) -> 0 | X7: =P7+T7 -> 0 | Y7: =IF(ISERR(X7/$X$11),"",X7/$X$11) -> 0 | Z7: =F7+J7+N7+R7 -> 34430373 | AA7: =IF(ISERR(Z7/$Z$11),"",Z7/$Z$11) -> 0.060208447 | AB7: =H7+L7+P7+T7 -> 34430373 | AC7: =IF(ISERR(AB7/$AB$11),"",AB7/$AB$11) -> 0.060208447 | AD7: =[1]東京事務!$L$6 -> 0 | AE7: =IF(ISERR(AD7/$AD$11),"",AD7/$AD$11) -> 0 | AF7: =AD7 -> 0 | AG7: =IF(ISERR(AF7/$AF$11),"",AF7/$AF$11) -> 0 | AH7: =[1]東京工場!$L$6 -> 0 | AI7: =IF(ISERR(AH7/$AH$11),"",AH7/$AH$11) -> 0 | AJ7: =AH7 -> 0 | AK7: =IF(ISERR(AJ7/$AJ$11),"",AJ7/$AJ$11) -> 0 | AL7: =AD7+AH7 -> 0 | AM7: =IF(ISERR(AL7/$AL$11),"",AL7/AL$11) -> 0 | AN7: =AF7+AJ7 -> 0 | AO7: =IF(ISERR(AN7/$AN$11),"",AN7/$AN$11) -> 0 | AP7: =B7+Z7+AL7 -> 34430373 | AQ7: =IF(ISERR(AP7/$AP$11),"",AP7/$AP$11) -> 0.04158438 | AR7: =D7+AB7+AN7 -> 34430373 | AS7: =IF(ISERR(AR7/$AR$11),"",AR7/$AR$11) -> 0.04158438 | AT7: =[1]全社合計!$N$6 -> 80023208 | AU7: =IF(ISERR(AT7/$AT$11),"",AT7/$AT$11) -> 0.082744869 | AV7: =AT7 -> 80023208 | AW7: =IF(ISERR(AV7/$AV$11),"",AV7/$AV$11) -> 0.082744869 | AX7: =AP7-AT7 -> -45592835 | AY7: =IF(ISERROR(AP7/AT7),"",AP7/AT7) -> 0.43025485 | AZ7: =AR7-AV7 -> -45592835 | BA7: =IF(ISERROR(AR7/AV7),"",AR7/AV7) -> 0.43025485
A8: 加工賃収入 | C8: =IF(ISERR(B8/$B$11),"",B8/$B$11) | D8: =B8 -> 0 | E8: =IF(ISERR(D8/$D$11),"",D8/$D$11) | F8: =[1]本社営業!$L$7 -> 2985710 | G8: =IF(ISERR(F8/$F$11),"",F8/$F$11) -> 0.005583349 | H8: =F8 -> 2985710 | I8: =IF(ISERR(H8/$H$11),"",H8/$H$11) -> 0.005583349 | J8: =[1]東大阪!$L$7 -> 0 | K8: =IF(ISERR(J8/$J$11),"",J8/$J$11) -> 0 | L8: =J8 -> 0 | M8: =IF(ISERR(L8/$L$11),"",L8/$L$11) -> 0 | N8: =[1]南港工場!$L$7 -> 14694120 | O8: =IF(ISERR(N8/$N$11),"",N8/$N$11) -> 0.52065321 | P8: =N8 -> 14694120 | Q8: =IF(ISERR(P8/$P$11),"",P8/$P$11) -> 0.52065321 | S8: =IF(ISERR(R8/$R$11),"",R8/$R$11) | T8: =R8 -> 0 | U8: =IF(ISERR(T8/$T$11),"",T8/$T$11) | V8: =N8+R8 -> 14694120 | W8: =IF(ISERR(V8/$V$11),"",V8/$V$11) -> 0.52065321 | X8: =P8+T8 -> 14694120 | Y8: =IF(ISERR(X8/$X$11),"",X8/$X$11) -> 0.52065321 | Z8: =F8+J8+N8+R8 -> 17679830 | AA8: =IF(ISERR(Z8/$Z$11),"",Z8/$Z$11) -> 0.030916746 | AB8: =H8+L8+P8+T8 -> 17679830 | AC8: =IF(ISERR(AB8/$AB$11),"",AB8/$AB$11) -> 0.030916746 | AD8: =[1]東京事務!$L$7 -> 114496 | AE8: =IF(ISERR(AD8/$AD$11),"",AD8/$AD$11) -> 0.00046486174 | AF8: =AD8 -> 114496 | AG8: =IF(ISERR(AF8/$AF$11),"",AF8/$AF$11) -> 0.00046486174 | AH8: =[1]東京工場!$L$7 -> 0 | AI8: =IF(ISERR(AH8/$AH$11),"",AH8/$AH$11) -> 0 | AJ8: =AH8 -> 0 | AK8: =IF(ISERR(AJ8/$AJ$11),"",AJ8/$AJ$11) -> 0 | AL8: =AD8+AH8 -> 114496 | AM8: =IF(ISERR(AL8/$AL$11),"",AL8/AL$11) -> 0.00044705576 | AN8: =AF8+AJ8 -> 114496 | AO8: =IF(ISERR(AN8/$AN$11),"",AN8/$AN$11) -> 0.00044705576 | AP8: =B8+Z8+AL8 -> 17794326 | AQ8: =IF(ISERR(AP8/$AP$11),"",AP8/$AP$11) -> 0.021491664 | AR8: =D8+AB8+AN8 -> 17794326 | AS8: =IF(ISERR(AR8/$AR$11),"",AR8/$AR$11) -> 0.021491664 | AT8: =[1]全社合計!$N$7 -> 14310081 | AU8: =IF(ISERR(AT8/$AT$11),"",AT8/$AT$11) -> 0.01479678 | AV8: =AT8 -> 14310081 | AW8: =IF(ISERR(AV8/$AV$11),"",AV8/$AV$11) -> 0.01479678 | AX8: =AP8-AT8 -> 3484245 | AY8: =IF(ISERROR(AP8/AT8),"",AP8/AT8) -> 1.2434819 | AZ8: =AR8-AV8 -> 3484245 | BA8: =IF(ISERROR(AR8/AV8),"",AR8/AV8) -> 1.2434819
A9: 役務収入 | C9: =IF(ISERR(B9/$B$11),"",B9/$B$11) | D9: =B9 -> 0 | E9: =IF(ISERR(D9/$D$11),"",D9/$D$11) | F9: =[1]本社営業!$L$8 -> 736070 | G9: =IF(ISERR(F9/$F$11),"",F9/$F$11) -> 0.0013764685 | H9: =F9 -> 736070 | I9: =IF(ISERR(H9/$H$11),"",H9/$H$11) -> 0.0013764685 | J9: =[1]東大阪!$L$8 -> 0 | K9: =IF(ISERR(J9/$J$11),"",J9/$J$11) -> 0 | L9: =J9 -> 0 | M9: =IF(ISERR(L9/$L$11),"",L9/$L$11) -> 0 | N9: =[1]南港工場!$L$8 -> 4480912 | O9: =IF(ISERR(N9/$N$11),"",N9/$N$11) -> 0.15877107 | P9: =N9 -> 4480912 | Q9: =IF(ISERR(P9/$P$11),"",P9/$P$11) -> 0.15877107 | S9: =IF(ISERR(R9/$R$11),"",R9/$R$11) | T9: =R9 -> 0 | U9: =IF(ISERR(T9/$T$11),"",T9/$T$11) | V9: =N9+R9 -> 4480912 | W9: =IF(ISERR(V9/$V$11),"",V9/$V$11) -> 0.15877107 | X9: =P9+T9 -> 4480912 | Y9: =IF(ISERR(X9/$X$11),"",X9/$X$11) -> 0.15877107 | Z9: =F9+J9+N9+R9 -> 5216982 | AA9: =IF(ISERR(Z9/$Z$11),"",Z9/$Z$11) -> 0.0091229446 | AB9: =H9+L9+P9+T9 -> 5216982 | AC9: =IF(ISERR(AB9/$AB$11),"",AB9/$AB$11) -> 0.0091229446 | AD9: =[1]東京事務!$L$8 -> 6000 | AE9: =IF(ISERR(AD9/$AD$11),"",AD9/$AD$11) -> 2.4360418e-05 | AF9: =AD9 -> 6000 | AG9: =IF(ISERR(AF9/$AF$11),"",AF9/$AF$11) -> 2.4360418e-05 | AH9: =[1]東京工場!$L$8 -> 0 | AI9: =IF(ISERR(AH9/$AH$11),"",AH9/$AH$11) -> 0 | AJ9: =AH9 -> 0 | AK9: =IF(ISERR(AJ9/$AJ$11),"",AJ9/$AJ$11) -> 0 | AL9: =AD9+AH9 -> 6000 | AM9: =IF(ISERR(AL9/$AL$11),"",AL9/AL$11) -> 2.3427321e-05 | AN9: =AF9+AJ9 -> 6000 | AO9: =IF(ISERR(AN9/$AN$11),"",AN9/$AN$11) -> 2.3427321e-05 | AP9: =B9+Z9+AL9 -> 5222982 | AQ9: =IF(ISERR(AP9/$AP$11),"",AP9/$AP$11) -> 0.0063082229 | AR9: =D9+AB9+AN9 -> 5222982 | AS9: =IF(ISERR(AR9/$AR$11),"",AR9/$AR$11) -> 0.0063082229 | AT9: =[1]全社合計!$N$8 -> 3799887 | AU9: =IF(ISERR(AT9/$AT$11),"",AT9/$AT$11) -> 0.0039291246 | AV9: =AT9 -> 3799887 | AW9: =IF(ISERR(AV9/$AV$11),"",AV9/$AV$11) -> 0.0039291246 | AX9: =AP9-AT9 -> 1423095 | AY9: =IF(ISERROR(AP9/AT9),"",AP9/AT9) -> 1.3745098 | AZ9: =AR9-AV9 -> 1423095 | BA9: =IF(ISERROR(AR9/AV9),"",AR9/AV9) -> 1.3745098
A10: 本支店売上高 | C10: =IF(ISERR(B10/$B$11),"",B10/$B$11) | D10: =B10 -> 0 | E10: =IF(ISERR(D10/$D$11),"",D10/$D$11) | F10: =[1]本社営業!$L$9 -> 62928838 | G10: =IF(ISERR(F10/$F$11),"",F10/$F$11) -> 0.11767843 | H10: =F10 -> 62928838 | I10: =IF(ISERR(H10/$H$11),"",H10/$H$11) -> 0.11767843 | J10: =[1]東大阪!$L$9 -> 8364925 | K10: =IF(ISERR(J10/$J$11),"",J10/$J$11) -> 0.94222313 | L10: =J10 -> 8364925 | M10: =IF(ISERR(L10/$L$11),"",L10/$L$11) -> 0.94222313 | N10: =[1]南港工場!$L$9 -> 5359929 | O10: =IF(ISERR(N10/$N$11),"",N10/$N$11) -> 0.18991707 | P10: =N10 -> 5359929 | Q10: =IF(ISERR(P10/$P$11),"",P10/$P$11) -> 0.18991707 | S10: =IF(ISERR(R10/$R$11),"",R10/$R$11) | T10: =R10 -> 0 | U10: =IF(ISERR(T10/$T$11),"",T10/$T$11) | V10: =N10+R10 -> 5359929 | W10: =IF(ISERR(V10/$V$11),"",V10/$V$11) -> 0.18991707 | X10: =P10+T10 -> 5359929 | Y10: =IF(ISERR(X10/$X$11),"",X10/$X$11) -> 0.18991707 | Z10: =F10+J10+N10+R10 -> 76653692 | AA10: =IF(ISERR(Z10/$Z$11),"",Z10/$Z$11) -> 0.13404443 | AB10: =H10+L10+P10+T10 -> 76653692 | AC10: =IF(ISERR(AB10/$AB$11),"",AB10/$AB$11) -> 0.13404443 | AD10: =[1]東京事務!$L$9 -> 88437110 | AE10: =IF(ISERR(AD10/$AD$11),"",AD10/$AD$11) -> 0.35906083 | AF10: =AD10 -> 88437110 | AG10: =IF(ISERR(AF10/$AF$11),"",AF10/$AF$11) -> 0.35906083 | AH10: =[1]東京工場!$L$9 -> 9810035 | AI10: =IF(ISERR(AH10/$AH$11),"",AH10/$AH$11) -> 1 | AJ10: =AH10 -> 9810035 | AK10: =IF(ISERR(AJ10/$AJ$11),"",AJ10/$AJ$11) -> 1 | AL10: =AD10+AH10 -> 98247145 | AM10: =IF(ISERR(AL10/$AL$11),"",AL10/AL$11) -> 0.38361124 | AN10: =AF10+AJ10 -> 98247145 | AO10: =IF(ISERR(AN10/$AN$11),"",AN10/$AN$11) -> 0.38361124 | AP10: =B10+Z10+AL10 -> 174900837 | AQ10: =IF(ISERR(AP10/$AP$11),"",AP10/$AP$11) -> 0.21124206 | AR10: =D10+AB10+AN10 -> 174900837 | AS10: =IF(ISERR(AR10/$AR$11),"",AR10/$AR$11) -> 0.21124206 | AT10: =[1]全社合計!$N$9 -> 213624607 | AU10: =IF(ISERR(AT10/$AT$11),"",AT10/$AT$11) -> 0.22089017 | AV10: =AT10 -> 213624607 | AW10: =IF(ISERR(AV10/$AV$11),"",AV10/$AV$11) -> 0.22089017 | AX10: =AP10-AT10 -> -38723770 | AY10: =IF(ISERROR(AP10/AT10),"",AP10/AT10) -> 0.81872982 | AZ10: =AR10-AV10 -> -38723770 | BA10: =IF(ISERROR(AR10/AV10),"",AR10/AV10) -> 0.81872982
A11: 【売上高合計】 | B11: =SUM(B6:B10) -> 0 | C11: =IF(ISERR(B11/$B$11),"",B11/$B$11) | D11: =B11 -> 0 | E11: =IF(ISERR(D11/$D$11),"",D11/$D$11) | F11: =SUM(F6:F10) -> 534752533 | G11: =IF(ISERR(F11/$F$11),"",F11/$F$11) -> 1 | H11: =F11 -> 534752533 | I11: =IF(ISERR(H11/$H$11),"",H11/$H$11) -> 1 | J11: =SUM(J6:J10) -> 8877860 | K11: =IF(ISERR(J11/$J$11),"",J11/$J$11) -> 1 | L11: =J11 -> 8877860 | M11: =IF(ISERR(L11/$L$11),"",L11/$L$11) -> 1 | N11: =SUM(N6:N10) -> 28222471 | O11: =IF(ISERR(N11/$N$11),"",N11/$N$11) -> 1 | P11: =N11 -> 28222471 | Q11: =IF(ISERR(P11/$P$11),"",P11/$P$11) -> 1 | R11: =SUM(R6:R10) -> 0 | S11: =IF(ISERR(R11/$R$11),"",R11/$R$11) | T11: =R11 -> 0 | U11: =IF(ISERR(T11/$T$11),"",T11/$T$11) | V11: =N11+R11 -> 28222471 | W11: =IF(ISERR(V11/$V$11),"",V11/$V$11) -> 1 | X11: =P11+T11 -> 28222471 | Y11: =IF(ISERR(X11/$X$11),"",X11/$X$11) -> 1 | Z11: =F11+J11+N11+R11 -> 571852864 | AA11: =IF(ISERR(Z11/$Z$11),"",Z11/$Z$11) -> 1 | AB11: =H11+L11+P11+T11 -> 571852864 | AC11: =IF(ISERR(AB11/$AB$11),"",AB11/$AB$11) -> 1 | AD11: =SUM(AD6:AD10) -> 246301191 | AE11: =IF(ISERR(AD11/$AD$11),"",AD11/$AD$11) -> 1 | AF11: =AD11 -> 246301191 | AG11: =IF(ISERR(AF11/$AF$11),"",AF11/$AF$11) -> 1 | AH11: =SUM(AH6:AH10) -> 9810035 | AI11: =IF(ISERR(AH11/$AH$11),"",AH11/$AH$11) -> 1 | AJ11: =AH11 -> 9810035 | AK11: =IF(ISERR(AJ11/$AJ$11),"",AJ11/$AJ$11) -> 1 | AL11: =AD11+AH11 -> 256111226 | AM11: =IF(ISERR(AL11/$AL$11),"",AL11/AL$11) -> 1 | AN11: =AF11+AJ11 -> 256111226 | AO11: =IF(ISERR(AN11/$AN$11),"",AN11/$AN$11) -> 1 | AP11: =B11+Z11+AL11 -> 827964090 | AQ11: =IF(ISERR(AP11/$AP$11),"",AP11/$AP$11) -> 1 | AR11: =D11+AB11+AN11 -> 827964090 | AS11: =IF(ISERR(AR11/$AR$11),"",AR11/$AR$11) -> 1 | AT11: =SUM(AT6:AT10) -> 967107793 | AU11: =IF(ISERR(AT11/$AT$11),"",AT11/$AT$11) -> 1 | AV11: =SUM(AV6:AV10) -> 967107793 | AW11: =IF(ISERR(AV11/$AV$11),"",AV11/$AV$11) -> 1 | AX11: =AP11-AT11 -> -139143703 | AY11: =IF(ISERROR(AP11/AT11),"",AP11/AT11) -> 0.85612389 | AZ11: =AR11-AV11 -> -139143703 | BA11: =IF(ISERROR(AR11/AV11),"",AR11/AV11) -> 0.85612389
A12: （売上重量） | F12: =[1]本社営業!$L$11 -> 2471715 | H12: =F12 -> 2471715 | J12: =[1]東大阪!$L$11 -> 17050 | L12: =J12 -> 17050 | N12: =[1]南港工場!$L$11 -> 93030 | P12: =N12 -> 93030 | T12: =R12 -> 0 | V12: =N12+R12 -> 93030 | X12: =P12+T12 -> 93030 | Z12: =F12+J12+N12+R12 -> 2581795 | AB12: =H12+L12+P12+T12 -> 2581795 | AD12: =[1]東京事務!$L$11 -> 1004923 | AF12: =AD12 -> 1004923 | AI12: =IF(ISERR(AH12/$AH$11),"",AH12/$AH$11) -> 0 | AJ12: =AH12 -> 0 | AL12: =AD12+AH12 -> 1004923 | AN12: =AF12+AJ12 -> 1004923 | AP12: =B12+Z12+AL12 -> 3586718 | AR12: =D12+AB12+AN12 -> 3586718 | AT12: =[1]全社合計!$N$11 -> 4336706 | AV12: =AT12 -> 4336706 | AX12: =AP12-AT12 -> -749988 | AY12: =IF(ISERROR(AP12/AT12),"",AP12/AT12) -> 0.82706045 | AZ12: =AR12-AV12 -> -749988 | BA12: =IF(ISERROR(AR12/AV12),"",AR12/AV12) -> 0.82706045
A13: （加工重量） | H13: =F13 -> 0 | L13: =J13 -> 0 | N13: =[1]南港工場!$L$12 -> 3976641 | P13: =N13 -> 3976641 | T13: =R13 -> 0 | V13: =N13+R13 -> 3976641 | X13: =P13+T13 -> 3976641 | Z13: =F13+J13+N13+R13 -> 3976641 | AB13: =H13+L13+P13+T13 -> 3976641 | AF13: =AD13 -> 0 | AI13: =IF(ISERR(AH13/$AH$11),"",AH13/$AH$11) -> 0 | AJ13: =AH13 -> 0 | AL13: =AD13+AH13 -> 0 | AN13: =AF13+AJ13 -> 0 | AP13: =B13+Z13+AL13 -> 3976641 | AR13: =D13+AB13+AN13 -> 3976641 | AT13: =[1]全社合計!$N$12 -> 3535788 | AV13: =AT13 -> 3535788 | AX13: =AP13-AT13 -> 440853 | AY13: =IF(ISERROR(AP13/AT13),"",AP13/AT13) -> 1.1246831 | AZ13: =AR13-AV13 -> 440853 | BA13: =IF(ISERROR(AR13/AV13),"",AR13/AV13) -> 1.1246831
A14: 期首商品棚卸高 | C14: =IF(ISERR(B14/$B$11),"",B14/$B$11) | D14: =B14 -> 0 | E14: =IF(ISERR(D14/$D$11),"",D14/$D$11) | F14: =[1]本社営業!$L$14 -> 1205973702 | G14: =IF(ISERR(F14/$F$11),"",F14/$F$11) -> 2.2551996 | H14: =F14 -> 1205973702 | I14: =IF(ISERR(H14/$H$11),"",H14/$H$11) -> 2.2551996 | K14: =IF(ISERR(J14/$J$11),"",J14/$J$11) -> 0 | L14: =J14 -> 0 | M14: =IF(ISERR(L14/$L$11),"",L14/$L$11) -> 0 | O14: =IF(ISERR(N14/$N$11),"",N14/$N$11) -> 0 | P14: =N14 -> 0 | Q14: =IF(ISERR(P14/$P$11),"",P14/$P$11) -> 0 | S14: =IF(ISERR(R14/$R$11),"",R14/$R$11) | T14: =R14 -> 0 | U14: =IF(ISERR(T14/$T$11),"",T14/$T$11) | V14: =N14+R14 -> 0 | W14: =IF(ISERR(V14/$V$11),"",V14/$V$11) -> 0 | X14: =P14+T14 -> 0 | Y14: =IF(ISERR(X14/$X$11),"",X14/$X$11) -> 0 | Z14: =F14+J14+N14+R14 -> 1205973702 | AA14: =IF(ISERR(Z14/$Z$11),"",Z14/$Z$11) -> 2.1088881 | AB14: =H14+L14+P14+T14 -> 1205973702 | AC14: =IF(ISERR(AB14/$AB$11),"",AB14/$AB$11) -> 2.1088881 | AD14: =[1]東京事務!$L$14 -> 804499700 | AE14: =IF(ISERR(AD14/$AD$11),"",AD14/$AD$11) -> 3.2663248 | AF14: =AD14 -> 804499700 | AG14: =IF(ISERR(AF14/$AF$11),"",AF14/$AF$11) -> 3.2663248 | AI14: =IF(ISERR(AH14/$AH$11),"",AH14/$AH$11) -> 0 | AJ14: =AH14 -> 0 | AK14: =IF(ISERR(AJ14/$AJ$11),"",AJ14/$AJ$11) -> 0 | AL14: =AD14+AH14 -> 804499700 | AM14: =IF(ISERR(AL14/$AL$11),"",AL14/AL$11) -> 3.1412122 | AN14: =AF14+AJ14 -> 804499700 | AO14: =IF(ISERR(AN14/$AN$11),"",AN14/$AN$11) -> 3.1412122 | AP14: =B14+Z14+AL14 -> 2010473402 | AQ14: =IF(ISERR(AP14/$AP$11),"",AP14/$AP$11) -> 2.4282133 | AR14: =D14+AB14+AN14 -> 2010473402 | AS14: =IF(ISERR(AR14/$AR$11),"",AR14/$AR$11) -> 2.4282133 | AT14: =[1]全社合計!$N$14 -> 1816376496 | AU14: =IF(ISERR(AT14/$AT$11),"",AT14/$AT$11) -> 1.8781531 | AV14: =AT14 -> 1816376496 | AW14: =IF(ISERR(AV14/$AV$11),"",AV14/$AV$11) -> 1.8781531 | AX14: =AP14-AT14 -> 194096906 | AY14: =IF(ISERROR(AP14/AT14),"",AP14/AT14) -> 1.1068594 | AZ14: =AR14-AV14 -> 194096906 | BA14: =IF(ISERROR(AR14/AV14),"",AR14/AV14) -> 1.1068594
A15: 当期商品仕入高 | C15: =IF(ISERR(B15/$B$11),"",B15/$B$11) | E15: =IF(ISERR(D15/$D$11),"",D15/$D$11) | F15: =[1]本社営業!$L$15 -> 470134699 | G15: =IF(ISERR(F15/$F$11),"",F15/$F$11) -> 0.87916311 | H15: =F15 -> 470134699 | I15: =IF(ISERR(H15/$H$11),"",H15/$H$11) -> 0.87916311 | J15: =[1]東大阪!$L$15 -> 495885 | K15: =IF(ISERR(J15/$J$11),"",J15/$J$11) -> 0.055856366 | L15: =J15 -> 495885 | M15: =IF(ISERR(L15/$L$11),"",L15/$L$11) -> 0.055856366 | N15: =[1]南港工場!$L$15 -> 2141339 | O15: =IF(ISERR(N15/$N$11),"",N15/$N$11) -> 0.075873548 | P15: =N15 -> 2141339 | Q15: =IF(ISERR(P15/$P$11),"",P15/$P$11) -> 0.075873548 | S15: =IF(ISERR(R15/$R$11),"",R15/$R$11) | T15: =R15 -> 0 | U15: =IF(ISERR(T15/$T$11),"",T15/$T$11) | V15: =N15+R15 -> 2141339 | W15: =IF(ISERR(V15/$V$11),"",V15/$V$11) -> 0.075873548 | X15: =P15+T15 -> 2141339 | Y15: =IF(ISERR(X15/$X$11),"",X15/$X$11) -> 0.075873548 | Z15: =F15+J15+N15+R15 -> 472771923 | AA15: =IF(ISERR(Z15/$Z$11),"",Z15/$Z$11) -> 0.826737 | AB15: =H15+L15+P15+T15 -> 472771923 | AC15: =IF(ISERR(AB15/$AB$11),"",AB15/$AB$11) -> 0.826737 | AD15: =[1]東京事務!$L$15 -> 199249578 | AE15: =IF(ISERR(AD15/$AD$11),"",AD15/$AD$11) -> 0.80896717 | AF15: =AD15 -> 199249578 | AG15: =IF(ISERR(AF15/$AF$11),"",AF15/$AF$11) -> 0.80896717 | AH15: =[1]東京工場!$L$15 -> 0 | AI15: =IF(ISERR(AH15/$AH$11),"",AH15/$AH$11) -> 0 | AJ15: =AH15 -> 0 | AK15: =IF(ISERR(AJ15/$AJ$11),"",AJ15/$AJ$11) -> 0 | AL15: =AD15+AH15 -> 199249578 | AM15: =IF(ISERR(AL15/$AL$11),"",AL15/AL$11) -> 0.77798065 | AN15: =AF15+AJ15 -> 199249578 | AO15: =IF(ISERR(AN15/$AN$11),"",AN15/$AN$11) -> 0.77798065 | AP15: =B15+Z15+AL15 -> 672021501 | AQ15: =IF(ISERR(AP15/$AP$11),"",AP15/$AP$11) -> 0.81165537 | AR15: =D15+AB15+AN15 -> 672021501 | AS15: =IF(ISERR(AR15/$AR$11),"",AR15/$AR$11) -> 0.81165537 | AT15: =[1]全社合計!$N$15 -> 867747663 | AU15: =IF(ISERR(AT15/$AT$11),"",AT15/$AT$11) -> 0.89726054 | AV15: =AT15 -> 867747663 | AW15: =IF(ISERR(AV15/$AV$11),"",AV15/$AV$11) -> 0.89726054 | AX15: =AP15-AT15 -> -195726162 | AY15: =IF(ISERROR(AP15/AT15),"",AP15/AT15) -> 0.77444346 | AZ15: =AR15-AV15 -> -195726162 | BA15: =IF(ISERROR(AR15/AV15),"",AR15/AV15) -> 0.77444346
A16: 期末商品棚卸高 | C16: =IF(ISERR(B16/$B$11),"",B16/$B$11) | D16: =B16 -> 0 | E16: =IF(ISERR(D16/$D$11),"",D16/$D$11) | F16: =[1]本社営業!$L$16 -> 1212643896 | G16: =IF(ISERR(F16/$F$11),"",F16/$F$11) -> 2.267673 | H16: =F16 -> 1212643896 | I16: =IF(ISERR(H16/$H$11),"",H16/$H$11) -> 2.267673 | K16: =IF(ISERR(J16/$J$11),"",J16/$J$11) -> 0 | L16: =J16 -> 0 | M16: =IF(ISERR(L16/$L$11),"",L16/$L$11) -> 0 | O16: =IF(ISERR(N16/$N$11),"",N16/$N$11) -> 0 | P16: =N16 -> 0 | Q16: =IF(ISERR(P16/$P$11),"",P16/$P$11) -> 0 | S16: =IF(ISERR(R16/$R$11),"",R16/$R$11) | T16: =R16 -> 0 | U16: =IF(ISERR(T16/$T$11),"",T16/$T$11) | V16: =N16+R16 -> 0 | W16: =IF(ISERR(V16/$V$11),"",V16/$V$11) -> 0 | X16: =P16+T16 -> 0 | Y16: =IF(ISERR(X16/$X$11),"",X16/$X$11) -> 0 | Z16: =F16+J16+N16+R16 -> 1212643896 | AA16: =IF(ISERR(Z16/$Z$11),"",Z16/$Z$11) -> 2.1205523 | AB16: =H16+L16+P16+T16 -> 1212643896 | AC16: =IF(ISERR(AB16/$AB$11),"",AB16/$AB$11) -> 2.1205523 | AD16: =[1]東京事務!$L$16 -> 778809293 | AE16: =IF(ISERR(AD16/$AD$11),"",AD16/$AD$11) -> 3.16202 | AF16: =AD16 -> 778809293 | AG16: =IF(ISERR(AF16/$AF$11),"",AF16/$AF$11) -> 3.16202 | AI16: =IF(ISERR(AH16/$AH$11),"",AH16/$AH$11) -> 0 | AJ16: =AH16 -> 0 | AK16: =IF(ISERR(AJ16/$AJ$11),"",AJ16/$AJ$11) -> 0 | AL16: =AD16+AH16 -> 778809293 | AM16: =IF(ISERR(AL16/$AL$11),"",AL16/AL$11) -> 3.0409026 | AN16: =AF16+AJ16 -> 778809293 | AO16: =IF(ISERR(AN16/$AN$11),"",AN16/$AN$11) -> 3.0409026 | AP16: =B16+Z16+AL16 -> 1991453189 | AQ16: =IF(ISERR(AP16/$AP$11),"",AP16/$AP$11) -> 2.405241 | AR16: =D16+AB16+AN16 -> 1991453189 | AS16: =IF(ISERR(AR16/$AR$11),"",AR16/$AR$11) -> 2.405241 | AT16: =[1]全社合計!$N$16 -> 1864108715 | AU16: =IF(ISERR(AT16/$AT$11),"",AT16/$AT$11) -> 1.9275087 | AV16: =AT16 -> 1864108715 | AW16: =IF(ISERR(AV16/$AV$11),"",AV16/$AV$11) -> 1.9275087 | AX16: =AP16-AT16 -> 127344474 | AY16: =IF(ISERROR(AP16/AT16),"",AP16/AT16) -> 1.0683139 | AZ16: =AR16-AV16 -> 127344474 | BA16: =IF(ISERROR(AR16/AV16),"",AR16/AV16) -> 1.0683139
A17: 《差引売上原価》 | B17: =+B14+B15-B16 -> 0 | C17: =IF(ISERR(B17/$B$11),"",B17/$B$11) | D17: =B17 -> 0 | E17: =IF(ISERR(D17/$D$11),"",D17/$D$11) | F17: =F14+F15-F16 -> 463464505 | G17: =IF(ISERR(F17/$F$11),"",F17/$F$11) -> 0.86668969 | H17: =F17 -> 463464505 | I17: =IF(ISERR(H17/$H$11),"",H17/$H$11) -> 0.86668969 | J17: =J14+J15-J16 -> 495885 | K17: =IF(ISERR(J17/$J$11),"",J17/$J$11) -> 0.055856366 | L17: =J17 -> 495885 | M17: =IF(ISERR(L17/$L$11),"",L17/$L$11) -> 0.055856366 | N17: =N14+N15-N16 -> 2141339 | O17: =IF(ISERR(N17/$N$11),"",N17/$N$11) -> 0.075873548 | P17: =N17 -> 2141339 | Q17: =IF(ISERR(P17/$P$11),"",P17/$P$11) -> 0.075873548 | R17: =R14+R15-R16 -> 0 | S17: =IF(ISERR(R17/$R$11),"",R17/$R$11) | T17: =R17 -> 0 | U17: =IF(ISERR(T17/$T$11),"",T17/$T$11) | V17: =N17+R17 -> 2141339 | W17: =IF(ISERR(V17/$V$11),"",V17/$V$11) -> 0.075873548 | X17: =P17+T17 -> 2141339 | Y17: =IF(ISERR(X17/$X$11),"",X17/$X$11) -> 0.075873548 | Z17: =F17+J17+N17+R17 -> 466101729 | AA17: =IF(ISERR(Z17/$Z$11),"",Z17/$Z$11) -> 0.81507282 | AB17: =H17+L17+P17+T17 -> 466101729 | AC17: =IF(ISERR(AB17/$AB$11),"",AB17/$AB$11) -> 0.81507282 | AD17: =AD14+AD15-AD16 -> 224939985 | AE17: =IF(ISERR(AD17/$AD$11),"",AD17/$AD$11) -> 0.91327201 | AF17: =AD17 -> 224939985 | AG17: =IF(ISERR(AF17/$AF$11),"",AF17/$AF$11) -> 0.91327201 | AH17: =AH14+AH15-AH16 -> 0 | AI17: =IF(ISERR(AH17/$AH$11),"",AH17/$AH$11) -> 0 | AJ17: =AH17 -> 0 | AK17: =IF(ISERR(AJ17/$AJ$11),"",AJ17/$AJ$11) -> 0 | AL17: =AD17+AH17 -> 224939985 | AM17: =IF(ISERR(AL17/$AL$11),"",AL17/AL$11) -> 0.87829022 | AN17: =AF17+AJ17 -> 224939985 | AO17: =IF(ISERR(AN17/$AN$11),"",AN17/$AN$11) -> 0.87829022 | AP17: =B17+Z17+AL17 -> 691041714 | AQ17: =IF(ISERR(AP17/$AP$11),"",AP17/$AP$11) -> 0.83462764 | AR17: =D17+AB17+AN17 -> 691041714 | AS17: =IF(ISERR(AR17/$AR$11),"",AR17/$AR$11) -> 0.83462764 | AT17: =AT14+AT15-AT16 -> 820015444 | AU17: =IF(ISERR(AT17/$AT$11),"",AT17/$AT$11) -> 0.84790491 | AV17: =AT17 -> 820015444 | AW17: =IF(ISERR(AV17/$AV$11),"",AV17/$AV$11) -> 0.84790491 | AX17: =AP17-AT17 -> -128973730 | AY17: =IF(ISERROR(AP17/AT17),"",AP17/AT17) -> 0.84271793 | AZ17: =AR17-AV17 -> -128973730 | BA17: =IF(ISERROR(AR17/AV17),"",AR17/AV17) -> 0.84271793
A18: 【売上総利益】 | B18: =+B11-B17 -> 0 | C18: =IF(ISERR(B18/$B$11),"",B18/$B$11) | D18: =B18 -> 0 | E18: =IF(ISERR(D18/$D$11),"",D18/$D$11) | F18: =F11-F17 -> 71288028 | G18: =IF(ISERR(F18/$F$11),"",F18/$F$11) -> 0.13331031 | H18: =F18 -> 71288028 | I18: =IF(ISERR(H18/$H$11),"",H18/$H$11) -> 0.13331031 | J18: =J11-J17 -> 8381975 | K18: =IF(ISERR(J18/$J$11),"",J18/$J$11) -> 0.94414363 | L18: =J18 -> 8381975 | M18: =IF(ISERR(L18/$L$11),"",L18/$L$11) -> 0.94414363 | N18: =N11-N17 -> 26081132 | O18: =IF(ISERR(N18/$N$11),"",N18/$N$11) -> 0.92412645 | P18: =N18 -> 26081132 | Q18: =IF(ISERR(P18/$P$11),"",P18/$P$11) -> 0.92412645 | R18: =R11-R17 -> 0 | S18: =IF(ISERR(R18/$R$11),"",R18/$R$11) | T18: =R18 -> 0 | U18: =IF(ISERR(T18/$T$11),"",T18/$T$11) | V18: =N18+R18 -> 26081132 | W18: =IF(ISERR(V18/$V$11),"",V18/$V$11) -> 0.92412645 | X18: =P18+T18 -> 26081132 | Y18: =IF(ISERR(X18/$X$11),"",X18/$X$11) -> 0.92412645 | Z18: =F18+J18+N18+R18 -> 105751135 | AA18: =IF(ISERR(Z18/$Z$11),"",Z18/$Z$11) -> 0.18492718 | AB18: =H18+L18+P18+T18 -> 105751135 | AC18: =IF(ISERR(AB18/$AB$11),"",AB18/$AB$11) -> 0.18492718 | AD18: =AD11-AD17 -> 21361206 | AE18: =IF(ISERR(AD18/$AD$11),"",AD18/$AD$11) -> 0.086727985 | AF18: =AD18 -> 21361206 | AG18: =IF(ISERR(AF18/$AF$11),"",AF18/$AF$11) -> 0.086727985 | AH18: =AH11-AH17 -> 9810035 | AI18: =IF(ISERR(AH18/$AH$11),"",AH18/$AH$11) -> 1 | AJ18: =AH18 -> 9810035 | AK18: =IF(ISERR(AJ18/$AJ$11),"",AJ18/$AJ$11) -> 1 | AL18: =AD18+AH18 -> 31171241 | AM18: =IF(ISERR(AL18/$AL$11),"",AL18/AL$11) -> 0.12170978 | AN18: =AF18+AJ18 -> 31171241 | AO18: =IF(ISERR(AN18/$AN$11),"",AN18/$AN$11) -> 0.12170978 | AP18: =B18+Z18+AL18 -> 136922376 | AQ18: =IF(ISERR(AP18/$AP$11),"",AP18/$AP$11) -> 0.16537236 | AR18: =D18+AB18+AN18 -> 136922376 | AS18: =IF(ISERR(AR18/$AR$11),"",AR18/$AR$11) -> 0.16537236 | AT18: =AT11-AT17 -> 147092349 | AU18: =IF(ISERR(AT18/$AT$11),"",AT18/$AT$11) -> 0.15209509 | AV18: =AT18 -> 147092349 | AW18: =IF(ISERR(AV18/$AV$11),"",AV18/$AV$11) -> 0.15209509 | AX18: =AP18-AT18 -> -10169973 | AY18: =IF(ISERROR(AP18/AT18),"",AP18/AT18) -> 0.93085995 | AZ18: =AR18-AV18 -> -10169973 | BA18: =IF(ISERROR(AR18/AV18),"",AR18/AV18) -> 0.93085995
A19: 給料 | B19: =[1]本部!$L$19 -> 5756800 | C19: =IF(ISERR(B19/$B$11),"",B19/$B$11) | D19: =B19 -> 5756800 | E19: =IF(ISERR(D19/$D$11),"",D19/$D$11) | F19: =[1]本社営業!$L$19 -> 10130507 | G19: =IF(ISERR(F19/$F$11),"",F19/$F$11) -> 0.01894429 | H19: =F19 -> 10130507 | I19: =IF(ISERR(H19/$H$11),"",H19/$H$11) -> 0.01894429 | J19: =[1]東大阪!$L$19 -> 3780080 | K19: =IF(ISERR(J19/$J$11),"",J19/$J$11) -> 0.4257873 | L19: =J19 -> 3780080 | M19: =IF(ISERR(L19/$L$11),"",L19/$L$11) -> 0.4257873 | N19: =[1]南港工場!$L$19 -> 6988011 | O19: =IF(ISERR(N19/$N$11),"",N19/$N$11) -> 0.24760451 | P19: =N19 -> 6988011 | Q19: =IF(ISERR(P19/$P$11),"",P19/$P$11) -> 0.24760451 | R19: =[1]南港事務!$L$19 -> 2788493 | S19: =IF(ISERR(R19/$R$11),"",R19/$R$11) | T19: =R19 -> 2788493 | U19: =IF(ISERR(T19/$T$11),"",T19/$T$11) | V19: =N19+R19 -> 9776504 | W19: =IF(ISERR(V19/$V$11),"",V19/$V$11) -> 0.34640851 | X19: =P19+T19 -> 9776504 | Y19: =IF(ISERR(X19/$X$11),"",X19/$X$11) -> 0.34640851 | Z19: =F19+J19+N19+R19 -> 23687091 | AA19: =IF(ISERR(Z19/$Z$11),"",Z19/$Z$11) -> 0.041421653 | AB19: =H19+L19+P19+T19 -> 23687091 | AC19: =IF(ISERR(AB19/$AB$11),"",AB19/$AB$11) -> 0.041421653 | AD19: =[1]東京事務!$L$19 -> 4513900 | AE19: =IF(ISERR(AD19/$AD$11),"",AD19/$AD$11) -> 0.018326749 | AF19: =AD19 -> 4513900 | AG19: =IF(ISERR(AF19/$AF$11),"",AF19/$AF$11) -> 0.018326749 | AH19: =[1]東京工場!$L$19 -> 4592338 | AI19: =IF(ISERR(AH19/$AH$11),"",AH19/$AH$11) -> 0.46812657 | AJ19: =AH19 -> 4592338 | AK19: =IF(ISERR(AJ19/$AJ$11),"",AJ19/$AJ$11) -> 0.46812657 | AL19: =AD19+AH19 -> 9106238 | AM19: =IF(ISERR(AL19/$AL$11),"",AL19/AL$11) -> 0.035555794 | AN19: =AF19+AJ19 -> 9106238 | AO19: =IF(ISERR(AN19/$AN$11),"",AN19/$AN$11) -> 0.035555794 | AP19: =B19+Z19+AL19 -> 38550129 | AQ19: =IF(ISERR(AP19/$AP$11),"",AP19/$AP$11) -> 0.046560146 | AR19: =D19+AB19+AN19 -> 38550129 | AS19: =IF(ISERR(AR19/$AR$11),"",AR19/$AR$11) -> 0.046560146 | AT19: =[1]全社合計!$N$19 -> 36878679 | AU19: =IF(ISERR(AT19/$AT$11),"",AT19/$AT$11) -> 0.038132956 | AV19: =AT19 -> 36878679 | AW19: =IF(ISERR(AV19/$AV$11),"",AV19/$AV$11) -> 0.038132956 | AX19: =AP19-AT19 -> 1671450 | AY19: =IF(ISERROR(AP19/AT19),"",AP19/AT19) -> 1.0453229 | AZ19: =AR19-AV19 -> 1671450 | BA19: =IF(ISERROR(AR19/AV19),"",AR19/AV19) -> 1.0453229
A20: 退職年金保険 | B20: =[1]本部!$L$20 -> 56110 | C20: =IF(ISERR(B20/$B$11),"",B20/$B$11) | D20: =B20 -> 56110 | E20: =IF(ISERR(D20/$D$11),"",D20/$D$11) | F20: =[1]本社営業!$L$20 -> 264862 | G20: =IF(ISERR(F20/$F$11),"",F20/$F$11) -> 0.00049529826 | H20: =F20 -> 264862 | I20: =IF(ISERR(H20/$H$11),"",H20/$H$11) -> 0.00049529826 | J20: =[1]東大阪!$L$20 -> 163642 | K20: =IF(ISERR(J20/$J$11),"",J20/$J$11) -> 0.018432595 | L20: =J20 -> 163642 | M20: =IF(ISERR(L20/$L$11),"",L20/$L$11) -> 0.018432595 | N20: =[1]南港工場!$L$20 -> 241330 | O20: =IF(ISERR(N20/$N$11),"",N20/$N$11) -> 0.0085509876 | P20: =N20 -> 241330 | Q20: =IF(ISERR(P20/$P$11),"",P20/$P$11) -> 0.0085509876 | R20: =[1]南港事務!$L$20 -> 88532 | S20: =IF(ISERR(R20/$R$11),"",R20/$R$11) | T20: =R20 -> 88532 | U20: =IF(ISERR(T20/$T$11),"",T20/$T$11) | V20: =N20+R20 -> 329862 | W20: =IF(ISERR(V20/$V$11),"",V20/$V$11) -> 0.011687921 | X20: =P20+T20 -> 329862 | Y20: =IF(ISERR(X20/$X$11),"",X20/$X$11) -> 0.011687921 | Z20: =F20+J20+N20+R20 -> 758366 | AA20: =IF(ISERR(Z20/$Z$11),"",Z20/$Z$11) -> 0.0013261558 | AB20: =H20+L20+P20+T20 -> 758366 | AC20: =IF(ISERR(AB20/$AB$11),"",AB20/$AB$11) -> 0.0013261558 | AD20: =[1]東京事務!$L$20 -> 124954 | AE20: =IF(ISERR(AD20/$AD$11),"",AD20/$AD$11) -> 0.00050732195 | AF20: =AD20 -> 124954 | AG20: =IF(ISERR(AF20/$AF$11),"",AF20/$AF$11) -> 0.00050732195 | AH20: =[1]東京工場!$L$20 -> 111642 | AI20: =IF(ISERR(AH20/$AH$11),"",AH20/$AH$11) -> 0.011380388 | AJ20: =AH20 -> 111642 | AK20: =IF(ISERR(AJ20/$AJ$11),"",AJ20/$AJ$11) -> 0.011380388 | AL20: =AD20+AH20 -> 236596 | AM20: =IF(ISERR(AL20/$AL$11),"",AL20/AL$11) -> 0.00092380175 | AN20: =AF20+AJ20 -> 236596 | AO20: =IF(ISERR(AN20/$AN$11),"",AN20/$AN$11) -> 0.00092380175 | AP20: =B20+Z20+AL20 -> 1051072 | AQ20: =IF(ISERR(AP20/$AP$11),"",AP20/$AP$11) -> 0.0012694657 | AR20: =D20+AB20+AN20 -> 1051072 | AS20: =IF(ISERR(AR20/$AR$11),"",AR20/$AR$11) -> 0.0012694657 | AT20: =[1]全社合計!$N$20 -> 1081228 | AU20: =IF(ISERR(AT20/$AT$11),"",AT20/$AT$11) -> 0.0011180015 | AV20: =AT20 -> 1081228 | AW20: =IF(ISERR(AV20/$AV$11),"",AV20/$AV$11) -> 0.0011180015 | AX20: =AP20-AT20 -> -30156 | AY20: =IF(ISERROR(AP20/AT20),"",AP20/AT20) -> 0.97210949 | AZ20: =AR20-AV20 -> -30156 | BA20: =IF(ISERROR(AR20/AV20),"",AR20/AV20) -> 0.97210949
A21: 退職金 | B21: =[1]本部!$L$21 -> 0 | C21: =IF(ISERR(B21/$B$11),"",B21/$B$11) | D21: =B21 -> 0 | E21: =IF(ISERR(D21/$D$11),"",D21/$D$11) | F21: =[1]本社営業!$L$21 -> 0 | G21: =IF(ISERR(F21/$F$11),"",F21/$F$11) -> 0 | H21: =F21 -> 0 | I21: =IF(ISERR(H21/$H$11),"",H21/$H$11) -> 0 | J21: =[1]東大阪!$L$21 -> 0 | K21: =IF(ISERR(J21/$J$11),"",J21/$J$11) -> 0 | L21: =J21 -> 0 | M21: =IF(ISERR(L21/$L$11),"",L21/$L$11) -> 0 | N21: =[1]南港工場!$L$21 -> 0 | O21: =IF(ISERR(N21/$N$11),"",N21/$N$11) -> 0 | P21: =N21 -> 0 | Q21: =IF(ISERR(P21/$P$11),"",P21/$P$11) -> 0 | R21: =[1]南港事務!$L$21 -> 0 | S21: =IF(ISERR(R21/$R$11),"",R21/$R$11) | T21: =R21 -> 0 | U21: =IF(ISERR(T21/$T$11),"",T21/$T$11) | V21: =N21+R21 -> 0 | W21: =IF(ISERR(V21/$V$11),"",V21/$V$11) -> 0 | X21: =P21+T21 -> 0 | Y21: =IF(ISERR(X21/$X$11),"",X21/$X$11) -> 0 | Z21: =F21+J21+N21+R21 -> 0 | AA21: =IF(ISERR(Z21/$Z$11),"",Z21/$Z$11) -> 0 | AB21: =H21+L21+P21+T21 -> 0 | AC21: =IF(ISERR(AB21/$AB$11),"",AB21/$AB$11) -> 0 | AD21: =[1]東京事務!$L$21 -> 0 | AE21: =IF(ISERR(AD21/$AD$11),"",AD21/$AD$11) -> 0 | AF21: =AD21 -> 0 | AG21: =IF(ISERR(AF21/$AF$11),"",AF21/$AF$11) -> 0 | AH21: =[1]東京工場!$L$21 -> 0 | AI21: =IF(ISERR(AH21/$AH$11),"",AH21/$AH$11) -> 0 | AJ21: =AH21 -> 0 | AK21: =IF(ISERR(AJ21/$AJ$11),"",AJ21/$AJ$11) -> 0 | AL21: =AD21+AH21 -> 0 | AM21: =IF(ISERR(AL21/$AL$11),"",AL21/AL$11) -> 0 | AN21: =AF21+AJ21 -> 0 | AO21: =IF(ISERR(AN21/$AN$11),"",AN21/$AN$11) -> 0 | AP21: =B21+Z21+AL21 -> 0 | AQ21: =IF(ISERR(AP21/$AP$11),"",AP21/$AP$11) -> 0 | AR21: =D21+AB21+AN21 -> 0 | AS21: =IF(ISERR(AR21/$AR$11),"",AR21/$AR$11) -> 0 | AT21: =[1]全社合計!$N$21 -> 0 | AU21: =IF(ISERR(AT21/$AT$11),"",AT21/$AT$11) -> 0 | AV21: =AT21 -> 0 | AW21: =IF(ISERR(AV21/$AV$11),"",AV21/$AV$11) -> 0 | AX21: =AP21-AT21 -> 0 | AY21: =IF(ISERROR(AP21/AT21),"",AP21/AT21) | AZ21: =AR21-AV21 -> 0 | BA21: =IF(ISERROR(AR21/AV21),"",AR21/AV21)
A22: 法定福利費 | B22: =[1]本部!$L$22 -> 0 | C22: =IF(ISERR(B22/$B$11),"",B22/$B$11) | D22: =B22 -> 0 | E22: =IF(ISERR(D22/$D$11),"",D22/$D$11) | F22: =[1]本社営業!$L$22 -> 0 | G22: =IF(ISERR(F22/$F$11),"",F22/$F$11) -> 0 | H22: =F22 -> 0 | I22: =IF(ISERR(H22/$H$11),"",H22/$H$11) -> 0 | J22: =[1]東大阪!$L$22 -> 0 | K22: =IF(ISERR(J22/$J$11),"",J22/$J$11) -> 0 | L22: =J22 -> 0 | M22: =IF(ISERR(L22/$L$11),"",L22/$L$11) -> 0 | N22: =[1]南港工場!$L$22 -> 0 | O22: =IF(ISERR(N22/$N$11),"",N22/$N$11) -> 0 | P22: =N22 -> 0 | Q22: =IF(ISERR(P22/$P$11),"",P22/$P$11) -> 0 | R22: =[1]南港事務!$L$22 -> 0 | S22: =IF(ISERR(R22/$R$11),"",R22/$R$11) | T22: =R22 -> 0 | U22: =IF(ISERR(T22/$T$11),"",T22/$T$11) | V22: =N22+R22 -> 0 | W22: =IF(ISERR(V22/$V$11),"",V22/$V$11) -> 0 | X22: =P22+T22 -> 0 | Y22: =IF(ISERR(X22/$X$11),"",X22/$X$11) -> 0 | Z22: =F22+J22+N22+R22 -> 0 | AA22: =IF(ISERR(Z22/$Z$11),"",Z22/$Z$11) -> 0 | AB22: =H22+L22+P22+T22 -> 0 | AC22: =IF(ISERR(AB22/$AB$11),"",AB22/$AB$11) -> 0 | AD22: =[1]東京事務!$L$22 -> 0 | AE22: =IF(ISERR(AD22/$AD$11),"",AD22/$AD$11) -> 0 | AF22: =AD22 -> 0 | AG22: =IF(ISERR(AF22/$AF$11),"",AF22/$AF$11) -> 0 | AH22: =[1]東京工場!$L$22 -> 0 | AI22: =IF(ISERR(AH22/$AH$11),"",AH22/$AH$11) -> 0 | AJ22: =AH22 -> 0 | AK22: =IF(ISERR(AJ22/$AJ$11),"",AJ22/$AJ$11) -> 0 | AL22: =AD22+AH22 -> 0 | AM22: =IF(ISERR(AL22/$AL$11),"",AL22/AL$11) -> 0 | AN22: =AF22+AJ22 -> 0 | AO22: =IF(ISERR(AN22/$AN$11),"",AN22/$AN$11) -> 0 | AP22: =B22+Z22+AL22 -> 0 | AQ22: =IF(ISERR(AP22/$AP$11),"",AP22/$AP$11) -> 0 | AR22: =D22+AB22+AN22 -> 0 | AS22: =IF(ISERR(AR22/$AR$11),"",AR22/$AR$11) -> 0 | AT22: =[1]全社合計!$N$22 -> 0 | AU22: =IF(ISERR(AT22/$AT$11),"",AT22/$AT$11) -> 0 | AV22: =AT22 -> 0 | AW22: =IF(ISERR(AV22/$AV$11),"",AV22/$AV$11) -> 0 | AX22: =AP22-AT22 -> 0 | AY22: =IF(ISERROR(AP22/AT22),"",AP22/AT22) | AZ22: =AR22-AV22 -> 0 | BA22: =IF(ISERROR(AR22/AV22),"",AR22/AV22)
A23: 厚生費 | B23: =[1]本部!$L$23 -> 535788 | C23: =IF(ISERR(B23/$B$11),"",B23/$B$11) | D23: =B23 -> 535788 | E23: =IF(ISERR(D23/$D$11),"",D23/$D$11) | F23: =[1]本社営業!$L$23 -> 101166 | G23: =IF(ISERR(F23/$F$11),"",F23/$F$11) -> 0.00018918283 | H23: =F23 -> 101166 | I23: =IF(ISERR(H23/$H$11),"",H23/$H$11) -> 0.00018918283 | J23: =[1]東大阪!$L$23 -> 63391 | K23: =IF(ISERR(J23/$J$11),"",J23/$J$11) -> 0.0071403469 | L23: =J23 -> 63391 | M23: =IF(ISERR(L23/$L$11),"",L23/$L$11) -> 0.0071403469 | N23: =[1]南港工場!$L$23 -> 73890 | O23: =IF(ISERR(N23/$N$11),"",N23/$N$11) -> 0.0026181265 | P23: =N23 -> 73890 | Q23: =IF(ISERR(P23/$P$11),"",P23/$P$11) -> 0.0026181265 | R23: =[1]南港事務!$L$23 -> 52641 | S23: =IF(ISERR(R23/$R$11),"",R23/$R$11) | T23: =R23 -> 52641 | U23: =IF(ISERR(T23/$T$11),"",T23/$T$11) | V23: =N23+R23 -> 126531 | W23: =IF(ISERR(V23/$V$11),"",V23/$V$11) -> 0.0044833424 | X23: =P23+T23 -> 126531 | Y23: =IF(ISERR(X23/$X$11),"",X23/$X$11) -> 0.0044833424 | Z23: =F23+J23+N23+R23 -> 291088 | AA23: =IF(ISERR(Z23/$Z$11),"",Z23/$Z$11) -> 0.00050902604 | AB23: =H23+L23+P23+T23 -> 291088 | AC23: =IF(ISERR(AB23/$AB$11),"",AB23/$AB$11) -> 0.00050902604 | AD23: =[1]東京事務!$L$23 -> 54263 | AE23: =IF(ISERR(AD23/$AD$11),"",AD23/$AD$11) -> 0.00022031156 | AF23: =AD23 -> 54263 | AG23: =IF(ISERR(AF23/$AF$11),"",AF23/$AF$11) -> 0.00022031156 | AH23: =[1]東京工場!$L$23 -> 53739 | AI23: =IF(ISERR(AH23/$AH$11),"",AH23/$AH$11) -> 0.0054779621 | AJ23: =AH23 -> 53739 | AK23: =IF(ISERR(AJ23/$AJ$11),"",AJ23/$AJ$11) -> 0.0054779621 | AL23: =AD23+AH23 -> 108002 | AM23: =IF(ISERR(AL23/$AL$11),"",AL23/AL$11) -> 0.00042169959 | AN23: =AF23+AJ23 -> 108002 | AO23: =IF(ISERR(AN23/$AN$11),"",AN23/$AN$11) -> 0.00042169959 | AP23: =B23+Z23+AL23 -> 934878 | AQ23: =IF(ISERR(AP23/$AP$11),"",AP23/$AP$11) -> 0.0011291287 | AR23: =D23+AB23+AN23 -> 934878 | AS23: =IF(ISERR(AR23/$AR$11),"",AR23/$AR$11) -> 0.0011291287 | AT23: =[1]全社合計!$N$23 -> 899087 | AU23: =IF(ISERR(AT23/$AT$11),"",AT23/$AT$11) -> 0.00092966576 | AV23: =AT23 -> 899087 | AW23: =IF(ISERR(AV23/$AV$11),"",AV23/$AV$11) -> 0.00092966576 | AX23: =AP23-AT23 -> 35791 | AY23: =IF(ISERROR(AP23/AT23),"",AP23/AT23) -> 1.0398082 | AZ23: =AR23-AV23 -> 35791 | BA23: =IF(ISERROR(AR23/AV23),"",AR23/AV23) -> 1.0398082
A24: 賃借料 | B24: =[1]本部!$L$24 -> 45000 | C24: =IF(ISERR(B24/$B$11),"",B24/$B$11) | D24: =B24 -> 45000 | E24: =IF(ISERR(D24/$D$11),"",D24/$D$11) | F24: =[1]本社営業!$L$24 -> 853650 | G24: =IF(ISERR(F24/$F$11),"",F24/$F$11) -> 0.0015963459 | H24: =F24 -> 853650 | I24: =IF(ISERR(H24/$H$11),"",H24/$H$11) -> 0.0015963459 | J24: =[1]東大阪!$L$24 -> 96410 | K24: =IF(ISERR(J24/$J$11),"",J24/$J$11) -> 0.010859599 | L24: =J24 -> 96410 | M24: =IF(ISERR(L24/$L$11),"",L24/$L$11) -> 0.010859599 | N24: =[1]南港工場!$L$24 -> 28600 | O24: =IF(ISERR(N24/$N$11),"",N24/$N$11) -> 0.0010133769 | P24: =N24 -> 28600 | Q24: =IF(ISERR(P24/$P$11),"",P24/$P$11) -> 0.0010133769 | R24: =[1]南港事務!$L$24 -> 0 | S24: =IF(ISERR(R24/$R$11),"",R24/$R$11) | T24: =R24 -> 0 | U24: =IF(ISERR(T24/$T$11),"",T24/$T$11) | V24: =N24+R24 -> 28600 | W24: =IF(ISERR(V24/$V$11),"",V24/$V$11) -> 0.0010133769 | X24: =P24+T24 -> 28600 | Y24: =IF(ISERR(X24/$X$11),"",X24/$X$11) -> 0.0010133769 | Z24: =F24+J24+N24+R24 -> 978660 | AA24: =IF(ISERR(Z24/$Z$11),"",Z24/$Z$11) -> 0.0017113843 | AB24: =H24+L24+P24+T24 -> 978660 | AC24: =IF(ISERR(AB24/$AB$11),"",AB24/$AB$11) -> 0.0017113843 | AD24: =[1]東京事務!$L$24 -> 143500 | AE24: =IF(ISERR(AD24/$AD$11),"",AD24/$AD$11) -> 0.00058262 | AF24: =AD24 -> 143500 | AG24: =IF(ISERR(AF24/$AF$11),"",AF24/$AF$11) -> 0.00058262 | AH24: =[1]東京工場!$L$24 -> 0 | AI24: =IF(ISERR(AH24/$AH$11),"",AH24/$AH$11) -> 0 | AJ24: =AH24 -> 0 | AK24: =IF(ISERR(AJ24/$AJ$11),"",AJ24/$AJ$11) -> 0 | AL24: =AD24+AH24 -> 143500 | AM24: =IF(ISERR(AL24/$AL$11),"",AL24/AL$11) -> 0.00056030344 | AN24: =AF24+AJ24 -> 143500 | AO24: =IF(ISERR(AN24/$AN$11),"",AN24/$AN$11) -> 0.00056030344 | AP24: =B24+Z24+AL24 -> 1167160 | AQ24: =IF(ISERR(AP24/$AP$11),"",AP24/$AP$11) -> 0.0014096747 | AR24: =D24+AB24+AN24 -> 1167160 | AS24: =IF(ISERR(AR24/$AR$11),"",AR24/$AR$11) -> 0.0014096747 | AT24: =[1]全社合計!$N$24 -> 1127978 | AU24: =IF(ISERR(AT24/$AT$11),"",AT24/$AT$11) -> 0.0011663415 | AV24: =AT24 -> 1127978 | AW24: =IF(ISERR(AV24/$AV$11),"",AV24/$AV$11) -> 0.0011663415 | AX24: =AP24-AT24 -> 39182 | AY24: =IF(ISERROR(AP24/AT24),"",AP24/AT24) -> 1.0347365 | AZ24: =AR24-AV24 -> 39182 | BA24: =IF(ISERROR(AR24/AV24),"",AR24/AV24) -> 1.0347365
A25: リース料 | B25: =[1]本部!$L$25 -> 129379 | C25: =IF(ISERR(B25/$B$11),"",B25/$B$11) | D25: =B25 -> 129379 | E25: =IF(ISERR(D25/$D$11),"",D25/$D$11) | F25: =[1]本社営業!$L$25 -> 86370 | G25: =IF(ISERR(F25/$F$11),"",F25/$F$11) -> 0.00016151396 | H25: =F25 -> 86370 | I25: =IF(ISERR(H25/$H$11),"",H25/$H$11) -> 0.00016151396 | J25: =[1]東大阪!$L$25 -> 10180 | K25: =IF(ISERR(J25/$J$11),"",J25/$J$11) -> 0.0011466727 | L25: =J25 -> 10180 | M25: =IF(ISERR(L25/$L$11),"",L25/$L$11) -> 0.0011466727 | N25: =[1]南港工場!$L$25 -> 0 | O25: =IF(ISERR(N25/$N$11),"",N25/$N$11) -> 0 | P25: =N25 -> 0 | Q25: =IF(ISERR(P25/$P$11),"",P25/$P$11) -> 0 | R25: =[1]南港事務!$L$25 -> 10180 | S25: =IF(ISERR(R25/$R$11),"",R25/$R$11) | T25: =R25 -> 10180 | U25: =IF(ISERR(T25/$T$11),"",T25/$T$11) | V25: =N25+R25 -> 10180 | W25: =IF(ISERR(V25/$V$11),"",V25/$V$11) -> 0.00036070548 | X25: =P25+T25 -> 10180 | Y25: =IF(ISERR(X25/$X$11),"",X25/$X$11) -> 0.00036070548 | Z25: =F25+J25+N25+R25 -> 106730 | AA25: =IF(ISERR(Z25/$Z$11),"",Z25/$Z$11) -> 0.00018663892 | AB25: =H25+L25+P25+T25 -> 106730 | AC25: =IF(ISERR(AB25/$AB$11),"",AB25/$AB$11) -> 0.00018663892 | AD25: =[1]東京事務!$L$25 -> 18542 | AE25: =IF(ISERR(AD25/$AD$11),"",AD25/$AD$11) -> 7.5281812e-05 | AF25: =AD25 -> 18542 | AG25: =IF(ISERR(AF25/$AF$11),"",AF25/$AF$11) -> 7.5281812e-05 | AH25: =[1]東京工場!$L$25 -> 8300 | AI25: =IF(ISERR(AH25/$AH$11),"",AH25/$AH$11) -> 0.00084607241 | AJ25: =AH25 -> 8300 | AK25: =IF(ISERR(AJ25/$AJ$11),"",AJ25/$AJ$11) -> 0.00084607241 | AL25: =AD25+AH25 -> 26842 | AM25: =IF(ISERR(AL25/$AL$11),"",AL25/AL$11) -> 0.00010480603 | AN25: =AF25+AJ25 -> 26842 | AO25: =IF(ISERR(AN25/$AN$11),"",AN25/$AN$11) -> 0.00010480603 | AP25: =B25+Z25+AL25 -> 262951 | AQ25: =IF(ISERR(AP25/$AP$11),"",AP25/$AP$11) -> 0.00031758745 | AR25: =D25+AB25+AN25 -> 262951 | AS25: =IF(ISERR(AR25/$AR$11),"",AR25/$AR$11) -> 0.00031758745 | AT25: =[1]全社合計!$N$25 -> 240981 | AU25: =IF(ISERR(AT25/$AT$11),"",AT25/$AT$11) -> 0.00024917698 | AV25: =AT25 -> 240981 | AW25: =IF(ISERR(AV25/$AV$11),"",AV25/$AV$11) -> 0.00024917698 | AX25: =AP25-AT25 -> 21970 | AY25: =IF(ISERROR(AP25/AT25),"",AP25/AT25) -> 1.091169 | AZ25: =AR25-AV25 -> 21970 | BA25: =IF(ISERROR(AR25/AV25),"",AR25/AV25) -> 1.091169
A26: 保守料 | B26: =[1]本部!$L$26 -> 328701 | C26: =IF(ISERR(B26/$B$11),"",B26/$B$11) | D26: =B26 -> 328701 | E26: =IF(ISERR(D26/$D$11),"",D26/$D$11) | F26: =[1]本社営業!$L$26 -> 680 | G26: =IF(ISERR(F26/$F$11),"",F26/$F$11) -> 1.2716162e-06 | H26: =F26 -> 680 | I26: =IF(ISERR(H26/$H$11),"",H26/$H$11) -> 1.2716162e-06 | J26: =[1]東大阪!$L$26 -> 7170 | K26: =IF(ISERR(J26/$J$11),"",J26/$J$11) -> 0.00080762706 | L26: =J26 -> 7170 | M26: =IF(ISERR(L26/$L$11),"",L26/$L$11) -> 0.00080762706 | N26: =[1]南港工場!$L$26 -> 0 | O26: =IF(ISERR(N26/$N$11),"",N26/$N$11) -> 0 | P26: =N26 -> 0 | Q26: =IF(ISERR(P26/$P$11),"",P26/$P$11) -> 0 | R26: =[1]南港事務!$L$26 -> 5520 | S26: =IF(ISERR(R26/$R$11),"",R26/$R$11) | T26: =R26 -> 5520 | U26: =IF(ISERR(T26/$T$11),"",T26/$T$11) | V26: =N26+R26 -> 5520 | W26: =IF(ISERR(V26/$V$11),"",V26/$V$11) -> 0.00019558883 | X26: =P26+T26 -> 5520 | Y26: =IF(ISERR(X26/$X$11),"",X26/$X$11) -> 0.00019558883 | Z26: =F26+J26+N26+R26 -> 13370 | AA26: =IF(ISERR(Z26/$Z$11),"",Z26/$Z$11) -> 2.338014e-05 | AB26: =H26+L26+P26+T26 -> 13370 | AC26: =IF(ISERR(AB26/$AB$11),"",AB26/$AB$11) -> 2.338014e-05 | AD26: =[1]東京事務!$L$26 -> 7170 | AE26: =IF(ISERR(AD26/$AD$11),"",AD26/$AD$11) -> 2.91107e-05 | AF26: =AD26 -> 7170 | AG26: =IF(ISERR(AF26/$AF$11),"",AF26/$AF$11) -> 2.91107e-05 | AH26: =[1]東京工場!$L$26 -> 13000 | AI26: =IF(ISERR(AH26/$AH$11),"",AH26/$AH$11) -> 0.0013251737 | AJ26: =AH26 -> 13000 | AK26: =IF(ISERR(AJ26/$AJ$11),"",AJ26/$AJ$11) -> 0.0013251737 | AL26: =AD26+AH26 -> 20170 | AM26: =IF(ISERR(AL26/$AL$11),"",AL26/AL$11) -> 7.8754845e-05 | AN26: =AF26+AJ26 -> 20170 | AO26: =IF(ISERR(AN26/$AN$11),"",AN26/$AN$11) -> 7.8754845e-05 | AP26: =B26+Z26+AL26 -> 362241 | AQ26: =IF(ISERR(AP26/$AP$11),"",AP26/$AP$11) -> 0.0004375081 | AR26: =D26+AB26+AN26 -> 362241 | AS26: =IF(ISERR(AR26/$AR$11),"",AR26/$AR$11) -> 0.0004375081 | AT26: =[1]全社合計!$N$26 -> 377291 | AU26: =IF(ISERR(AT26/$AT$11),"",AT26/$AT$11) -> 0.00039012301 | AV26: =AT26 -> 377291 | AW26: =IF(ISERR(AV26/$AV$11),"",AV26/$AV$11) -> 0.00039012301 | AX26: =AP26-AT26 -> -15050 | AY26: =IF(ISERROR(AP26/AT26),"",AP26/AT26) -> 0.96011037 | AZ26: =AR26-AV26 -> -15050 | BA26: =IF(ISERROR(AR26/AV26),"",AR26/AV26) -> 0.96011037
A27: 修繕費 | B27: =[1]本部!$L$27 -> 0 | C27: =IF(ISERR(B27/$B$11),"",B27/$B$11) | D27: =B27 -> 0 | E27: =IF(ISERR(D27/$D$11),"",D27/$D$11) | F27: =[1]本社営業!$L$27 -> 0 | G27: =IF(ISERR(F27/$F$11),"",F27/$F$11) -> 0 | H27: =F27 -> 0 | I27: =IF(ISERR(H27/$H$11),"",H27/$H$11) -> 0 | J27: =[1]東大阪!$L$27 -> 14400 | K27: =IF(ISERR(J27/$J$11),"",J27/$J$11) -> 0.0016220125 | L27: =J27 -> 14400 | M27: =IF(ISERR(L27/$L$11),"",L27/$L$11) -> 0.0016220125 | N27: =[1]南港工場!$L$27 -> 55610 | O27: =IF(ISERR(N27/$N$11),"",N27/$N$11) -> 0.0019704157 | P27: =N27 -> 55610 | Q27: =IF(ISERR(P27/$P$11),"",P27/$P$11) -> 0.0019704157 | R27: =[1]南港事務!$L$27 -> 0 | S27: =IF(ISERR(R27/$R$11),"",R27/$R$11) | T27: =R27 -> 0 | U27: =IF(ISERR(T27/$T$11),"",T27/$T$11) | V27: =N27+R27 -> 55610 | W27: =IF(ISERR(V27/$V$11),"",V27/$V$11) -> 0.0019704157 | X27: =P27+T27 -> 55610 | Y27: =IF(ISERR(X27/$X$11),"",X27/$X$11) -> 0.0019704157 | Z27: =F27+J27+N27+R27 -> 70010 | AA27: =IF(ISERR(Z27/$Z$11),"",Z27/$Z$11) -> 0.0001224266 | AB27: =H27+L27+P27+T27 -> 70010 | AC27: =IF(ISERR(AB27/$AB$11),"",AB27/$AB$11) -> 0.0001224266 | AD27: =[1]東京事務!$L$27 -> 0 | AE27: =IF(ISERR(AD27/$AD$11),"",AD27/$AD$11) -> 0 | AF27: =AD27 -> 0 | AG27: =IF(ISERR(AF27/$AF$11),"",AF27/$AF$11) -> 0 | AH27: =[1]東京工場!$L$27 -> 45900 | AI27: =IF(ISERR(AH27/$AH$11),"",AH27/$AH$11) -> 0.0046788824 | AJ27: =AH27 -> 45900 | AK27: =IF(ISERR(AJ27/$AJ$11),"",AJ27/$AJ$11) -> 0.0046788824 | AL27: =AD27+AH27 -> 45900 | AM27: =IF(ISERR(AL27/$AL$11),"",AL27/AL$11) -> 0.00017921901 | AN27: =AF27+AJ27 -> 45900 | AO27: =IF(ISERR(AN27/$AN$11),"",AN27/$AN$11) -> 0.00017921901 | AP27: =B27+Z27+AL27 -> 115910 | AQ27: =IF(ISERR(AP27/$AP$11),"",AP27/$AP$11) -> 0.00013999399 | AR27: =D27+AB27+AN27 -> 115910 | AS27: =IF(ISERR(AR27/$AR$11),"",AR27/$AR$11) -> 0.00013999399 | AT27: =[1]全社合計!$N$27 -> 600000 | AU27: =IF(ISERR(AT27/$AT$11),"",AT27/$AT$11) -> 0.00062040654 | AV27: =AT27 -> 600000 | AW27: =IF(ISERR(AV27/$AV$11),"",AV27/$AV$11) -> 0.00062040654 | AX27: =AP27-AT27 -> -484090 | AY27: =IF(ISERROR(AP27/AT27),"",AP27/AT27) -> 0.19318333 | AZ27: =AR27-AV27 -> -484090 | BA27: =IF(ISERROR(AR27/AV27),"",AR27/AV27) -> 0.19318333
A28: 事務用消耗品費 | B28: =[1]本部!$L$28 -> 377326 | C28: =IF(ISERR(B28/$B$11),"",B28/$B$11) | D28: =B28 -> 377326 | E28: =IF(ISERR(D28/$D$11),"",D28/$D$11) | F28: =[1]本社営業!$L$28 -> 104894 | G28: =IF(ISERR(F28/$F$11),"",F28/$F$11) -> 0.00019615428 | H28: =F28 -> 104894 | I28: =IF(ISERR(H28/$H$11),"",H28/$H$11) -> 0.00019615428 | J28: =[1]東大阪!$L$28 -> 4120 | K28: =IF(ISERR(J28/$J$11),"",J28/$J$11) -> 0.0004640758 | L28: =J28 -> 4120 | M28: =IF(ISERR(L28/$L$11),"",L28/$L$11) -> 0.0004640758 | N28: =[1]南港工場!$L$28 -> 0 | O28: =IF(ISERR(N28/$N$11),"",N28/$N$11) -> 0 | P28: =N28 -> 0 | Q28: =IF(ISERR(P28/$P$11),"",P28/$P$11) -> 0 | R28: =[1]南港事務!$L$28 -> 4108 | S28: =IF(ISERR(R28/$R$11),"",R28/$R$11) | T28: =R28 -> 4108 | U28: =IF(ISERR(T28/$T$11),"",T28/$T$11) | V28: =N28+R28 -> 4108 | W28: =IF(ISERR(V28/$V$11),"",V28/$V$11) -> 0.00014555777 | X28: =P28+T28 -> 4108 | Y28: =IF(ISERR(X28/$X$11),"",X28/$X$11) -> 0.00014555777 | Z28: =F28+J28+N28+R28 -> 113122 | AA28: =IF(ISERR(Z28/$Z$11),"",Z28/$Z$11) -> 0.00019781662 | AB28: =H28+L28+P28+T28 -> 113122 | AC28: =IF(ISERR(AB28/$AB$11),"",AB28/$AB$11) -> 0.00019781662 | AD28: =[1]東京事務!$L$28 -> 0 | AE28: =IF(ISERR(AD28/$AD$11),"",AD28/$AD$11) -> 0 | AF28: =AD28 -> 0 | AG28: =IF(ISERR(AF28/$AF$11),"",AF28/$AF$11) -> 0 | AH28: =[1]東京工場!$L$28 -> 0 | AI28: =IF(ISERR(AH28/$AH$11),"",AH28/$AH$11) -> 0 | AJ28: =AH28 -> 0 | AK28: =IF(ISERR(AJ28/$AJ$11),"",AJ28/$AJ$11) -> 0 | AL28: =AD28+AH28 -> 0 | AM28: =IF(ISERR(AL28/$AL$11),"",AL28/AL$11) -> 0 | AN28: =AF28+AJ28 -> 0 | AO28: =IF(ISERR(AN28/$AN$11),"",AN28/$AN$11) -> 0 | AP28: =B28+Z28+AL28 -> 490448 | AQ28: =IF(ISERR(AP28/$AP$11),"",AP28/$AP$11) -> 0.00059235419 | AR28: =D28+AB28+AN28 -> 490448 | AS28: =IF(ISERR(AR28/$AR$11),"",AR28/$AR$11) -> 0.00059235419 | AT28: =[1]全社合計!$N$28 -> 367814 | AU28: =IF(ISERR(AT28/$AT$11),"",AT28/$AT$11) -> 0.00038032369 | AV28: =AT28 -> 367814 | AW28: =IF(ISERR(AV28/$AV$11),"",AV28/$AV$11) -> 0.00038032369 | AX28: =AP28-AT28 -> 122634 | AY28: =IF(ISERROR(AP28/AT28),"",AP28/AT28) -> 1.3334131 | AZ28: =AR28-AV28 -> 122634 | BA28: =IF(ISERROR(AR28/AV28),"",AR28/AV28) -> 1.3334131
A29: 消耗品費 | B29: =[1]本部!$L$29 -> 0 | C29: =IF(ISERR(B29/$B$11),"",B29/$B$11) | D29: =B29 -> 0 | E29: =IF(ISERR(D29/$D$11),"",D29/$D$11) | F29: =[1]本社営業!$L$29 -> 22000 | G29: =IF(ISERR(F29/$F$11),"",F29/$F$11) -> 4.1140525e-05 | H29: =F29 -> 22000 | I29: =IF(ISERR(H29/$H$11),"",H29/$H$11) -> 4.1140525e-05 | J29: =[1]東大阪!$L$29 -> 268490 | K29: =IF(ISERR(J29/$J$11),"",J29/$J$11) -> 0.030242649 | L29: =J29 -> 268490 | M29: =IF(ISERR(L29/$L$11),"",L29/$L$11) -> 0.030242649 | N29: =[1]南港工場!$L$29 -> 809706 | O29: =IF(ISERR(N29/$N$11),"",N29/$N$11) -> 0.028690117 | P29: =N29 -> 809706 | Q29: =IF(ISERR(P29/$P$11),"",P29/$P$11) -> 0.028690117 | R29: =[1]南港事務!$L$29 -> 0 | S29: =IF(ISERR(R29/$R$11),"",R29/$R$11) | T29: =R29 -> 0 | U29: =IF(ISERR(T29/$T$11),"",T29/$T$11) | V29: =N29+R29 -> 809706 | W29: =IF(ISERR(V29/$V$11),"",V29/$V$11) -> 0.028690117 | X29: =P29+T29 -> 809706 | Y29: =IF(ISERR(X29/$X$11),"",X29/$X$11) -> 0.028690117 | Z29: =F29+J29+N29+R29 -> 1100196 | AA29: =IF(ISERR(Z29/$Z$11),"",Z29/$Z$11) -> 0.0019239145 | AB29: =H29+L29+P29+T29 -> 1100196 | AC29: =IF(ISERR(AB29/$AB$11),"",AB29/$AB$11) -> 0.0019239145 | AD29: =[1]東京事務!$L$29 -> 0 | AE29: =IF(ISERR(AD29/$AD$11),"",AD29/$AD$11) -> 0 | AF29: =AD29 -> 0 | AG29: =IF(ISERR(AF29/$AF$11),"",AF29/$AF$11) -> 0 | AH29: =[1]東京工場!$L$29 -> 228538 | AI29: =IF(ISERR(AH29/$AH$11),"",AH29/$AH$11) -> 0.023296349 | AJ29: =AH29 -> 228538 | AK29: =IF(ISERR(AJ29/$AJ$11),"",AJ29/$AJ$11) -> 0.023296349 | AL29: =AD29+AH29 -> 228538 | AM29: =IF(ISERR(AL29/$AL$11),"",AL29/AL$11) -> 0.00089233886 | AN29: =AF29+AJ29 -> 228538 | AO29: =IF(ISERR(AN29/$AN$11),"",AN29/$AN$11) -> 0.00089233886 | AP29: =B29+Z29+AL29 -> 1328734 | AQ29: =IF(ISERR(AP29/$AP$11),"",AP29/$AP$11) -> 0.0016048208 | AR29: =D29+AB29+AN29 -> 1328734 | AS29: =IF(ISERR(AR29/$AR$11),"",AR29/$AR$11) -> 0.0016048208 | AT29: =[1]全社合計!$N$29 -> 896717 | AU29: =IF(ISERR(AT29/$AT$11),"",AT29/$AT$11) -> 0.00092721515 | AV29: =AT29 -> 896717 | AW29: =IF(ISERR(AV29/$AV$11),"",AV29/$AV$11) -> 0.00092721515 | AX29: =AP29-AT29 -> 432017 | AY29: =IF(ISERROR(AP29/AT29),"",AP29/AT29) -> 1.4817763 | AZ29: =AR29-AV29 -> 432017 | BA29: =IF(ISERROR(AR29/AV29),"",AR29/AV29) -> 1.4817763
A30: 水道光熱費 | B30: =[1]本部!$L$30 -> 12910 | C30: =IF(ISERR(B30/$B$11),"",B30/$B$11) | D30: =B30 -> 12910 | E30: =IF(ISERR(D30/$D$11),"",D30/$D$11) | F30: =[1]本社営業!$L$30 -> 25821 | G30: =IF(ISERR(F30/$F$11),"",F30/$F$11) -> 4.8285886e-05 | H30: =F30 -> 25821 | I30: =IF(ISERR(H30/$H$11),"",H30/$H$11) -> 4.8285886e-05 | J30: =[1]東大阪!$L$30 -> 433946 | K30: =IF(ISERR(J30/$J$11),"",J30/$J$11) -> 0.048879572 | L30: =J30 -> 433946 | M30: =IF(ISERR(L30/$L$11),"",L30/$L$11) -> 0.048879572 | N30: =[1]南港工場!$L$30 -> 586335 | O30: =IF(ISERR(N30/$N$11),"",N30/$N$11) -> 0.020775466 | P30: =N30 -> 586335 | Q30: =IF(ISERR(P30/$P$11),"",P30/$P$11) -> 0.020775466 | R30: =[1]南港事務!$L$30 -> 21731 | S30: =IF(ISERR(R30/$R$11),"",R30/$R$11) | T30: =R30 -> 21731 | U30: =IF(ISERR(T30/$T$11),"",T30/$T$11) | V30: =N30+R30 -> 608066 | W30: =IF(ISERR(V30/$V$11),"",V30/$V$11) -> 0.021545456 | X30: =P30+T30 -> 608066 | Y30: =IF(ISERR(X30/$X$11),"",X30/$X$11) -> 0.021545456 | Z30: =F30+J30+N30+R30 -> 1067833 | AA30: =IF(ISERR(Z30/$Z$11),"",Z30/$Z$11) -> 0.0018673212 | AB30: =H30+L30+P30+T30 -> 1067833 | AC30: =IF(ISERR(AB30/$AB$11),"",AB30/$AB$11) -> 0.0018673212 | AD30: =[1]東京事務!$L$30 -> 45961 | AE30: =IF(ISERR(AD30/$AD$11),"",AD30/$AD$11) -> 0.00018660486 | AF30: =AD30 -> 45961 | AG30: =IF(ISERR(AF30/$AF$11),"",AF30/$AF$11) -> 0.00018660486 | AH30: =[1]東京工場!$L$30 -> 199518 | AI30: =IF(ISERR(AH30/$AH$11),"",AH30/$AH$11) -> 0.020338154 | AJ30: =AH30 -> 199518 | AK30: =IF(ISERR(AJ30/$AJ$11),"",AJ30/$AJ$11) -> 0.020338154 | AL30: =AD30+AH30 -> 245479 | AM30: =IF(ISERR(AL30/$AL$11),"",AL30/AL$11) -> 0.0009584859 | AN30: =AF30+AJ30 -> 245479 | AO30: =IF(ISERR(AN30/$AN$11),"",AN30/$AN$11) -> 0.0009584859 | AP30: =B30+Z30+AL30 -> 1326222 | AQ30: =IF(ISERR(AP30/$AP$11),"",AP30/$AP$11) -> 0.0016017869 | AR30: =D30+AB30+AN30 -> 1326222 | AS30: =IF(ISERR(AR30/$AR$11),"",AR30/$AR$11) -> 0.0016017869 | AT30: =[1]全社合計!$N$30 -> 1323813 | AU30: =IF(ISERR(AT30/$AT$11),"",AT30/$AT$11) -> 0.0013688371 | AV30: =AT30 -> 1323813 | AW30: =IF(ISERR(AV30/$AV$11),"",AV30/$AV$11) -> 0.0013688371 | AX30: =AP30-AT30 -> 2409 | AY30: =IF(ISERROR(AP30/AT30),"",AP30/AT30) -> 1.0018197 | AZ30: =AR30-AV30 -> 2409 | BA30: =IF(ISERROR(AR30/AV30),"",AR30/AV30) -> 1.0018197
A31: 旅費交通費 | B31: =[1]本部!$L$31 -> 189304 | C31: =IF(ISERR(B31/$B$11),"",B31/$B$11) | D31: =B31 -> 189304 | E31: =IF(ISERR(D31/$D$11),"",D31/$D$11) | F31: =[1]本社営業!$L$31 -> 715946 | G31: =IF(ISERR(F31/$F$11),"",F31/$F$11) -> 0.0013388361 | H31: =F31 -> 715946 | I31: =IF(ISERR(H31/$H$11),"",H31/$H$11) -> 0.0013388361 | J31: =[1]東大阪!$L$31 -> 112818 | K31: =IF(ISERR(J31/$J$11),"",J31/$J$11) -> 0.012707792 | L31: =J31 -> 112818 | M31: =IF(ISERR(L31/$L$11),"",L31/$L$11) -> 0.012707792 | N31: =[1]南港工場!$L$31 -> 265719 | O31: =IF(ISERR(N31/$N$11),"",N31/$N$11) -> 0.0094151572 | P31: =N31 -> 265719 | Q31: =IF(ISERR(P31/$P$11),"",P31/$P$11) -> 0.0094151572 | R31: =[1]南港事務!$L$31 -> 130777 | S31: =IF(ISERR(R31/$R$11),"",R31/$R$11) | T31: =R31 -> 130777 | U31: =IF(ISERR(T31/$T$11),"",T31/$T$11) | V31: =N31+R31 -> 396496 | W31: =IF(ISERR(V31/$V$11),"",V31/$V$11) -> 0.014048947 | X31: =P31+T31 -> 396496 | Y31: =IF(ISERR(X31/$X$11),"",X31/$X$11) -> 0.014048947 | Z31: =F31+J31+N31+R31 -> 1225260 | AA31: =IF(ISERR(Z31/$Z$11),"",Z31/$Z$11) -> 0.0021426141 | AB31: =H31+L31+P31+T31 -> 1225260 | AC31: =IF(ISERR(AB31/$AB$11),"",AB31/$AB$11) -> 0.0021426141 | AD31: =[1]東京事務!$L$31 -> 336941 | AE31: =IF(ISERR(AD31/$AD$11),"",AD31/$AD$11) -> 0.0013680039 | AF31: =AD31 -> 336941 | AG31: =IF(ISERR(AF31/$AF$11),"",AF31/$AF$11) -> 0.0013680039 | AH31: =[1]東京工場!$L$31 -> 174855 | AI31: =IF(ISERR(AH31/$AH$11),"",AH31/$AH$11) -> 0.017824095 | AJ31: =AH31 -> 174855 | AK31: =IF(ISERR(AJ31/$AJ$11),"",AJ31/$AJ$11) -> 0.017824095 | AL31: =AD31+AH31 -> 511796 | AM31: =IF(ISERR(AL31/$AL$11),"",AL31/AL$11) -> 0.0019983349 | AN31: =AF31+AJ31 -> 511796 | AO31: =IF(ISERR(AN31/$AN$11),"",AN31/$AN$11) -> 0.0019983349 | AP31: =B31+Z31+AL31 -> 1926360 | AQ31: =IF(ISERR(AP31/$AP$11),"",AP31/$AP$11) -> 0.0023266226 | AR31: =D31+AB31+AN31 -> 1926360 | AS31: =IF(ISERR(AR31/$AR$11),"",AR31/$AR$11) -> 0.0023266226 | AT31: =[1]全社合計!$N$31 -> 1486264 | AU31: =IF(ISERR(AT31/$AT$11),"",AT31/$AT$11) -> 0.0015368132 | AV31: =AT31 -> 1486264 | AW31: =IF(ISERR(AV31/$AV$11),"",AV31/$AV$11) -> 0.0015368132 | AX31: =AP31-AT31 -> 440096 | AY31: =IF(ISERROR(AP31/AT31),"",AP31/AT31) -> 1.2961089 | AZ31: =AR31-AV31 -> 440096 | BA31: =IF(ISERROR(AR31/AV31),"",AR31/AV31) -> 1.2961089
A32: 支払手数料 | B32: =[1]本部!$L$32 -> 453880 | C32: =IF(ISERR(B32/$B$11),"",B32/$B$11) | D32: =B32 -> 453880 | E32: =IF(ISERR(D32/$D$11),"",D32/$D$11) | F32: =[1]本社営業!$L$32 -> 903148 | G32: =IF(ISERR(F32/$F$11),"",F32/$F$11) -> 0.0016889083 | H32: =F32 -> 903148 | I32: =IF(ISERR(H32/$H$11),"",H32/$H$11) -> 0.0016889083 | J32: =[1]東大阪!$L$32 -> 159200 | K32: =IF(ISERR(J32/$J$11),"",J32/$J$11) -> 0.017932249 | L32: =J32 -> 159200 | M32: =IF(ISERR(L32/$L$11),"",L32/$L$11) -> 0.017932249 | N32: =[1]南港工場!$L$32 -> 133550 | O32: =IF(ISERR(N32/$N$11),"",N32/$N$11) -> 0.0047320449 | P32: =N32 -> 133550 | Q32: =IF(ISERR(P32/$P$11),"",P32/$P$11) -> 0.0047320449 | R32: =[1]南港事務!$L$32 -> 150707 | S32: =IF(ISERR(R32/$R$11),"",R32/$R$11) | T32: =R32 -> 150707 | U32: =IF(ISERR(T32/$T$11),"",T32/$T$11) | V32: =N32+R32 -> 284257 | W32: =IF(ISERR(V32/$V$11),"",V32/$V$11) -> 0.01007201 | X32: =P32+T32 -> 284257 | Y32: =IF(ISERR(X32/$X$11),"",X32/$X$11) -> 0.01007201 | Z32: =F32+J32+N32+R32 -> 1346605 | AA32: =IF(ISERR(Z32/$Z$11),"",Z32/$Z$11) -> 0.0023548103 | AB32: =H32+L32+P32+T32 -> 1346605 | AC32: =IF(ISERR(AB32/$AB$11),"",AB32/$AB$11) -> 0.0023548103 | AD32: =[1]東京事務!$L$32 -> 70000 | AE32: =IF(ISERR(AD32/$AD$11),"",AD32/$AD$11) -> 0.00028420488 | AF32: =AD32 -> 70000 | AG32: =IF(ISERR(AF32/$AF$11),"",AF32/$AF$11) -> 0.00028420488 | AH32: =[1]東京工場!$L$32 -> 37150 | AI32: =IF(ISERR(AH32/$AH$11),"",AH32/$AH$11) -> 0.0037869386 | AJ32: =AH32 -> 37150 | AK32: =IF(ISERR(AJ32/$AJ$11),"",AJ32/$AJ$11) -> 0.0037869386 | AL32: =AD32+AH32 -> 107150 | AM32: =IF(ISERR(AL32/$AL$11),"",AL32/AL$11) -> 0.00041837291 | AN32: =AF32+AJ32 -> 107150 | AO32: =IF(ISERR(AN32/$AN$11),"",AN32/$AN$11) -> 0.00041837291 | AP32: =B32+Z32+AL32 -> 1907635 | AQ32: =IF(ISERR(AP32/$AP$11),"",AP32/$AP$11) -> 0.0023040069 | AR32: =D32+AB32+AN32 -> 1907635 | AS32: =IF(ISERR(AR32/$AR$11),"",AR32/$AR$11) -> 0.0023040069 | AT32: =[1]全社合計!$N$32 -> 2887731 | AU32: =IF(ISERR(AT32/$AT$11),"",AT32/$AT$11) -> 0.0029859453 | AV32: =AT32 -> 2887731 | AW32: =IF(ISERR(AV32/$AV$11),"",AV32/$AV$11) -> 0.0029859453 | AX32: =AP32-AT32 -> -980096 | AY32: =IF(ISERROR(AP32/AT32),"",AP32/AT32) -> 0.66059997 | AZ32: =AR32-AV32 -> -980096 | BA32: =IF(ISERROR(AR32/AV32),"",AR32/AV32) -> 0.66059997
A33: 租税公課 | B33: =[1]本部!$L$33 -> 197626 | C33: =IF(ISERR(B33/$B$11),"",B33/$B$11) | D33: =B33 -> 197626 | E33: =IF(ISERR(D33/$D$11),"",D33/$D$11) | F33: =[1]本社営業!$L$33 -> 55000 | G33: =IF(ISERR(F33/$F$11),"",F33/$F$11) -> 0.00010285131 | H33: =F33 -> 55000 | I33: =IF(ISERR(H33/$H$11),"",H33/$H$11) -> 0.00010285131 | J33: =[1]東大阪!$L$33 -> 440000 | K33: =IF(ISERR(J33/$J$11),"",J33/$J$11) -> 0.049561493 | L33: =J33 -> 440000 | M33: =IF(ISERR(L33/$L$11),"",L33/$L$11) -> 0.049561493 | N33: =[1]南港工場!$L$33 -> 525000 | O33: =IF(ISERR(N33/$N$11),"",N33/$N$11) -> 0.018602198 | P33: =N33 -> 525000 | Q33: =IF(ISERR(P33/$P$11),"",P33/$P$11) -> 0.018602198 | R33: =[1]南港事務!$L$33 -> 20000 | S33: =IF(ISERR(R33/$R$11),"",R33/$R$11) | T33: =R33 -> 20000 | U33: =IF(ISERR(T33/$T$11),"",T33/$T$11) | V33: =N33+R33 -> 545000 | W33: =IF(ISERR(V33/$V$11),"",V33/$V$11) -> 0.019310853 | X33: =P33+T33 -> 545000 | Y33: =IF(ISERR(X33/$X$11),"",X33/$X$11) -> 0.019310853 | Z33: =F33+J33+N33+R33 -> 1040000 | AA33: =IF(ISERR(Z33/$Z$11),"",Z33/$Z$11) -> 0.0018186496 | AB33: =H33+L33+P33+T33 -> 1040000 | AC33: =IF(ISERR(AB33/$AB$11),"",AB33/$AB$11) -> 0.0018186496 | AD33: =[1]東京事務!$L$33 -> 55000 | AE33: =IF(ISERR(AD33/$AD$11),"",AD33/$AD$11) -> 0.00022330383 | AF33: =AD33 -> 55000 | AG33: =IF(ISERR(AF33/$AF$11),"",AF33/$AF$11) -> 0.00022330383 | AH33: =[1]東京工場!$L$33 -> 325000 | AI33: =IF(ISERR(AH33/$AH$11),"",AH33/$AH$11) -> 0.033129342 | AJ33: =AH33 -> 325000 | AK33: =IF(ISERR(AJ33/$AJ$11),"",AJ33/$AJ$11) -> 0.033129342 | AL33: =AD33+AH33 -> 380000 | AM33: =IF(ISERR(AL33/$AL$11),"",AL33/AL$11) -> 0.0014837304 | AN33: =AF33+AJ33 -> 380000 | AO33: =IF(ISERR(AN33/$AN$11),"",AN33/$AN$11) -> 0.0014837304 | AP33: =B33+Z33+AL33 -> 1617626 | AQ33: =IF(ISERR(AP33/$AP$11),"",AP33/$AP$11) -> 0.0019537393 | AR33: =D33+AB33+AN33 -> 1617626 | AS33: =IF(ISERR(AR33/$AR$11),"",AR33/$AR$11) -> 0.0019537393 | AT33: =[1]全社合計!$N$33 -> 1613174 | AU33: =IF(ISERR(AT33/$AT$11),"",AT33/$AT$11) -> 0.0016680395 | AV33: =AT33 -> 1613174 | AW33: =IF(ISERR(AV33/$AV$11),"",AV33/$AV$11) -> 0.0016680395 | AX33: =AP33-AT33 -> 4452 | AY33: =IF(ISERROR(AP33/AT33),"",AP33/AT33) -> 1.0027598 | AZ33: =AR33-AV33 -> 4452 | BA33: =IF(ISERROR(AR33/AV33),"",AR33/AV33) -> 1.0027598
A34: 交際費 | B34: =[1]本部!$L$34 -> 0 | C34: =IF(ISERR(B34/$B$11),"",B34/$B$11) | D34: =B34 -> 0 | E34: =IF(ISERR(D34/$D$11),"",D34/$D$11) | F34: =[1]本社営業!$L$34 -> 277676 | G34: =IF(ISERR(F34/$F$11),"",F34/$F$11) -> 0.00051926075 | H34: =F34 -> 277676 | I34: =IF(ISERR(H34/$H$11),"",H34/$H$11) -> 0.00051926075 | J34: =[1]東大阪!$L$34 -> 0 | K34: =IF(ISERR(J34/$J$11),"",J34/$J$11) -> 0 | L34: =J34 -> 0 | M34: =IF(ISERR(L34/$L$11),"",L34/$L$11) -> 0 | N34: =[1]南港工場!$L$34 -> 0 | O34: =IF(ISERR(N34/$N$11),"",N34/$N$11) -> 0 | P34: =N34 -> 0 | Q34: =IF(ISERR(P34/$P$11),"",P34/$P$11) -> 0 | R34: =[1]南港事務!$L$34 -> 0 | S34: =IF(ISERR(R34/$R$11),"",R34/$R$11) | T34: =R34 -> 0 | U34: =IF(ISERR(T34/$T$11),"",T34/$T$11) | V34: =N34+R34 -> 0 | W34: =IF(ISERR(V34/$V$11),"",V34/$V$11) -> 0 | X34: =P34+T34 -> 0 | Y34: =IF(ISERR(X34/$X$11),"",X34/$X$11) -> 0 | Z34: =F34+J34+N34+R34 -> 277676 | AA34: =IF(ISERR(Z34/$Z$11),"",Z34/$Z$11) -> 0.00048557246 | AB34: =H34+L34+P34+T34 -> 277676 | AC34: =IF(ISERR(AB34/$AB$11),"",AB34/$AB$11) -> 0.00048557246 | AD34: =[1]東京事務!$L$34 -> 460664 | AE34: =IF(ISERR(AD34/$AD$11),"",AD34/$AD$11) -> 0.0018703279 | AF34: =AD34 -> 460664 | AG34: =IF(ISERR(AF34/$AF$11),"",AF34/$AF$11) -> 0.0018703279 | AH34: =[1]東京工場!$L$34 -> 0 | AI34: =IF(ISERR(AH34/$AH$11),"",AH34/$AH$11) -> 0 | AJ34: =AH34 -> 0 | AK34: =IF(ISERR(AJ34/$AJ$11),"",AJ34/$AJ$11) -> 0 | AL34: =AD34+AH34 -> 460664 | AM34: =IF(ISERR(AL34/$AL$11),"",AL34/AL$11) -> 0.0017986873 | AN34: =AF34+AJ34 -> 460664 | AO34: =IF(ISERR(AN34/$AN$11),"",AN34/$AN$11) -> 0.0017986873 | AP34: =B34+Z34+AL34 -> 738340 | AQ34: =IF(ISERR(AP34/$AP$11),"",AP34/$AP$11) -> 0.00089175365 | AR34: =D34+AB34+AN34 -> 738340 | AS34: =IF(ISERR(AR34/$AR$11),"",AR34/$AR$11) -> 0.00089175365 | AT34: =[1]全社合計!$N$34 -> 496966 | AU34: =IF(ISERR(AT34/$AT$11),"",AT34/$AT$11) -> 0.00051386826 | AV34: =AT34 -> 496966 | AW34: =IF(ISERR(AV34/$AV$11),"",AV34/$AV$11) -> 0.00051386826 | AX34: =AP34-AT34 -> 241374 | AY34: =IF(ISERROR(AP34/AT34),"",AP34/AT34) -> 1.4856952 | AZ34: =AR34-AV34 -> 241374 | BA34: =IF(ISERROR(AR34/AV34),"",AR34/AV34) -> 1.4856952
A35: 保険料 | B35: =[1]本部!$L$35 -> 221520 | C35: =IF(ISERR(B35/$B$11),"",B35/$B$11) | D35: =B35 -> 221520 | E35: =IF(ISERR(D35/$D$11),"",D35/$D$11) | F35: =[1]本社営業!$L$35 -> 0 | G35: =IF(ISERR(F35/$F$11),"",F35/$F$11) -> 0 | H35: =F35 -> 0 | I35: =IF(ISERR(H35/$H$11),"",H35/$H$11) -> 0 | J35: =[1]東大阪!$L$35 -> 0 | K35: =IF(ISERR(J35/$J$11),"",J35/$J$11) -> 0 | L35: =J35 -> 0 | M35: =IF(ISERR(L35/$L$11),"",L35/$L$11) -> 0 | N35: =[1]南港工場!$L$35 -> 0 | O35: =IF(ISERR(N35/$N$11),"",N35/$N$11) -> 0 | P35: =N35 -> 0 | Q35: =IF(ISERR(P35/$P$11),"",P35/$P$11) -> 0 | R35: =[1]南港事務!$L$35 -> 0 | S35: =IF(ISERR(R35/$R$11),"",R35/$R$11) | T35: =R35 -> 0 | U35: =IF(ISERR(T35/$T$11),"",T35/$T$11) | V35: =N35+R35 -> 0 | W35: =IF(ISERR(V35/$V$11),"",V35/$V$11) -> 0 | X35: =P35+T35 -> 0 | Y35: =IF(ISERR(X35/$X$11),"",X35/$X$11) -> 0 | Z35: =F35+J35+N35+R35 -> 0 | AA35: =IF(ISERR(Z35/$Z$11),"",Z35/$Z$11) -> 0 | AB35: =H35+L35+P35+T35 -> 0 | AC35: =IF(ISERR(AB35/$AB$11),"",AB35/$AB$11) -> 0 | AD35: =[1]東京事務!$L$35 -> 0 | AE35: =IF(ISERR(AD35/$AD$11),"",AD35/$AD$11) -> 0 | AF35: =AD35 -> 0 | AG35: =IF(ISERR(AF35/$AF$11),"",AF35/$AF$11) -> 0 | AH35: =[1]東京工場!$L$35 -> 0 | AI35: =IF(ISERR(AH35/$AH$11),"",AH35/$AH$11) -> 0 | AJ35: =AH35 -> 0 | AK35: =IF(ISERR(AJ35/$AJ$11),"",AJ35/$AJ$11) -> 0 | AL35: =AD35+AH35 -> 0 | AM35: =IF(ISERR(AL35/$AL$11),"",AL35/AL$11) -> 0 | AN35: =AF35+AJ35 -> 0 | AO35: =IF(ISERR(AN35/$AN$11),"",AN35/$AN$11) -> 0 | AP35: =B35+Z35+AL35 -> 221520 | AQ35: =IF(ISERR(AP35/$AP$11),"",AP35/$AP$11) -> 0.00026754784 | AR35: =D35+AB35+AN35 -> 221520 | AS35: =IF(ISERR(AR35/$AR$11),"",AR35/$AR$11) -> 0.00026754784 | AT35: =[1]全社合計!$N$35 -> 217865 | AU35: =IF(ISERR(AT35/$AT$11),"",AT35/$AT$11) -> 0.00022527478 | AV35: =AT35 -> 217865 | AW35: =IF(ISERR(AV35/$AV$11),"",AV35/$AV$11) -> 0.00022527478 | AX35: =AP35-AT35 -> 3655 | AY35: =IF(ISERROR(AP35/AT35),"",AP35/AT35) -> 1.0167764 | AZ35: =AR35-AV35 -> 3655 | BA35: =IF(ISERROR(AR35/AV35),"",AR35/AV35) -> 1.0167764
A36: 通信費 | B36: =[1]本部!$L$36 -> 47881 | C36: =IF(ISERR(B36/$B$11),"",B36/$B$11) | D36: =B36 -> 47881 | E36: =IF(ISERR(D36/$D$11),"",D36/$D$11) | F36: =[1]本社営業!$L$36 -> 25206 | G36: =IF(ISERR(F36/$F$11),"",F36/$F$11) -> 4.7135822e-05 | H36: =F36 -> 25206 | I36: =IF(ISERR(H36/$H$11),"",H36/$H$11) -> 4.7135822e-05 | J36: =[1]東大阪!$L$36 -> 24911 | K36: =IF(ISERR(J36/$J$11),"",J36/$J$11) -> 0.002805969 | L36: =J36 -> 24911 | M36: =IF(ISERR(L36/$L$11),"",L36/$L$11) -> 0.002805969 | N36: =[1]南港工場!$L$36 -> 9888 | O36: =IF(ISERR(N36/$N$11),"",N36/$N$11) -> 0.00035035912 | P36: =N36 -> 9888 | Q36: =IF(ISERR(P36/$P$11),"",P36/$P$11) -> 0.00035035912 | R36: =[1]南港事務!$L$36 -> 35021 | S36: =IF(ISERR(R36/$R$11),"",R36/$R$11) | T36: =R36 -> 35021 | U36: =IF(ISERR(T36/$T$11),"",T36/$T$11) | V36: =N36+R36 -> 44909 | W36: =IF(ISERR(V36/$V$11),"",V36/$V$11) -> 0.0015912498 | X36: =P36+T36 -> 44909 | Y36: =IF(ISERR(X36/$X$11),"",X36/$X$11) -> 0.0015912498 | Z36: =F36+J36+N36+R36 -> 95026 | AA36: =IF(ISERR(Z36/$Z$11),"",Z36/$Z$11) -> 0.00016617212 | AB36: =H36+L36+P36+T36 -> 95026 | AC36: =IF(ISERR(AB36/$AB$11),"",AB36/$AB$11) -> 0.00016617212 | AD36: =[1]東京事務!$L$36 -> 32981 | AE36: =IF(ISERR(AD36/$AD$11),"",AD36/$AD$11) -> 0.00013390516 | AF36: =AD36 -> 32981 | AG36: =IF(ISERR(AF36/$AF$11),"",AF36/$AF$11) -> 0.00013390516 | AH36: =[1]東京工場!$L$36 -> 3003 | AI36: =IF(ISERR(AH36/$AH$11),"",AH36/$AH$11) -> 0.00030611512 | AJ36: =AH36 -> 3003 | AK36: =IF(ISERR(AJ36/$AJ$11),"",AJ36/$AJ$11) -> 0.00030611512 | AL36: =AD36+AH36 -> 35984 | AM36: =IF(ISERR(AL36/$AL$11),"",AL36/AL$11) -> 0.00014050146 | AN36: =AF36+AJ36 -> 35984 | AO36: =IF(ISERR(AN36/$AN$11),"",AN36/$AN$11) -> 0.00014050146 | AP36: =B36+Z36+AL36 -> 178891 | AQ36: =IF(ISERR(AP36/$AP$11),"",AP36/$AP$11) -> 0.0002160613 | AR36: =D36+AB36+AN36 -> 178891 | AS36: =IF(ISERR(AR36/$AR$11),"",AR36/$AR$11) -> 0.0002160613 | AT36: =[1]全社合計!$N$36 -> 240058 | AU36: =IF(ISERR(AT36/$AT$11),"",AT36/$AT$11) -> 0.00024822259 | AV36: =AT36 -> 240058 | AW36: =IF(ISERR(AV36/$AV$11),"",AV36/$AV$11) -> 0.00024822259 | AX36: =AP36-AT36 -> -61167 | AY36: =IF(ISERROR(AP36/AT36),"",AP36/AT36) -> 0.74519908 | AZ36: =AR36-AV36 -> -61167 | BA36: =IF(ISERROR(AR36/AV36),"",AR36/AV36) -> 0.74519908
A37: 備品費 | B37: =[1]本部!$L$37 -> 0 | C37: =IF(ISERR(B37/$B$11),"",B37/$B$11) | D37: =B37 -> 0 | E37: =IF(ISERR(D37/$D$11),"",D37/$D$11) | F37: =[1]本社営業!$L$37 -> 0 | G37: =IF(ISERR(F37/$F$11),"",F37/$F$11) -> 0 | H37: =F37 -> 0 | I37: =IF(ISERR(H37/$H$11),"",H37/$H$11) -> 0 | J37: =[1]東大阪!$L$37 -> 37692 | K37: =IF(ISERR(J37/$J$11),"",J37/$J$11) -> 0.0042456178 | L37: =J37 -> 37692 | M37: =IF(ISERR(L37/$L$11),"",L37/$L$11) -> 0.0042456178 | N37: =[1]南港工場!$L$37 -> 0 | O37: =IF(ISERR(N37/$N$11),"",N37/$N$11) -> 0 | P37: =N37 -> 0 | Q37: =IF(ISERR(P37/$P$11),"",P37/$P$11) -> 0 | R37: =[1]南港事務!$L$37 -> 0 | S37: =IF(ISERR(R37/$R$11),"",R37/$R$11) | T37: =R37 -> 0 | U37: =IF(ISERR(T37/$T$11),"",T37/$T$11) | V37: =N37+R37 -> 0 | W37: =IF(ISERR(V37/$V$11),"",V37/$V$11) -> 0 | X37: =P37+T37 -> 0 | Y37: =IF(ISERR(X37/$X$11),"",X37/$X$11) -> 0 | Z37: =F37+J37+N37+R37 -> 37692 | AA37: =IF(ISERR(Z37/$Z$11),"",Z37/$Z$11) -> 6.591206e-05 | AB37: =H37+L37+P37+T37 -> 37692 | AC37: =IF(ISERR(AB37/$AB$11),"",AB37/$AB$11) -> 6.591206e-05 | AD37: =[1]東京事務!$L$37 -> 0 | AE37: =IF(ISERR(AD37/$AD$11),"",AD37/$AD$11) -> 0 | AF37: =AD37 -> 0 | AG37: =IF(ISERR(AF37/$AF$11),"",AF37/$AF$11) -> 0 | AH37: =[1]東京工場!$L$37 -> 7600 | AI37: =IF(ISERR(AH37/$AH$11),"",AH37/$AH$11) -> 0.00077471691 | AJ37: =AH37 -> 7600 | AK37: =IF(ISERR(AJ37/$AJ$11),"",AJ37/$AJ$11) -> 0.00077471691 | AL37: =AD37+AH37 -> 7600 | AM37: =IF(ISERR(AL37/$AL$11),"",AL37/AL$11) -> 2.9674607e-05 | AN37: =AF37+AJ37 -> 7600 | AO37: =IF(ISERR(AN37/$AN$11),"",AN37/$AN$11) -> 2.9674607e-05 | AP37: =B37+Z37+AL37 -> 45292 | AQ37: =IF(ISERR(AP37/$AP$11),"",AP37/$AP$11) -> 5.4702856e-05 | AR37: =D37+AB37+AN37 -> 45292 | AS37: =IF(ISERR(AR37/$AR$11),"",AR37/$AR$11) -> 5.4702856e-05 | AT37: =[1]全社合計!$N$37 -> 0 | AU37: =IF(ISERR(AT37/$AT$11),"",AT37/$AT$11) -> 0 | AV37: =AT37 -> 0 | AW37: =IF(ISERR(AV37/$AV$11),"",AV37/$AV$11) -> 0 | AX37: =AP37-AT37 -> 45292 | AY37: =IF(ISERROR(AP37/AT37),"",AP37/AT37) | AZ37: =AR37-AV37 -> 45292 | BA37: =IF(ISERROR(AR37/AV37),"",AR37/AV37)
A38: 車両費 | B38: =[1]本部!$L$38 -> 0 | C38: =IF(ISERR(B38/$B$11),"",B38/$B$11) | D38: =B38 -> 0 | E38: =IF(ISERR(D38/$D$11),"",D38/$D$11) | F38: =[1]本社営業!$L$38 -> 35025 | G38: =IF(ISERR(F38/$F$11),"",F38/$F$11) -> 6.5497586e-05 | H38: =F38 -> 35025 | I38: =IF(ISERR(H38/$H$11),"",H38/$H$11) -> 6.5497586e-05 | J38: =[1]東大阪!$L$38 -> 0 | K38: =IF(ISERR(J38/$J$11),"",J38/$J$11) -> 0 | L38: =J38 -> 0 | M38: =IF(ISERR(L38/$L$11),"",L38/$L$11) -> 0 | N38: =[1]南港工場!$L$38 -> 0 | O38: =IF(ISERR(N38/$N$11),"",N38/$N$11) -> 0 | P38: =N38 -> 0 | Q38: =IF(ISERR(P38/$P$11),"",P38/$P$11) -> 0 | R38: =[1]南港事務!$L$38 -> 0 | S38: =IF(ISERR(R38/$R$11),"",R38/$R$11) | T38: =R38 -> 0 | U38: =IF(ISERR(T38/$T$11),"",T38/$T$11) | V38: =N38+R38 -> 0 | W38: =IF(ISERR(V38/$V$11),"",V38/$V$11) -> 0 | X38: =P38+T38 -> 0 | Y38: =IF(ISERR(X38/$X$11),"",X38/$X$11) -> 0 | Z38: =F38+J38+N38+R38 -> 35025 | AA38: =IF(ISERR(Z38/$Z$11),"",Z38/$Z$11) -> 6.1248272e-05 | AB38: =H38+L38+P38+T38 -> 35025 | AC38: =IF(ISERR(AB38/$AB$11),"",AB38/$AB$11) -> 6.1248272e-05 | AD38: =[1]東京事務!$L$38 -> 28697 | AE38: =IF(ISERR(AD38/$AD$11),"",AD38/$AD$11) -> 0.00011651182 | AF38: =AD38 -> 28697 | AG38: =IF(ISERR(AF38/$AF$11),"",AF38/$AF$11) -> 0.00011651182 | AH38: =[1]東京工場!$L$38 -> 3380 | AI38: =IF(ISERR(AH38/$AH$11),"",AH38/$AH$11) -> 0.00034454515 | AJ38: =AH38 -> 3380 | AK38: =IF(ISERR(AJ38/$AJ$11),"",AJ38/$AJ$11) -> 0.00034454515 | AL38: =AD38+AH38 -> 32077 | AM38: =IF(ISERR(AL38/$AL$11),"",AL38/AL$11) -> 0.00012524636 | AN38: =AF38+AJ38 -> 32077 | AO38: =IF(ISERR(AN38/$AN$11),"",AN38/$AN$11) -> 0.00012524636 | AP38: =B38+Z38+AL38 -> 67102 | AQ38: =IF(ISERR(AP38/$AP$11),"",AP38/$AP$11) -> 8.1044578e-05 | AR38: =D38+AB38+AN38 -> 67102 | AS38: =IF(ISERR(AR38/$AR$11),"",AR38/$AR$11) -> 8.1044578e-05 | AT38: =[1]全社合計!$N$38 -> 83588 | AU38: =IF(ISERR(AT38/$AT$11),"",AT38/$AT$11) -> 8.6430903e-05 | AV38: =AT38 -> 83588 | AW38: =IF(ISERR(AV38/$AV$11),"",AV38/$AV$11) -> 8.6430903e-05 | AX38: =AP38-AT38 -> -16486 | AY38: =IF(ISERROR(AP38/AT38),"",AP38/AT38) -> 0.80277073 | AZ38: =AR38-AV38 -> -16486 | BA38: =IF(ISERROR(AR38/AV38),"",AR38/AV38) -> 0.80277073
A39: 新聞図書費 | B39: =[1]本部!$L$39 -> 4445 | C39: =IF(ISERR(B39/$B$11),"",B39/$B$11) | D39: =B39 -> 4445 | E39: =IF(ISERR(D39/$D$11),"",D39/$D$11) | F39: =[1]本社営業!$L$39 -> 0 | G39: =IF(ISERR(F39/$F$11),"",F39/$F$11) -> 0 | H39: =F39 -> 0 | I39: =IF(ISERR(H39/$H$11),"",H39/$H$11) -> 0 | J39: =[1]東大阪!$L$39 -> 0 | K39: =IF(ISERR(J39/$J$11),"",J39/$J$11) -> 0 | L39: =J39 -> 0 | M39: =IF(ISERR(L39/$L$11),"",L39/$L$11) -> 0 | N39: =[1]南港工場!$L$39 -> 0 | O39: =IF(ISERR(N39/$N$11),"",N39/$N$11) -> 0 | P39: =N39 -> 0 | Q39: =IF(ISERR(P39/$P$11),"",P39/$P$11) -> 0 | R39: =[1]南港事務!$L$39 -> 0 | S39: =IF(ISERR(R39/$R$11),"",R39/$R$11) | T39: =R39 -> 0 | U39: =IF(ISERR(T39/$T$11),"",T39/$T$11) | V39: =N39+R39 -> 0 | W39: =IF(ISERR(V39/$V$11),"",V39/$V$11) -> 0 | X39: =P39+T39 -> 0 | Y39: =IF(ISERR(X39/$X$11),"",X39/$X$11) -> 0 | Z39: =F39+J39+N39+R39 -> 0 | AA39: =IF(ISERR(Z39/$Z$11),"",Z39/$Z$11) -> 0 | AB39: =H39+L39+P39+T39 -> 0 | AC39: =IF(ISERR(AB39/$AB$11),"",AB39/$AB$11) -> 0 | AD39: =[1]東京事務!$L$39 -> 0 | AE39: =IF(ISERR(AD39/$AD$11),"",AD39/$AD$11) -> 0 | AF39: =AD39 -> 0 | AG39: =IF(ISERR(AF39/$AF$11),"",AF39/$AF$11) -> 0 | AH39: =[1]東京工場!$L$39 -> 0 | AI39: =IF(ISERR(AH39/$AH$11),"",AH39/$AH$11) -> 0 | AJ39: =AH39 -> 0 | AK39: =IF(ISERR(AJ39/$AJ$11),"",AJ39/$AJ$11) -> 0 | AL39: =AD39+AH39 -> 0 | AM39: =IF(ISERR(AL39/$AL$11),"",AL39/AL$11) -> 0 | AN39: =AF39+AJ39 -> 0 | AO39: =IF(ISERR(AN39/$AN$11),"",AN39/$AN$11) -> 0 | AP39: =B39+Z39+AL39 -> 4445 | AQ39: =IF(ISERR(AP39/$AP$11),"",AP39/$AP$11) -> 5.3685903e-06 | AR39: =D39+AB39+AN39 -> 4445 | AS39: =IF(ISERR(AR39/$AR$11),"",AR39/$AR$11) -> 5.3685903e-06 | AT39: =[1]全社合計!$N$39 -> 4445 | AU39: =IF(ISERR(AT39/$AT$11),"",AT39/$AT$11) -> 4.5961785e-06 | AV39: =AT39 -> 4445 | AW39: =IF(ISERR(AV39/$AV$11),"",AV39/$AV$11) -> 4.5961785e-06 | AX39: =AP39-AT39 -> 0 | AY39: =IF(ISERROR(AP39/AT39),"",AP39/AT39) -> 1 | AZ39: =AR39-AV39 -> 0 | BA39: =IF(ISERROR(AR39/AV39),"",AR39/AV39) -> 1
A40: 会議費 | B40: =[1]本部!$L$40 -> 0 | C40: =IF(ISERR(B40/$B$11),"",B40/$B$11) | D40: =B40 -> 0 | E40: =IF(ISERR(D40/$D$11),"",D40/$D$11) | F40: =[1]本社営業!$L$40 -> 19547 | G40: =IF(ISERR(F40/$F$11),"",F40/$F$11) -> 3.6553357e-05 | H40: =F40 -> 19547 | I40: =IF(ISERR(H40/$H$11),"",H40/$H$11) -> 3.6553357e-05 | J40: =[1]東大阪!$L$40 -> 0 | K40: =IF(ISERR(J40/$J$11),"",J40/$J$11) -> 0 | L40: =J40 -> 0 | M40: =IF(ISERR(L40/$L$11),"",L40/$L$11) -> 0 | N40: =[1]南港工場!$L$40 -> 0 | O40: =IF(ISERR(N40/$N$11),"",N40/$N$11) -> 0 | P40: =N40 -> 0 | Q40: =IF(ISERR(P40/$P$11),"",P40/$P$11) -> 0 | R40: =[1]南港事務!$L$40 -> 0 | S40: =IF(ISERR(R40/$R$11),"",R40/$R$11) | T40: =R40 -> 0 | U40: =IF(ISERR(T40/$T$11),"",T40/$T$11) | V40: =N40+R40 -> 0 | W40: =IF(ISERR(V40/$V$11),"",V40/$V$11) -> 0 | X40: =P40+T40 -> 0 | Y40: =IF(ISERR(X40/$X$11),"",X40/$X$11) -> 0 | Z40: =F40+J40+N40+R40 -> 19547 | AA40: =IF(ISERR(Z40/$Z$11),"",Z40/$Z$11) -> 3.418187e-05 | AB40: =H40+L40+P40+T40 -> 19547 | AC40: =IF(ISERR(AB40/$AB$11),"",AB40/$AB$11) -> 3.418187e-05 | AD40: =[1]東京事務!$L$40 -> 0 | AE40: =IF(ISERR(AD40/$AD$11),"",AD40/$AD$11) -> 0 | AF40: =AD40 -> 0 | AG40: =IF(ISERR(AF40/$AF$11),"",AF40/$AF$11) -> 0 | AH40: =[1]東京工場!$L$40 -> 0 | AI40: =IF(ISERR(AH40/$AH$11),"",AH40/$AH$11) -> 0 | AJ40: =AH40 -> 0 | AK40: =IF(ISERR(AJ40/$AJ$11),"",AJ40/$AJ$11) -> 0 | AL40: =AD40+AH40 -> 0 | AM40: =IF(ISERR(AL40/$AL$11),"",AL40/AL$11) -> 0 | AN40: =AF40+AJ40 -> 0 | AO40: =IF(ISERR(AN40/$AN$11),"",AN40/$AN$11) -> 0 | AP40: =B40+Z40+AL40 -> 19547 | AQ40: =IF(ISERR(AP40/$AP$11),"",AP40/$AP$11) -> 2.3608512e-05 | AR40: =D40+AB40+AN40 -> 19547 | AS40: =IF(ISERR(AR40/$AR$11),"",AR40/$AR$11) -> 2.3608512e-05 | AT40: =[1]全社合計!$N$40 -> 28958 | AU40: =IF(ISERR(AT40/$AT$11),"",AT40/$AT$11) -> 2.9942888e-05 | AV40: =AT40 -> 28958 | AW40: =IF(ISERR(AV40/$AV$11),"",AV40/$AV$11) -> 2.9942888e-05 | AX40: =AP40-AT40 -> -9411 | AY40: =IF(ISERROR(AP40/AT40),"",AP40/AT40) -> 0.67501209 | AZ40: =AR40-AV40 -> -9411 | BA40: =IF(ISERROR(AR40/AV40),"",AR40/AV40) -> 0.67501209
A41: 組合費 | B41: =[1]本部!$L$41 -> 33800 | C41: =IF(ISERR(B41/$B$11),"",B41/$B$11) | D41: =B41 -> 33800 | E41: =IF(ISERR(D41/$D$11),"",D41/$D$11) | F41: =[1]本社営業!$L$41 -> 67000 | G41: =IF(ISERR(F41/$F$11),"",F41/$F$11) -> 0.0001252916 | H41: =F41 -> 67000 | I41: =IF(ISERR(H41/$H$11),"",H41/$H$11) -> 0.0001252916 | J41: =[1]東大阪!$L$41 -> 10000 | K41: =IF(ISERR(J41/$J$11),"",J41/$J$11) -> 0.0011263976 | L41: =J41 -> 10000 | M41: =IF(ISERR(L41/$L$11),"",L41/$L$11) -> 0.0011263976 | N41: =[1]南港工場!$L$41 -> 0 | O41: =IF(ISERR(N41/$N$11),"",N41/$N$11) -> 0 | P41: =N41 -> 0 | Q41: =IF(ISERR(P41/$P$11),"",P41/$P$11) -> 0 | R41: =[1]南港事務!$L$41 -> 0 | S41: =IF(ISERR(R41/$R$11),"",R41/$R$11) | T41: =R41 -> 0 | U41: =IF(ISERR(T41/$T$11),"",T41/$T$11) | V41: =N41+R41 -> 0 | W41: =IF(ISERR(V41/$V$11),"",V41/$V$11) -> 0 | X41: =P41+T41 -> 0 | Y41: =IF(ISERR(X41/$X$11),"",X41/$X$11) -> 0 | Z41: =F41+J41+N41+R41 -> 77000 | AA41: =IF(ISERR(Z41/$Z$11),"",Z41/$Z$11) -> 0.00013465002 | AB41: =H41+L41+P41+T41 -> 77000 | AC41: =IF(ISERR(AB41/$AB$11),"",AB41/$AB$11) -> 0.00013465002 | AD41: =[1]東京事務!$L$41 -> 143000 | AE41: =IF(ISERR(AD41/$AD$11),"",AD41/$AD$11) -> 0.00058058997 | AF41: =AD41 -> 143000 | AG41: =IF(ISERR(AF41/$AF$11),"",AF41/$AF$11) -> 0.00058058997 | AH41: =[1]東京工場!$L$41 -> 0 | AI41: =IF(ISERR(AH41/$AH$11),"",AH41/$AH$11) -> 0 | AJ41: =AH41 -> 0 | AK41: =IF(ISERR(AJ41/$AJ$11),"",AJ41/$AJ$11) -> 0 | AL41: =AD41+AH41 -> 143000 | AM41: =IF(ISERR(AL41/$AL$11),"",AL41/AL$11) -> 0.00055835116 | AN41: =AF41+AJ41 -> 143000 | AO41: =IF(ISERR(AN41/$AN$11),"",AN41/$AN$11) -> 0.00055835116 | AP41: =B41+Z41+AL41 -> 253800 | AQ41: =IF(ISERR(AP41/$AP$11),"",AP41/$AP$11) -> 0.00030653503 | AR41: =D41+AB41+AN41 -> 253800 | AS41: =IF(ISERR(AR41/$AR$11),"",AR41/$AR$11) -> 0.00030653503 | AT41: =[1]全社合計!$N$41 -> 335073 | AU41: =IF(ISERR(AT41/$AT$11),"",AT41/$AT$11) -> 0.00034646913 | AV41: =AT41 -> 335073 | AW41: =IF(ISERR(AV41/$AV$11),"",AV41/$AV$11) -> 0.00034646913 | AX41: =AP41-AT41 -> -81273 | AY41: =IF(ISERROR(AP41/AT41),"",AP41/AT41) -> 0.75744688 | AZ41: =AR41-AV41 -> -81273 | BA41: =IF(ISERROR(AR41/AV41),"",AR41/AV41) -> 0.75744688
A42: 広告費 | B42: =[1]本部!$L$42 -> 0 | C42: =IF(ISERR(B42/$B$11),"",B42/$B$11) | D42: =B42 -> 0 | E42: =IF(ISERR(D42/$D$11),"",D42/$D$11) | F42: =[1]本社営業!$L$42 -> 510000 | G42: =IF(ISERR(F42/$F$11),"",F42/$F$11) -> 0.00095371217 | H42: =F42 -> 510000 | I42: =IF(ISERR(H42/$H$11),"",H42/$H$11) -> 0.00095371217 | J42: =[1]東大阪!$L$42 -> 0 | K42: =IF(ISERR(J42/$J$11),"",J42/$J$11) -> 0 | L42: =J42 -> 0 | M42: =IF(ISERR(L42/$L$11),"",L42/$L$11) -> 0 | N42: =[1]南港工場!$L$42 -> 0 | O42: =IF(ISERR(N42/$N$11),"",N42/$N$11) -> 0 | P42: =N42 -> 0 | Q42: =IF(ISERR(P42/$P$11),"",P42/$P$11) -> 0 | R42: =[1]南港事務!$L$42 -> 0 | S42: =IF(ISERR(R42/$R$11),"",R42/$R$11) | T42: =R42 -> 0 | U42: =IF(ISERR(T42/$T$11),"",T42/$T$11) | V42: =N42+R42 -> 0 | W42: =IF(ISERR(V42/$V$11),"",V42/$V$11) -> 0 | X42: =P42+T42 -> 0 | Y42: =IF(ISERR(X42/$X$11),"",X42/$X$11) -> 0 | Z42: =F42+J42+N42+R42 -> 510000 | AA42: =IF(ISERR(Z42/$Z$11),"",Z42/$Z$11) -> 0.0008918378 | AB42: =H42+L42+P42+T42 -> 510000 | AC42: =IF(ISERR(AB42/$AB$11),"",AB42/$AB$11) -> 0.0008918378 | AD42: =[1]東京事務!$L$42 -> 0 | AE42: =IF(ISERR(AD42/$AD$11),"",AD42/$AD$11) -> 0 | AF42: =AD42 -> 0 | AG42: =IF(ISERR(AF42/$AF$11),"",AF42/$AF$11) -> 0 | AH42: =[1]東京工場!$L$42 -> 0 | AI42: =IF(ISERR(AH42/$AH$11),"",AH42/$AH$11) -> 0 | AJ42: =AH42 -> 0 | AK42: =IF(ISERR(AJ42/$AJ$11),"",AJ42/$AJ$11) -> 0 | AL42: =AD42+AH42 -> 0 | AM42: =IF(ISERR(AL42/$AL$11),"",AL42/AL$11) -> 0 | AN42: =AF42+AJ42 -> 0 | AO42: =IF(ISERR(AN42/$AN$11),"",AN42/$AN$11) -> 0 | AP42: =B42+Z42+AL42 -> 510000 | AQ42: =IF(ISERR(AP42/$AP$11),"",AP42/$AP$11) -> 0.00061596874 | AR42: =D42+AB42+AN42 -> 510000 | AS42: =IF(ISERR(AR42/$AR$11),"",AR42/$AR$11) -> 0.00061596874 | AT42: =[1]全社合計!$N$42 -> 0 | AU42: =IF(ISERR(AT42/$AT$11),"",AT42/$AT$11) -> 0 | AV42: =AT42 -> 0 | AW42: =IF(ISERR(AV42/$AV$11),"",AV42/$AV$11) -> 0 | AX42: =AP42-AT42 -> 510000 | AY42: =IF(ISERROR(AP42/AT42),"",AP42/AT42) | AZ42: =AR42-AV42 -> 510000 | BA42: =IF(ISERROR(AR42/AV42),"",AR42/AV42)
A43: 運搬費 | B43: =[1]本部!$L$43 -> 0 | C43: =IF(ISERR(B43/$B$11),"",B43/$B$11) | D43: =B43 -> 0 | E43: =IF(ISERR(D43/$D$11),"",D43/$D$11) | F43: =[1]本社営業!$L$43 -> 9330033 | G43: =IF(ISERR(F43/$F$11),"",F43/$F$11) -> 0.017447384 | H43: =F43 -> 9330033 | I43: =IF(ISERR(H43/$H$11),"",H43/$H$11) -> 0.017447384 | J43: =[1]東大阪!$L$43 -> -510100 | K43: =IF(ISERR(J43/$J$11),"",J43/$J$11) -> -0.05745754 | L43: =J43 -> -510100 | M43: =IF(ISERR(L43/$L$11),"",L43/$L$11) -> -0.05745754 | N43: =[1]南港工場!$L$43 -> 1233535 | O43: =IF(ISERR(N43/$N$11),"",N43/$N$11) -> 0.043707548 | P43: =N43 -> 1233535 | Q43: =IF(ISERR(P43/$P$11),"",P43/$P$11) -> 0.043707548 | R43: =[1]南港事務!$L$43 -> 0 | S43: =IF(ISERR(R43/$R$11),"",R43/$R$11) | T43: =R43 -> 0 | U43: =IF(ISERR(T43/$T$11),"",T43/$T$11) | V43: =N43+R43 -> 1233535 | W43: =IF(ISERR(V43/$V$11),"",V43/$V$11) -> 0.043707548 | X43: =P43+T43 -> 1233535 | Y43: =IF(ISERR(X43/$X$11),"",X43/$X$11) -> 0.043707548 | Z43: =F43+J43+N43+R43 -> 10053468 | AA43: =IF(ISERR(Z43/$Z$11),"",Z43/$Z$11) -> 0.017580515 | AB43: =H43+L43+P43+T43 -> 10053468 | AC43: =IF(ISERR(AB43/$AB$11),"",AB43/$AB$11) -> 0.017580515 | AD43: =[1]東京事務!$L$43 -> 3011525 | AE43: =IF(ISERR(AD43/$AD$11),"",AD43/$AD$11) -> 0.012227001 | AF43: =AD43 -> 3011525 | AG43: =IF(ISERR(AF43/$AF$11),"",AF43/$AF$11) -> 0.012227001 | AH43: =[1]東京工場!$L$43 -> 0 | AI43: =IF(ISERR(AH43/$AH$11),"",AH43/$AH$11) -> 0 | AJ43: =AH43 -> 0 | AK43: =IF(ISERR(AJ43/$AJ$11),"",AJ43/$AJ$11) -> 0 | AL43: =AD43+AH43 -> 3011525 | AM43: =IF(ISERR(AL43/$AL$11),"",AL43/AL$11) -> 0.011758661 | AN43: =AF43+AJ43 -> 3011525 | AO43: =IF(ISERR(AN43/$AN$11),"",AN43/$AN$11) -> 0.011758661 | AP43: =B43+Z43+AL43 -> 13064993 | AQ43: =IF(ISERR(AP43/$AP$11),"",AP43/$AP$11) -> 0.015779661 | AR43: =D43+AB43+AN43 -> 13064993 | AS43: =IF(ISERR(AR43/$AR$11),"",AR43/$AR$11) -> 0.015779661 | AT43: =[1]全社合計!$N$43 -> 12762673 | AU43: =IF(ISERR(AT43/$AT$11),"",AT43/$AT$11) -> 0.013196743 | AV43: =AT43 -> 12762673 | AW43: =IF(ISERR(AV43/$AV$11),"",AV43/$AV$11) -> 0.013196743 | AX43: =AP43-AT43 -> 302320 | AY43: =IF(ISERROR(AP43/AT43),"",AP43/AT43) -> 1.0236878 | AZ43: =AR43-AV43 -> 302320 | BA43: =IF(ISERROR(AR43/AV43),"",AR43/AV43) -> 1.0236878
A44: 減価償却費 | B44: =[1]本部!$L$44 -> -165000 | C44: =IF(ISERR(B44/$B$11),"",B44/$B$11) | D44: =B44 -> -165000 | E44: =IF(ISERR(D44/$D$11),"",D44/$D$11) | F44: =[1]本社営業!$L$44 -> 475000 | G44: =IF(ISERR(F44/$F$11),"",F44/$F$11) -> 0.00088826134 | H44: =F44 -> 475000 | I44: =IF(ISERR(H44/$H$11),"",H44/$H$11) -> 0.00088826134 | J44: =[1]東大阪!$L$44 -> 375000 | K44: =IF(ISERR(J44/$J$11),"",J44/$J$11) -> 0.042239909 | L44: =J44 -> 375000 | M44: =IF(ISERR(L44/$L$11),"",L44/$L$11) -> 0.042239909 | N44: =[1]南港工場!$L$44 -> 360000 | O44: =IF(ISERR(N44/$N$11),"",N44/$N$11) -> 0.012755793 | P44: =N44 -> 360000 | Q44: =IF(ISERR(P44/$P$11),"",P44/$P$11) -> 0.012755793 | R44: =[1]南港事務!$L$44 -> 80000 | S44: =IF(ISERR(R44/$R$11),"",R44/$R$11) | T44: =R44 -> 80000 | U44: =IF(ISERR(T44/$T$11),"",T44/$T$11) | V44: =N44+R44 -> 440000 | W44: =IF(ISERR(V44/$V$11),"",V44/$V$11) -> 0.015590414 | X44: =P44+T44 -> 440000 | Y44: =IF(ISERR(X44/$X$11),"",X44/$X$11) -> 0.015590414 | Z44: =F44+J44+N44+R44 -> 1290000 | AA44: =IF(ISERR(Z44/$Z$11),"",Z44/$Z$11) -> 0.002255825 | AB44: =H44+L44+P44+T44 -> 1290000 | AC44: =IF(ISERR(AB44/$AB$11),"",AB44/$AB$11) -> 0.002255825 | AD44: =[1]東京事務!$L$44 -> 55000 | AE44: =IF(ISERR(AD44/$AD$11),"",AD44/$AD$11) -> 0.00022330383 | AF44: =AD44 -> 55000 | AG44: =IF(ISERR(AF44/$AF$11),"",AF44/$AF$11) -> 0.00022330383 | AH44: =[1]東京工場!$L$44 -> 275000 | AI44: =IF(ISERR(AH44/$AH$11),"",AH44/$AH$11) -> 0.02803252 | AJ44: =AH44 -> 275000 | AK44: =IF(ISERR(AJ44/$AJ$11),"",AJ44/$AJ$11) -> 0.02803252 | AL44: =AD44+AH44 -> 330000 | AM44: =IF(ISERR(AL44/$AL$11),"",AL44/AL$11) -> 0.0012885027 | AN44: =AF44+AJ44 -> 330000 | AO44: =IF(ISERR(AN44/$AN$11),"",AN44/$AN$11) -> 0.0012885027 | AP44: =B44+Z44+AL44 -> 1455000 | AQ44: =IF(ISERR(AP44/$AP$11),"",AP44/$AP$11) -> 0.0017573226 | AR44: =D44+AB44+AN44 -> 1455000 | AS44: =IF(ISERR(AR44/$AR$11),"",AR44/$AR$11) -> 0.0017573226 | AT44: =[1]全社合計!$N$44 -> 1280000 | AU44: =IF(ISERR(AT44/$AT$11),"",AT44/$AT$11) -> 0.001323534 | AV44: =AT44 -> 1280000 | AW44: =IF(ISERR(AV44/$AV$11),"",AV44/$AV$11) -> 0.001323534 | AX44: =AP44-AT44 -> 175000 | AY44: =IF(ISERROR(AP44/AT44),"",AP44/AT44) -> 1.1367188 | AZ44: =AR44-AV44 -> 175000 | BA44: =IF(ISERROR(AR44/AV44),"",AR44/AV44) -> 1.1367188
A45: 修繕引当金繰入 | B45: =[1]本部!$L$45 -> 0 | C45: =IF(ISERR(B45/$B$11),"",B45/$B$11) | D45: =B45 -> 0 | E45: =IF(ISERR(D45/$D$11),"",D45/$D$11) | F45: =[1]本社営業!$L$45 -> 0 | G45: =IF(ISERR(F45/$F$11),"",F45/$F$11) -> 0 | H45: =F45 -> 0 | I45: =IF(ISERR(H45/$H$11),"",H45/$H$11) -> 0 | J45: =[1]東大阪!$L$45 -> 0 | K45: =IF(ISERR(J45/$J$11),"",J45/$J$11) -> 0 | L45: =J45 -> 0 | M45: =IF(ISERR(L45/$L$11),"",L45/$L$11) -> 0 | N45: =[1]南港工場!$L$45 -> 0 | O45: =IF(ISERR(N45/$N$11),"",N45/$N$11) -> 0 | P45: =N45 -> 0 | Q45: =IF(ISERR(P45/$P$11),"",P45/$P$11) -> 0 | R45: =[1]南港事務!$L$45 -> 0 | S45: =IF(ISERR(R45/$R$11),"",R45/$R$11) | T45: =R45 -> 0 | U45: =IF(ISERR(T45/$T$11),"",T45/$T$11) | V45: =N45+R45 -> 0 | W45: =IF(ISERR(V45/$V$11),"",V45/$V$11) -> 0 | X45: =P45+T45 -> 0 | Y45: =IF(ISERR(X45/$X$11),"",X45/$X$11) -> 0 | Z45: =F45+J45+N45+R45 -> 0 | AA45: =IF(ISERR(Z45/$Z$11),"",Z45/$Z$11) -> 0 | AB45: =H45+L45+P45+T45 -> 0 | AC45: =IF(ISERR(AB45/$AB$11),"",AB45/$AB$11) -> 0 | AD45: =[1]東京事務!$L$45 -> 0 | AE45: =IF(ISERR(AD45/$AD$11),"",AD45/$AD$11) -> 0 | AF45: =AD45 -> 0 | AG45: =IF(ISERR(AF45/$AF$11),"",AF45/$AF$11) -> 0 | AH45: =[1]東京工場!$L$45 -> 0 | AI45: =IF(ISERR(AH45/$AH$11),"",AH45/$AH$11) -> 0 | AJ45: =AH45 -> 0 | AK45: =IF(ISERR(AJ45/$AJ$11),"",AJ45/$AJ$11) -> 0 | AL45: =AD45+AH45 -> 0 | AM45: =IF(ISERR(AL45/$AL$11),"",AL45/AL$11) -> 0 | AN45: =AF45+AJ45 -> 0 | AO45: =IF(ISERR(AN45/$AN$11),"",AN45/$AN$11) -> 0 | AP45: =B45+Z45+AL45 -> 0 | AQ45: =IF(ISERR(AP45/$AP$11),"",AP45/$AP$11) -> 0 | AR45: =D45+AB45+AN45 -> 0 | AS45: =IF(ISERR(AR45/$AR$11),"",AR45/$AR$11) -> 0 | AT45: =[1]全社合計!$N$45 -> 0 | AU45: =IF(ISERR(AT45/$AT$11),"",AT45/$AT$11) -> 0 | AV45: =AT45 -> 0 | AW45: =IF(ISERR(AV45/$AV$11),"",AV45/$AV$11) -> 0 | AX45: =AP45-AT45 -> 0 | AY45: =IF(ISERROR(AP45/AT45),"",AP45/AT45) | AZ45: =AR45-AV45 -> 0 | BA45: =IF(ISERROR(AR45/AV45),"",AR45/AV45)
A46: 雑費 | B46: =[1]本部!$L$46 -> 30000 | C46: =IF(ISERR(B46/$B$11),"",B46/$B$11) | D46: =B46 -> 30000 | E46: =IF(ISERR(D46/$D$11),"",D46/$D$11) | F46: =[1]本社営業!$L$46 -> 0 | G46: =IF(ISERR(F46/$F$11),"",F46/$F$11) -> 0 | H46: =F46 -> 0 | I46: =IF(ISERR(H46/$H$11),"",H46/$H$11) -> 0 | J46: =[1]東大阪!$L$46 -> 0 | K46: =IF(ISERR(J46/$J$11),"",J46/$J$11) -> 0 | L46: =J46 -> 0 | M46: =IF(ISERR(L46/$L$11),"",L46/$L$11) -> 0 | N46: =[1]南港工場!$L$46 -> 0 | O46: =IF(ISERR(N46/$N$11),"",N46/$N$11) -> 0 | P46: =N46 -> 0 | Q46: =IF(ISERR(P46/$P$11),"",P46/$P$11) -> 0 | R46: =[1]南港事務!$L$46 -> 0 | S46: =IF(ISERR(R46/$R$11),"",R46/$R$11) | T46: =R46 -> 0 | U46: =IF(ISERR(T46/$T$11),"",T46/$T$11) | V46: =N46+R46 -> 0 | W46: =IF(ISERR(V46/$V$11),"",V46/$V$11) -> 0 | X46: =P46+T46 -> 0 | Y46: =IF(ISERR(X46/$X$11),"",X46/$X$11) -> 0 | Z46: =F46+J46+N46+R46 -> 0 | AA46: =IF(ISERR(Z46/$Z$11),"",Z46/$Z$11) -> 0 | AB46: =H46+L46+P46+T46 -> 0 | AC46: =IF(ISERR(AB46/$AB$11),"",AB46/$AB$11) -> 0 | AD46: =[1]東京事務!$L$46 -> 0 | AE46: =IF(ISERR(AD46/$AD$11),"",AD46/$AD$11) -> 0 | AF46: =AD46 -> 0 | AG46: =IF(ISERR(AF46/$AF$11),"",AF46/$AF$11) -> 0 | AH46: =[1]東京工場!$L$46 -> 0 | AI46: =IF(ISERR(AH46/$AH$11),"",AH46/$AH$11) -> 0 | AJ46: =AH46 -> 0 | AK46: =IF(ISERR(AJ46/$AJ$11),"",AJ46/$AJ$11) -> 0 | AL46: =AD46+AH46 -> 0 | AM46: =IF(ISERR(AL46/$AL$11),"",AL46/AL$11) -> 0 | AN46: =AF46+AJ46 -> 0 | AO46: =IF(ISERR(AN46/$AN$11),"",AN46/$AN$11) -> 0 | AP46: =B46+Z46+AL46 -> 30000 | AQ46: =IF(ISERR(AP46/$AP$11),"",AP46/$AP$11) -> 3.6233455e-05 | AR46: =D46+AB46+AN46 -> 30000 | AS46: =IF(ISERR(AR46/$AR$11),"",AR46/$AR$11) -> 3.6233455e-05 | AT46: =[1]全社合計!$N$46 -> 30000 | AU46: =IF(ISERR(AT46/$AT$11),"",AT46/$AT$11) -> 3.1020327e-05 | AV46: =AT46 -> 30000 | AW46: =IF(ISERR(AV46/$AV$11),"",AV46/$AV$11) -> 3.1020327e-05 | AX46: =AP46-AT46 -> 0 | AY46: =IF(ISERROR(AP46/AT46),"",AP46/AT46) -> 1 | AZ46: =AR46-AV46 -> 0 | BA46: =IF(ISERROR(AR46/AV46),"",AR46/AV46) -> 1
A47: 《経費合計》 | B47: =SUM(B19:B46) -> 8255470 | C47: =IF(ISERR(B47/$B$11),"",B47/$B$11) | D47: =B47 -> 8255470 | E47: =IF(ISERR(D47/$D$11),"",D47/$D$11) | F47: =SUM(F19:F46) -> 24003531 | G47: =IF(ISERR(F47/$F$11),"",F47/$F$11) -> 0.044887176 | H47: =F47 -> 24003531 | I47: =IF(ISERR(H47/$H$11),"",H47/$H$11) -> 0.044887176 | J47: =SUM(J19:J46) -> 5491350 | K47: =IF(ISERR(J47/$J$11),"",J47/$J$11) -> 0.61854433 | L47: =J47 -> 5491350 | M47: =IF(ISERR(L47/$L$11),"",L47/$L$11) -> 0.61854433 | N47: =SUM(N19:N46) -> 11311174 | O47: =IF(ISERR(N47/$N$11),"",N47/$N$11) -> 0.4007861 | P47: =N47 -> 11311174 | Q47: =IF(ISERR(P47/$P$11),"",P47/$P$11) -> 0.4007861 | R47: =SUM(R19:R46) -> 3387710 | S47: =IF(ISERR(R47/$R$11),"",R47/$R$11) | T47: =R47 -> 3387710 | U47: =IF(ISERR(T47/$T$11),"",T47/$T$11) | V47: =N47+R47 -> 14698884 | W47: =IF(ISERR(V47/$V$11),"",V47/$V$11) -> 0.52082201 | X47: =P47+T47 -> 14698884 | Y47: =IF(ISERR(X47/$X$11),"",X47/$X$11) -> 0.52082201 | Z47: =F47+J47+N47+R47 -> 44193765 | AA47: =IF(ISERR(Z47/$Z$11),"",Z47/$Z$11) -> 0.077281706 | AB47: =H47+L47+P47+T47 -> 44193765 | AC47: =IF(ISERR(AB47/$AB$11),"",AB47/$AB$11) -> 0.077281706 | AD47: =SUM(AD19:AD46) -> 9102098 | AE47: =IF(ISERR(AD47/$AD$11),"",AD47/$AD$11) -> 0.036955152 | AF47: =AD47 -> 9102098 | AG47: =IF(ISERR(AF47/$AF$11),"",AF47/$AF$11) -> 0.036955152 | AH47: =SUM(AH19:AH46) -> 6078963 | AI47: =IF(ISERR(AH47/$AH$11),"",AH47/$AH$11) -> 0.61966782 | AJ47: =AH47 -> 6078963 | AK47: =IF(ISERR(AJ47/$AJ$11),"",AJ47/$AJ$11) -> 0.61966782 | AL47: =AD47+AH47 -> 15181061 | AM47: =IF(ISERR(AL47/$AL$11),"",AL47/AL$11) -> 0.059275266 | AN47: =AF47+AJ47 -> 15181061 | AO47: =IF(ISERR(AN47/$AN$11),"",AN47/$AN$11) -> 0.059275266 | AP47: =B47+Z47+AL47 -> 67630296 | AQ47: =IF(ISERR(AP47/$AP$11),"",AP47/$AP$11) -> 0.081682644 | AR47: =D47+AB47+AN47 -> 67630296 | AS47: =IF(ISERR(AR47/$AR$11),"",AR47/$AR$11) -> 0.081682644 | AT47: =SUM(AT19:AT46) -> 65260383 | AU47: =IF(ISERR(AT47/$AT$11),"",AT47/$AT$11) -> 0.067479947 | AV47: =AT47 -> 65260383 | AW47: =IF(ISERR(AV47/$AV$11),"",AV47/$AV$11) -> 0.067479947 | AX47: =AP47-AT47 -> 2369913 | AY47: =IF(ISERROR(AP47/AT47),"",AP47/AT47) -> 1.0363147 | AZ47: =AR47-AV47 -> 2369913 | BA47: =IF(ISERROR(AR47/AV47),"",AR47/AV47) -> 1.0363147
A48: 【営業利益】 | B48: =+B18-B47 -> -8255470 | C48: =IF(ISERR(B48/$B$11),"",B48/$B$11) | D48: =B48 -> -8255470 | E48: =IF(ISERR(D48/$D$11),"",D48/$D$11) | F48: =F18-F47 -> 47284497 | G48: =IF(ISERR(F48/$F$11),"",F48/$F$11) -> 0.088423138 | H48: =F48 -> 47284497 | I48: =IF(ISERR(H48/$H$11),"",H48/$H$11) -> 0.088423138 | J48: =J18-J47 -> 2890625 | K48: =IF(ISERR(J48/$J$11),"",J48/$J$11) -> 0.3255993 | L48: =J48 -> 2890625 | M48: =IF(ISERR(L48/$L$11),"",L48/$L$11) -> 0.3255993 | N48: =N18-N47 -> 14769958 | O48: =IF(ISERR(N48/$N$11),"",N48/$N$11) -> 0.52334036 | P48: =N48 -> 14769958 | Q48: =IF(ISERR(P48/$P$11),"",P48/$P$11) -> 0.52334036 | R48: =R18-R47 -> -3387710 | S48: =IF(ISERR(R48/$R$11),"",R48/$R$11) | T48: =R48 -> -3387710 | U48: =IF(ISERR(T48/$T$11),"",T48/$T$11) | V48: =N48+R48 -> 11382248 | W48: =IF(ISERR(V48/$V$11),"",V48/$V$11) -> 0.40330444 | X48: =P48+T48 -> 11382248 | Y48: =IF(ISERR(X48/$X$11),"",X48/$X$11) -> 0.40330444 | Z48: =F48+J48+N48+R48 -> 61557370 | AA48: =IF(ISERR(Z48/$Z$11),"",Z48/$Z$11) -> 0.10764547 | AB48: =H48+L48+P48+T48 -> 61557370 | AC48: =IF(ISERR(AB48/$AB$11),"",AB48/$AB$11) -> 0.10764547 | AD48: =AD18-AD47 -> 12259108 | AE48: =IF(ISERR(AD48/$AD$11),"",AD48/$AD$11) -> 0.049772833 | AF48: =AD48 -> 12259108 | AG48: =IF(ISERR(AF48/$AF$11),"",AF48/$AF$11) -> 0.049772833 | AH48: =AH18-AH47 -> 3731072 | AI48: =IF(ISERR(AH48/$AH$11),"",AH48/$AH$11) -> 0.38033218 | AJ48: =AH48 -> 3731072 | AK48: =IF(ISERR(AJ48/$AJ$11),"",AJ48/$AJ$11) -> 0.38033218 | AL48: =AD48+AH48 -> 15990180 | AM48: =IF(ISERR(AL48/$AL$11),"",AL48/AL$11) -> 0.062434514 | AN48: =AF48+AJ48 -> 15990180 | AO48: =IF(ISERR(AN48/$AN$11),"",AN48/$AN$11) -> 0.062434514 | AP48: =B48+Z48+AL48 -> 69292080 | AQ48: =IF(ISERR(AP48/$AP$11),"",AP48/$AP$11) -> 0.083689717 | AR48: =D48+AB48+AN48 -> 69292080 | AS48: =IF(ISERR(AR48/$AR$11),"",AR48/$AR$11) -> 0.083689717 | AT48: =AT18-AT47 -> 81831966 | AU48: =IF(ISERR(AT48/$AT$11),"",AT48/$AT$11) -> 0.084615145 | AV48: =AT48 -> 81831966 | AW48: =IF(ISERR(AV48/$AV$11),"",AV48/$AV$11) -> 0.084615145 | AX48: =AP48-AT48 -> -12539886 | AY48: =IF(ISERROR(AP48/AT48),"",AP48/AT48) -> 0.84676054 | AZ48: =AR48-AV48 -> -12539886 | BA48: =IF(ISERROR(AR48/AV48),"",AR48/AV48) -> 0.84676054
A49: 受取利息配当金 | B49: =[1]本部!$L$49 -> 1441751 | C49: =IF(ISERR(B49/$B$11),"",B49/$B$11) | D49: =B49 -> 1441751 | E49: =IF(ISERR(D49/$D$11),"",D49/$D$11) | F49: =[1]本社営業!$L$49 -> 0 | G49: =IF(ISERR(F49/$F$11),"",F49/$F$11) -> 0 | H49: =F49 -> 0 | I49: =IF(ISERR(H49/$H$11),"",H49/$H$11) -> 0 | J49: =[1]東大阪!$L$49 -> 0 | K49: =IF(ISERR(J49/$J$11),"",J49/$J$11) -> 0 | L49: =J49 -> 0 | M49: =IF(ISERR(L49/$L$11),"",L49/$L$11) -> 0 | N49: =[1]南港工場!$L$49 -> 0 | O49: =IF(ISERR(N49/$N$11),"",N49/$N$11) -> 0 | P49: =N49 -> 0 | Q49: =IF(ISERR(P49/$P$11),"",P49/$P$11) -> 0 | R49: =[1]南港事務!$L$49 -> 0 | S49: =IF(ISERR(R49/$R$11),"",R49/$R$11) | T49: =R49 -> 0 | U49: =IF(ISERR(T49/$T$11),"",T49/$T$11) | V49: =N49+R49 -> 0 | W49: =IF(ISERR(V49/$V$11),"",V49/$V$11) -> 0 | X49: =P49+T49 -> 0 | Y49: =IF(ISERR(X49/$X$11),"",X49/$X$11) -> 0 | Z49: =F49+J49+N49+R49 -> 0 | AA49: =IF(ISERR(Z49/$Z$11),"",Z49/$Z$11) -> 0 | AB49: =H49+L49+P49+T49 -> 0 | AC49: =IF(ISERR(AB49/$AB$11),"",AB49/$AB$11) -> 0 | AD49: =[1]東京事務!$L$49 -> 0 | AE49: =IF(ISERR(AD49/$AD$11),"",AD49/$AD$11) -> 0 | AF49: =AD49 -> 0 | AG49: =IF(ISERR(AF49/$AF$11),"",AF49/$AF$11) -> 0 | AH49: =[1]東京工場!$L$49 -> 0 | AI49: =IF(ISERR(AH49/$AH$11),"",AH49/$AH$11) -> 0 | AJ49: =AH49 -> 0 | AK49: =IF(ISERR(AJ49/$AJ$11),"",AJ49/$AJ$11) -> 0 | AL49: =AD49+AH49 -> 0 | AM49: =IF(ISERR(AL49/$AL$11),"",AL49/AL$11) -> 0 | AN49: =AF49+AJ49 -> 0 | AO49: =IF(ISERR(AN49/$AN$11),"",AN49/$AN$11) -> 0 | AP49: =B49+Z49+AL49 -> 1441751 | AQ49: =IF(ISERR(AP49/$AP$11),"",AP49/$AP$11) -> 0.0017413207 | AR49: =D49+AB49+AN49 -> 1441751 | AS49: =IF(ISERR(AR49/$AR$11),"",AR49/$AR$11) -> 0.0017413207 | AT49: =[1]全社合計!$N$49 -> 1178102 | AU49: =IF(ISERR(AT49/$AT$11),"",AT49/$AT$11) -> 0.0012181703 | AV49: =AT49 -> 1178102 | AW49: =IF(ISERR(AV49/$AV$11),"",AV49/$AV$11) -> 0.0012181703 | AX49: =AP49-AT49 -> 263649 | AY49: =IF(ISERROR(AP49/AT49),"",AP49/AT49) -> 1.2237913 | AZ49: =AR49-AV49 -> 263649 | BA49: =IF(ISERROR(AR49/AV49),"",AR49/AV49) -> 1.2237913
A50: 有価証券売却益 | B50: =[1]本部!$L$50 -> 0 | C50: =IF(ISERR(B50/$B$11),"",B50/$B$11) | D50: =B50 -> 0 | E50: =IF(ISERR(D50/$D$11),"",D50/$D$11) | F50: =[1]本社営業!$L$50 -> 0 | G50: =IF(ISERR(F50/$F$11),"",F50/$F$11) -> 0 | H50: =F50 -> 0 | I50: =IF(ISERR(H50/$H$11),"",H50/$H$11) -> 0 | J50: =[1]東大阪!$L$50 -> 0 | K50: =IF(ISERR(J50/$J$11),"",J50/$J$11) -> 0 | L50: =J50 -> 0 | M50: =IF(ISERR(L50/$L$11),"",L50/$L$11) -> 0 | N50: =[1]南港工場!$L$50 -> 0 | O50: =IF(ISERR(N50/$N$11),"",N50/$N$11) -> 0 | P50: =N50 -> 0 | Q50: =IF(ISERR(P50/$P$11),"",P50/$P$11) -> 0 | R50: =[1]南港事務!$L$50 -> 0 | S50: =IF(ISERR(R50/$R$11),"",R50/$R$11) | T50: =R50 -> 0 | U50: =IF(ISERR(T50/$T$11),"",T50/$T$11) | V50: =N50+R50 -> 0 | W50: =IF(ISERR(V50/$V$11),"",V50/$V$11) -> 0 | X50: =P50+T50 -> 0 | Y50: =IF(ISERR(X50/$X$11),"",X50/$X$11) -> 0 | Z50: =F50+J50+N50+R50 -> 0 | AA50: =IF(ISERR(Z50/$Z$11),"",Z50/$Z$11) -> 0 | AB50: =H50+L50+P50+T50 -> 0 | AC50: =IF(ISERR(AB50/$AB$11),"",AB50/$AB$11) -> 0 | AD50: =[1]東京事務!$L$50 -> 0 | AE50: =IF(ISERR(AD50/$AD$11),"",AD50/$AD$11) -> 0 | AF50: =AD50 -> 0 | AG50: =IF(ISERR(AF50/$AF$11),"",AF50/$AF$11) -> 0 | AH50: =[1]東京工場!$L$50 -> 0 | AI50: =IF(ISERR(AH50/$AH$11),"",AH50/$AH$11) -> 0 | AJ50: =AH50 -> 0 | AK50: =IF(ISERR(AJ50/$AJ$11),"",AJ50/$AJ$11) -> 0 | AL50: =AD50+AH50 -> 0 | AM50: =IF(ISERR(AL50/$AL$11),"",AL50/AL$11) -> 0 | AN50: =AF50+AJ50 -> 0 | AO50: =IF(ISERR(AN50/$AN$11),"",AN50/$AN$11) -> 0 | AP50: =B50+Z50+AL50 -> 0 | AQ50: =IF(ISERR(AP50/$AP$11),"",AP50/$AP$11) -> 0 | AR50: =D50+AB50+AN50 -> 0 | AS50: =IF(ISERR(AR50/$AR$11),"",AR50/$AR$11) -> 0 | AT50: =[1]全社合計!$N$50 -> 0 | AU50: =IF(ISERR(AT50/$AT$11),"",AT50/$AT$11) -> 0 | AV50: =AT50 -> 0 | AW50: =IF(ISERR(AV50/$AV$11),"",AV50/$AV$11) -> 0 | AX50: =AP50-AT50 -> 0 | AY50: =IF(ISERROR(AP50/AT50),"",AP50/AT50) | AZ50: =AR50-AV50 -> 0 | BA50: =IF(ISERROR(AR50/AV50),"",AR50/AV50)
A51: 賃貸料収入 | B51: =[1]本部!$L$51 -> 1063000 | C51: =IF(ISERR(B51/$B$11),"",B51/$B$11) | D51: =B51 -> 1063000 | E51: =IF(ISERR(D51/$D$11),"",D51/$D$11) | F51: =[1]本社営業!$L$51 -> 0 | G51: =IF(ISERR(F51/$F$11),"",F51/$F$11) -> 0 | H51: =F51 -> 0 | I51: =IF(ISERR(H51/$H$11),"",H51/$H$11) -> 0 | J51: =[1]東大阪!$L$51 -> 850000 | K51: =IF(ISERR(J51/$J$11),"",J51/$J$11) -> 0.095743794 | L51: =J51 -> 850000 | M51: =IF(ISERR(L51/$L$11),"",L51/$L$11) -> 0.095743794 | N51: =[1]南港工場!$L$51 -> 100000 | O51: =IF(ISERR(N51/$N$11),"",N51/$N$11) -> 0.0035432759 | P51: =N51 -> 100000 | Q51: =IF(ISERR(P51/$P$11),"",P51/$P$11) -> 0.0035432759 | R51: =[1]南港事務!$L$51 -> 0 | S51: =IF(ISERR(R51/$R$11),"",R51/$R$11) | T51: =R51 -> 0 | U51: =IF(ISERR(T51/$T$11),"",T51/$T$11) | V51: =N51+R51 -> 100000 | W51: =IF(ISERR(V51/$V$11),"",V51/$V$11) -> 0.0035432759 | X51: =P51+T51 -> 100000 | Y51: =IF(ISERR(X51/$X$11),"",X51/$X$11) -> 0.0035432759 | Z51: =F51+J51+N51+R51 -> 950000 | AA51: =IF(ISERR(Z51/$Z$11),"",Z51/$Z$11) -> 0.0016612665 | AB51: =H51+L51+P51+T51 -> 950000 | AC51: =IF(ISERR(AB51/$AB$11),"",AB51/$AB$11) -> 0.0016612665 | AD51: =[1]東京事務!$L$51 -> 0 | AE51: =IF(ISERR(AD51/$AD$11),"",AD51/$AD$11) -> 0 | AF51: =AD51 -> 0 | AG51: =IF(ISERR(AF51/$AF$11),"",AF51/$AF$11) -> 0 | AH51: =[1]東京工場!$L$51 -> 0 | AI51: =IF(ISERR(AH51/$AH$11),"",AH51/$AH$11) -> 0 | AJ51: =AH51 -> 0 | AK51: =IF(ISERR(AJ51/$AJ$11),"",AJ51/$AJ$11) -> 0 | AL51: =AD51+AH51 -> 0 | AM51: =IF(ISERR(AL51/$AL$11),"",AL51/AL$11) -> 0 | AN51: =AF51+AJ51 -> 0 | AO51: =IF(ISERR(AN51/$AN$11),"",AN51/$AN$11) -> 0 | AP51: =B51+Z51+AL51 -> 2013000 | AQ51: =IF(ISERR(AP51/$AP$11),"",AP51/$AP$11) -> 0.0024312649 | AR51: =D51+AB51+AN51 -> 2013000 | AS51: =IF(ISERR(AR51/$AR$11),"",AR51/$AR$11) -> 0.0024312649 | AT51: =[1]全社合計!$N$51 -> 1910000 | AU51: =IF(ISERR(AT51/$AT$11),"",AT51/$AT$11) -> 0.0019749608 | AV51: =AT51 -> 1910000 | AW51: =IF(ISERR(AV51/$AV$11),"",AV51/$AV$11) -> 0.0019749608 | AX51: =AP51-AT51 -> 103000 | AY51: =IF(ISERROR(AP51/AT51),"",AP51/AT51) -> 1.0539267 | AZ51: =AR51-AV51 -> 103000 | BA51: =IF(ISERROR(AR51/AV51),"",AR51/AV51) -> 1.0539267
A52: 貸倒引当金 | B52: =[1]本部!$L$52 -> 0 | C52: =IF(ISERR(B52/$B$11),"",B52/$B$11) | D52: =B52 -> 0 | E52: =IF(ISERR(D52/$D$11),"",D52/$D$11) | F52: =[1]本社営業!$L$52 -> 0 | G52: =IF(ISERR(F52/$F$11),"",F52/$F$11) -> 0 | H52: =F52 -> 0 | I52: =IF(ISERR(H52/$H$11),"",H52/$H$11) -> 0 | J52: =[1]東大阪!$L$52 -> 0 | K52: =IF(ISERR(J52/$J$11),"",J52/$J$11) -> 0 | L52: =J52 -> 0 | M52: =IF(ISERR(L52/$L$11),"",L52/$L$11) -> 0 | N52: =[1]南港工場!$L$52 -> 0 | O52: =IF(ISERR(N52/$N$11),"",N52/$N$11) -> 0 | P52: =N52 -> 0 | Q52: =IF(ISERR(P52/$P$11),"",P52/$P$11) -> 0 | R52: =[1]南港事務!$L$52 -> 0 | S52: =IF(ISERR(R52/$R$11),"",R52/$R$11) | T52: =R52 -> 0 | U52: =IF(ISERR(T52/$T$11),"",T52/$T$11) | V52: =N52+R52 -> 0 | W52: =IF(ISERR(V52/$V$11),"",V52/$V$11) -> 0 | X52: =P52+T52 -> 0 | Y52: =IF(ISERR(X52/$X$11),"",X52/$X$11) -> 0 | Z52: =F52+J52+N52+R52 -> 0 | AA52: =IF(ISERR(Z52/$Z$11),"",Z52/$Z$11) -> 0 | AB52: =H52+L52+P52+T52 -> 0 | AC52: =IF(ISERR(AB52/$AB$11),"",AB52/$AB$11) -> 0 | AD52: =[1]東京事務!$L$52 -> 0 | AE52: =IF(ISERR(AD52/$AD$11),"",AD52/$AD$11) -> 0 | AF52: =AD52 -> 0 | AG52: =IF(ISERR(AF52/$AF$11),"",AF52/$AF$11) -> 0 | AH52: =[1]東京工場!$L$52 -> 0 | AI52: =IF(ISERR(AH52/$AH$11),"",AH52/$AH$11) -> 0 | AJ52: =AH52 -> 0 | AK52: =IF(ISERR(AJ52/$AJ$11),"",AJ52/$AJ$11) -> 0 | AL52: =AD52+AH52 -> 0 | AM52: =IF(ISERR(AL52/$AL$11),"",AL52/AL$11) -> 0 | AN52: =AF52+AJ52 -> 0 | AO52: =IF(ISERR(AN52/$AN$11),"",AN52/$AN$11) -> 0 | AP52: =B52+Z52+AL52 -> 0 | AQ52: =IF(ISERR(AP52/$AP$11),"",AP52/$AP$11) -> 0 | AR52: =D52+AB52+AN52 -> 0 | AS52: =IF(ISERR(AR52/$AR$11),"",AR52/$AR$11) -> 0 | AT52: =[1]全社合計!$N$52 -> 0 | AU52: =IF(ISERR(AT52/$AT$11),"",AT52/$AT$11) -> 0 | AV52: =AT52 -> 0 | AW52: =IF(ISERR(AV52/$AV$11),"",AV52/$AV$11) -> 0 | AX52: =AP52-AT52 -> 0 | AY52: =IF(ISERROR(AP52/AT52),"",AP52/AT52) | AZ52: =AR52-AV52 -> 0 | BA52: =IF(ISERROR(AR52/AV52),"",AR52/AV52)
A53: 雑収入 | B53: =[1]本部!$L$53 -> 0 | C53: =IF(ISERR(B53/$B$11),"",B53/$B$11) | D53: =B53 -> 0 | E53: =IF(ISERR(D53/$D$11),"",D53/$D$11) | F53: =[1]本社営業!$L$53 -> 33831115 | G53: =IF(ISERR(F53/$F$11),"",F53/$F$11) -> 0.063264993 | H53: =F53 -> 33831115 | I53: =IF(ISERR(H53/$H$11),"",H53/$H$11) -> 0.063264993 | J53: =[1]東大阪!$L$53 -> 50000 | K53: =IF(ISERR(J53/$J$11),"",J53/$J$11) -> 0.0056319879 | L53: =J53 -> 50000 | M53: =IF(ISERR(L53/$L$11),"",L53/$L$11) -> 0.0056319879 | N53: =[1]南港工場!$L$53 -> 19 | O53: =IF(ISERR(N53/$N$11),"",N53/$N$11) -> 6.7322241e-07 | P53: =N53 -> 19 | Q53: =IF(ISERR(P53/$P$11),"",P53/$P$11) -> 6.7322241e-07 | R53: =[1]南港事務!$L$53 -> 0 | S53: =IF(ISERR(R53/$R$11),"",R53/$R$11) | T53: =R53 -> 0 | U53: =IF(ISERR(T53/$T$11),"",T53/$T$11) | V53: =N53+R53 -> 19 | W53: =IF(ISERR(V53/$V$11),"",V53/$V$11) -> 6.7322241e-07 | X53: =P53+T53 -> 19 | Y53: =IF(ISERR(X53/$X$11),"",X53/$X$11) -> 6.7322241e-07 | Z53: =F53+J53+N53+R53 -> 33881134 | AA53: =IF(ISERR(Z53/$Z$11),"",Z53/$Z$11) -> 0.059247992 | AB53: =H53+L53+P53+T53 -> 33881134 | AC53: =IF(ISERR(AB53/$AB$11),"",AB53/$AB$11) -> 0.059247992 | AD53: =[1]東京事務!$L$53 -> 7 | AE53: =IF(ISERR(AD53/$AD$11),"",AD53/$AD$11) -> 2.8420488e-08 | AF53: =AD53 -> 7 | AG53: =IF(ISERR(AF53/$AF$11),"",AF53/$AF$11) -> 2.8420488e-08 | AH53: =[1]東京工場!$L$53 -> 0 | AI53: =IF(ISERR(AH53/$AH$11),"",AH53/$AH$11) -> 0 | AJ53: =AH53 -> 0 | AK53: =IF(ISERR(AJ53/$AJ$11),"",AJ53/$AJ$11) -> 0 | AL53: =AD53+AH53 -> 7 | AM53: =IF(ISERR(AL53/$AL$11),"",AL53/AL$11) -> 2.7331875e-08 | AN53: =AF53+AJ53 -> 7 | AO53: =IF(ISERR(AN53/$AN$11),"",AN53/$AN$11) -> 2.7331875e-08 | AP53: =B53+Z53+AL53 -> 33881141 | AQ53: =IF(ISERR(AP53/$AP$11),"",AP53/$AP$11) -> 0.040921027 | AR53: =D53+AB53+AN53 -> 33881141 | AS53: =IF(ISERR(AR53/$AR$11),"",AR53/$AR$11) -> 0.040921027 | AT53: =[1]全社合計!$N$53 -> 8952836 | AU53: =IF(ISERR(AT53/$AT$11),"",AT53/$AT$11) -> 0.00925733 | AV53: =AT53 -> 8952836 | AW53: =IF(ISERR(AV53/$AV$11),"",AV53/$AV$11) -> 0.00925733 | AX53: =AP53-AT53 -> 24928305 | AY53: =IF(ISERROR(AP53/AT53),"",AP53/AT53) -> 3.7844032 | AZ53: =AR53-AV53 -> 24928305 | BA53: =IF(ISERROR(AR53/AV53),"",AR53/AV53) -> 3.7844032
A54: 《営業外収益》 | B54: =SUM(B49:B53) -> 2504751 | C54: =IF(ISERR(B54/$B$11),"",B54/$B$11) | D54: =B54 -> 2504751 | E54: =IF(ISERR(D54/$D$11),"",D54/$D$11) | F54: =SUM(F49:F53) -> 33831115 | G54: =IF(ISERR(F54/$F$11),"",F54/$F$11) -> 0.063264993 | H54: =F54 -> 33831115 | I54: =IF(ISERR(H54/$H$11),"",H54/$H$11) -> 0.063264993 | J54: =SUM(J49:J53) -> 900000 | K54: =IF(ISERR(J54/$J$11),"",J54/$J$11) -> 0.10137578 | L54: =J54 -> 900000 | M54: =IF(ISERR(L54/$L$11),"",L54/$L$11) -> 0.10137578 | N54: =SUM(N49:N53) -> 100019 | O54: =IF(ISERR(N54/$N$11),"",N54/$N$11) -> 0.0035439491 | P54: =N54 -> 100019 | Q54: =IF(ISERR(P54/$P$11),"",P54/$P$11) -> 0.0035439491 | R54: =SUM(R49:R53) -> 0 | S54: =IF(ISERR(R54/$R$11),"",R54/$R$11) | T54: =R54 -> 0 | U54: =IF(ISERR(T54/$T$11),"",T54/$T$11) | V54: =N54+R54 -> 100019 | W54: =IF(ISERR(V54/$V$11),"",V54/$V$11) -> 0.0035439491 | X54: =P54+T54 -> 100019 | Y54: =IF(ISERR(X54/$X$11),"",X54/$X$11) -> 0.0035439491 | Z54: =F54+J54+N54+R54 -> 34831134 | AA54: =IF(ISERR(Z54/$Z$11),"",Z54/$Z$11) -> 0.060909259 | AB54: =H54+L54+P54+T54 -> 34831134 | AC54: =IF(ISERR(AB54/$AB$11),"",AB54/$AB$11) -> 0.060909259 | AD54: =SUM(AD49:AD53) -> 7 | AE54: =IF(ISERR(AD54/$AD$11),"",AD54/$AD$11) -> 2.8420488e-08 | AF54: =AD54 -> 7 | AG54: =IF(ISERR(AF54/$AF$11),"",AF54/$AF$11) -> 2.8420488e-08 | AH54: =SUM(AH49:AH53) -> 0 | AI54: =IF(ISERR(AH54/$AH$11),"",AH54/$AH$11) -> 0 | AJ54: =AH54 -> 0 | AK54: =IF(ISERR(AJ54/$AJ$11),"",AJ54/$AJ$11) -> 0 | AL54: =AD54+AH54 -> 7 | AM54: =IF(ISERR(AL54/$AL$11),"",AL54/AL$11) -> 2.7331875e-08 | AN54: =AF54+AJ54 -> 7 | AO54: =IF(ISERR(AN54/$AN$11),"",AN54/$AN$11) -> 2.7331875e-08 | AP54: =B54+Z54+AL54 -> 37335892 | AQ54: =IF(ISERR(AP54/$AP$11),"",AP54/$AP$11) -> 0.045093613 | AR54: =D54+AB54+AN54 -> 37335892 | AS54: =IF(ISERR(AR54/$AR$11),"",AR54/$AR$11) -> 0.045093613 | AT54: =SUM(AT49:AT53) -> 12040938 | AU54: =IF(ISERR(AT54/$AT$11),"",AT54/$AT$11) -> 0.012450461 | AV54: =AT54 -> 12040938 | AW54: =IF(ISERR(AV54/$AV$11),"",AV54/$AV$11) -> 0.012450461 | AX54: =AP54-AT54 -> 25294954 | AY54: =IF(ISERROR(AP54/AT54),"",AP54/AT54) -> 3.1007461 | AZ54: =AR54-AV54 -> 25294954 | BA54: =IF(ISERROR(AR54/AV54),"",AR54/AV54) -> 3.1007461
A55: 支払利息割引料 | B55: =[1]本部!$L$55 -> 635280 | C55: =IF(ISERR(B55/$B$11),"",B55/$B$11) | D55: =B55 -> 635280 | E55: =IF(ISERR(D55/$D$11),"",D55/$D$11) | F55: =[1]本社営業!$L$55 -> 177708 | G55: =IF(ISERR(F55/$F$11),"",F55/$F$11) -> 0.0003323182 | H55: =F55 -> 177708 | I55: =IF(ISERR(H55/$H$11),"",H55/$H$11) -> 0.0003323182 | J55: =[1]東大阪!$L$55 -> 0 | K55: =IF(ISERR(J55/$J$11),"",J55/$J$11) -> 0 | L55: =J55 -> 0 | M55: =IF(ISERR(L55/$L$11),"",L55/$L$11) -> 0 | N55: =[1]南港工場!$L$55 -> 0 | O55: =IF(ISERR(N55/$N$11),"",N55/$N$11) -> 0 | P55: =N55 -> 0 | Q55: =IF(ISERR(P55/$P$11),"",P55/$P$11) -> 0 | R55: =[1]南港事務!$L$55 -> 0 | S55: =IF(ISERR(R55/$R$11),"",R55/$R$11) | T55: =R55 -> 0 | U55: =IF(ISERR(T55/$T$11),"",T55/$T$11) | V55: =N55+R55 -> 0 | W55: =IF(ISERR(V55/$V$11),"",V55/$V$11) -> 0 | X55: =P55+T55 -> 0 | Y55: =IF(ISERR(X55/$X$11),"",X55/$X$11) -> 0 | Z55: =F55+J55+N55+R55 -> 177708 | AA55: =IF(ISERR(Z55/$Z$11),"",Z55/$Z$11) -> 0.00031075826 | AB55: =H55+L55+P55+T55 -> 177708 | AC55: =IF(ISERR(AB55/$AB$11),"",AB55/$AB$11) -> 0.00031075826 | AD55: =[1]東京事務!$L$55 -> 0 | AE55: =IF(ISERR(AD55/$AD$11),"",AD55/$AD$11) -> 0 | AF55: =AD55 -> 0 | AG55: =IF(ISERR(AF55/$AF$11),"",AF55/$AF$11) -> 0 | AH55: =[1]東京工場!$L$55 -> 0 | AI55: =IF(ISERR(AH55/$AH$11),"",AH55/$AH$11) -> 0 | AJ55: =AH55 -> 0 | AK55: =IF(ISERR(AJ55/$AJ$11),"",AJ55/$AJ$11) -> 0 | AL55: =AD55+AH55 -> 0 | AM55: =IF(ISERR(AL55/$AL$11),"",AL55/AL$11) -> 0 | AN55: =AF55+AJ55 -> 0 | AO55: =IF(ISERR(AN55/$AN$11),"",AN55/$AN$11) -> 0 | AP55: =B55+Z55+AL55 -> 812988 | AQ55: =IF(ISERR(AP55/$AP$11),"",AP55/$AP$11) -> 0.00098191215 | AR55: =D55+AB55+AN55 -> 812988 | AS55: =IF(ISERR(AR55/$AR$11),"",AR55/$AR$11) -> 0.00098191215 | AT55: =[1]全社合計!$N$55 -> 649639 | AU55: =IF(ISERR(AT55/$AT$11),"",AT55/$AT$11) -> 0.00067173381 | AV55: =AT55 -> 649639 | AW55: =IF(ISERR(AV55/$AV$11),"",AV55/$AV$11) -> 0.00067173381 | AX55: =AP55-AT55 -> 163349 | AY55: =IF(ISERROR(AP55/AT55),"",AP55/AT55) -> 1.2514458 | AZ55: =AR55-AV55 -> 163349 | BA55: =IF(ISERROR(AR55/AV55),"",AR55/AV55) -> 1.2514458
A56: 株式手数料 | B56: =[1]本部!$L$56 -> 0 | C56: =IF(ISERR(B56/$B$11),"",B56/$B$11) | D56: =B56 -> 0 | E56: =IF(ISERR(D56/$D$11),"",D56/$D$11) | F56: =[1]本社営業!$L$56 -> 0 | G56: =IF(ISERR(F56/$F$11),"",F56/$F$11) -> 0 | H56: =F56 -> 0 | I56: =IF(ISERR(H56/$H$11),"",H56/$H$11) -> 0 | J56: =[1]東大阪!$L$56 -> 0 | K56: =IF(ISERR(J56/$J$11),"",J56/$J$11) -> 0 | L56: =J56 -> 0 | M56: =IF(ISERR(L56/$L$11),"",L56/$L$11) -> 0 | N56: =[1]南港工場!$L$56 -> 0 | O56: =IF(ISERR(N56/$N$11),"",N56/$N$11) -> 0 | P56: =N56 -> 0 | Q56: =IF(ISERR(P56/$P$11),"",P56/$P$11) -> 0 | R56: =[1]南港事務!$L$56 -> 0 | S56: =IF(ISERR(R56/$R$11),"",R56/$R$11) | T56: =R56 -> 0 | U56: =IF(ISERR(T56/$T$11),"",T56/$T$11) | V56: =N56+R56 -> 0 | W56: =IF(ISERR(V56/$V$11),"",V56/$V$11) -> 0 | X56: =P56+T56 -> 0 | Y56: =IF(ISERR(X56/$X$11),"",X56/$X$11) -> 0 | Z56: =F56+J56+N56+R56 -> 0 | AA56: =IF(ISERR(Z56/$Z$11),"",Z56/$Z$11) -> 0 | AB56: =H56+L56+P56+T56 -> 0 | AC56: =IF(ISERR(AB56/$AB$11),"",AB56/$AB$11) -> 0 | AD56: =[1]東京事務!$L$56 -> 0 | AE56: =IF(ISERR(AD56/$AD$11),"",AD56/$AD$11) -> 0 | AF56: =AD56 -> 0 | AG56: =IF(ISERR(AF56/$AF$11),"",AF56/$AF$11) -> 0 | AH56: =[1]東京工場!$L$56 -> 0 | AI56: =IF(ISERR(AH56/$AH$11),"",AH56/$AH$11) -> 0 | AJ56: =AH56 -> 0 | AK56: =IF(ISERR(AJ56/$AJ$11),"",AJ56/$AJ$11) -> 0 | AL56: =AD56+AH56 -> 0 | AM56: =IF(ISERR(AL56/$AL$11),"",AL56/AL$11) -> 0 | AN56: =AF56+AJ56 -> 0 | AO56: =IF(ISERR(AN56/$AN$11),"",AN56/$AN$11) -> 0 | AP56: =B56+Z56+AL56 -> 0 | AQ56: =IF(ISERR(AP56/$AP$11),"",AP56/$AP$11) -> 0 | AR56: =D56+AB56+AN56 -> 0 | AS56: =IF(ISERR(AR56/$AR$11),"",AR56/$AR$11) -> 0 | AT56: =[1]全社合計!$N$56 -> 0 | AU56: =IF(ISERR(AT56/$AT$11),"",AT56/$AT$11) -> 0 | AV56: =AT56 -> 0 | AW56: =IF(ISERR(AV56/$AV$11),"",AV56/$AV$11) -> 0 | AX56: =AP56-AT56 -> 0 | AY56: =IF(ISERROR(AP56/AT56),"",AP56/AT56) | AZ56: =AR56-AV56 -> 0 | BA56: =IF(ISERROR(AR56/AV56),"",AR56/AV56)
A57: 社債発行費 | B57: =[1]本部!$L$57 -> 0 | C57: =IF(ISERR(B57/$B$11),"",B57/$B$11) | D57: =B57 -> 0 | E57: =IF(ISERR(D57/$D$11),"",D57/$D$11) | F57: =[1]本社営業!$L$57 -> 0 | G57: =IF(ISERR(F57/$F$11),"",F57/$F$11) -> 0 | H57: =F57 -> 0 | I57: =IF(ISERR(H57/$H$11),"",H57/$H$11) -> 0 | J57: =[1]東大阪!$L$57 -> 0 | K57: =IF(ISERR(J57/$J$11),"",J57/$J$11) -> 0 | L57: =J57 -> 0 | M57: =IF(ISERR(L57/$L$11),"",L57/$L$11) -> 0 | N57: =[1]南港工場!$L$57 -> 0 | O57: =IF(ISERR(N57/$N$11),"",N57/$N$11) -> 0 | P57: =N57 -> 0 | Q57: =IF(ISERR(P57/$P$11),"",P57/$P$11) -> 0 | R57: =[1]南港事務!$L$57 -> 0 | S57: =IF(ISERR(R57/$R$11),"",R57/$R$11) | T57: =R57 -> 0 | U57: =IF(ISERR(T57/$T$11),"",T57/$T$11) | V57: =N57+R57 -> 0 | W57: =IF(ISERR(V57/$V$11),"",V57/$V$11) -> 0 | X57: =P57+T57 -> 0 | Y57: =IF(ISERR(X57/$X$11),"",X57/$X$11) -> 0 | Z57: =F57+J57+N57+R57 -> 0 | AA57: =IF(ISERR(Z57/$Z$11),"",Z57/$Z$11) -> 0 | AB57: =H57+L57+P57+T57 -> 0 | AC57: =IF(ISERR(AB57/$AB$11),"",AB57/$AB$11) -> 0 | AD57: =[1]東京事務!$L$57 -> 0 | AE57: =IF(ISERR(AD57/$AD$11),"",AD57/$AD$11) -> 0 | AF57: =AD57 -> 0 | AG57: =IF(ISERR(AF57/$AF$11),"",AF57/$AF$11) -> 0 | AH57: =[1]東京工場!$L$57 -> 0 | AI57: =IF(ISERR(AH57/$AH$11),"",AH57/$AH$11) -> 0 | AJ57: =AH57 -> 0 | AK57: =IF(ISERR(AJ57/$AJ$11),"",AJ57/$AJ$11) -> 0 | AL57: =AD57+AH57 -> 0 | AM57: =IF(ISERR(AL57/$AL$11),"",AL57/AL$11) -> 0 | AN57: =AF57+AJ57 -> 0 | AO57: =IF(ISERR(AN57/$AN$11),"",AN57/$AN$11) -> 0 | AP57: =B57+Z57+AL57 -> 0 | AQ57: =IF(ISERR(AP57/$AP$11),"",AP57/$AP$11) -> 0 | AR57: =D57+AB57+AN57 -> 0 | AS57: =IF(ISERR(AR57/$AR$11),"",AR57/$AR$11) -> 0 | AT57: =[1]全社合計!$N$57 -> 0 | AU57: =IF(ISERR(AT57/$AT$11),"",AT57/$AT$11) -> 0 | AV57: =AT57 -> 0 | AW57: =IF(ISERR(AV57/$AV$11),"",AV57/$AV$11) -> 0 | AX57: =AP57-AT57 -> 0 | AY57: =IF(ISERROR(AP57/AT57),"",AP57/AT57) | AZ57: =AR57-AV57 -> 0 | BA57: =IF(ISERROR(AR57/AV57),"",AR57/AV57)
A58: 有価証券売却損 | B58: =[1]本部!$L$58 -> 0 | C58: =IF(ISERR(B58/$B$11),"",B58/$B$11) | D58: =B58 -> 0 | E58: =IF(ISERR(D58/$D$11),"",D58/$D$11) | F58: =[1]本社営業!$L$58 -> 0 | G58: =IF(ISERR(F58/$F$11),"",F58/$F$11) -> 0 | H58: =F58 -> 0 | I58: =IF(ISERR(H58/$H$11),"",H58/$H$11) -> 0 | J58: =[1]東大阪!$L$58 -> 0 | K58: =IF(ISERR(J58/$J$11),"",J58/$J$11) -> 0 | M58: =IF(ISERR(L58/$L$11),"",L58/$L$11) -> 0 | N58: =[1]南港工場!$L$58 -> 0 | O58: =IF(ISERR(N58/$N$11),"",N58/$N$11) -> 0 | P58: =N58 -> 0 | Q58: =IF(ISERR(P58/$P$11),"",P58/$P$11) -> 0 | R58: =[1]南港事務!$L$58 -> 0 | S58: =IF(ISERR(R58/$R$11),"",R58/$R$11) | T58: =R58 -> 0 | U58: =IF(ISERR(T58/$T$11),"",T58/$T$11) | V58: =N58+R58 -> 0 | W58: =IF(ISERR(V58/$V$11),"",V58/$V$11) -> 0 | X58: =P58+T58 -> 0 | Y58: =IF(ISERR(X58/$X$11),"",X58/$X$11) -> 0 | Z58: =F58+J58+N58+R58 -> 0 | AA58: =IF(ISERR(Z58/$Z$11),"",Z58/$Z$11) -> 0 | AB58: =H58+L58+P58+T58 -> 0 | AC58: =IF(ISERR(AB58/$AB$11),"",AB58/$AB$11) -> 0 | AD58: =[1]東京事務!$L$58 -> 0 | AE58: =IF(ISERR(AD58/$AD$11),"",AD58/$AD$11) -> 0 | AF58: =AD58 -> 0 | AG58: =IF(ISERR(AF58/$AF$11),"",AF58/$AF$11) -> 0 | AH58: =[1]東京工場!$L$58 -> 0 | AI58: =IF(ISERR(AH58/$AH$11),"",AH58/$AH$11) -> 0 | AJ58: =AH58 -> 0 | AK58: =IF(ISERR(AJ58/$AJ$11),"",AJ58/$AJ$11) -> 0 | AL58: =AD58+AH58 -> 0 | AM58: =IF(ISERR(AL58/$AL$11),"",AL58/AL$11) -> 0 | AN58: =AF58+AJ58 -> 0 | AO58: =IF(ISERR(AN58/$AN$11),"",AN58/$AN$11) -> 0 | AP58: =B58+Z58+AL58 -> 0 | AQ58: =IF(ISERR(AP58/$AP$11),"",AP58/$AP$11) -> 0 | AR58: =D58+AB58+AN58 -> 0 | AS58: =IF(ISERR(AR58/$AR$11),"",AR58/$AR$11) -> 0 | AT58: =[1]全社合計!$N$58 -> 0 | AU58: =IF(ISERR(AT58/$AT$11),"",AT58/$AT$11) -> 0 | AV58: =AT58 -> 0 | AW58: =IF(ISERR(AV58/$AV$11),"",AV58/$AV$11) -> 0 | AX58: =AP58-AT58 -> 0 | AY58: =IF(ISERROR(AP58/AT58),"",AP58/AT58) | AZ58: =AR58-AV58 -> 0 | BA58: =IF(ISERROR(AR58/AV58),"",AR58/AV58)
A59: 貸倒損失 | B59: =[1]本部!$L$59 -> 0 | C59: =IF(ISERR(B59/$B$11),"",B59/$B$11) | E59: =IF(ISERR(D59/$D$11),"",D59/$D$11) | F59: =[1]本社営業!$L$59 -> 0 | G59: =IF(ISERR(F59/$F$11),"",F59/$F$11) -> 0 | H59: =F59 -> 0 | I59: =IF(ISERR(H59/$H$11),"",H59/$H$11) -> 0 | J59: =[1]東大阪!$L$59 -> 0 | K59: =IF(ISERR(J59/$J$11),"",J59/$J$11) -> 0 | M59: =IF(ISERR(L59/$L$11),"",L59/$L$11) -> 0 | N59: =[1]南港工場!$L$59 -> 0 | O59: =IF(ISERR(N59/$N$11),"",N59/$N$11) -> 0 | Q59: =IF(ISERR(P59/$P$11),"",P59/$P$11) -> 0 | R59: =[1]南港事務!$L$59 -> 0 | S59: =IF(ISERR(R59/$R$11),"",R59/$R$11) | U59: =IF(ISERR(T59/$T$11),"",T59/$T$11) | V59: =N59+R59 -> 0 | W59: =IF(ISERR(V59/$V$11),"",V59/$V$11) -> 0 | X59: =P59+T59 -> 0 | Y59: =IF(ISERR(X59/$X$11),"",X59/$X$11) -> 0 | Z59: =F59+J59+N59+R59 -> 0 | AA59: =IF(ISERR(Z59/$Z$11),"",Z59/$Z$11) -> 0 | AB59: =H59+L59+P59+T59 -> 0 | AC59: =IF(ISERR(AB59/$AB$11),"",AB59/$AB$11) -> 0 | AD59: =[1]東京事務!$L$59 -> 0 | AE59: =IF(ISERR(AD59/$AD$11),"",AD59/$AD$11) -> 0 | AG59: =IF(ISERR(AF59/$AF$11),"",AF59/$AF$11) -> 0 | AH59: =[1]東京工場!$L$59 -> 0 | AI59: =IF(ISERR(AH59/$AH$11),"",AH59/$AH$11) -> 0 | AK59: =IF(ISERR(AJ59/$AJ$11),"",AJ59/$AJ$11) -> 0 | AL59: =AD59+AH59 -> 0 | AM59: =IF(ISERR(AL59/$AL$11),"",AL59/AL$11) -> 0 | AN59: =AF59+AJ59 -> 0 | AO59: =IF(ISERR(AN59/$AN$11),"",AN59/$AN$11) -> 0 | AP59: =B59+Z59+AL59 -> 0 | AQ59: =IF(ISERR(AP59/$AP$11),"",AP59/$AP$11) -> 0 | AR59: =D59+AB59+AN59 -> 0 | AS59: =IF(ISERR(AR59/$AR$11),"",AR59/$AR$11) -> 0 | AT59: =[1]全社合計!$N$59 -> 0 | AU59: =IF(ISERR(AT59/$AT$11),"",AT59/$AT$11) -> 0 | AW59: =IF(ISERR(AV59/$AV$11),"",AV59/$AV$11) -> 0 | AX59: =AP59-AT59 -> 0 | AY59: =IF(ISERROR(AP59/AT59),"",AP59/AT59) | AZ59: =AR59-AV59 -> 0 | BA59: =IF(ISERROR(AR59/AV59),"",AR59/AV59)
A60: 役員退職引当金繰入 | B60: =[1]本部!$L$60 -> 500000 | C60: =IF(ISERR(B60/$B$11),"",B60/$B$11) | D60: =B60 -> 500000 | E60: =IF(ISERR(D60/$D$11),"",D60/$D$11) | F60: =[1]本社営業!$L$60 -> 0 | G60: =IF(ISERR(F60/$F$11),"",F60/$F$11) -> 0 | H60: =F60 -> 0 | I60: =IF(ISERR(H60/$H$11),"",H60/$H$11) -> 0 | J60: =[1]東大阪!$L$60 -> 0 | K60: =IF(ISERR(J60/$J$11),"",J60/$J$11) -> 0 | L60: =J60 -> 0 | M60: =IF(ISERR(L60/$L$11),"",L60/$L$11) -> 0 | N60: =[1]南港工場!$L$60 -> 0 | O60: =IF(ISERR(N60/$N$11),"",N60/$N$11) -> 0 | P60: =N60 -> 0 | Q60: =IF(ISERR(P60/$P$11),"",P60/$P$11) -> 0 | R60: =[1]南港事務!$L$60 -> 0 | S60: =IF(ISERR(R60/$R$11),"",R60/$R$11) | T60: =R60 -> 0 | U60: =IF(ISERR(T60/$T$11),"",T60/$T$11) | V60: =N60+R60 -> 0 | W60: =IF(ISERR(V60/$V$11),"",V60/$V$11) -> 0 | X60: =P60+T60 -> 0 | Y60: =IF(ISERR(X60/$X$11),"",X60/$X$11) -> 0 | Z60: =F60+J60+N60+R60 -> 0 | AA60: =IF(ISERR(Z60/$Z$11),"",Z60/$Z$11) -> 0 | AB60: =H60+L60+P60+T60 -> 0 | AC60: =IF(ISERR(AB60/$AB$11),"",AB60/$AB$11) -> 0 | AD60: =[1]東京事務!$L$60 -> 0 | AE60: =IF(ISERR(AD60/$AD$11),"",AD60/$AD$11) -> 0 | AF60: =AD60 -> 0 | AG60: =IF(ISERR(AF60/$AF$11),"",AF60/$AF$11) -> 0 | AH60: =[1]東京工場!$L$60 -> 0 | AI60: =IF(ISERR(AH60/$AH$11),"",AH60/$AH$11) -> 0 | AJ60: =AH60 -> 0 | AK60: =IF(ISERR(AJ60/$AJ$11),"",AJ60/$AJ$11) -> 0 | AL60: =AD60+AH60 -> 0 | AM60: =IF(ISERR(AL60/$AL$11),"",AL60/AL$11) -> 0 | AN60: =AF60+AJ60 -> 0 | AO60: =IF(ISERR(AN60/$AN$11),"",AN60/$AN$11) -> 0 | AP60: =B60+Z60+AL60 -> 500000 | AQ60: =IF(ISERR(AP60/$AP$11),"",AP60/$AP$11) -> 0.00060389092 | AR60: =D60+AB60+AN60 -> 500000 | AS60: =IF(ISERR(AR60/$AR$11),"",AR60/$AR$11) -> 0.00060389092 | AT60: =[1]全社合計!$N$60 -> 500000 | AU60: =IF(ISERR(AT60/$AT$11),"",AT60/$AT$11) -> 0.00051700545 | AV60: =AT60 -> 500000 | AW60: =IF(ISERR(AV60/$AV$11),"",AV60/$AV$11) -> 0.00051700545 | AX60: =AP60-AT60 -> 0 | AY60: =IF(ISERROR(AP60/AT60),"",AP60/AT60) -> 1 | AZ60: =AR60-AV60 -> 0 | BA60: =IF(ISERROR(AR60/AV60),"",AR60/AV60) -> 1
A61: 雑損失 | B61: =[1]本部!$L$61 -> 0 | C61: =IF(ISERR(B61/$B$11),"",B61/$B$11) | D61: =B61 -> 0 | E61: =IF(ISERR(D61/$D$11),"",D61/$D$11) | F61: =[1]本社営業!$L$61 -> 44784 | G61: =IF(ISERR(F61/$F$11),"",F61/$F$11) -> 8.3747149e-05 | H61: =F61 -> 44784 | I61: =IF(ISERR(H61/$H$11),"",H61/$H$11) -> 8.3747149e-05 | J61: =[1]東大阪!$L$61 -> 0 | K61: =IF(ISERR(J61/$J$11),"",J61/$J$11) -> 0 | L61: =J61 -> 0 | M61: =IF(ISERR(L61/$L$11),"",L61/$L$11) -> 0 | N61: =[1]南港工場!$L$61 -> 1 | O61: =IF(ISERR(N61/$N$11),"",N61/$N$11) -> 3.5432759e-08 | P61: =N61 -> 1 | Q61: =IF(ISERR(P61/$P$11),"",P61/$P$11) -> 3.5432759e-08 | R61: =[1]南港事務!$L$61 -> 0 | S61: =IF(ISERR(R61/$R$11),"",R61/$R$11) | T61: =R61 -> 0 | U61: =IF(ISERR(T61/$T$11),"",T61/$T$11) | V61: =N61+R61 -> 1 | W61: =IF(ISERR(V61/$V$11),"",V61/$V$11) -> 3.5432759e-08 | X61: =P61+T61 -> 1 | Y61: =IF(ISERR(X61/$X$11),"",X61/$X$11) -> 3.5432759e-08 | Z61: =F61+J61+N61+R61 -> 44785 | AA61: =IF(ISERR(Z61/$Z$11),"",Z61/$Z$11) -> 7.83156e-05 | AB61: =H61+L61+P61+T61 -> 44785 | AC61: =IF(ISERR(AB61/$AB$11),"",AB61/$AB$11) -> 7.83156e-05 | AD61: =[1]東京事務!$L$61 -> 28 | AE61: =IF(ISERR(AD61/$AD$11),"",AD61/$AD$11) -> 1.1368195e-07 | AF61: =AD61 -> 28 | AG61: =IF(ISERR(AF61/$AF$11),"",AF61/$AF$11) -> 1.1368195e-07 | AH61: =[1]東京工場!$L$61 -> 0 | AI61: =IF(ISERR(AH61/$AH$11),"",AH61/$AH$11) -> 0 | AJ61: =AH61 -> 0 | AK61: =IF(ISERR(AJ61/$AJ$11),"",AJ61/$AJ$11) -> 0 | AL61: =AD61+AH61 -> 28 | AM61: =IF(ISERR(AL61/$AL$11),"",AL61/AL$11) -> 1.093275e-07 | AN61: =AF61+AJ61 -> 28 | AO61: =IF(ISERR(AN61/$AN$11),"",AN61/$AN$11) -> 1.093275e-07 | AP61: =B61+Z61+AL61 -> 44813 | AQ61: =IF(ISERR(AP61/$AP$11),"",AP61/$AP$11) -> 5.4124328e-05 | AR61: =D61+AB61+AN61 -> 44813 | AS61: =IF(ISERR(AR61/$AR$11),"",AR61/$AR$11) -> 5.4124328e-05 | AT61: =[1]全社合計!$N$61 -> 9223 | AU61: =IF(ISERR(AT61/$AT$11),"",AT61/$AT$11) -> 9.5366825e-06 | AV61: =AT61 -> 9223 | AW61: =IF(ISERR(AV61/$AV$11),"",AV61/$AV$11) -> 9.5366825e-06 | AX61: =AP61-AT61 -> 35590 | AY61: =IF(ISERROR(AP61/AT61),"",AP61/AT61) -> 4.8588312 | AZ61: =AR61-AV61 -> 35590 | BA61: =IF(ISERROR(AR61/AV61),"",AR61/AV61) -> 4.8588312
A62: 《営業外費用》 | B62: =SUM(B55:B61) -> 1135280 | C62: =IF(ISERR(B62/$B$11),"",B62/$B$11) | D62: =B62 -> 1135280 | E62: =IF(ISERR(D62/$D$11),"",D62/$D$11) | F62: =SUM(F55:F61) -> 222492 | G62: =IF(ISERR(F62/$F$11),"",F62/$F$11) -> 0.00041606535 | H62: =F62 -> 222492 | I62: =IF(ISERR(H62/$H$11),"",H62/$H$11) -> 0.00041606535 | J62: =SUM(J55:J61) -> 0 | K62: =IF(ISERR(J62/$J$11),"",J62/$J$11) -> 0 | L62: =J62 -> 0 | M62: =IF(ISERR(L62/$L$11),"",L62/$L$11) -> 0 | N62: =SUM(N55:N61) -> 1 | O62: =IF(ISERR(N62/$N$11),"",N62/$N$11) -> 3.5432759e-08 | P62: =N62 -> 1 | Q62: =IF(ISERR(P62/$P$11),"",P62/$P$11) -> 3.5432759e-08 | R62: =SUM(R55:R61) -> 0 | S62: =IF(ISERR(R62/$R$11),"",R62/$R$11) | T62: =R62 -> 0 | U62: =IF(ISERR(T62/$T$11),"",T62/$T$11) | V62: =N62+R62 -> 1 | W62: =IF(ISERR(V62/$V$11),"",V62/$V$11) -> 3.5432759e-08 | X62: =P62+T62 -> 1 | Y62: =IF(ISERR(X62/$X$11),"",X62/$X$11) -> 3.5432759e-08 | Z62: =F62+J62+N62+R62 -> 222493 | AA62: =IF(ISERR(Z62/$Z$11),"",Z62/$Z$11) -> 0.00038907386 | AB62: =H62+L62+P62+T62 -> 222493 | AC62: =IF(ISERR(AB62/$AB$11),"",AB62/$AB$11) -> 0.00038907386 | AD62: =SUM(AD55:AD61) -> 28 | AE62: =IF(ISERR(AD62/$AD$11),"",AD62/$AD$11) -> 1.1368195e-07 | AF62: =AD62 -> 28 | AG62: =IF(ISERR(AF62/$AF$11),"",AF62/$AF$11) -> 1.1368195e-07 | AH62: =SUM(AH55:AH61) -> 0 | AI62: =IF(ISERR(AH62/$AH$11),"",AH62/$AH$11) -> 0 | AJ62: =AH62 -> 0 | AK62: =IF(ISERR(AJ62/$AJ$11),"",AJ62/$AJ$11) -> 0 | AL62: =AD62+AH62 -> 28 | AM62: =IF(ISERR(AL62/$AL$11),"",AL62/AL$11) -> 1.093275e-07 | AN62: =AF62+AJ62 -> 28 | AO62: =IF(ISERR(AN62/$AN$11),"",AN62/$AN$11) -> 1.093275e-07 | AP62: =B62+Z62+AL62 -> 1357801 | AQ62: =IF(ISERR(AP62/$AP$11),"",AP62/$AP$11) -> 0.0016399274 | AR62: =D62+AB62+AN62 -> 1357801 | AS62: =IF(ISERR(AR62/$AR$11),"",AR62/$AR$11) -> 0.0016399274 | AT62: =SUM(AT55:AT61) -> 1158862 | AU62: =IF(ISERR(AT62/$AT$11),"",AT62/$AT$11) -> 0.0011982759 | AV62: =AT62 -> 1158862 | AW62: =IF(ISERR(AV62/$AV$11),"",AV62/$AV$11) -> 0.0011982759 | AX62: =AP62-AT62 -> 198939 | AY62: =IF(ISERROR(AP62/AT62),"",AP62/AT62) -> 1.1716675 | AZ62: =AR62-AV62 -> 198939 | BA62: =IF(ISERROR(AR62/AV62),"",AR62/AV62) -> 1.1716675
A63: 本社費分担金 | B63: =[1]本部!$L$63 -> -6885999 | C63: =IF(ISERR(B63/$B$11),"",B63/$B$11) | D63: =B63 -> -6885999 | E63: =IF(ISERR(D63/$D$11),"",D63/$D$11) | F63: =[1]本社営業!$L$63 -> 3387911 | G63: =IF(ISERR(F63/$F$11),"",F63/$F$11) -> 0.0063354744 | H63: =F63 -> 3387911 | I63: =IF(ISERR(H63/$H$11),"",H63/$H$11) -> 0.0063354744 | J63: =[1]東大阪!$L$63 -> 426932 | K63: =IF(ISERR(J63/$J$11),"",J63/$J$11) -> 0.048089517 | L63: =J63 -> 426932 | M63: =IF(ISERR(L63/$L$11),"",L63/$L$11) -> 0.048089517 | N63: =[1]南港工場!$L$63 -> 1005356 | O63: =IF(ISERR(N63/$N$11),"",N63/$N$11) -> 0.035622536 | P63: =N63 -> 1005356 | Q63: =IF(ISERR(P63/$P$11),"",P63/$P$11) -> 0.035622536 | R63: =[1]南港事務!$L$63 -> 192808 | S63: =IF(ISERR(R63/$R$11),"",R63/$R$11) | T63: =R63 -> 192808 | U63: =IF(ISERR(T63/$T$11),"",T63/$T$11) | V63: =N63+R63 -> 1198164 | W63: =IF(ISERR(V63/$V$11),"",V63/$V$11) -> 0.042454256 | X63: =P63+T63 -> 1198164 | Y63: =IF(ISERR(X63/$X$11),"",X63/$X$11) -> 0.042454256 | Z63: =F63+J63+N63+R63 -> 5013007 | AA63: =IF(ISERR(Z63/$Z$11),"",Z63/$Z$11) -> 0.0087662532 | AB63: =H63+L63+P63+T63 -> 5013007 | AC63: =IF(ISERR(AB63/$AB$11),"",AB63/$AB$11) -> 0.0087662532 | AD63: =[1]東京事務!$L$63 -> 1356542 | AE63: =IF(ISERR(AD63/$AD$11),"",AD63/$AD$11) -> 0.0055076551 | AF63: =AD63 -> 1356542 | AG63: =IF(ISERR(AF63/$AF$11),"",AF63/$AF$11) -> 0.0055076551 | AH63: =[1]東京工場!$L$63 -> 516450 | AI63: =IF(ISERR(AH63/$AH$11),"",AH63/$AH$11) -> 0.052645072 | AJ63: =AH63 -> 516450 | AK63: =IF(ISERR(AJ63/$AJ$11),"",AJ63/$AJ$11) -> 0.052645072 | AL63: =AD63+AH63 -> 1872992 | AM63: =IF(ISERR(AL63/$AL$11),"",AL63/AL$11) -> 0.0073131976 | AN63: =AF63+AJ63 -> 1872992 | AO63: =IF(ISERR(AN63/$AN$11),"",AN63/$AN$11) -> 0.0073131976 | AP63: =B63+Z63+AL63 -> 0 | AQ63: =IF(ISERR(AP63/$AP$11),"",AP63/$AP$11) -> 0 | AR63: =D63+AB63+AN63 -> 0 | AS63: =IF(ISERR(AR63/$AR$11),"",AR63/$AR$11) -> 0 | AT63: =[1]全社合計!$N$63 -> 0 | AU63: =IF(ISERR(AT63/$AT$11),"",AT63/$AT$11) -> 0 | AV63: =AT63 -> 0 | AW63: =IF(ISERR(AV63/$AV$11),"",AV63/$AV$11) -> 0 | AX63: =AP63-AT63 -> 0 | AY63: =IF(ISERROR(AP63/AT63),"",AP63/AT63) | AZ63: =AR63-AV63 -> 0 | BA63: =IF(ISERROR(AR63/AV63),"",AR63/AV63)
A64: 【経常利益】 | B64: =+B48+B54-B62-B63 -> 0 | C64: =IF(ISERR(B64/$B$11),"",B64/$B$11) | D64: =B64 -> 0 | E64: =IF(ISERR(D64/$D$11),"",D64/$D$11) | F64: =F48+F54-F62-F63 -> 77505209 | G64: =IF(ISERR(F64/$F$11),"",F64/$F$11) -> 0.14493659 | H64: =F64 -> 77505209 | I64: =IF(ISERR(H64/$H$11),"",H64/$H$11) -> 0.14493659 | J64: =J48+J54-J62-J63 -> 3363693 | K64: =IF(ISERR(J64/$J$11),"",J64/$J$11) -> 0.37888556 | L64: =J64 -> 3363693 | M64: =IF(ISERR(L64/$L$11),"",L64/$L$11) -> 0.37888556 | N64: =N48+N54-N62-N63 -> 13864620 | O64: =IF(ISERR(N64/$N$11),"",N64/$N$11) -> 0.49126173 | P64: =N64 -> 13864620 | Q64: =IF(ISERR(P64/$P$11),"",P64/$P$11) -> 0.49126173 | R64: =R48+R54-R62-R63 -> -3580518 | S64: =IF(ISERR(R64/$R$11),"",R64/$R$11) | T64: =R64 -> -3580518 | U64: =IF(ISERR(T64/$T$11),"",T64/$T$11) | V64: =N64+R64 -> 10284102 | W64: =IF(ISERR(V64/$V$11),"",V64/$V$11) -> 0.3643941 | X64: =P64+T64 -> 10284102 | Y64: =IF(ISERR(X64/$X$11),"",X64/$X$11) -> 0.3643941 | Z64: =F64+J64+N64+R64 -> 91153004 | AA64: =IF(ISERR(Z64/$Z$11),"",Z64/$Z$11) -> 0.1593994 | AB64: =H64+L64+P64+T64 -> 91153004 | AC64: =IF(ISERR(AB64/$AB$11),"",AB64/$AB$11) -> 0.1593994 | AD64: =AD48+AD54-AD62-AD63 -> 10902545 | AE64: =IF(ISERR(AD64/$AD$11),"",AD64/$AD$11) -> 0.044265092 | AF64: =AD64 -> 10902545 | AG64: =IF(ISERR(AF64/$AF$11),"",AF64/$AF$11) -> 0.044265092 | AH64: =AH48+AH54-AH62-AH63 -> 3214622 | AI64: =IF(ISERR(AH64/$AH$11),"",AH64/$AH$11) -> 0.32768711 | AJ64: =AH64 -> 3214622 | AK64: =IF(ISERR(AJ64/$AJ$11),"",AJ64/$AJ$11) -> 0.32768711 | AL64: =AD64+AH64 -> 14117167 | AM64: =IF(ISERR(AL64/$AL$11),"",AL64/AL$11) -> 0.055121235 | AN64: =AF64+AJ64 -> 14117167 | AO64: =IF(ISERR(AN64/$AN$11),"",AN64/$AN$11) -> 0.055121235 | AP64: =B64+Z64+AL64 -> 105270171 | AQ64: =IF(ISERR(AP64/$AP$11),"",AP64/$AP$11) -> 0.1271434 | AR64: =D64+AB64+AN64 -> 105270171 | AS64: =IF(ISERR(AR64/$AR$11),"",AR64/$AR$11) -> 0.1271434 | AT64: =AT48+AT54-AT62-AT63 -> 92714042 | AU64: =IF(ISERR(AT64/$AT$11),"",AT64/$AT$11) -> 0.09586733 | AV64: =AT64 -> 92714042 | AW64: =IF(ISERR(AV64/$AV$11),"",AV64/$AV$11) -> 0.09586733 | AX64: =AP64-AT64 -> 12556129 | AY64: =IF(ISERROR(AP64/AT64),"",AP64/AT64) -> 1.1354286 | AZ64: =AR64-AV64 -> 12556129 | BA64: =IF(ISERROR(AR64/AV64),"",AR64/AV64) -> 1.1354286
A65: 特別利益 | B65: =[1]本部!$L$65 -> 0 | C65: =IF(ISERR(B65/$B$11),"",B65/$B$11) | D65: =B65 -> 0 | E65: =IF(ISERR(D65/$D$11),"",D65/$D$11) | F65: =[1]本社営業!$L$65 -> 0 | G65: =IF(ISERR(F65/$F$11),"",F65/$F$11) -> 0 | H65: =F65 -> 0 | I65: =IF(ISERR(H65/$H$11),"",H65/$H$11) -> 0 | J65: =[1]東大阪!$L$65 -> 0 | K65: =IF(ISERR(J65/$J$11),"",J65/$J$11) -> 0 | L65: =J65 -> 0 | M65: =IF(ISERR(L65/$L$11),"",L65/$L$11) -> 0 | N65: =[1]南港工場!$L$65 -> 0 | O65: =IF(ISERR(N65/$N$11),"",N65/$N$11) -> 0 | P65: =N65 -> 0 | Q65: =IF(ISERR(P65/$P$11),"",P65/$P$11) -> 0 | R65: =[1]南港事務!$L$65 -> 0 | S65: =IF(ISERR(R65/$R$11),"",R65/$R$11) | T65: =R65 -> 0 | U65: =IF(ISERR(T65/$T$11),"",T65/$T$11) | V65: =N65+R65 -> 0 | W65: =IF(ISERR(V65/$V$11),"",V65/$V$11) -> 0 | X65: =P65+T65 -> 0 | Y65: =IF(ISERR(X65/$X$11),"",X65/$X$11) -> 0 | Z65: =F65+J65+N65+R65 -> 0 | AA65: =IF(ISERR(Z65/$Z$11),"",Z65/$Z$11) -> 0 | AB65: =H65+L65+P65+T65 -> 0 | AC65: =IF(ISERR(AB65/$AB$11),"",AB65/$AB$11) -> 0 | AD65: =[1]東京事務!$L$65 -> 0 | AE65: =IF(ISERR(AD65/$AD$11),"",AD65/$AD$11) -> 0 | AF65: =AD65 -> 0 | AG65: =IF(ISERR(AF65/$AF$11),"",AF65/$AF$11) -> 0 | AH65: =[1]東京工場!$L$65 -> 0 | AI65: =IF(ISERR(AH65/$AH$11),"",AH65/$AH$11) -> 0 | AJ65: =AH65 -> 0 | AK65: =IF(ISERR(AJ65/$AJ$11),"",AJ65/$AJ$11) -> 0 | AL65: =AD65+AH65 -> 0 | AM65: =IF(ISERR(AL65/$AL$11),"",AL65/AL$11) -> 0 | AN65: =AF65+AJ65 -> 0 | AO65: =IF(ISERR(AN65/$AN$11),"",AN65/$AN$11) -> 0 | AP65: =B65+Z65+AL65 -> 0 | AQ65: =IF(ISERR(AP65/$AP$11),"",AP65/$AP$11) -> 0 | AR65: =D65+AB65+AN65 -> 0 | AS65: =IF(ISERR(AR65/$AR$11),"",AR65/$AR$11) -> 0 | AT65: =[1]全社合計!$N$65 -> 0 | AU65: =IF(ISERR(AT65/$AT$11),"",AT65/$AT$11) -> 0 | AV65: =AT65 -> 0 | AW65: =IF(ISERR(AV65/$AV$11),"",AV65/$AV$11) -> 0 | AX65: =AP65-AT65 -> 0 | AY65: =IF(ISERROR(AP65/AT65),"",AP65/AT65) | AZ65: =AR65-AV65 -> 0 | BA65: =IF(ISERROR(AR65/AV65),"",AR65/AV65)
A66: 特別損失 | B66: =[1]本部!$L$66 -> 0 | C66: =IF(ISERR(B66/$B$11),"",B66/$B$11) | D66: =B66 -> 0 | E66: =IF(ISERR(D66/$D$11),"",D66/$D$11) | F66: =[1]本社営業!$L$66 -> 0 | G66: =IF(ISERR(F66/$F$11),"",F66/$F$11) -> 0 | H66: =F66 -> 0 | I66: =IF(ISERR(H66/$H$11),"",H66/$H$11) -> 0 | J66: =[1]東大阪!$L$66 -> 0 | K66: =IF(ISERR(J66/$J$11),"",J66/$J$11) -> 0 | L66: =J66 -> 0 | M66: =IF(ISERR(L66/$L$11),"",L66/$L$11) -> 0 | N66: =[1]南港工場!$L$66 -> 0 | O66: =IF(ISERR(N66/$N$11),"",N66/$N$11) -> 0 | P66: =N66 -> 0 | Q66: =IF(ISERR(P66/$P$11),"",P66/$P$11) -> 0 | R66: =[1]南港事務!$L$66 -> 0 | S66: =IF(ISERR(R66/$R$11),"",R66/$R$11) | T66: =R66 -> 0 | U66: =IF(ISERR(T66/$T$11),"",T66/$T$11) | V66: =N66+R66 -> 0 | W66: =IF(ISERR(V66/$V$11),"",V66/$V$11) -> 0 | X66: =P66+T66 -> 0 | Y66: =IF(ISERR(X66/$X$11),"",X66/$X$11) -> 0 | Z66: =F66+J66+N66+R66 -> 0 | AA66: =IF(ISERR(Z66/$Z$11),"",Z66/$Z$11) -> 0 | AB66: =H66+L66+P66+T66 -> 0 | AC66: =IF(ISERR(AB66/$AB$11),"",AB66/$AB$11) -> 0 | AD66: =[1]東京事務!$L$66 -> 0 | AE66: =IF(ISERR(AD66/$AD$11),"",AD66/$AD$11) -> 0 | AF66: =AD66 -> 0 | AG66: =IF(ISERR(AF66/$AF$11),"",AF66/$AF$11) -> 0 | AH66: =[1]東京工場!$L$66 -> 0 | AI66: =IF(ISERR(AH66/$AH$11),"",AH66/$AH$11) -> 0 | AJ66: =AH66 -> 0 | AK66: =IF(ISERR(AJ66/$AJ$11),"",AJ66/$AJ$11) -> 0 | AL66: =AD66+AH66 -> 0 | AM66: =IF(ISERR(AL66/$AL$11),"",AL66/AL$11) -> 0 | AN66: =AF66+AJ66 -> 0 | AO66: =IF(ISERR(AN66/$AN$11),"",AN66/$AN$11) -> 0 | AP66: =B66+Z66+AL66 -> 0 | AQ66: =IF(ISERR(AP66/$AP$11),"",AP66/$AP$11) -> 0 | AR66: =D66+AB66+AN66 -> 0 | AS66: =IF(ISERR(AR66/$AR$11),"",AR66/$AR$11) -> 0 | AT66: =[1]全社合計!$N$66 -> 0 | AU66: =IF(ISERR(AT66/$AT$11),"",AT66/$AT$11) -> 0 | AV66: =AT66 -> 0 | AW66: =IF(ISERR(AV66/$AV$11),"",AV66/$AV$11) -> 0 | AX66: =AP66-AT66 -> 0 | AY66: =IF(ISERROR(AP66/AT66),"",AP66/AT66) | AZ66: =AR66-AV66 -> 0 | BA66: =IF(ISERROR(AR66/AV66),"",AR66/AV66)
A67: 【税引前当期利益】 | B67: =+B64+B65-B66 -> 0 | C67: =IF(ISERR(B67/$B$11),"",B67/$B$11) | D67: =B67 -> 0 | E67: =IF(ISERR(D67/$D$11),"",D67/$D$11) | F67: =F64+F65-F66 -> 77505209 | G67: =IF(ISERR(F67/$F$11),"",F67/$F$11) -> 0.14493659 | H67: =F67 -> 77505209 | I67: =IF(ISERR(H67/$H$11),"",H67/$H$11) -> 0.14493659 | J67: =J64+J65-J66 -> 3363693 | K67: =IF(ISERR(J67/$J$11),"",J67/$J$11) -> 0.37888556 | L67: =J67 -> 3363693 | M67: =IF(ISERR(L67/$L$11),"",L67/$L$11) -> 0.37888556 | N67: =N64+N65-N66 -> 13864620 | O67: =IF(ISERR(N67/$N$11),"",N67/$N$11) -> 0.49126173 | P67: =N67 -> 13864620 | Q67: =IF(ISERR(P67/$P$11),"",P67/$P$11) -> 0.49126173 | R67: =R64+R65-R66 -> -3580518 | S67: =IF(ISERR(R67/$R$11),"",R67/$R$11) | T67: =R67 -> -3580518 | U67: =IF(ISERR(T67/$T$11),"",T67/$T$11) | V67: =N67+R67 -> 10284102 | W67: =IF(ISERR(V67/$V$11),"",V67/$V$11) -> 0.3643941 | X67: =P67+T67 -> 10284102 | Y67: =IF(ISERR(X67/$X$11),"",X67/$X$11) -> 0.3643941 | Z67: =F67+J67+N67+R67 -> 91153004 | AA67: =IF(ISERR(Z67/$Z$11),"",Z67/$Z$11) -> 0.1593994 | AB67: =H67+L67+P67+T67 -> 91153004 | AC67: =IF(ISERR(AB67/$AB$11),"",AB67/$AB$11) -> 0.1593994 | AD67: =AD64+AD65-AD66 -> 10902545 | AE67: =IF(ISERR(AD67/$AD$11),"",AD67/$AD$11) -> 0.044265092 | AF67: =AD67 -> 10902545 | AG67: =IF(ISERR(AF67/$AF$11),"",AF67/$AF$11) -> 0.044265092 | AH67: =AH64+AH65-AH66 -> 3214622 | AI67: =IF(ISERR(AH67/$AH$11),"",AH67/$AH$11) -> 0.32768711 | AJ67: =AH67 -> 3214622 | AK67: =IF(ISERR(AJ67/$AJ$11),"",AJ67/$AJ$11) -> 0.32768711 | AL67: =AD67+AH67 -> 14117167 | AM67: =IF(ISERR(AL67/$AL$11),"",AL67/AL$11) -> 0.055121235 | AN67: =AF67+AJ67 -> 14117167 | AO67: =IF(ISERR(AN67/$AN$11),"",AN67/$AN$11) -> 0.055121235 | AP67: =B67+Z67+AL67 -> 105270171 | AQ67: =IF(ISERR(AP67/$AP$11),"",AP67/$AP$11) -> 0.1271434 | AR67: =D67+AB67+AN67 -> 105270171 | AS67: =IF(ISERR(AR67/$AR$11),"",AR67/$AR$11) -> 0.1271434 | AT67: =AT64+AT65-AT66 -> 92714042 | AU67: =IF(ISERR(AT67/$AT$11),"",AT67/$AT$11) -> 0.09586733 | AV67: =AT67 -> 92714042 | AW67: =IF(ISERR(AV67/$AV$11),"",AV67/$AV$11) -> 0.09586733 | AX67: =AP67-AT67 -> 12556129 | AY67: =IF(ISERROR(AP67/AT67),"",AP67/AT67) -> 1.1354286 | AZ67: =AR67-AV67 -> 12556129 | BA67: =IF(ISERROR(AR67/AV67),"",AR67/AV67) -> 1.1354286
A68: 法人税等充当額 | C68: =IF(ISERR(B68/$B$11),"",B68/$B$11) | D68: =B68 -> 0 | E68: =IF(ISERR(D68/$D$11),"",D68/$D$11) | G68: =IF(ISERR(F68/$F$11),"",F68/$F$11) -> 0 | H68: =F68 -> 0 | I68: =IF(ISERR(H68/$H$11),"",H68/$H$11) -> 0 | K68: =IF(ISERR(J68/$J$11),"",J68/$J$11) -> 0 | L68: =J68 -> 0 | M68: =IF(ISERR(L68/$L$11),"",L68/$L$11) -> 0 | O68: =IF(ISERR(N68/$N$11),"",N68/$N$11) -> 0 | P68: =N68 -> 0 | Q68: =IF(ISERR(P68/$P$11),"",P68/$P$11) -> 0 | S68: =IF(ISERR(R68/$R$11),"",R68/$R$11) | T68: =R68 -> 0 | U68: =IF(ISERR(T68/$T$11),"",T68/$T$11) | V68: =N68+R68 -> 0 | W68: =IF(ISERR(V68/$V$11),"",V68/$V$11) -> 0 | X68: =P68+T68 -> 0 | Y68: =IF(ISERR(X68/$X$11),"",X68/$X$11) -> 0 | Z68: =F68+J68+N68+R68 -> 0 | AA68: =IF(ISERR(Z68/$Z$11),"",Z68/$Z$11) -> 0 | AB68: =H68+L68+P68+T68 -> 0 | AC68: =IF(ISERR(AB68/$AB$11),"",AB68/$AB$11) -> 0 | AE68: =IF(ISERR(AD68/$AD$11),"",AD68/$AD$11) -> 0 | AF68: =AD68 -> 0 | AG68: =IF(ISERR(AF68/$AF$11),"",AF68/$AF$11) -> 0 | AI68: =IF(ISERR(AH68/$AH$11),"",AH68/$AH$11) -> 0 | AJ68: =AH68 -> 0 | AK68: =IF(ISERR(AJ68/$AJ$11),"",AJ68/$AJ$11) -> 0 | AL68: =AD68+AH68 -> 0 | AN68: =AF68+AJ68 -> 0 | AO68: =IF(ISERR(AN68/$AN$11),"",AN68/$AN$11) -> 0 | AP68: =B68+Z68+AL68 -> 0 | AQ68: =IF(ISERR(AP68/$AP$11),"",AP68/$AP$11) -> 0 | AR68: =D68+AB68+AN68 -> 0 | AS68: =IF(ISERR(AR68/$AR$11),"",AR68/$AR$11) -> 0 | AU68: =IF(ISERR(AT68/$AT$11),"",AT68/$AT$11) -> 0 | AV68: =AT68 -> 0 | AW68: =IF(ISERR(AV68/$AV$11),"",AV68/$AV$11) -> 0 | AX68: =AP68-AT68 -> 0 | AY68: =IF(ISERROR(AP68/AT68),"",AP68/AT68) | AZ68: =AR68-AV68 -> 0 | BA68: =IF(ISERROR(AR68/AV68),"",AR68/AV68)
A69: 【当期利益】 | B69: =+B67-B68 -> 0 | C69: =IF(ISERR(B69/$B$11),"",B69/$B$11) | D69: =B69 -> 0 | E69: =IF(ISERR(D69/$D$11),"",D69/$D$11) | F69: =F67-F68 -> 77505209 | G69: =IF(ISERR(F69/$F$11),"",F69/$F$11) -> 0.14493659 | H69: =F69 -> 77505209 | I69: =IF(ISERR(H69/$H$11),"",H69/$H$11) -> 0.14493659 | J69: =J67-J68 -> 3363693 | K69: =IF(ISERR(J69/$J$11),"",J69/$J$11) -> 0.37888556 | L69: =J69 -> 3363693 | M69: =IF(ISERR(L69/$L$11),"",L69/$L$11) -> 0.37888556 | N69: =N67-N68 -> 13864620 | O69: =IF(ISERR(N69/$N$11),"",N69/$N$11) -> 0.49126173 | P69: =N69 -> 13864620 | Q69: =IF(ISERR(P69/$P$11),"",P69/$P$11) -> 0.49126173 | R69: =R67-R68 -> -3580518 | S69: =IF(ISERR(R69/$R$11),"",R69/$R$11) | T69: =R69 -> -3580518 | U69: =IF(ISERR(T69/$T$11),"",T69/$T$11) | V69: =N69+R69 -> 10284102 | W69: =IF(ISERR(V69/$V$11),"",V69/$V$11) -> 0.3643941 | X69: =P69+T69 -> 10284102 | Y69: =IF(ISERR(X69/$X$11),"",X69/$X$11) -> 0.3643941 | Z69: =F69+J69+N69+R69 -> 91153004 | AA69: =IF(ISERR(Z69/$Z$11),"",Z69/$Z$11) -> 0.1593994 | AB69: =H69+L69+P69+T69 -> 91153004 | AC69: =IF(ISERR(AB69/$AB$11),"",AB69/$AB$11) -> 0.1593994 | AD69: =AD67-AD68 -> 10902545 | AE69: =IF(ISERR(AD69/$AD$11),"",AD69/$AD$11) -> 0.044265092 | AF69: =AD69 -> 10902545 | AG69: =IF(ISERR(AF69/$AF$11),"",AF69/$AF$11) -> 0.044265092 | AH69: =+AH67-AH68 -> 3214622 | AI69: =IF(ISERR(AH69/$AH$11),"",AH69/$AH$11) -> 0.32768711 | AJ69: =AH69 -> 3214622 | AK69: =IF(ISERR(AJ69/$AJ$11),"",AJ69/$AJ$11) -> 0.32768711 | AL69: =AD69+AH69 -> 14117167 | AN69: =AF69+AJ69 -> 14117167 | AO69: =IF(ISERR(AN69/$AN$11),"",AN69/$AN$11) -> 0.055121235 | AP69: =B69+Z69+AL69 -> 105270171 | AQ69: =IF(ISERR(AP69/$AP$11),"",AP69/$AP$11) -> 0.1271434 | AR69: =D69+AB69+AN69 -> 105270171 | AS69: =IF(ISERR(AR69/$AR$11),"",AR69/$AR$11) -> 0.1271434 | AT69: =AT67-AT68 -> 92714042 | AU69: =IF(ISERR(AT69/$AT$11),"",AT69/$AT$11) -> 0.09586733 | AV69: =AT69 -> 92714042 | AW69: =IF(ISERR(AV69/$AV$11),"",AV69/$AV$11) -> 0.09586733 | AX69: =AP69-AT69 -> 12556129 | AY69: =IF(ISERROR(AP69/AT69),"",AP69/AT69) -> 1.1354286 | AZ69: =AR69-AV69 -> 12556129 | BA69: =IF(ISERROR(AR69/AV69),"",AR69/AV69) -> 1.1354286
A70: （月末人員･稼働日） | B70: =[1]本部!$L$68 -> 6 | D70: =B70 -> 6 | F70: =[1]本社営業!$L$68 -> 19 | H70: =F70 -> 19 | J70: =[1]東大阪!$L$68 -> 15 | L70: =J70 -> 15 | N70: =[1]南港工場!$L$68 -> 17 | P70: =N70 -> 17 | R70: =[1]南港事務!$L$68 -> 6 | T70: =R70 -> 6 | V70: =N70+R70 -> 23 | X70: =P70+T70 -> 23 | Z70: =F70+J70+N70+R70 -> 57 | AB70: =H70+L70+P70+T70 -> 57 | AD70: =[1]東京事務!$L$68 -> 8 | AF70: =AD70 -> 8 | AH70: =[1]東京工場!$L$68 -> 12 | AJ70: =AH70 -> 12 | AL70: =AD70+AH70 -> 20 | AN70: =AF70+AJ70 -> 20 | AP70: =B70+Z70+AL70 -> 83 | AR70: =D70+AB70+AN70 -> 83 | AT70: =[1]全社合計!$N$68 -> 78 | AV70: =AT70 -> 78 | AX70: =AP70-AT70 -> 5 | AZ70: =AR70-AV70 -> 5
A71: 賞与月割額 | B71: =[1]本部!$L$71 -> 850000 | C71: =IF(ISERR(B71/$B$11),"",B71/$B$11) | D71: =B71 -> 850000 | E71: =IF(ISERR(D72/$D$11),"",D72/$D$11) | F71: =[1]本社営業!$L$71 -> 2050000 | G71: =IF(ISERR(F71/$F$11),"",F71/$F$11) -> 0.0038335489 | H71: =F71 -> 2050000 | I71: =IF(ISERR(H71/$H$11),"",H71/$H$11) -> 0.0038335489 | J71: =[1]東大阪!$L$71 -> 750000 | K71: =IF(ISERR(J71/$J$11),"",J71/$J$11) -> 0.084479818 | L71: =J71 -> 750000 | M71: =IF(ISERR(L71/$L$11),"",L71/$L$11) -> 0.084479818 | N71: =[1]南港工場!$L$71 -> 1550000 | O71: =IF(ISERR(N71/$N$11),"",N71/$N$11) -> 0.054920776 | P71: =N71 -> 1550000 | Q71: =IF(ISERR(P71/$P$11),"",P71/$P$11) -> 0.054920776 | R71: =[1]南港事務!$L$71 -> 520000 | S71: =IF(ISERR(R71/$R$11),"",R71/$R$11) | T71: =R71 -> 520000 | U71: =IF(ISERR(T71/$T$11),"",T71/$T$11) | V71: =N71+R71 -> 2070000 | W71: =IF(ISERR(V71/$V$11),"",V71/$V$11) -> 0.07334581 | X71: =P71+T71 -> 2070000 | Y71: =IF(ISERR(X71/$X$11),"",X71/$X$11) -> 0.07334581 | Z71: =F71+J71+N71+R71 -> 4870000 | AA71: =IF(ISERR(Z71/$Z$11),"",Z71/$Z$11) -> 0.0085161766 | AB71: =H71+L71+P71+T71 -> 4870000 | AC71: =IF(ISERR(AB71/$AB$11),"",AB71/$AB$11) -> 0.0085161766 | AD71: =[1]東京事務!$L$71 -> 750000 | AE71: =IF(ISERR(AD71/$AD$11),"",AD71/$AD$11) -> 0.0030450523 | AF71: =AD71 -> 750000 | AG71: =IF(ISERR(AF71/$AF$11),"",AF71/$AF$11) -> 0.0030450523 | AH71: =[1]東京工場!$L$71 -> 920000 | AI71: =IF(ISERR(AH71/$AH$11),"",AH71/$AH$11) -> 0.093781521 | AJ71: =AH71 -> 920000 | AK71: =IF(ISERR(AJ71/$AJ$11),"",AJ71/$AJ$11) -> 0.093781521 | AL71: =AD71+AH71 -> 1670000 | AM71: =IF(ISERR(AL71/$AL$11),"",AL71/AL$11) -> 0.0065206045 | AN71: =AF71+AJ71 -> 1670000 | AO71: =IF(ISERR(AN71/$AN$11),"",AN71/$AN$11) -> 0.0065206045 | AP71: =B71+Z71+AL71 -> 7390000 | AQ71: =IF(ISERR(AP71/$AP$11),"",AP71/$AP$11) -> 0.0089255079 | AR71: =D71+AB71+AN71 -> 7390000 | AS71: =IF(ISERR(AR71/$AR$11),"",AR71/$AR$11) -> 0.0089255079 | AT71: =[1]全社合計!$N$71 -> 7095000 | AU71: =IF(ISERR(AT71/$AT$11),"",AT71/$AT$11) -> 0.0073363073 | AV71: =AT71 -> 7095000 | AW71: =IF(ISERR(AV71/$AV$11),"",AV71/$AV$11) -> 0.0073363073 | AX71: =AP71-AT71 -> 295000 | AY71: =IF(ISERROR(AP71/AT71),"",AP71/AT71) -> 1.0415786 | AZ71: =AR71-AV71 -> 295000 | BA71: =IF(ISERROR(AR71/AV71),"",AR71/AV71) -> 1.0415786
A72: 固定資産税月割額 | B72: =[1]本部!$L$72 -> 115000 | C72: =IF(ISERR(B72/$B$11),"",B72/$B$11) | D72: =B72 -> 115000 | E72: =IF(ISERR(D73/$D$11),"",D73/$D$11) | F72: =[1]本社営業!$L$72 -> 55000 | G72: =IF(ISERR(F72/$F$11),"",F72/$F$11) -> 0.00010285131 | H72: =F72 -> 55000 | I72: =IF(ISERR(H72/$H$11),"",H72/$H$11) -> 0.00010285131 | J72: =[1]東大阪!$L$72 -> 440000 | K72: =IF(ISERR(J72/$J$11),"",J72/$J$11) -> 0.049561493 | L72: =J72 -> 440000 | M72: =IF(ISERR(L72/$L$11),"",L72/$L$11) -> 0.049561493 | N72: =[1]南港工場!$L$72 -> 525000 | O72: =IF(ISERR(N72/$N$11),"",N72/$N$11) -> 0.018602198 | P72: =N72 -> 525000 | Q72: =IF(ISERR(P72/$P$11),"",P72/$P$11) -> 0.018602198 | R72: =[1]南港事務!$L$72 -> 20000 | S72: =IF(ISERR(R72/$R$11),"",R72/$R$11) | T72: =R72 -> 20000 | U72: =IF(ISERR(T72/$T$11),"",T72/$T$11) | V72: =N72+R72 -> 545000 | W72: =IF(ISERR(V72/$V$11),"",V72/$V$11) -> 0.019310853 | X72: =P72+T72 -> 545000 | Y72: =IF(ISERR(X72/$X$11),"",X72/$X$11) -> 0.019310853 | Z72: =F72+J72+N72+R72 -> 1040000 | AA72: =IF(ISERR(Z72/$Z$11),"",Z72/$Z$11) -> 0.0018186496 | AB72: =H72+L72+P72+T72 -> 1040000 | AC72: =IF(ISERR(AB72/$AB$11),"",AB72/$AB$11) -> 0.0018186496 | AD72: =[1]東京事務!$L$72 -> 55000 | AE72: =IF(ISERR(AD72/$AD$11),"",AD72/$AD$11) -> 0.00022330383 | AF72: =AD72 -> 55000 | AG72: =IF(ISERR(AF72/$AF$11),"",AF72/$AF$11) -> 0.00022330383 | AH72: =[1]東京工場!$L$72 -> 325000 | AI72: =IF(ISERR(AH72/$AH$11),"",AH72/$AH$11) -> 0.033129342 | AJ72: =AH72 -> 325000 | AK72: =IF(ISERR(AJ72/$AJ$11),"",AJ72/$AJ$11) -> 0.033129342 | AL72: =AD72+AH72 -> 380000 | AM72: =IF(ISERR(AL72/$AL$11),"",AL72/AL$11) -> 0.0014837304 | AN72: =AF72+AJ72 -> 380000 | AO72: =IF(ISERR(AN72/$AN$11),"",AN72/$AN$11) -> 0.0014837304 | AP72: =B72+Z72+AL72 -> 1535000 | AQ72: =IF(ISERR(AP72/$AP$11),"",AP72/$AP$11) -> 0.0018539451 | AR72: =D72+AB72+AN72 -> 1535000 | AS72: =IF(ISERR(AR72/$AR$11),"",AR72/$AR$11) -> 0.0018539451 | AT72: =[1]全社合計!$N$72 -> 1495000 | AU72: =IF(ISERR(AT72/$AT$11),"",AT72/$AT$11) -> 0.0015458463 | AV72: =AT72 -> 1495000 | AW72: =IF(ISERR(AV72/$AV$11),"",AV72/$AV$11) -> 0.0015458463 | AX72: =AP72-AT72 -> 40000 | AY72: =IF(ISERROR(AP72/AT72),"",AP72/AT72) -> 1.0267559 | AZ72: =AR72-AV72 -> 40000 | BA72: =IF(ISERROR(AR72/AV72),"",AR72/AV72) -> 1.0267559
A73: 保険料・社会保険料 | B73: =[1]本部!$L$70 -> 0 | C73: =IF(ISERR(B73/$B$11),"",B73/$B$11) | D73: =B73 -> 0 | E73: =IF(ISERR(D74/$D$11),"",D74/$D$11) | F73: =[1]本社営業!$L$70 -> 0 | G73: =IF(ISERR(F73/$F$11),"",F73/$F$11) -> 0 | H73: =F73 -> 0 | I73: =IF(ISERR(H73/$H$11),"",H73/$H$11) -> 0 | J73: =[1]東大阪!$L$70 -> 0 | K73: =IF(ISERR(J73/$J$11),"",J73/$J$11) -> 0 | L73: =J73 -> 0 | M73: =IF(ISERR(L73/$L$11),"",L73/$L$11) -> 0 | N73: =[1]南港工場!$L$70 -> 0 | O73: =IF(ISERR(N73/$N$11),"",N73/$N$11) -> 0 | P73: =N73 -> 0 | Q73: =IF(ISERR(P73/$P$11),"",P73/$P$11) -> 0 | R73: =[1]南港事務!$L$70 -> 0 | S73: =IF(ISERR(R73/$R$11),"",R73/$R$11) | T73: =R73 -> 0 | U73: =IF(ISERR(T73/$T$11),"",T73/$T$11) | V73: =N73+R73 -> 0 | W73: =IF(ISERR(V73/$V$11),"",V73/$V$11) -> 0 | X73: =P73+T73 -> 0 | Y73: =IF(ISERR(X73/$X$11),"",X73/$X$11) -> 0 | Z73: =F73+J73+N73+R73 -> 0 | AA73: =IF(ISERR(Z73/$Z$11),"",Z73/$Z$11) -> 0 | AB73: =H73+L73+P73+T73 -> 0 | AC73: =IF(ISERR(AB73/$AB$11),"",AB73/$AB$11) -> 0 | AD73: =[1]東京事務!$L$70 -> 0 | AE73: =IF(ISERR(AD73/$AD$11),"",AD73/$AD$11) -> 0 | AF73: =AD73 -> 0 | AG73: =IF(ISERR(AF73/$AF$11),"",AF73/$AF$11) -> 0 | AH73: =[1]東京工場!$L$70 -> 0 | AI73: =IF(ISERR(AH73/$AH$11),"",AH73/$AH$11) -> 0 | AJ73: =AH73 -> 0 | AK73: =IF(ISERR(AJ73/$AJ$11),"",AJ73/$AJ$11) -> 0 | AL73: =AD73+AH73 -> 0 | AM73: =IF(ISERR(AL73/$AL$11),"",AL73/AL$11) -> 0 | AN73: =AF73+AJ73 -> 0 | AO73: =IF(ISERR(AN73/$AN$11),"",AN73/$AN$11) -> 0 | AP73: =B73+Z73+AL73 -> 0 | AQ73: =IF(ISERR(AP73/$AP$11),"",AP73/$AP$11) -> 0 | AR73: =D73+AB73+AN73 -> 0 | AS73: =IF(ISERR(AR73/$AR$11),"",AR73/$AR$11) -> 0 | AT73: =[1]全社合計!$N$70 -> 0 | AU73: =IF(ISERR(AT73/$AT$11),"",AT73/$AT$11) -> 0 | AV73: =AT73 -> 0 | AW73: =IF(ISERR(AV73/$AV$11),"",AV73/$AV$11) -> 0 | AX73: =AP73-AT73 -> 0 | AY73: =IF(ISERROR(AP73/AT73),"",AP73/AT73) | AZ73: =AR73-AV73 -> 0 | BA73: =IF(ISERROR(AR73/AV73),"",AR73/AV73)
A74: 事業所税他 | B74: =[1]本部!$L$74 -> 0 | C74: =IF(ISERR(B74/$B$11),"",B74/$B$11) | D74: =B74 -> 0 | E74: =IF(ISERR(D75/$D$11),"",D75/$D$11) | F74: =[1]本社営業!$L$74 -> 0 | G74: =IF(ISERR(F74/$F$11),"",F74/$F$11) -> 0 | H74: =F74 -> 0 | I74: =IF(ISERR(H74/$H$11),"",H74/$H$11) -> 0 | J74: =[1]東大阪!$L$74 -> 0 | K74: =IF(ISERR(J74/$J$11),"",J74/$J$11) -> 0 | L74: =J74 -> 0 | M74: =IF(ISERR(L74/$L$11),"",L74/$L$11) -> 0 | N74: =[1]南港工場!$L$74 -> 0 | O74: =IF(ISERR(N74/$N$11),"",N74/$N$11) -> 0 | P74: =N74 -> 0 | Q74: =IF(ISERR(P74/$P$11),"",P74/$P$11) -> 0 | R74: =[1]南港事務!$L$74 -> 0 | S74: =IF(ISERR(R74/$R$11),"",R74/$R$11) | T74: =R74 -> 0 | U74: =IF(ISERR(T74/$T$11),"",T74/$T$11) | V74: =N74+R74 -> 0 | W74: =IF(ISERR(V74/$V$11),"",V74/$V$11) -> 0 | X74: =P74+T74 -> 0 | Y74: =IF(ISERR(X74/$X$11),"",X74/$X$11) -> 0 | Z74: =F74+J74+N74+R74 -> 0 | AA74: =IF(ISERR(Z74/$Z$11),"",Z74/$Z$11) -> 0 | AB74: =H74+L74+P74+T74 -> 0 | AC74: =IF(ISERR(AB74/$AB$11),"",AB74/$AB$11) -> 0 | AD74: =[1]東京事務!$L$70 -> 0 | AE74: =IF(ISERR(AD74/$AD$11),"",AD74/$AD$11) -> 0 | AF74: =AD74 -> 0 | AG74: =IF(ISERR(AF74/$AF$11),"",AF74/$AF$11) -> 0 | AH74: =[1]東京工場!$L$74 -> 0 | AI74: =IF(ISERR(AH74/$AH$11),"",AH74/$AH$11) -> 0 | AJ74: =AH74 -> 0 | AK74: =IF(ISERR(AJ74/$AJ$11),"",AJ74/$AJ$11) -> 0 | AL74: =AD74+AH74 -> 0 | AM74: =IF(ISERR(AL74/$AL$11),"",AL74/AL$11) -> 0 | AN74: =AF74+AJ74 -> 0 | AO74: =IF(ISERR(AN74/$AN$11),"",AN74/$AN$11) -> 0 | AP74: =B74+Z74+AL74 -> 0 | AQ74: =IF(ISERR(AP74/$AP$11),"",AP74/$AP$11) -> 0 | AR74: =D74+AB74+AN74 -> 0 | AS74: =IF(ISERR(AR74/$AR$11),"",AR74/$AR$11) -> 0 | AT74: =[1]全社合計!$N$74 -> 0 | AU74: =IF(ISERR(AT74/$AT$11),"",AT74/$AT$11) -> 0 | AV74: =AT74 -> 0 | AW74: =IF(ISERR(AV74/$AV$11),"",AV74/$AV$11) -> 0 | AX74: =AP74-AT74 -> 0 | AY74: =IF(ISERROR(AP74/AT74),"",AP74/AT74) | AZ74: =AR74-AV74 -> 0 | BA74: =IF(ISERROR(AR74/AV74),"",AR74/AV74)
A75: 中元歳暮 | B75: =[1]本部!$L$73 -> 0 | C75: =IF(ISERR(B75/$B$11),"",B75/$B$11) | D75: =B75 -> 0 | E75: =IF(ISERR(D76/$D$11),"",D76/$D$11) | F75: =[1]本社営業!$L$73 -> 0 | G75: =IF(ISERR(F75/$F$11),"",F75/$F$11) -> 0 | H75: =F75 -> 0 | I75: =IF(ISERR(H75/$H$11),"",H75/$H$11) -> 0 | J75: =[1]東大阪!$L$73 -> 0 | K75: =IF(ISERR(J75/$J$11),"",J75/$J$11) -> 0 | L75: =J75 -> 0 | M75: =IF(ISERR(L75/$L$11),"",L75/$L$11) -> 0 | N75: =[1]南港工場!$L$73 -> 0 | O75: =IF(ISERR(N75/$N$11),"",N75/$N$11) -> 0 | P75: =N75 -> 0 | Q75: =IF(ISERR(P75/$P$11),"",P75/$P$11) -> 0 | R75: =[1]南港事務!$L$73 -> 0 | S75: =IF(ISERR(R75/$R$11),"",R75/$R$11) | T75: =R75 -> 0 | U75: =IF(ISERR(T75/$T$11),"",T75/$T$11) | V75: =N75+R75 -> 0 | W75: =IF(ISERR(V75/$V$11),"",V75/$V$11) -> 0 | X75: =P75+T75 -> 0 | Y75: =IF(ISERR(X75/$X$11),"",X75/$X$11) -> 0 | Z75: =F75+J75+N75+R75 -> 0 | AA75: =IF(ISERR(Z75/$Z$11),"",Z75/$Z$11) -> 0 | AB75: =H75+L75+P75+T75 -> 0 | AC75: =IF(ISERR(AB75/$AB$11),"",AB75/$AB$11) -> 0 | AD75: =[1]東京事務!$L$73 -> 229861 | AE75: =IF(ISERR(AD75/$AD$11),"",AD75/$AD$11) -> 0.00093325168 | AF75: =AD75 -> 229861 | AG75: =IF(ISERR(AF75/$AF$11),"",AF75/$AF$11) -> 0.00093325168 | AH75: =[1]東京工場!$L$73 -> 0 | AI75: =IF(ISERR(AH75/$AH$11),"",AH75/$AH$11) -> 0 | AJ75: =AH75 -> 0 | AK75: =IF(ISERR(AJ75/$AJ$11),"",AJ75/$AJ$11) -> 0 | AL75: =AD75+AH75 -> 229861 | AM75: =IF(ISERR(AL75/$AL$11),"",AL75/AL$11) -> 0.00089750459 | AN75: =AF75+AJ75 -> 229861 | AO75: =IF(ISERR(AN75/$AN$11),"",AN75/$AN$11) -> 0.00089750459 | AP75: =B75+Z75+AL75 -> 229861 | AQ75: =IF(ISERR(AP75/$AP$11),"",AP75/$AP$11) -> 0.00027762194 | AR75: =D75+AB75+AN75 -> 229861 | AS75: =IF(ISERR(AR75/$AR$11),"",AR75/$AR$11) -> 0.00027762194 | AT75: =[1]全社合計!$N$73 -> 26778 | AU75: =IF(ISERR(AT75/$AT$11),"",AT75/$AT$11) -> 2.7688744e-05 | AV75: =AT75 -> 26778 | AW75: =IF(ISERR(AV75/$AV$11),"",AV75/$AV$11) -> 2.7688744e-05 | AX75: =AP75-AT75 -> 203083 | AY75: =IF(ISERROR(AP75/AT75),"",AP75/AT75) -> 8.5839495 | AZ75: =AR75-AV75 -> 203083 | BA75: =IF(ISERROR(AR75/AV75),"",AR75/AV75) -> 8.5839495
A76: 修繕費 | C76: =IF(ISERR(B76/$B$11),"",B76/$B$11) | D76: =B76 -> 0 | E76: =IF(ISERR(D77/$D$11),"",D77/$D$11) | G76: =IF(ISERR(F76/$F$11),"",F76/$F$11) -> 0 | H76: =F76 -> 0 | I76: =IF(ISERR(H76/$H$11),"",H76/$H$11) -> 0 | K76: =IF(ISERR(J76/$J$11),"",J76/$J$11) -> 0 | L76: =J76 -> 0 | M76: =IF(ISERR(L76/$L$11),"",L76/$L$11) -> 0 | O76: =IF(ISERR(N76/$N$11),"",N76/$N$11) -> 0 | P76: =N76 -> 0 | Q76: =IF(ISERR(P76/$P$11),"",P76/$P$11) -> 0 | S76: =IF(ISERR(R76/$R$11),"",R76/$R$11) | T76: =R76 -> 0 | U76: =IF(ISERR(T76/$T$11),"",T76/$T$11) | V76: =N76+R76 -> 0 | W76: =IF(ISERR(V76/$V$11),"",V76/$V$11) -> 0 | X76: =P76+T76 -> 0 | Y76: =IF(ISERR(X76/$X$11),"",X76/$X$11) -> 0 | Z76: =F76+J76+N76+R76 -> 0 | AA76: =IF(ISERR(Z76/$Z$11),"",Z76/$Z$11) -> 0 | AB76: =H76+L76+P76+T76 -> 0 | AC76: =IF(ISERR(AB76/$AB$11),"",AB76/$AB$11) -> 0 | AE76: =IF(ISERR(AD76/$AD$11),"",AD76/$AD$11) -> 0 | AF76: =AD76 -> 0 | AG76: =IF(ISERR(AF76/$AF$11),"",AF76/$AF$11) -> 0 | AI76: =IF(ISERR(AH76/$AH$11),"",AH76/$AH$11) -> 0 | AJ76: =AH76 -> 0 | AK76: =IF(ISERR(AJ76/$AJ$11),"",AJ76/$AJ$11) -> 0 | AL76: =AD76+AH76 -> 0 | AM76: =IF(ISERR(AL76/$AL$11),"",AL76/AL$11) -> 0 | AN76: =AF76+AJ76 -> 0 | AO76: =IF(ISERR(AN76/$AN$11),"",AN76/$AN$11) -> 0 | AP76: =B76+Z76+AL76 -> 0 | AQ76: =IF(ISERR(AP76/$AP$11),"",AP76/$AP$11) -> 0 | AR76: =D76+AB76+AN76 -> 0 | AS76: =IF(ISERR(AR76/$AR$11),"",AR76/$AR$11) -> 0 | AT76: 0 | AU76: =IF(ISERR(AT76/$AT$11),"",AT76/$AT$11) -> 0 | AV76: =AT76 -> 0 | AW76: =IF(ISERR(AV76/$AV$11),"",AV76/$AV$11) -> 0 | AX76: =AP76-AT76 -> 0 | AY76: =IF(ISERROR(AP76/AT76),"",AP76/AT76) | AZ76: =AR76-AV76 -> 0 | BA76: =IF(ISERROR(AR76/AV76),"",AR76/AV76)
A77: その他特別経費 | C77: =IF(ISERR(B77/$B$11),"",B77/$B$11) | D77: =B77 -> 0 | E77: =IF(ISERR(#REF!/$D$11),"",#REF!/$D$11) | F77: =[1]本社営業!$L$75 -> 672000 | G77: =IF(ISERR(F77/$F$11),"",F77/$F$11) -> 0.001256656 | H77: =F77 -> 672000 | I77: =IF(ISERR(H77/$H$11),"",H77/$H$11) -> 0.001256656 | K77: =IF(ISERR(J77/$J$11),"",J77/$J$11) -> 0 | L77: =J77 -> 0 | M77: =IF(ISERR(L77/$L$11),"",L77/$L$11) -> 0 | O77: =IF(ISERR(N77/$N$11),"",N77/$N$11) -> 0 | P77: =N77 -> 0 | Q77: =IF(ISERR(P77/$P$11),"",P77/$P$11) -> 0 | S77: =IF(ISERR(R77/$R$11),"",R77/$R$11) | T77: =R77 -> 0 | U77: =IF(ISERR(T77/$T$11),"",T77/$T$11) | V77: =N77+R77 -> 0 | W77: =IF(ISERR(V77/$V$11),"",V77/$V$11) -> 0 | X77: =P77+T77 -> 0 | Y77: =IF(ISERR(X77/$X$11),"",X77/$X$11) -> 0 | Z77: =F77+J77+N77+R77 -> 672000 | AA77: =IF(ISERR(Z77/$Z$11),"",Z77/$Z$11) -> 0.0011751275 | AB77: =H77+L77+P77+T77 -> 672000 | AC77: =IF(ISERR(AB77/$AB$11),"",AB77/$AB$11) -> 0.0011751275 | AE77: =IF(ISERR(AD77/$AD$11),"",AD77/$AD$11) -> 0 | AF77: =AD77 -> 0 | AG77: =IF(ISERR(AF77/$AF$11),"",AF77/$AF$11) -> 0 | AI77: =IF(ISERR(AH77/$AH$11),"",AH77/$AH$11) -> 0 | AJ77: =AH77 -> 0 | AK77: =IF(ISERR(AJ77/$AJ$11),"",AJ77/$AJ$11) -> 0 | AL77: =AD77+AH77 -> 0 | AM77: =IF(ISERR(AL77/$AL$11),"",AL77/AL$11) -> 0 | AN77: =AF77+AJ77 -> 0 | AO77: =IF(ISERR(AN77/$AN$11),"",AN77/$AN$11) -> 0 | AP77: =B77+Z77+AL77 -> 672000 | AQ77: =IF(ISERR(AP77/$AP$11),"",AP77/$AP$11) -> 0.0008116294 | AR77: =D77+AB77+AN77 -> 672000 | AS77: =IF(ISERR(AR77/$AR$11),"",AR77/$AR$11) -> 0.0008116294 | AT77: =[1]全社合計!$N$75 -> 672000 | AU77: =IF(ISERR(AT77/$AT$11),"",AT77/$AT$11) -> 0.00069485533 | AV77: =AT77 -> 672000 | AW77: =IF(ISERR(AV77/$AV$11),"",AV77/$AV$11) -> 0.00069485533 | AX77: =AP77-AT77 -> 0 | AY77: =IF(ISERROR(AP77/AT77),"",AP77/AT77) -> 1 | AZ77: =AR77-AV77 -> 0 | BA77: =IF(ISERROR(AR77/AV77),"",AR77/AV77) -> 1
C78: =IF(ISERR(B78/$B$11),"",B78/$B$11) | D78: =B78 -> 0 | E78: =IF(ISERR(#REF!/$D$11),"",#REF!/$D$11) | G78: =IF(ISERR(F78/$F$11),"",F78/$F$11) -> 0 | H78: =F78 -> 0 | I78: =IF(ISERR(H78/$H$11),"",H78/$H$11) -> 0 | K78: =IF(ISERR(J78/$J$11),"",J78/$J$11) -> 0 | L78: =J78 -> 0 | M78: =IF(ISERR(L78/$L$11),"",L78/$L$11) -> 0 | O78: =IF(ISERR(N78/$N$11),"",N78/$N$11) -> 0 | P78: =N78 -> 0 | Q78: =IF(ISERR(P78/$P$11),"",P78/$P$11) -> 0 | S78: =IF(ISERR(R78/$R$11),"",R78/$R$11) | T78: =R78 -> 0 | U78: =IF(ISERR(T78/$T$11),"",T78/$T$11) | V78: =N78+R78 -> 0 | W78: =IF(ISERR(V78/$V$11),"",V78/$V$11) -> 0 | X78: =P78+T78 -> 0 | Y78: =IF(ISERR(X78/$X$11),"",X78/$X$11) -> 0 | Z78: =F78+J78+N78+R78 -> 0 | AA78: =IF(ISERR(Z78/$Z$11),"",Z78/$Z$11) -> 0 | AB78: =H78+L78+P78+T78 -> 0 | AC78: =IF(ISERR(AB78/$AB$11),"",AB78/$AB$11) -> 0 | AE78: =IF(ISERR(AD78/$AD$11),"",AD78/$AD$11) -> 0 | AF78: =AD78 -> 0 | AG78: =IF(ISERR(AF78/$AF$11),"",AF78/$AF$11) -> 0 | AI78: =IF(ISERR(AH78/$AH$11),"",AH78/$AH$11) -> 0 | AJ78: =AH78 -> 0 | AK78: =IF(ISERR(AJ78/$AJ$11),"",AJ78/$AJ$11) -> 0 | AL78: =AD78+AH78 -> 0 | AM78: =IF(ISERR(AL78/$AL$11),"",AL78/AL$11) -> 0 | AN78: =AF78+AJ78 -> 0 | AO78: =IF(ISERR(AN78/$AN$11),"",AN78/$AN$11) -> 0 | AP78: =B78+Z78+AL78 -> 0 | AQ78: =IF(ISERR(AP78/$AP$11),"",AP78/$AP$11) -> 0 | AR78: =D78+AB78+AN78 -> 0 | AS78: =IF(ISERR(AR78/$AR$11),"",AR78/$AR$11) -> 0 | AT78: 0 | AU78: =IF(ISERR(AT78/$AT$11),"",AT78/$AT$11) -> 0 | AV78: =AT78 -> 0 | AW78: =IF(ISERR(AV78/$AV$11),"",AV78/$AV$11) -> 0 | AX78: =AP78-AT78 -> 0 | AY78: =IF(ISERROR(AP78/AT78),"",AP78/AT78) | AZ78: =AR78-AV78 -> 0 | BA78: =IF(ISERROR(AR78/AV78),"",AR78/AV78)
A79: 総経費 | B79: =+B18-B67 -> 0 | C79: =IF(ISERR(B79/$B$11),"",B79/$B$11) | D79: =+D18-D67 -> 0 | E79: =IF(ISERR(#REF!/$D$11),"",#REF!/$D$11) | F79: =F18-F67 -> -6217181 | G79: =IF(ISERR(F79/$F$11),"",F79/$F$11) -> -0.011626277 | H79: =H18-H67 -> -6217181 | I79: =IF(ISERR(H79/$H$11),"",H79/$H$11) -> -0.011626277 | J79: =J18-J67 -> 5018282 | K79: =IF(ISERR(J79/$J$11),"",J79/$J$11) -> 0.56525807 | L79: =J79 -> 5018282 | M79: =IF(ISERR(L79/$L$11),"",L79/$L$11) -> 0.56525807 | N79: =N18-N67 -> 12216512 | O79: =IF(ISERR(N79/$N$11),"",N79/$N$11) -> 0.43286472 | P79: =N79 -> 12216512 | Q79: =IF(ISERR(P79/$P$11),"",P79/$P$11) -> 0.43286472 | R79: =R18-R67 -> 3580518 | T79: =R79 -> 3580518 | U79: =IF(ISERR(T79/$T$11),"",T79/$T$11) | V79: =N79+R79 -> 15797030 | W79: =IF(ISERR(V79/$V$11),"",V79/$V$11) -> 0.55973235 | X79: =P79+T79 -> 15797030 | Y79: =IF(ISERR(X79/$X$11),"",X79/$X$11) -> 0.55973235 | Z79: =F79+J79+V79 -> 14598131 | AA79: =IF(ISERR(Z79/$Z$11),"",Z79/$Z$11) -> 0.025527775 | AB79: =H79+L79+P79+T79 -> 14598131 | AC79: =IF(ISERR(AB79/$AB$11),"",AB79/$AB$11) -> 0.025527775 | AD79: =AD18-AD67 -> 10458661 | AE79: =IF(ISERR(AD79/$AD$11),"",AD79/$AD$11) -> 0.042462893 | AF79: =AD79 -> 10458661 | AG79: =IF(ISERR(AF79/$AF$11),"",AF79/$AF$11) -> 0.042462893 | AH79: =AH18-AH67 -> 6595413 | AI79: =IF(ISERR(AH79/$AH$11),"",AH79/$AH$11) -> 0.67231289 | AJ79: =AH79 -> 6595413 | AK79: =IF(ISERR(AJ79/$AJ$11),"",AJ79/$AJ$11) -> 0.67231289 | AL79: =AD79+AH79 -> 17054074 | AM79: =IF(ISERR(AL79/$AL$11),"",AL79/AL$11) -> 0.066588545 | AN79: =AF79+AJ79 -> 17054074 | AP79: =B79+Z79+AL79 -> 31652205 | AQ79: =IF(ISERR(AP79/$AP$11),"",AP79/$AP$11) -> 0.038228959 | AR79: =D79+AB79+AN79 -> 31652205 | AS79: =IF(ISERR(AR79/$AR$11),"",AR79/$AR$11) -> 0.038228959 | AT79: =AT18-AT67 -> 54378307 | AU79: =IF(ISERR(AT79/$AT$11),"",AT79/$AT$11) -> 0.056227762 | AV79: =AT79 -> 54378307 | AW79: =IF(ISERR(AV79/$AV$11),"",AV79/$AV$11) -> 0.056227762 | AX79: =AP79-AT79 -> -22726102 | AY79: =IF(ISERROR(AP79/AT79),"",AP79/AT79) -> 0.58207412 | AZ79: =AR79-AV79 -> -22726102 | BA79: =IF(ISERROR(AR79/AV79),"",AR79/AV79) -> 0.58207412
A81: 月初在庫重量 | F81: 6712201 | H81: =+F81 -> 6712201 | L81: =+J81 -> 0 | P81: =+N81 -> 0 | T81: =+R81 -> 0 | V81: =N81+R81 -> 0 | X81: =P81+T81 -> 0 | Z81: =F81+J81+N81+R81 -> 6712201 | AB81: =H81+L81+P81+T81 -> 6712201 | AD81: 4214746 | AF81: =+AD81 -> 4214746 | AJ81: =+AH81 -> 0 | AL81: =+AD81+AH81 -> 4214746 | AN81: =+AL81 -> 4214746 | AP81: =+AB81+AL81 -> 10926947 | AR81: =+AP81 -> 10926947 | AT81: 10388772 | AV81: =+AT81 -> 10388772 | AX81: =AP81-AT81 -> 538175 | AY81: =IF(ISERROR(AP81/AT81),"",AP81/AT81) -> 1.0518035 | AZ81: =AR81-AV81 -> 538175 | BA81: =IF(ISERROR(AR81/AV81),"",AR81/AV81) -> 1.0518035
A82: 仕入重量 | F82: 2620536 | H82: =+F82 -> 2620536 | J82: 17050 | L82: =+J82 -> 17050 | N82: 74042 | P82: =+N82 -> 74042 | T82: =+R82 -> 0 | V82: =N82+R82 -> 74042 | X82: =P82+T82 -> 74042 | Z82: =F82+J82+N82+R82 -> 2711628 | AB82: =H82+L82+P82+T82 -> 2711628 | AD82: 816898 | AF82: =+AD82 -> 816898 | AJ82: =+AH82 -> 0 | AL82: =+AD82+AH82 -> 816898 | AN82: =+AL82 -> 816898 | AP82: =+AL82+Z82 -> 3528526 | AR82: =+AP82 -> 3528526 | AT82: 4366781 | AV82: =+AT82 -> 4366781 | AX82: =AP82-AT82 -> -838255 | AY82: =IF(ISERROR(AP82/AT82),"",AP82/AT82) -> 0.80803823 | AZ82: =AR82-AV82 -> -838255 | BA82: =IF(ISERROR(AR82/AV82),"",AR82/AV82) -> 0.80803823
A83: 月末在庫重量 | F83: =[1]本社営業!$L$13 -> 6865951 | H83: =+F83 -> 6865951 | L83: =+J83 -> 0 | P83: =+N83 -> 0 | T83: =+R83 -> 0 | V83: =N83+R83 -> 0 | X83: =P83+T83 -> 0 | Z83: =F83+J83+N83+R83 -> 6865951 | AB83: =H83+L83+P83+T83 -> 6865951 | AD83: =[1]東京事務!$L$13 -> 4129816 | AF83: =+AD83 -> 4129816 | AJ83: =+AH83 -> 0 | AL83: =+AD83+AH83 -> 4129816 | AN83: =+AL83 -> 4129816 | AP83: =+AB83+AL83 -> 10995767 | AR83: =+AP83 -> 10995767 | AT83: =[1]全社合計!$N$13 -> 10538573 | AV83: =+AT83 -> 10538573 | AX83: =AP83-AT83 -> 457194 | AY83: =IF(ISERROR(AP83/AT83),"",AP83/AT83) -> 1.0433829 | AZ83: =AR83-AV83 -> 457194 | BA83: =IF(ISERROR(AR83/AV83),"",AR83/AV83) -> 1.0433829

Sheet 7月
A2: 科 目 | B2: 本部 | F2: 本社営業本部 | AD2: 東京支店 | AP2: 全社合計 | AT2: 前期実績 | AX2: 前期比較
F3: 営業本部 | J3: 東大阪 | N3: 南港工場 | R3: 南港事務 | V3: 南港合計 | Z3: 本社営業合計 | AD3: 東京営業 | AH3: 東京工場 | AL3: 東京合計
B4: 45869 | D4: 累計 | F4: 45869 | H4: 累計 | J4: 45869 | L4: 累計 | N4: 45869 | P4: 累計 | R4: 45869 | T4: 累計 | V4: 45869 | X4: 累計 | Z4: 45869 | AB4: 累計 | AD4: 45869 | AF4: 累計 | AH4: 45869 | AJ4: 累計 | AL4: 45869 | AN4: 累計 | AP4: 45869 | AR4: 累計 | AT4: 45504 | AV4: 累計 | AX4: 月中比較 | AZ4: 累計比較
B5: 金 額 | C5: 比率 | D5: 金 額 | E5: 比率 | F5: 金 額 | G5: 比率 | H5: 金 額 | I5: 比率 | J5: 金 額 | K5: 比率 | L5: 金 額 | M5: 比率 | N5: 金 額 | O5: 比率 | P5: 金 額 | Q5: 比率 | R5: 金 額 | S5: 比率 | T5: 金 額 | U5: 比率 | V5: 金 額 | W5: 比率 | X5: 金 額 | Y5: 比率 | Z5: 金 額 | AA5: 比率 | AB5: 金 額 | AC5: 比率 | AD5: 金 額 | AE5: 比率 | AF5: 金 額 | AG5: 比率 | AH5: 金 額 | AI5: 比率 | AJ5: 金 額 | AK5: 比率 | AL5: 金 額 | AM5: 比率 | AN5: 金 額 | AO5: 比率 | AP5: 金 額 | AQ5: 比率 | AR5: 金 額 | AS5: 比率 | AT5: 金 額 | AU5: 比率 | AV5: 金 額 | AW5: 比率 | AX5: 金 額 | AY5: 比率 | AZ5: 金 額 | BA5: 比率
A6: 売上高 | C6: =IF(ISERR(B6/$B$11),"",B6/$B$11) | E6: =IF(ISERR(D6/$D$11),"",D6/$D$11) | F6: =[2]本社営業!$I$5 -> 436730147 | G6: =IF(ISERR(F6/$F$11),"",F6/$F$11) -> 0.83946412 | H6: =[2]本社営業!$L$5 -> 870401689 | I6: =IF(ISERR(H6/$H$11),"",H6/$H$11) -> 0.82502431 | J6: =[2]東大阪!$I$5 -> 486450 | K6: =IF(ISERR(J6/$J$11),"",J6/$J$11) -> 0.051858301 | L6: =[2]東大阪!$L$5 -> 999385 | M6: =IF(ISERR(L6/$L$11),"",L6/$L$11) -> 0.054736141 | N6: =[2]南港工場!$I$5 -> 3474164 | O6: =IF(ISERR(N6/$N$11),"",N6/$N$11) -> 0.12489589 | P6: =[2]南港工場!$L$5 -> 7161674 | Q6: =IF(ISERR(P6/$P$11),"",P6/$P$11) -> 0.12779815 | S6: =IF(ISERR(R6/$R$11),"",R6/$R$11) | T6: =[2]南港事務!$L$5 -> 0 | U6: =IF(ISERR(T6/$T$11),"",T6/$T$11) | V6: =N6+R6 -> 3474164 | W6: =IF(ISERR(V6/$V$11),"",V6/$V$11) -> 0.12489589 | X6: =P6+T6 -> 7161674 | Y6: =IF(ISERR(X6/$X$11),"",X6/$X$11) -> 0.12779815 | Z6: =F6+J6+N6+R6 -> 440690761 | AA6: =IF(ISERR(Z6/$Z$11),"",Z6/$Z$11) -> 0.79055387 | AB6: =H6+L6+P6+T6 -> 878562748 | AC6: =IF(ISERR(AB6/$AB$11),"",AB6/$AB$11) -> 0.77797216 | AD6: =[2]東京事務!$I$5 -> 149072563 | AE6: =IF(ISERR(AD6/$AD$11),"",AD6/$AD$11) -> 0.61512127 | AF6: =[2]東京事務!$L$5 -> 306816148 | AG6: =IF(ISERR(AF6/$AF$11),"",AF6/$AF$11) -> 0.6278881 | AH6: =[2]東京工場!$I$5 -> 0 | AI6: =IF(ISERR(AH6/$AH$11),"",AH6/$AH$11) -> 0 | AJ6: =[2]東京工場!$L$5 -> 0 | AK6: =IF(ISERR(AJ6/$AJ$11),"",AJ6/$AJ$11) -> 0 | AL6: =AD6+AH6 -> 149072563 | AM6: =IF(ISERR(AL6/$AL$11),"",AL6/AL$11) -> 0.58942857 | AN6: =AF6+AJ6 -> 306816148 | AO6: =IF(ISERR(AN6/$AN$11),"",AN6/$AN$11) -> 0.60275671 | AP6: =B6+Z6+AL6 -> 589763324 | AQ6: =IF(ISERR(AP6/$AP$11),"",AP6/$AP$11) -> 0.7277831 | AR6: =D6+AB6+AN6 -> 1185378896 | AS6: =IF(ISERR(AR6/$AR$11),"",AR6/$AR$11) -> 0.7235332 | AT6: =[2]全社合計!$G$5 -> 690388950 | AU6: =IF(ISERR(AT6/$AT$11),"",AT6/$AT$11) -> 0.73996385 | AV6: =[2]全社合計!$N$5 -> 1345738960 | AW6: =IF(ISERR(AV6/$AV$11),"",AV6/$AV$11) -> 0.70824213 | AX6: =AP6-AT6 -> -100625626 | AY6: =IF(ISERROR(AP6/AT6),"",AP6/AT6) -> 0.85424792 | AZ6: =AR6-AV6 -> -160360064 | BA6: =IF(ISERROR(AR6/AV6),"",AR6/AV6) -> 0.88083866
A7: 輸出売上高 | C7: =IF(ISERR(B7/$B$11),"",B7/$B$11) | E7: =IF(ISERR(D7/$D$11),"",D7/$D$11) | F7: =[2]本社営業!$I$6 -> 44666319 | G7: =IF(ISERR(F7/$F$11),"",F7/$F$11) -> 0.085855699 | H7: =[2]本社営業!$L$6 -> 79096692 | I7: =IF(ISERR(H7/$H$11),"",H7/$H$11) -> 0.074973078 | J7: =[2]東大阪!$I$6 -> 0 | K7: =IF(ISERR(J7/$J$11),"",J7/$J$11) -> 0 | L7: =[2]東大阪!$L$6 -> 0 | M7: =IF(ISERR(L7/$L$11),"",L7/$L$11) -> 0 | N7: =[2]南港工場!$I$6 -> 0 | O7: =IF(ISERR(N7/$N$11),"",N7/$N$11) -> 0 | P7: =[2]南港工場!$L$6 -> 0 | Q7: =IF(ISERR(P7/$P$11),"",P7/$P$11) -> 0 | S7: =IF(ISERR(R7/$R$11),"",R7/$R$11) | T7: =[2]南港事務!$L$6 -> 0 | U7: =IF(ISERR(T7/$T$11),"",T7/$T$11) | V7: =N7+R7 -> 0 | W7: =IF(ISERR(V7/$V$11),"",V7/$V$11) -> 0 | X7: =P7+T7 -> 0 | Y7: =IF(ISERR(X7/$X$11),"",X7/$X$11) -> 0 | Z7: =F7+J7+N7+R7 -> 44666319 | AA7: =IF(ISERR(Z7/$Z$11),"",Z7/$Z$11) -> 0.080126779 | AB7: =H7+L7+P7+T7 -> 79096692 | AC7: =IF(ISERR(AB7/$AB$11),"",AB7/$AB$11) -> 0.070040557 | AD7: =[2]東京事務!$I$6 -> 0 | AE7: =IF(ISERR(AD7/$AD$11),"",AD7/$AD$11) -> 0 | AF7: =[2]東京事務!$L$6 -> 0 | AG7: =IF(ISERR(AF7/$AF$11),"",AF7/$AF$11) -> 0 | AH7: =[2]東京工場!$I$6 -> 0 | AI7: =IF(ISERR(AH7/$AH$11),"",AH7/$AH$11) -> 0 | AJ7: =[2]東京工場!$L$6 -> 0 | AK7: =IF(ISERR(AJ7/$AJ$11),"",AJ7/$AJ$11) -> 0 | AL7: =AD7+AH7 -> 0 | AM7: =IF(ISERR(AL7/$AL$11),"",AL7/AL$11) -> 0 | AN7: =AF7+AJ7 -> 0 | AO7: =IF(ISERR(AN7/$AN$11),"",AN7/$AN$11) -> 0 | AP7: =B7+Z7+AL7 -> 44666319 | AQ7: =IF(ISERR(AP7/$AP$11),"",AP7/$AP$11) -> 0.055119386 | AR7: =D7+AB7+AN7 -> 79096692 | AS7: =IF(ISERR(AR7/$AR$11),"",AR7/$AR$11) -> 0.048279147 | AT7: =[2]全社合計!$G$6 -> 24215359 | AU7: =IF(ISERR(AT7/$AT$11),"",AT7/$AT$11) -> 0.025954196 | AV7: =[2]全社合計!$N$6 -> 104238567 | AW7: =IF(ISERR(AV7/$AV$11),"",AV7/$AV$11) -> 0.054859187 | AX7: =AP7-AT7 -> 20450960 | AY7: =IF(ISERROR(AP7/AT7),"",AP7/AT7) -> 1.844545 | AZ7: =AR7-AV7 -> -25141875 | BA7: =IF(ISERROR(AR7/AV7),"",AR7/AV7) -> 0.75880448
A8: 加工賃収入 | C8: =IF(ISERR(B8/$B$11),"",B8/$B$11) | E8: =IF(ISERR(D8/$D$11),"",D8/$D$11) | F8: =[2]本社営業!$I$7 -> 1489357 | G8: =IF(ISERR(F8/$F$11),"",F8/$F$11) -> 0.0028627787 | H8: =[2]本社営業!$L$7 -> 4475067 | I8: =IF(ISERR(H8/$H$11),"",H8/$H$11) -> 0.0042417646 | J8: =[2]東大阪!$I$7 -> 0 | K8: =IF(ISERR(J8/$J$11),"",J8/$J$11) -> 0 | L8: =[2]東大阪!$L$7 -> 0 | M8: =IF(ISERR(L8/$L$11),"",L8/$L$11) -> 0 | N8: =[2]南港工場!$I$7 -> 14579426 | O8: =IF(ISERR(N8/$N$11),"",N8/$N$11) -> 0.52412908 | P8: =[2]南港工場!$L$7 -> 29273546 | Q8: =IF(ISERR(P8/$P$11),"",P8/$P$11) -> 0.52237855 | S8: =IF(ISERR(R8/$R$11),"",R8/$R$11) | T8: =[2]南港事務!$L$7 -> 0 | U8: =IF(ISERR(T8/$T$11),"",T8/$T$11) | V8: =N8+R8 -> 14579426 | W8: =IF(ISERR(V8/$V$11),"",V8/$V$11) -> 0.52412908 | X8: =P8+T8 -> 29273546 | Y8: =IF(ISERR(X8/$X$11),"",X8/$X$11) -> 0.52237855 | Z8: =F8+J8+N8+R8 -> 16068783 | AA8: =IF(ISERR(Z8/$Z$11),"",Z8/$Z$11) -> 0.028825743 | AB8: =H8+L8+P8+T8 -> 33748613 | AC8: =IF(ISERR(AB8/$AB$11),"",AB8/$AB$11) -> 0.029884583 | AD8: =[2]東京事務!$I$7 -> 217128 | AE8: =IF(ISERR(AD8/$AD$11),"",AD8/$AD$11) -> 0.00089593986 | AF8: =[2]東京事務!$L$7 -> 331624 | AG8: =IF(ISERR(AF8/$AF$11),"",AF8/$AF$11) -> 0.00067865647 | AH8: =[2]東京工場!$I$7 -> 0 | AI8: =IF(ISERR(AH8/$AH$11),"",AH8/$AH$11) -> 0 | AJ8: =[2]東京工場!$L$7 -> 0 | AK8: =IF(ISERR(AJ8/$AJ$11),"",AJ8/$AJ$11) -> 0 | AL8: =AD8+AH8 -> 217128 | AM8: =IF(ISERR(AL8/$AL$11),"",AL8/AL$11) -> 0.00085851779 | AN8: =AF8+AJ8 -> 331624 | AO8: =IF(ISERR(AN8/$AN$11),"",AN8/$AN$11) -> 0.00065149307 | AP8: =B8+Z8+AL8 -> 16285911 | AQ8: =IF(ISERR(AP8/$AP$11),"",AP8/$AP$11) -> 0.020097233 | AR8: =D8+AB8+AN8 -> 34080237 | AS8: =IF(ISERR(AR8/$AR$11),"",AR8/$AR$11) -> 0.020801942 | AT8: =[2]全社合計!$G$7 -> 17230567 | AU8: =IF(ISERR(AT8/$AT$11),"",AT8/$AT$11) -> 0.018467846 | AV8: =[2]全社合計!$N$7 -> 31540648 | AW8: =IF(ISERR(AV8/$AV$11),"",AV8/$AV$11) -> 0.016599368 | AX8: =AP8-AT8 -> -944656 | AY8: =IF(ISERROR(AP8/AT8),"",AP8/AT8) -> 0.94517557 | AZ8: =AR8-AV8 -> 2539589 | BA8: =IF(ISERROR(AR8/AV8),"",AR8/AV8) -> 1.080518
A9: 役務収入 | C9: =IF(ISERR(B9/$B$11),"",B9/$B$11) | E9: =IF(ISERR(D9/$D$11),"",D9/$D$11) | F9: =[2]本社営業!$I$8 -> 738300 | G9: =IF(ISERR(F9/$F$11),"",F9/$F$11) -> 0.0014191289 | H9: =[2]本社営業!$L$8 -> 1474370 | I9: =IF(ISERR(H9/$H$11),"",H9/$H$11) -> 0.0013975054 | J9: =[2]東大阪!$I$8 -> 0 | K9: =IF(ISERR(J9/$J$11),"",J9/$J$11) -> 0 | L9: =[2]東大阪!$L$8 -> 0 | M9: =IF(ISERR(L9/$L$11),"",L9/$L$11) -> 0 | N9: =[2]南港工場!$I$8 -> 4453640 | O9: =IF(ISERR(N9/$N$11),"",N9/$N$11) -> 0.16010796 | P9: =[2]南港工場!$L$8 -> 8934552 | Q9: =IF(ISERR(P9/$P$11),"",P9/$P$11) -> 0.15943468 | S9: =IF(ISERR(R9/$R$11),"",R9/$R$11) | T9: =[2]南港事務!$L$8 -> 0 | U9: =IF(ISERR(T9/$T$11),"",T9/$T$11) | V9: =N9+R9 -> 4453640 | W9: =IF(ISERR(V9/$V$11),"",V9/$V$11) -> 0.16010796 | X9: =P9+T9 -> 8934552 | Y9: =IF(ISERR(X9/$X$11),"",X9/$X$11) -> 0.15943468 | Z9: =F9+J9+N9+R9 -> 5191940 | AA9: =IF(ISERR(Z9/$Z$11),"",Z9/$Z$11) -> 0.009313806 | AB9: =H9+L9+P9+T9 -> 10408922 | AC9: =IF(ISERR(AB9/$AB$11),"",AB9/$AB$11) -> 0.0092171578 | AD9: =[2]東京事務!$I$8 -> 15180 | AE9: =IF(ISERR(AD9/$AD$11),"",AD9/$AD$11) -> 6.2637555e-05 | AF9: =[2]東京事務!$L$8 -> 21180 | AG9: =IF(ISERR(AF9/$AF$11),"",AF9/$AF$11) -> 4.3344101e-05 | AH9: =[2]東京工場!$I$8 -> 0 | AI9: =IF(ISERR(AH9/$AH$11),"",AH9/$AH$11) -> 0 | AJ9: =[2]東京工場!$L$8 -> 0 | AK9: =IF(ISERR(AJ9/$AJ$11),"",AJ9/$AJ$11) -> 0 | AL9: =AD9+AH9 -> 15180 | AM9: =IF(ISERR(AL9/$AL$11),"",AL9/AL$11) -> 6.0021278e-05 | AN9: =AF9+AJ9 -> 21180 | AO9: =IF(ISERR(AN9/$AN$11),"",AN9/$AN$11) -> 4.1609242e-05 | AP9: =B9+Z9+AL9 -> 5207120 | AQ9: =IF(ISERR(AP9/$AP$11),"",AP9/$AP$11) -> 0.0064257199 | AR9: =D9+AB9+AN9 -> 10430102 | AS9: =IF(ISERR(AR9/$AR$11),"",AR9/$AR$11) -> 0.00636634 | AT9: =[2]全社合計!$G$8 -> 5828020 | AU9: =IF(ISERR(AT9/$AT$11),"",AT9/$AT$11) -> 0.0062465138 | AV9: =[2]全社合計!$N$8 -> 9627907 | AW9: =IF(ISERR(AV9/$AV$11),"",AV9/$AV$11) -> 0.0050670224 | AX9: =AP9-AT9 -> -620900 | AY9: =IF(ISERROR(AP9/AT9),"",AP9/AT9) -> 0.89346296 | AZ9: =AR9-AV9 -> 802195 | BA9: =IF(ISERROR(AR9/AV9),"",AR9/AV9) -> 1.0833198
A10: 本支店売上高 | C10: =IF(ISERR(B10/$B$11),"",B10/$B$11) | E10: =IF(ISERR(D10/$D$11),"",D10/$D$11) | F10: =[2]本社営業!$I$9 -> 36624612 | G10: =IF(ISERR(F10/$F$11),"",F10/$F$11) -> 0.070398272 | H10: =[2]本社営業!$L$9 -> 99553450 | I10: =IF(ISERR(H10/$H$11),"",H10/$H$11) -> 0.094363346 | J10: =[2]東大阪!$I$9 -> 8893919 | K10: =IF(ISERR(J10/$J$11),"",J10/$J$11) -> 0.9481417 | L10: =[2]東大阪!$L$9 -> 17258844 | M10: =IF(ISERR(L10/$L$11),"",L10/$L$11) -> 0.94526386 | N10: =[2]南港工場!$I$9 -> 5309250 | O10: =IF(ISERR(N10/$N$11),"",N10/$N$11) -> 0.19086707 | P10: =[2]南港工場!$L$9 -> 10669179 | Q10: =IF(ISERR(P10/$P$11),"",P10/$P$11) -> 0.19038863 | S10: =IF(ISERR(R10/$R$11),"",R10/$R$11) | T10: =[2]南港事務!$L$9 -> 0 | U10: =IF(ISERR(T10/$T$11),"",T10/$T$11) | V10: =N10+R10 -> 5309250 | W10: =IF(ISERR(V10/$V$11),"",V10/$V$11) -> 0.19086707 | X10: =P10+T10 -> 10669179 | Y10: =IF(ISERR(X10/$X$11),"",X10/$X$11) -> 0.19038863 | Z10: =F10+J10+N10+R10 -> 50827781 | AA10: =IF(ISERR(Z10/$Z$11),"",Z10/$Z$11) -> 0.091179807 | AB10: =H10+L10+P10+T10 -> 127481473 | AC10: =IF(ISERR(AB10/$AB$11),"",AB10/$AB$11) -> 0.11288555 | AD10: =[2]東京事務!$I$9 -> 93041752 | AE10: =IF(ISERR(AD10/$AD$11),"",AD10/$AD$11) -> 0.38392015 | AF10: =[2]東京事務!$L$9 -> 181478862 | AG10: =IF(ISERR(AF10/$AF$11),"",AF10/$AF$11) -> 0.3713899 | AH10: =[2]東京工場!$I$9 -> 10563686 | AI10: =IF(ISERR(AH10/$AH$11),"",AH10/$AH$11) -> 1 | AJ10: =[2]東京工場!$L$9 -> 20373721 | AK10: =IF(ISERR(AJ10/$AJ$11),"",AJ10/$AJ$11) -> 1 | AL10: =AD10+AH10 -> 103605438 | AM10: =IF(ISERR(AL10/$AL$11),"",AL10/AL$11) -> 0.40965289 | AN10: =AF10+AJ10 -> 201852583 | AO10: =IF(ISERR(AN10/$AN$11),"",AN10/$AN$11) -> 0.39655018 | AP10: =B10+Z10+AL10 -> 154433219 | AQ10: =IF(ISERR(AP10/$AP$11),"",AP10/$AP$11) -> 0.19057456 | AR10: =D10+AB10+AN10 -> 329334056 | AS10: =IF(ISERR(AR10/$AR$11),"",AR10/$AR$11) -> 0.20101937 | AT10: =[2]全社合計!$G$9 -> 195340719 | AU10: =IF(ISERR(AT10/$AT$11),"",AT10/$AT$11) -> 0.20936759 | AV10: =[2]全社合計!$N$9 -> 408965326 | AW10: =IF(ISERR(AV10/$AV$11),"",AV10/$AV$11) -> 0.21523229 | AX10: =AP10-AT10 -> -40907500 | AY10: =IF(ISERROR(AP10/AT10),"",AP10/AT10) -> 0.79058386 | AZ10: =AR10-AV10 -> -79631270 | BA10: =IF(ISERROR(AR10/AV10),"",AR10/AV10) -> 0.80528601
A11: 【売上高合計】 | C11: =IF(ISERR(B11/$B$11),"",B11/$B$11) | E11: =IF(ISERR(D11/$D$11),"",D11/$D$11) | F11: =SUM(F6:F10) -> 520248735 | G11: =IF(ISERR(F11/$F$11),"",F11/$F$11) -> 1 | H11: =SUM(H6:H10) -> 1055001268 | I11: =IF(ISERR(H11/$H$11),"",H11/$H$11) -> 1 | J11: =SUM(J6:J10) -> 9380369 | K11: =IF(ISERR(J11/$J$11),"",J11/$J$11) -> 1 | L11: =SUM(L6:L10) -> 18258229 | M11: =IF(ISERR(L11/$L$11),"",L11/$L$11) -> 1 | N11: =SUM(N6:N10) -> 27816480 | O11: =IF(ISERR(N11/$N$11),"",N11/$N$11) -> 1 | P11: =SUM(P6:P10) -> 56038951 | Q11: =IF(ISERR(P11/$P$11),"",P11/$P$11) -> 1 | R11: =SUM(R6:R10) -> 0 | S11: =IF(ISERR(R11/$R$11),"",R11/$R$11) | T11: =SUM(T6:T10) -> 0 | U11: =IF(ISERR(T11/$T$11),"",T11/$T$11) | V11: =N11+R11 -> 27816480 | W11: =IF(ISERR(V11/$V$11),"",V11/$V$11) -> 1 | X11: =P11+T11 -> 56038951 | Y11: =IF(ISERR(X11/$X$11),"",X11/$X$11) -> 1 | Z11: =F11+J11+N11+R11 -> 557445584 | AA11: =IF(ISERR(Z11/$Z$11),"",Z11/$Z$11) -> 1 | AB11: =H11+L11+P11+T11 -> 1129298448 | AC11: =IF(ISERR(AB11/$AB$11),"",AB11/$AB$11) -> 1 | AD11: =SUM(AD6:AD10) -> 242346623 | AE11: =IF(ISERR(AD11/$AD$11),"",AD11/$AD$11) -> 1 | AF11: =SUM(AF6:AF10) -> 488647814 | AG11: =IF(ISERR(AF11/$AF$11),"",AF11/$AF$11) -> 1 | AH11: =SUM(AH6:AH10) -> 10563686 | AI11: =IF(ISERR(AH11/$AH$11),"",AH11/$AH$11) -> 1 | AJ11: =SUM(AJ6:AJ10) -> 20373721 | AK11: =IF(ISERR(AJ11/$AJ$11),"",AJ11/$AJ$11) -> 1 | AL11: =AD11+AH11 -> 252910309 | AM11: =IF(ISERR(AL11/$AL$11),"",AL11/AL$11) -> 1 | AN11: =AF11+AJ11 -> 509021535 | AO11: =IF(ISERR(AN11/$AN$11),"",AN11/$AN$11) -> 1 | AP11: =B11+Z11+AL11 -> 810355893 | AQ11: =IF(ISERR(AP11/$AP$11),"",AP11/$AP$11) -> 1 | AR11: =D11+AB11+AN11 -> 1638319983 | AS11: =IF(ISERR(AR11/$AR$11),"",AR11/$AR$11) -> 1 | AT11: =SUM(AT6:AT10) -> 933003615 | AU11: =IF(ISERR(AT11/$AT$11),"",AT11/$AT$11) -> 1 | AV11: =SUM(AV6:AV10) -> 1900111408 | AW11: =IF(ISERR(AV11/$AV$11),"",AV11/$AV$11) -> 1 | AX11: =AP11-AT11 -> -122647722 | AY11: =IF(ISERROR(AP11/AT11),"",AP11/AT11) -> 0.86854529 | AZ11: =AR11-AV11 -> -261791425 | BA11: =IF(ISERROR(AR11/AV11),"",AR11/AV11) -> 0.86222312
A12: （売上重量） | F12: =[2]本社営業!$I$11 -> 2430735 | H12: =[2]本社営業!$L$11 -> 4902450 | J12: =[2]東大阪!$I$11 -> 35091 | L12: =[2]東大阪!$L$11 -> 52141 | N12: =[2]南港工場!$I$11 -> 84804 | P12: =[2]南港工場!$L$11 -> 177834 | T12: =[2]南港事務!$L$11 -> 0 | V12: =N12+R12 -> 84804 | X12: =P12+T12 -> 177834 | Z12: =F12+J12+N12+R12 -> 2550630 | AB12: =H12+L12+P12+T12 -> 5132425 | AD12: =[2]東京事務!$I$11 -> 1015914 | AF12: =[2]東京事務!$L$11 -> 2020837 | AI12: =IF(ISERR(AH12/$AH$11),"",AH12/$AH$11) -> 0 | AJ12: =[2]東京工場!$L$11 -> 0 | AL12: =AD12+AH12 -> 1015914 | AN12: =AF12+AJ12 -> 2020837 | AP12: =B12+Z12+AL12 -> 3566544 | AR12: =D12+AB12+AN12 -> 7153262 | AT12: =[2]全社合計!$G$11 -> 3844692 | AV12: =[2]全社合計!$N$11 -> 8181398 | AX12: =AP12-AT12 -> -278148 | AY12: =IF(ISERROR(AP12/AT12),"",AP12/AT12) -> 0.92765402 | AZ12: =AR12-AV12 -> -1028136 | BA12: =IF(ISERROR(AR12/AV12),"",AR12/AV12) -> 0.87433248
A13: （加工重量） | H13: =[2]本社営業!$N$12 -> 0 | L13: =[2]東大阪!$L$12 -> 0 | N13: =[2]南港工場!$I$12 -> 3888320 | P13: =[2]南港工場!$L$12 -> 7864961 | T13: =[2]南港事務!$N$12 -> 0 | V13: =N13+R13 -> 3888320 | X13: =P13+T13 -> 7864961 | Z13: =F13+J13+N13+R13 -> 3888320 | AB13: =H13+L13+P13+T13 -> 7864961 | AF13: =[2]東京事務!$L$12 -> 0 | AI13: =IF(ISERR(AH13/$AH$11),"",AH13/$AH$11) -> 0 | AJ13: =[2]東京工場!$L$12 -> 0 | AL13: =AD13+AH13 -> 0 | AN13: =AF13+AJ13 -> 0 | AP13: =B13+Z13+AL13 -> 3888320 | AR13: =D13+AB13+AN13 -> 7864961 | AT13: =[2]全社合計!$G$12 -> 4081128 | AV13: =[2]全社合計!$N$12 -> 7616916 | AX13: =AP13-AT13 -> -192808 | AY13: =IF(ISERROR(AP13/AT13),"",AP13/AT13) -> 0.9527562 | AZ13: =AR13-AV13 -> 248045 | BA13: =IF(ISERROR(AR13/AV13),"",AR13/AV13) -> 1.032565
A14: 期首商品棚卸高 | C14: =IF(ISERR(B14/$B$11),"",B14/$B$11) | E14: =IF(ISERR(D14/$D$11),"",D14/$D$11) | F14: =[2]本社営業!$I$14 -> 1212643896 | G14: =IF(ISERR(F14/$F$11),"",F14/$F$11) -> 2.3308925 | H14: =[2]本社営業!$L$14 -> 1205973702 | I14: =IF(ISERR(H14/$H$11),"",H14/$H$11) -> 1.1431017 | K14: =IF(ISERR(J14/$J$11),"",J14/$J$11) -> 0 | L14: =[2]東大阪!$L$14 -> 0 | M14: =IF(ISERR(L14/$L$11),"",L14/$L$11) -> 0 | O14: =IF(ISERR(N14/$N$11),"",N14/$N$11) -> 0 | P14: =[2]南港工場!$L$14 -> 0 | Q14: =IF(ISERR(P14/$P$11),"",P14/$P$11) -> 0 | S14: =IF(ISERR(R14/$R$11),"",R14/$R$11) | T14: =[2]南港事務!$L$14 -> 0 | U14: =IF(ISERR(T14/$T$11),"",T14/$T$11) | V14: =N14+R14 -> 0 | W14: =IF(ISERR(V14/$V$11),"",V14/$V$11) -> 0 | X14: =P14+T14 -> 0 | Y14: =IF(ISERR(X14/$X$11),"",X14/$X$11) -> 0 | Z14: =F14+J14+N14+R14 -> 1212643896 | AA14: =IF(ISERR(Z14/$Z$11),"",Z14/$Z$11) -> 2.1753583 | AB14: =H14+L14+P14+T14 -> 1205973702 | AC14: =IF(ISERR(AB14/$AB$11),"",AB14/$AB$11) -> 1.0678964 | AD14: =[2]東京事務!$I$14 -> 778809293 | AE14: =IF(ISERR(AD14/$AD$11),"",AD14/$AD$11) -> 3.2136173 | AF14: =[2]東京事務!$L$14 -> 804499700 | AG14: =IF(ISERR(AF14/$AF$11),"",AF14/$AF$11) -> 1.6463794 | AI14: =IF(ISERR(AH14/$AH$11),"",AH14/$AH$11) -> 0 | AJ14: =[2]東京工場!$L$14 -> 0 | AK14: =IF(ISERR(AJ14/$AJ$11),"",AJ14/$AJ$11) -> 0 | AL14: =AD14+AH14 -> 778809293 | AM14: =IF(ISERR(AL14/$AL$11),"",AL14/AL$11) -> 3.0793893 | AN14: =AF14+AJ14 -> 804499700 | AO14: =IF(ISERR(AN14/$AN$11),"",AN14/$AN$11) -> 1.5804826 | AP14: =B14+Z14+AL14 -> 1991453189 | AQ14: =IF(ISERR(AP14/$AP$11),"",AP14/$AP$11) -> 2.4575044 | AR14: =D14+AB14+AN14 -> 2010473402 | AS14: =IF(ISERR(AR14/$AR$11),"",AR14/$AR$11) -> 1.2271555 | AT14: =[2]全社合計!$G$14 -> 1864108715 | AU14: =IF(ISERR(AT14/$AT$11),"",AT14/$AT$11) -> 1.9979652 | AV14: =[2]全社合計!$N$14 -> 1816376496 | AW14: =IF(ISERR(AV14/$AV$11),"",AV14/$AV$11) -> 0.95593158 | AX14: =AP14-AT14 -> 127344474 | AY14: =IF(ISERROR(AP14/AT14),"",AP14/AT14) -> 1.0683139 | AZ14: =AR14-AV14 -> 194096906 | BA14: =IF(ISERROR(AR14/AV14),"",AR14/AV14) -> 1.1068594
A15: 当期商品仕入高 | C15: =IF(ISERR(B15/$B$11),"",B15/$B$11) | E15: =IF(ISERR(D15/$D$11),"",D15/$D$11) | F15: =[2]本社営業!$I$15 -> 420297650 | G15: =IF(ISERR(F15/$F$11),"",F15/$F$11) -> 0.80787827 | H15: =[2]本社営業!$L$15 -> 890432349 | I15: =IF(ISERR(H15/$H$11),"",H15/$H$11) -> 0.84401069 | J15: =[2]東大阪!$I$15 -> 563411 | K15: =IF(ISERR(J15/$J$11),"",J15/$J$11) -> 0.060062776 | L15: =[2]東大阪!$L$15 -> 1059296 | M15: =IF(ISERR(L15/$L$11),"",L15/$L$11) -> 0.058017456 | N15: =[2]南港工場!$I$15 -> 1830609 | O15: =IF(ISERR(N15/$N$11),"",N15/$N$11) -> 0.065810232 | P15: =[2]南港工場!$L$15 -> 3971948 | Q15: =IF(ISERR(P15/$P$11),"",P15/$P$11) -> 0.070878343 | S15: =IF(ISERR(R15/$R$11),"",R15/$R$11) | T15: =[2]南港事務!$L$15 -> 0 | U15: =IF(ISERR(T15/$T$11),"",T15/$T$11) | V15: =N15+R15 -> 1830609 | W15: =IF(ISERR(V15/$V$11),"",V15/$V$11) -> 0.065810232 | X15: =P15+T15 -> 3971948 | Y15: =IF(ISERR(X15/$X$11),"",X15/$X$11) -> 0.070878343 | Z15: =F15+J15+N15+R15 -> 422691670 | AA15: =IF(ISERR(Z15/$Z$11),"",Z15/$Z$11) -> 0.75826535 | AB15: =H15+L15+P15+T15 -> 895463593 | AC15: =IF(ISERR(AB15/$AB$11),"",AB15/$AB$11) -> 0.79293795 | AD15: =[2]東京事務!$I$15 -> 200040689 | AE15: =IF(ISERR(AD15/$AD$11),"",AD15/$AD$11) -> 0.82543213 | AF15: =[2]東京事務!$L$15 -> 399290267 | AG15: =IF(ISERR(AF15/$AF$11),"",AF15/$AF$11) -> 0.81713303 | AH15: =[2]東京工場!$I$15 -> 0 | AI15: =IF(ISERR(AH15/$AH$11),"",AH15/$AH$11) -> 0 | AJ15: =[2]東京工場!$L$15 -> 0 | AK15: =IF(ISERR(AJ15/$AJ$11),"",AJ15/$AJ$11) -> 0 | AL15: =AD15+AH15 -> 200040689 | AM15: =IF(ISERR(AL15/$AL$11),"",AL15/AL$11) -> 0.79095506 | AN15: =AF15+AJ15 -> 399290267 | AO15: =IF(ISERR(AN15/$AN$11),"",AN15/$AN$11) -> 0.78442706 | AP15: =B15+Z15+AL15 -> 622732359 | AQ15: =IF(ISERR(AP15/$AP$11),"",AP15/$AP$11) -> 0.76846774 | AR15: =D15+AB15+AN15 -> 1294753860 | AS15: =IF(ISERR(AR15/$AR$11),"",AR15/$AR$11) -> 0.79029364 | AT15: =[2]全社合計!$G$15 -> 821388398 | AU15: =IF(ISERR(AT15/$AT$11),"",AT15/$AT$11) -> 0.88037001 | AV15: =[2]全社合計!$N$15 -> 1689136061 | AW15: =IF(ISERR(AV15/$AV$11),"",AV15/$AV$11) -> 0.88896685 | AX15: =AP15-AT15 -> -198656039 | AY15: =IF(ISERROR(AP15/AT15),"",AP15/AT15) -> 0.75814604 | AZ15: =AR15-AV15 -> -394382201 | BA15: =IF(ISERROR(AR15/AV15),"",AR15/AV15) -> 0.76651839
A16: 期末商品棚卸高 | C16: =IF(ISERR(B16/$B$11),"",B16/$B$11) | E16: =IF(ISERR(D16/$D$11),"",D16/$D$11) | F16: =[2]本社営業!$I$16 -> 1186732279 | G16: =IF(ISERR(F16/$F$11),"",F16/$F$11) -> 2.2810863 | H16: =[2]本社営業!$L$16 -> 1186732279 | I16: =IF(ISERR(H16/$H$11),"",H16/$H$11) -> 1.1248634 | K16: =IF(ISERR(J16/$J$11),"",J16/$J$11) -> 0 | L16: =[2]東大阪!$L$16 -> 0 | M16: =IF(ISERR(L16/$L$11),"",L16/$L$11) -> 0 | O16: =IF(ISERR(N16/$N$11),"",N16/$N$11) -> 0 | P16: =[2]南港工場!$L$16 -> 0 | Q16: =IF(ISERR(P16/$P$11),"",P16/$P$11) -> 0 | S16: =IF(ISERR(R16/$R$11),"",R16/$R$11) | T16: =[2]南港事務!$L$16 -> 0 | U16: =IF(ISERR(T16/$T$11),"",T16/$T$11) | V16: =N16+R16 -> 0 | W16: =IF(ISERR(V16/$V$11),"",V16/$V$11) -> 0 | X16: =P16+T16 -> 0 | Y16: =IF(ISERR(X16/$X$11),"",X16/$X$11) -> 0 | Z16: =F16+J16+N16+R16 -> 1186732279 | AA16: =IF(ISERR(Z16/$Z$11),"",Z16/$Z$11) -> 2.1288756 | AB16: =H16+L16+P16+T16 -> 1186732279 | AC16: =IF(ISERR(AB16/$AB$11),"",AB16/$AB$11) -> 1.050858 | AD16: =[2]東京事務!$I$16 -> 755986627 | AE16: =IF(ISERR(AD16/$AD$11),"",AD16/$AD$11) -> 3.1194436 | AF16: =[2]東京事務!$L$16 -> 755986627 | AG16: =IF(ISERR(AF16/$AF$11),"",AF16/$AF$11) -> 1.5470992 | AI16: =IF(ISERR(AH16/$AH$11),"",AH16/$AH$11) -> 0 | AJ16: =[2]東京工場!$L$16 -> 0 | AK16: =IF(ISERR(AJ16/$AJ$11),"",AJ16/$AJ$11) -> 0 | AL16: =AD16+AH16 -> 755986627 | AM16: =IF(ISERR(AL16/$AL$11),"",AL16/AL$11) -> 2.9891491 | AN16: =AF16+AJ16 -> 755986627 | AO16: =IF(ISERR(AN16/$AN$11),"",AN16/$AN$11) -> 1.4851761 | AP16: =B16+Z16+AL16 -> 1942718906 | AQ16: =IF(ISERR(AP16/$AP$11),"",AP16/$AP$11) -> 2.3973651 | AR16: =D16+AB16+AN16 -> 1942718906 | AS16: =IF(ISERR(AR16/$AR$11),"",AR16/$AR$11) -> 1.1857994 | AT16: =[2]全社合計!$G$16 -> 1899825427 | AU16: =IF(ISERR(AT16/$AT$11),"",AT16/$AT$11) -> 2.0362466 | AV16: =[2]全社合計!$N$16 -> 1899825427 | AW16: =IF(ISERR(AV16/$AV$11),"",AV16/$AV$11) -> 0.99984949 | AX16: =AP16-AT16 -> 42893479 | AY16: =IF(ISERROR(AP16/AT16),"",AP16/AT16) -> 1.0225776 | AZ16: =AR16-AV16 -> 42893479 | BA16: =IF(ISERROR(AR16/AV16),"",AR16/AV16) -> 1.0225776
A17: 《差引売上原価》 | C17: =IF(ISERR(B17/$B$11),"",B17/$B$11) | E17: =IF(ISERR(D17/$D$11),"",D17/$D$11) | F17: =F14+F15-F16 -> 446209267 | G17: =IF(ISERR(F17/$F$11),"",F17/$F$11) -> 0.85768448 | H17: =H14+H15-H16 -> 909673772 | I17: =IF(ISERR(H17/$H$11),"",H17/$H$11) -> 0.86224898 | J17: =J14+J15-J16 -> 563411 | K17: =IF(ISERR(J17/$J$11),"",J17/$J$11) -> 0.060062776 | L17: =L14+L15-L16 -> 1059296 | M17: =IF(ISERR(L17/$L$11),"",L17/$L$11) -> 0.058017456 | N17: =N14+N15-N16 -> 1830609 | O17: =IF(ISERR(N17/$N$11),"",N17/$N$11) -> 0.065810232 | P17: =P14+P15-P16 -> 3971948 | Q17: =IF(ISERR(P17/$P$11),"",P17/$P$11) -> 0.070878343 | R17: =R14+R15-R16 -> 0 | S17: =IF(ISERR(R17/$R$11),"",R17/$R$11) | T17: =T14+T15-T16 -> 0 | U17: =IF(ISERR(T17/$T$11),"",T17/$T$11) | V17: =N17+R17 -> 1830609 | W17: =IF(ISERR(V17/$V$11),"",V17/$V$11) -> 0.065810232 | X17: =P17+T17 -> 3971948 | Y17: =IF(ISERR(X17/$X$11),"",X17/$X$11) -> 0.070878343 | Z17: =F17+J17+N17+R17 -> 448603287 | AA17: =IF(ISERR(Z17/$Z$11),"",Z17/$Z$11) -> 0.80474812 | AB17: =H17+L17+P17+T17 -> 914705016 | AC17: =IF(ISERR(AB17/$AB$11),"",AB17/$AB$11) -> 0.80997633 | AD17: =AD14+AD15-AD16 -> 222863355 | AE17: =IF(ISERR(AD17/$AD$11),"",AD17/$AD$11) -> 0.91960578 | AF17: =AF14+AF15-AF16 -> 447803340 | AG17: =IF(ISERR(AF17/$AF$11),"",AF17/$AF$11) -> 0.91641327 | AH17: =AH14+AH15-AH16 -> 0 | AI17: =IF(ISERR(AH17/$AH$11),"",AH17/$AH$11) -> 0 | AJ17: =AJ14+AJ15-AJ16 -> 0 | AK17: =IF(ISERR(AJ17/$AJ$11),"",AJ17/$AJ$11) -> 0 | AL17: =AD17+AH17 -> 222863355 | AM17: =IF(ISERR(AL17/$AL$11),"",AL17/AL$11) -> 0.88119522 | AN17: =AF17+AJ17 -> 447803340 | AO17: =IF(ISERR(AN17/$AN$11),"",AN17/$AN$11) -> 0.87973359 | AP17: =B17+Z17+AL17 -> 671466642 | AQ17: =IF(ISERR(AP17/$AP$11),"",AP17/$AP$11) -> 0.82860709 | AR17: =D17+AB17+AN17 -> 1362508356 | AS17: =IF(ISERR(AR17/$AR$11),"",AR17/$AR$11) -> 0.83164972 | AT17: =AT14+AT15-AT16 -> 785671686 | AU17: =IF(ISERR(AT17/$AT$11),"",AT17/$AT$11) -> 0.84208858 | AV17: =AV14+AV15-AV16 -> 1605687130 | AW17: =IF(ISERR(AV17/$AV$11),"",AV17/$AV$11) -> 0.84504894 | AX17: =AP17-AT17 -> -114205044 | AY17: =IF(ISERROR(AP17/AT17),"",AP17/AT17) -> 0.85464024 | AZ17: =AR17-AV17 -> -243178774 | BA17: =IF(ISERROR(AR17/AV17),"",AR17/AV17) -> 0.84855158
A18: 【売上総利益】 | C18: =IF(ISERR(B18/$B$11),"",B18/$B$11) | E18: =IF(ISERR(D18/$D$11),"",D18/$D$11) | F18: =F11-F17 -> 74039468 | G18: =IF(ISERR(F18/$F$11),"",F18/$F$11) -> 0.14231552 | H18: =H11-H17 -> 145327496 | I18: =IF(ISERR(H18/$H$11),"",H18/$H$11) -> 0.13775102 | J18: =J11-J17 -> 8816958 | K18: =IF(ISERR(J18/$J$11),"",J18/$J$11) -> 0.93993722 | L18: =L11-L17 -> 17198933 | M18: =IF(ISERR(L18/$L$11),"",L18/$L$11) -> 0.94198254 | N18: =N11-N17 -> 25985871 | O18: =IF(ISERR(N18/$N$11),"",N18/$N$11) -> 0.93418977 | P18: =P11-P17 -> 52067003 | Q18: =IF(ISERR(P18/$P$11),"",P18/$P$11) -> 0.92912166 | R18: =R11-R17 -> 0 | S18: =IF(ISERR(R18/$R$11),"",R18/$R$11) | T18: =T11-T17 -> 0 | U18: =IF(ISERR(T18/$T$11),"",T18/$T$11) | V18: =N18+R18 -> 25985871 | W18: =IF(ISERR(V18/$V$11),"",V18/$V$11) -> 0.93418977 | X18: =P18+T18 -> 52067003 | Y18: =IF(ISERR(X18/$X$11),"",X18/$X$11) -> 0.92912166 | Z18: =F18+J18+N18+R18 -> 108842297 | AA18: =IF(ISERR(Z18/$Z$11),"",Z18/$Z$11) -> 0.19525188 | AB18: =H18+L18+P18+T18 -> 214593432 | AC18: =IF(ISERR(AB18/$AB$11),"",AB18/$AB$11) -> 0.19002367 | AD18: =AD11-AD17 -> 19483268 | AE18: =IF(ISERR(AD18/$AD$11),"",AD18/$AD$11) -> 0.080394221 | AF18: =AF11-AF17 -> 40844474 | AG18: =IF(ISERR(AF18/$AF$11),"",AF18/$AF$11) -> 0.083586732 | AH18: =AH11-AH17 -> 10563686 | AI18: =IF(ISERR(AH18/$AH$11),"",AH18/$AH$11) -> 1 | AJ18: =AJ11-AJ17 -> 20373721 | AK18: =IF(ISERR(AJ18/$AJ$11),"",AJ18/$AJ$11) -> 1 | AL18: =AD18+AH18 -> 30046954 | AM18: =IF(ISERR(AL18/$AL$11),"",AL18/AL$11) -> 0.11880478 | AN18: =AF18+AJ18 -> 61218195 | AO18: =IF(ISERR(AN18/$AN$11),"",AN18/$AN$11) -> 0.12026641 | AP18: =B18+Z18+AL18 -> 138889251 | AQ18: =IF(ISERR(AP18/$AP$11),"",AP18/$AP$11) -> 0.17139291 | AR18: =D18+AB18+AN18 -> 275811627 | AS18: =IF(ISERR(AR18/$AR$11),"",AR18/$AR$11) -> 0.16835028 | AT18: =AT11-AT17 -> 147331929 | AU18: =IF(ISERR(AT18/$AT$11),"",AT18/$AT$11) -> 0.15791142 | AV18: =AV11-AV17 -> 294424278 | AW18: =IF(ISERR(AV18/$AV$11),"",AV18/$AV$11) -> 0.15495106 | AX18: =AP18-AT18 -> -8442678 | AY18: =IF(ISERROR(AP18/AT18),"",AP18/AT18) -> 0.94269621 | AZ18: =AR18-AV18 -> -18612651 | BA18: =IF(ISERROR(AR18/AV18),"",AR18/AV18) -> 0.93678289
A19: 給料 | B19: =[2]本部!$I$19 -> 5756800 | C19: =IF(ISERR(B19/$B$11),"",B19/$B$11) | D19: =[2]本部!$L$19 -> 11513600 | E19: =IF(ISERR(D19/$D$11),"",D19/$D$11) | F19: =[2]本社営業!$I$19 -> 10316328 | G19: =IF(ISERR(F19/$F$11),"",F19/$F$11) -> 0.019829607 | H19: =[2]本社営業!$L$19 -> 20446835 | I19: =IF(ISERR(H19/$H$11),"",H19/$H$11) -> 0.019380863 | J19: =[2]東大阪!$I$19 -> 2055720 | K19: =IF(ISERR(J19/$J$11),"",J19/$J$11) -> 0.21915129 | L19: =[2]東大阪!$L$19 -> 5835800 | M19: =IF(ISERR(L19/$L$11),"",L19/$L$11) -> 0.31962574 | N19: =[2]南港工場!$I$19 -> 7132633 | O19: =IF(ISERR(N19/$N$11),"",N19/$N$11) -> 0.25641753 | P19: =[2]南港工場!$L$19 -> 14120644 | Q19: =IF(ISERR(P19/$P$11),"",P19/$P$11) -> 0.25197909 | R19: =[2]南港事務!$I$19 -> 2794249 | S19: =IF(ISERR(R19/$R$11),"",R19/$R$11) | T19: =[2]南港事務!$L$19 -> 5582742 | U19: =IF(ISERR(T19/$T$11),"",T19/$T$11) | V19: =N19+R19 -> 9926882 | W19: =IF(ISERR(V19/$V$11),"",V19/$V$11) -> 0.35687053 | X19: =P19+T19 -> 19703386 | Y19: =IF(ISERR(X19/$X$11),"",X19/$X$11) -> 0.35160162 | Z19: =F19+J19+N19+R19 -> 22298930 | AA19: =IF(ISERR(Z19/$Z$11),"",Z19/$Z$11) -> 0.040001985 | AB19: =H19+L19+P19+T19 -> 45986021 | AC19: =IF(ISERR(AB19/$AB$11),"",AB19/$AB$11) -> 0.040720875 | AD19: =[2]東京事務!$I$19 -> 4513900 | AE19: =IF(ISERR(AD19/$AD$11),"",AD19/$AD$11) -> 0.018625801 | AF19: =[2]東京事務!$L$19 -> 9027800 | AG19: =IF(ISERR(AF19/$AF$11),"",AF19/$AF$11) -> 0.018475065 | AH19: =[2]東京工場!$I$19 -> 4490004 | AI19: =IF(ISERR(AH19/$AH$11),"",AH19/$AH$11) -> 0.42504141 | AJ19: =[2]東京工場!$L$19 -> 9082342 | AK19: =IF(ISERR(AJ19/$AJ$11),"",AJ19/$AJ$11) -> 0.4457871 | AL19: =AD19+AH19 -> 9003904 | AM19: =IF(ISERR(AL19/$AL$11),"",AL19/AL$11) -> 0.035601174 | AN19: =AF19+AJ19 -> 18110142 | AO19: =IF(ISERR(AN19/$AN$11),"",AN19/$AN$11) -> 0.035578341 | AP19: =B19+Z19+AL19 -> 37059634 | AQ19: =IF(ISERR(AP19/$AP$11),"",AP19/$AP$11) -> 0.045732541 | AR19: =D19+AB19+AN19 -> 75609763 | AS19: =IF(ISERR(AR19/$AR$11),"",AR19/$AR$11) -> 0.046150791 | AT19: =[2]全社合計!$G$19 -> 34949373 | AU19: =IF(ISERR(AT19/$AT$11),"",AT19/$AT$11) -> 0.03745899 | AV19: =[2]全社合計!$N$19 -> 71828052 | AW19: =IF(ISERR(AV19/$AV$11),"",AV19/$AV$11) -> 0.037802021 | AX19: =AP19-AT19 -> 2110261 | AY19: =IF(ISERROR(AP19/AT19),"",AP19/AT19) -> 1.0603805 | AZ19: =AR19-AV19 -> 3781711 | BA19: =IF(ISERROR(AR19/AV19),"",AR19/AV19) -> 1.0526495
A20: 退職年金保険 | B20: =[2]本部!$I$20 -> 56110 | C20: =IF(ISERR(B20/$B$11),"",B20/$B$11) | D20: =[2]本部!$L$20 -> 112220 | E20: =IF(ISERR(D20/$D$11),"",D20/$D$11) | F20: =[2]本社営業!$I$20 -> 259440 | G20: =IF(ISERR(F20/$F$11),"",F20/$F$11) -> 0.00049868454 | H20: =[2]本社営業!$L$20 -> 524302 | I20: =IF(ISERR(H20/$H$11),"",H20/$H$11) -> 0.00049696812 | J20: =[2]東大阪!$I$20 -> 163642 | K20: =IF(ISERR(J20/$J$11),"",J20/$J$11) -> 0.017445156 | L20: =[2]東大阪!$L$20 -> 327284 | M20: =IF(ISERR(L20/$L$11),"",L20/$L$11) -> 0.017925287 | N20: =[2]南港工場!$I$20 -> 241330 | O20: =IF(ISERR(N20/$N$11),"",N20/$N$11) -> 0.0086757922 | P20: =[2]南港工場!$L$20 -> 482660 | Q20: =IF(ISERR(P20/$P$11),"",P20/$P$11) -> 0.0086129378 | R20: =[2]南港事務!$I$20 -> 88532 | S20: =IF(ISERR(R20/$R$11),"",R20/$R$11) | T20: =[2]南港事務!$L$20 -> 177064 | U20: =IF(ISERR(T20/$T$11),"",T20/$T$11) | V20: =N20+R20 -> 329862 | W20: =IF(ISERR(V20/$V$11),"",V20/$V$11) -> 0.01185851 | X20: =P20+T20 -> 659724 | Y20: =IF(ISERR(X20/$X$11),"",X20/$X$11) -> 0.011772597 | Z20: =F20+J20+N20+R20 -> 752944 | AA20: =IF(ISERR(Z20/$Z$11),"",Z20/$Z$11) -> 0.001350704 | AB20: =H20+L20+P20+T20 -> 1511310 | AC20: =IF(ISERR(AB20/$AB$11),"",AB20/$AB$11) -> 0.0013382733 | AD20: =[2]東京事務!$I$20 -> 124954 | AE20: =IF(ISERR(AD20/$AD$11),"",AD20/$AD$11) -> 0.00051560033 | AF20: =[2]東京事務!$L$20 -> 249908 | AG20: =IF(ISERR(AF20/$AF$11),"",AF20/$AF$11) -> 0.00051142764 | AH20: =[2]東京工場!$I$20 -> 111642 | AI20: =IF(ISERR(AH20/$AH$11),"",AH20/$AH$11) -> 0.01056847 | AJ20: =[2]東京工場!$L$20 -> 223284 | AK20: =IF(ISERR(AJ20/$AJ$11),"",AJ20/$AJ$11) -> 0.010959412 | AL20: =AD20+AH20 -> 236596 | AM20: =IF(ISERR(AL20/$AL$11),"",AL20/AL$11) -> 0.0009354937 | AN20: =AF20+AJ20 -> 473192 | AO20: =IF(ISERR(AN20/$AN$11),"",AN20/$AN$11) -> 0.00092961096 | AP20: =B20+Z20+AL20 -> 1045650 | AQ20: =IF(ISERR(AP20/$AP$11),"",AP20/$AP$11) -> 0.001290359 | AR20: =D20+AB20+AN20 -> 2096722 | AS20: =IF(ISERR(AR20/$AR$11),"",AR20/$AR$11) -> 0.0012798001 | AT20: =[2]全社合計!$G$20 -> 1081228 | AU20: =IF(ISERR(AT20/$AT$11),"",AT20/$AT$11) -> 0.001158868 | AV20: =[2]全社合計!$N$20 -> 2162456 | AW20: =IF(ISERR(AV20/$AV$11),"",AV20/$AV$11) -> 0.001138068 | AX20: =AP20-AT20 -> -35578 | AY20: =IF(ISERROR(AP20/AT20),"",AP20/AT20) -> 0.96709482 | AZ20: =AR20-AV20 -> -65734 | BA20: =IF(ISERROR(AR20/AV20),"",AR20/AV20) -> 0.96960216
A21: 退職金 | B21: =[2]本部!$I$21 -> 0 | C21: =IF(ISERR(B21/$B$11),"",B21/$B$11) | D21: =[2]本部!$L$21 -> 0 | E21: =IF(ISERR(D21/$D$11),"",D21/$D$11) | F21: =[2]本社営業!$I$21 -> 0 | G21: =IF(ISERR(F21/$F$11),"",F21/$F$11) -> 0 | H21: =[2]本社営業!$L$21 -> 0 | I21: =IF(ISERR(H21/$H$11),"",H21/$H$11) -> 0 | J21: =[2]東大阪!$I$21 -> 0 | K21: =IF(ISERR(J21/$J$11),"",J21/$J$11) -> 0 | L21: =[2]東大阪!$L$21 -> 0 | M21: =IF(ISERR(L21/$L$11),"",L21/$L$11) -> 0 | N21: =[2]南港工場!$I$21 -> 0 | O21: =IF(ISERR(N21/$N$11),"",N21/$N$11) -> 0 | P21: =[2]南港工場!$L$21 -> 0 | Q21: =IF(ISERR(P21/$P$11),"",P21/$P$11) -> 0 | R21: =[2]南港事務!$I$21 -> 0 | S21: =IF(ISERR(R21/$R$11),"",R21/$R$11) | T21: =[2]南港事務!$L$21 -> 0 | U21: =IF(ISERR(T21/$T$11),"",T21/$T$11) | V21: =N21+R21 -> 0 | W21: =IF(ISERR(V21/$V$11),"",V21/$V$11) -> 0 | X21: =P21+T21 -> 0 | Y21: =IF(ISERR(X21/$X$11),"",X21/$X$11) -> 0 | Z21: =F21+J21+N21+R21 -> 0 | AA21: =IF(ISERR(Z21/$Z$11),"",Z21/$Z$11) -> 0 | AB21: =H21+L21+P21+T21 -> 0 | AC21: =IF(ISERR(AB21/$AB$11),"",AB21/$AB$11) -> 0 | AD21: =[2]東京事務!$I$21 -> 0 | AE21: =IF(ISERR(AD21/$AD$11),"",AD21/$AD$11) -> 0 | AF21: =[2]東京事務!$L$21 -> 0 | AG21: =IF(ISERR(AF21/$AF$11),"",AF21/$AF$11) -> 0 | AH21: =[2]東京工場!$I$21 -> 0 | AI21: =IF(ISERR(AH21/$AH$11),"",AH21/$AH$11) -> 0 | AJ21: =[2]東京工場!$L$21 -> 0 | AK21: =IF(ISERR(AJ21/$AJ$11),"",AJ21/$AJ$11) -> 0 | AL21: =AD21+AH21 -> 0 | AM21: =IF(ISERR(AL21/$AL$11),"",AL21/AL$11) -> 0 | AN21: =AF21+AJ21 -> 0 | AO21: =IF(ISERR(AN21/$AN$11),"",AN21/$AN$11) -> 0 | AP21: =B21+Z21+AL21 -> 0 | AQ21: =IF(ISERR(AP21/$AP$11),"",AP21/$AP$11) -> 0 | AR21: =D21+AB21+AN21 -> 0 | AS21: =IF(ISERR(AR21/$AR$11),"",AR21/$AR$11) -> 0 | AT21: =[2]全社合計!$G$21 -> 2035207 | AU21: =IF(ISERR(AT21/$AT$11),"",AT21/$AT$11) -> 0.0021813495 | AV21: =[2]全社合計!$N$21 -> 2035207 | AW21: =IF(ISERR(AV21/$AV$11),"",AV21/$AV$11) -> 0.0010710988 | AX21: =AP21-AT21 -> -2035207 | AY21: =IF(ISERROR(AP21/AT21),"",AP21/AT21) -> 0 | AZ21: =AR21-AV21 -> -2035207 | BA21: =IF(ISERROR(AR21/AV21),"",AR21/AV21) -> 0
A22: 法定福利費 | B22: =[2]本部!$I$22 -> 408499 | C22: =IF(ISERR(B22/$B$11),"",B22/$B$11) | D22: =[2]本部!$L$22 -> 408499 | E22: =IF(ISERR(D22/$D$11),"",D22/$D$11) | F22: =[2]本社営業!$I$22 -> 2163512 | G22: =IF(ISERR(F22/$F$11),"",F22/$F$11) -> 0.0041586108 | H22: =[2]本社営業!$L$22 -> 2163512 | I22: =IF(ISERR(H22/$H$11),"",H22/$H$11) -> 0.0020507198 | J22: =[2]東大阪!$I$22 -> 1664959 | K22: =IF(ISERR(J22/$J$11),"",J22/$J$11) -> 0.17749398 | L22: =[2]東大阪!$L$22 -> 1664959 | M22: =IF(ISERR(L22/$L$11),"",L22/$L$11) -> 0.091189512 | N22: =[2]南港工場!$I$22 -> 2331084 | O22: =IF(ISERR(N22/$N$11),"",N22/$N$11) -> 0.083802264 | P22: =[2]南港工場!$L$22 -> 2331084 | Q22: =IF(ISERR(P22/$P$11),"",P22/$P$11) -> 0.041597567 | R22: =[2]南港事務!$I$22 -> 985479 | S22: =IF(ISERR(R22/$R$11),"",R22/$R$11) | T22: =[2]南港事務!$L$22 -> 985479 | U22: =IF(ISERR(T22/$T$11),"",T22/$T$11) | V22: =N22+R22 -> 3316563 | W22: =IF(ISERR(V22/$V$11),"",V22/$V$11) -> 0.11923015 | X22: =P22+T22 -> 3316563 | Y22: =IF(ISERR(X22/$X$11),"",X22/$X$11) -> 0.059183174 | Z22: =F22+J22+N22+R22 -> 7145034 | AA22: =IF(ISERR(Z22/$Z$11),"",Z22/$Z$11) -> 0.012817456 | AB22: =H22+L22+P22+T22 -> 7145034 | AC22: =IF(ISERR(AB22/$AB$11),"",AB22/$AB$11) -> 0.006326967 | AD22: =[2]東京事務!$I$22 -> 1064452 | AE22: =IF(ISERR(AD22/$AD$11),"",AD22/$AD$11) -> 0.0043922708 | AF22: =[2]東京事務!$L$22 -> 1064452 | AG22: =IF(ISERR(AF22/$AF$11),"",AF22/$AF$11) -> 0.0021783623 | AH22: =[2]東京工場!$I$22 -> 1459377 | AI22: =IF(ISERR(AH22/$AH$11),"",AH22/$AH$11) -> 0.13815036 | AJ22: =[2]東京工場!$L$22 -> 1459377 | AK22: =IF(ISERR(AJ22/$AJ$11),"",AJ22/$AJ$11) -> 0.071630361 | AL22: =AD22+AH22 -> 2523829 | AM22: =IF(ISERR(AL22/$AL$11),"",AL22/AL$11) -> 0.0099791464 | AN22: =AF22+AJ22 -> 2523829 | AO22: =IF(ISERR(AN22/$AN$11),"",AN22/$AN$11) -> 0.0049581969 | AP22: =B22+Z22+AL22 -> 10077362 | AQ22: =IF(ISERR(AP22/$AP$11),"",AP22/$AP$11) -> 0.012435724 | AR22: =D22+AB22+AN22 -> 10077362 | AS22: =IF(ISERR(AR22/$AR$11),"",AR22/$AR$11) -> 0.006151034 | AT22: =[2]全社合計!$G$22 -> 9150224 | AU22: =IF(ISERR(AT22/$AT$11),"",AT22/$AT$11) -> 0.009807276 | AV22: =[2]全社合計!$N$22 -> 9150224 | AW22: =IF(ISERR(AV22/$AV$11),"",AV22/$AV$11) -> 0.004815625 | AX22: =AP22-AT22 -> 927138 | AY22: =IF(ISERROR(AP22/AT22),"",AP22/AT22) -> 1.1013241 | AZ22: =AR22-AV22 -> 927138 | BA22: =IF(ISERROR(AR22/AV22),"",AR22/AV22) -> 1.1013241
A23: 厚生費 | B23: =[2]本部!$I$23 -> 536704 | C23: =IF(ISERR(B23/$B$11),"",B23/$B$11) | D23: =[2]本部!$L$23 -> 1072492 | E23: =IF(ISERR(D23/$D$11),"",D23/$D$11) | F23: =[2]本社営業!$I$23 -> 496643 | G23: =IF(ISERR(F23/$F$11),"",F23/$F$11) -> 0.00095462606 | H23: =[2]本社営業!$L$23 -> 597809 | I23: =IF(ISERR(H23/$H$11),"",H23/$H$11) -> 0.00056664292 | J23: =[2]東大阪!$I$23 -> 127268 | K23: =IF(ISERR(J23/$J$11),"",J23/$J$11) -> 0.013567483 | L23: =[2]東大阪!$L$23 -> 190659 | M23: =IF(ISERR(L23/$L$11),"",L23/$L$11) -> 0.01044236 | N23: =[2]南港工場!$I$23 -> 89155 | O23: =IF(ISERR(N23/$N$11),"",N23/$N$11) -> 0.0032051144 | P23: =[2]南港工場!$L$23 -> 163045 | Q23: =IF(ISERR(P23/$P$11),"",P23/$P$11) -> 0.0029094941 | R23: =[2]南港事務!$I$23 -> 122382 | S23: =IF(ISERR(R23/$R$11),"",R23/$R$11) | T23: =[2]南港事務!$L$23 -> 175023 | U23: =IF(ISERR(T23/$T$11),"",T23/$T$11) | V23: =N23+R23 -> 211537 | W23: =IF(ISERR(V23/$V$11),"",V23/$V$11) -> 0.0076047365 | X23: =P23+T23 -> 338068 | Y23: =IF(ISERR(X23/$X$11),"",X23/$X$11) -> 0.0060327325 | Z23: =F23+J23+N23+R23 -> 835448 | AA23: =IF(ISERR(Z23/$Z$11),"",Z23/$Z$11) -> 0.0014987077 | AB23: =H23+L23+P23+T23 -> 1126536 | AC23: =IF(ISERR(AB23/$AB$11),"",AB23/$AB$11) -> 0.00099755384 | AD23: =[2]東京事務!$I$23 -> 104311 | AE23: =IF(ISERR(AD23/$AD$11),"",AD23/$AD$11) -> 0.00043042069 | AF23: =[2]東京事務!$L$23 -> 158574 | AG23: =IF(ISERR(AF23/$AF$11),"",AF23/$AF$11) -> 0.00032451593 | AH23: =[2]東京工場!$I$23 -> 92816 | AI23: =IF(ISERR(AH23/$AH$11),"",AH23/$AH$11) -> 0.008786327 | AJ23: =[2]東京工場!$L$23 -> 146555 | AK23: =IF(ISERR(AJ23/$AJ$11),"",AJ23/$AJ$11) -> 0.007193335 | AL23: =AD23+AH23 -> 197127 | AM23: =IF(ISERR(AL23/$AL$11),"",AL23/AL$11) -> 0.00077943442 | AN23: =AF23+AJ23 -> 305129 | AO23: =IF(ISERR(AN23/$AN$11),"",AN23/$AN$11) -> 0.00059944222 | AP23: =B23+Z23+AL23 -> 1569279 | AQ23: =IF(ISERR(AP23/$AP$11),"",AP23/$AP$11) -> 0.0019365306 | AR23: =D23+AB23+AN23 -> 2504157 | AS23: =IF(ISERR(AR23/$AR$11),"",AR23/$AR$11) -> 0.0015284908 | AT23: =[2]全社合計!$G$23 -> 1361752 | AU23: =IF(ISERR(AT23/$AT$11),"",AT23/$AT$11) -> 0.0014595356 | AV23: =[2]全社合計!$N$23 -> 2260839 | AW23: =IF(ISERR(AV23/$AV$11),"",AV23/$AV$11) -> 0.0011898455 | AX23: =AP23-AT23 -> 207527 | AY23: =IF(ISERROR(AP23/AT23),"",AP23/AT23) -> 1.1523971 | AZ23: =AR23-AV23 -> 243318 | BA23: =IF(ISERROR(AR23/AV23),"",AR23/AV23) -> 1.1076229
A24: 賃借料 | B24: =[2]本部!$I$24 -> 45000 | C24: =IF(ISERR(B24/$B$11),"",B24/$B$11) | D24: =[2]本部!$L$24 -> 90000 | E24: =IF(ISERR(D24/$D$11),"",D24/$D$11) | F24: =[2]本社営業!$I$24 -> 181650 | G24: =IF(ISERR(F24/$F$11),"",F24/$F$11) -> 0.00034915991 | H24: =[2]本社営業!$L$24 -> 1035300 | I24: =IF(ISERR(H24/$H$11),"",H24/$H$11) -> 0.00098132583 | J24: =[2]東大阪!$I$24 -> 96410 | K24: =IF(ISERR(J24/$J$11),"",J24/$J$11) -> 0.010277847 | L24: =[2]東大阪!$L$24 -> 192820 | M24: =IF(ISERR(L24/$L$11),"",L24/$L$11) -> 0.010560718 | N24: =[2]南港工場!$I$24 -> 28600 | O24: =IF(ISERR(N24/$N$11),"",N24/$N$11) -> 0.0010281675 | P24: =[2]南港工場!$L$24 -> 57200 | Q24: =IF(ISERR(P24/$P$11),"",P24/$P$11) -> 0.0010207186 | R24: =[2]南港事務!$I$24 -> 0 | S24: =IF(ISERR(R24/$R$11),"",R24/$R$11) | T24: =[2]南港事務!$L$24 -> 0 | U24: =IF(ISERR(T24/$T$11),"",T24/$T$11) | V24: =N24+R24 -> 28600 | W24: =IF(ISERR(V24/$V$11),"",V24/$V$11) -> 0.0010281675 | X24: =P24+T24 -> 57200 | Y24: =IF(ISERR(X24/$X$11),"",X24/$X$11) -> 0.0010207186 | Z24: =F24+J24+N24+R24 -> 306660 | AA24: =IF(ISERR(Z24/$Z$11),"",Z24/$Z$11) -> 0.00055011648 | AB24: =H24+L24+P24+T24 -> 1285320 | AC24: =IF(ISERR(AB24/$AB$11),"",AB24/$AB$11) -> 0.0011381579 | AD24: =[2]東京事務!$I$24 -> 143500 | AE24: =IF(ISERR(AD24/$AD$11),"",AD24/$AD$11) -> 0.00059212709 | AF24: =[2]東京事務!$L$24 -> 287000 | AG24: =IF(ISERR(AF24/$AF$11),"",AF24/$AF$11) -> 0.00058733507 | AH24: =[2]東京工場!$I$24 -> 0 | AI24: =IF(ISERR(AH24/$AH$11),"",AH24/$AH$11) -> 0 | AJ24: =[2]東京工場!$L$24 -> 0 | AK24: =IF(ISERR(AJ24/$AJ$11),"",AJ24/$AJ$11) -> 0 | AL24: =AD24+AH24 -> 143500 | AM24: =IF(ISERR(AL24/$AL$11),"",AL24/AL$11) -> 0.00056739482 | AN24: =AF24+AJ24 -> 287000 | AO24: =IF(ISERR(AN24/$AN$11),"",AN24/$AN$11) -> 0.00056382683 | AP24: =B24+Z24+AL24 -> 495160 | AQ24: =IF(ISERR(AP24/$AP$11),"",AP24/$AP$11) -> 0.00061104017 | AR24: =D24+AB24+AN24 -> 1662320 | AS24: =IF(ISERR(AR24/$AR$11),"",AR24/$AR$11) -> 0.0010146492 | AT24: =[2]全社合計!$G$24 -> 455978 | AU24: =IF(ISERR(AT24/$AT$11),"",AT24/$AT$11) -> 0.00048872051 | AV24: =[2]全社合計!$N$24 -> 1583956 | AW24: =IF(ISERR(AV24/$AV$11),"",AV24/$AV$11) -> 0.00083361217 | AX24: =AP24-AT24 -> 39182 | AY24: =IF(ISERROR(AP24/AT24),"",AP24/AT24) -> 1.0859296 | AZ24: =AR24-AV24 -> 78364 | BA24: =IF(ISERROR(AR24/AV24),"",AR24/AV24) -> 1.0494736
A25: リース料 | B25: =[2]本部!$I$25 -> 129379 | C25: =IF(ISERR(B25/$B$11),"",B25/$B$11) | D25: =[2]本部!$L$25 -> 258758 | E25: =IF(ISERR(D25/$D$11),"",D25/$D$11) | F25: =[2]本社営業!$I$25 -> 86370 | G25: =IF(ISERR(F25/$F$11),"",F25/$F$11) -> 0.00016601674 | H25: =[2]本社営業!$L$25 -> 172740 | I25: =IF(ISERR(H25/$H$11),"",H25/$H$11) -> 0.0001637344 | J25: =[2]東大阪!$I$25 -> 10180 | K25: =IF(ISERR(J25/$J$11),"",J25/$J$11) -> 0.0010852452 | L25: =[2]東大阪!$L$25 -> 20360 | M25: =IF(ISERR(L25/$L$11),"",L25/$L$11) -> 0.0011151136 | N25: =[2]南港工場!$I$25 -> 0 | O25: =IF(ISERR(N25/$N$11),"",N25/$N$11) -> 0 | P25: =[2]南港工場!$L$25 -> 0 | Q25: =IF(ISERR(P25/$P$11),"",P25/$P$11) -> 0 | R25: =[2]南港事務!$I$25 -> 19840 | S25: =IF(ISERR(R25/$R$11),"",R25/$R$11) | T25: =[2]南港事務!$L$25 -> 30020 | U25: =IF(ISERR(T25/$T$11),"",T25/$T$11) | V25: =N25+R25 -> 19840 | W25: =IF(ISERR(V25/$V$11),"",V25/$V$11) -> 0.00071324625 | X25: =P25+T25 -> 30020 | Y25: =IF(ISERR(X25/$X$11),"",X25/$X$11) -> 0.00053569882 | Z25: =F25+J25+N25+R25 -> 116390 | AA25: =IF(ISERR(Z25/$Z$11),"",Z25/$Z$11) -> 0.00020879168 | AB25: =H25+L25+P25+T25 -> 223120 | AC25: =IF(ISERR(AB25/$AB$11),"",AB25/$AB$11) -> 0.00019757399 | AD25: =[2]東京事務!$I$25 -> 37082 | AE25: =IF(ISERR(AD25/$AD$11),"",AD25/$AD$11) -> 0.00015301224 | AF25: =[2]東京事務!$L$25 -> 55624 | AG25: =IF(ISERR(AF25/$AF$11),"",AF25/$AF$11) -> 0.0001138325 | AH25: =[2]東京工場!$I$25 -> 8300 | AI25: =IF(ISERR(AH25/$AH$11),"",AH25/$AH$11) -> 0.00078571059 | AJ25: =[2]東京工場!$L$25 -> 16600 | AK25: =IF(ISERR(AJ25/$AJ$11),"",AJ25/$AJ$11) -> 0.00081477507 | AL25: =AD25+AH25 -> 45382 | AM25: =IF(ISERR(AL25/$AL$11),"",AL25/AL$11) -> 0.00017943911 | AN25: =AF25+AJ25 -> 72224 | AO25: =IF(ISERR(AN25/$AN$11),"",AN25/$AN$11) -> 0.00014188791 | AP25: =B25+Z25+AL25 -> 291151 | AQ25: =IF(ISERR(AP25/$AP$11),"",AP25/$AP$11) -> 0.00035928782 | AR25: =D25+AB25+AN25 -> 554102 | AS25: =IF(ISERR(AR25/$AR$11),"",AR25/$AR$11) -> 0.00033821354 | AT25: =[2]全社合計!$G$25 -> 269181 | AU25: =IF(ISERR(AT25/$AT$11),"",AT25/$AT$11) -> 0.00028851014 | AV25: =[2]全社合計!$N$25 -> 510162 | AW25: =IF(ISERR(AV25/$AV$11),"",AV25/$AV$11) -> 0.00026849057 | AX25: =AP25-AT25 -> 21970 | AY25: =IF(ISERROR(AP25/AT25),"",AP25/AT25) -> 1.0816179 | AZ25: =AR25-AV25 -> 43940 | BA25: =IF(ISERROR(AR25/AV25),"",AR25/AV25) -> 1.0861295
A26: 保守料 | B26: =[2]本部!$I$26 -> 328701 | C26: =IF(ISERR(B26/$B$11),"",B26/$B$11) | D26: =[2]本部!$L$26 -> 657402 | E26: =IF(ISERR(D26/$D$11),"",D26/$D$11) | F26: =[2]本社営業!$I$26 -> 680 | G26: =IF(ISERR(F26/$F$11),"",F26/$F$11) -> 1.3070671e-06 | H26: =[2]本社営業!$L$26 -> 1360 | I26: =IF(ISERR(H26/$H$11),"",H26/$H$11) -> 1.289098e-06 | J26: =[2]東大阪!$I$26 -> 7170 | K26: =IF(ISERR(J26/$J$11),"",J26/$J$11) -> 0.00076436225 | L26: =[2]東大阪!$L$26 -> 14340 | M26: =IF(ISERR(L26/$L$11),"",L26/$L$11) -> 0.00078539928 | N26: =[2]南港工場!$I$26 -> 0 | O26: =IF(ISERR(N26/$N$11),"",N26/$N$11) -> 0 | P26: =[2]南港工場!$L$26 -> 0 | Q26: =IF(ISERR(P26/$P$11),"",P26/$P$11) -> 0 | R26: =[2]南港事務!$I$26 -> 5520 | S26: =IF(ISERR(R26/$R$11),"",R26/$R$11) | T26: =[2]南港事務!$L$26 -> 11040 | U26: =IF(ISERR(T26/$T$11),"",T26/$T$11) | V26: =N26+R26 -> 5520 | W26: =IF(ISERR(V26/$V$11),"",V26/$V$11) -> 0.00019844351 | X26: =P26+T26 -> 11040 | Y26: =IF(ISERR(X26/$X$11),"",X26/$X$11) -> 0.00019700583 | Z26: =F26+J26+N26+R26 -> 13370 | AA26: =IF(ISERR(Z26/$Z$11),"",Z26/$Z$11) -> 2.3984404e-05 | AB26: =H26+L26+P26+T26 -> 26740 | AC26: =IF(ISERR(AB26/$AB$11),"",AB26/$AB$11) -> 2.3678417e-05 | AD26: =[2]東京事務!$I$26 -> 7170 | AE26: =IF(ISERR(AD26/$AD$11),"",AD26/$AD$11) -> 2.9585723e-05 | AF26: =[2]東京事務!$L$26 -> 14340 | AG26: =IF(ISERR(AF26/$AF$11),"",AF26/$AF$11) -> 2.9346289e-05 | AH26: =[2]東京工場!$I$26 -> 25000 | AI26: =IF(ISERR(AH26/$AH$11),"",AH26/$AH$11) -> 0.0023665982 | AJ26: =[2]東京工場!$L$26 -> 38000 | AK26: =IF(ISERR(AJ26/$AJ$11),"",AJ26/$AJ$11) -> 0.0018651478 | AL26: =AD26+AH26 -> 32170 | AM26: =IF(ISERR(AL26/$AL$11),"",AL26/AL$11) -> 0.00012719924 | AN26: =AF26+AJ26 -> 52340 | AO26: =IF(ISERR(AN26/$AN$11),"",AN26/$AN$11) -> 0.00010282473 | AP26: =B26+Z26+AL26 -> 374241 | AQ26: =IF(ISERR(AP26/$AP$11),"",AP26/$AP$11) -> 0.00046182301 | AR26: =D26+AB26+AN26 -> 736482 | AS26: =IF(ISERR(AR26/$AR$11),"",AR26/$AR$11) -> 0.00044953489 | AT26: =[2]全社合計!$G$26 -> 390281 | AU26: =IF(ISERR(AT26/$AT$11),"",AT26/$AT$11) -> 0.00041830599 | AV26: =[2]全社合計!$N$26 -> 767572 | AW26: =IF(ISERR(AV26/$AV$11),"",AV26/$AV$11) -> 0.00040396158 | AX26: =AP26-AT26 -> -16040 | AY26: =IF(ISERROR(AP26/AT26),"",AP26/AT26) -> 0.95890141 | AZ26: =AR26-AV26 -> -31090 | BA26: =IF(ISERROR(AR26/AV26),"",AR26/AV26) -> 0.95949566
A27: 修繕費 | B27: =[2]本部!$I$27 -> 0 | C27: =IF(ISERR(B27/$B$11),"",B27/$B$11) | D27: =[2]本部!$L$27 -> 0 | E27: =IF(ISERR(D27/$D$11),"",D27/$D$11) | F27: =[2]本社営業!$I$27 -> 0 | G27: =IF(ISERR(F27/$F$11),"",F27/$F$11) -> 0 | H27: =[2]本社営業!$L$27 -> 0 | I27: =IF(ISERR(H27/$H$11),"",H27/$H$11) -> 0 | J27: =[2]東大阪!$I$27 -> 160500 | K27: =IF(ISERR(J27/$J$11),"",J27/$J$11) -> 0.017110201 | L27: =[2]東大阪!$L$27 -> 174900 | M27: =IF(ISERR(L27/$L$11),"",L27/$L$11) -> 0.0095792423 | N27: =[2]南港工場!$I$27 -> 1641940 | O27: =IF(ISERR(N27/$N$11),"",N27/$N$11) -> 0.059027598 | P27: =[2]南港工場!$L$27 -> 1697550 | Q27: =IF(ISERR(P27/$P$11),"",P27/$P$11) -> 0.030292323 | R27: =[2]南港事務!$I$27 -> 0 | S27: =IF(ISERR(R27/$R$11),"",R27/$R$11) | T27: =[2]南港事務!$L$27 -> 0 | U27: =IF(ISERR(T27/$T$11),"",T27/$T$11) | V27: =N27+R27 -> 1641940 | W27: =IF(ISERR(V27/$V$11),"",V27/$V$11) -> 0.059027598 | X27: =P27+T27 -> 1697550 | Y27: =IF(ISERR(X27/$X$11),"",X27/$X$11) -> 0.030292323 | Z27: =F27+J27+N27+R27 -> 1802440 | AA27: =IF(ISERR(Z27/$Z$11),"",Z27/$Z$11) -> 0.0032333918 | AB27: =H27+L27+P27+T27 -> 1872450 | AC27: =IF(ISERR(AB27/$AB$11),"",AB27/$AB$11) -> 0.0016580648 | AD27: =[2]東京事務!$I$27 -> 0 | AE27: =IF(ISERR(AD27/$AD$11),"",AD27/$AD$11) -> 0 | AF27: =[2]東京事務!$L$27 -> 0 | AG27: =IF(ISERR(AF27/$AF$11),"",AF27/$AF$11) -> 0 | AH27: =[2]東京工場!$I$27 -> 59960 | AI27: =IF(ISERR(AH27/$AH$11),"",AH27/$AH$11) -> 0.0056760491 | AJ27: =[2]東京工場!$L$27 -> 105860 | AK27: =IF(ISERR(AJ27/$AJ$11),"",AJ27/$AJ$11) -> 0.005195909 | AL27: =AD27+AH27 -> 59960 | AM27: =IF(ISERR(AL27/$AL$11),"",AL27/AL$11) -> 0.00023708009 | AN27: =AF27+AJ27 -> 105860 | AO27: =IF(ISERR(AN27/$AN$11),"",AN27/$AN$11) -> 0.00020796763 | AP27: =B27+Z27+AL27 -> 1862400 | AQ27: =IF(ISERR(AP27/$AP$11),"",AP27/$AP$11) -> 0.0022982495 | AR27: =D27+AB27+AN27 -> 1978310 | AS27: =IF(ISERR(AR27/$AR$11),"",AR27/$AR$11) -> 0.0012075236 | AT27: =[2]全社合計!$G$27 -> 577384 | AU27: =IF(ISERR(AT27/$AT$11),"",AT27/$AT$11) -> 0.00061884433 | AV27: =[2]全社合計!$N$27 -> 1177384 | AW27: =IF(ISERR(AV27/$AV$11),"",AV27/$AV$11) -> 0.00061963946 | AX27: =AP27-AT27 -> 1285016 | AY27: =IF(ISERROR(AP27/AT27),"",AP27/AT27) -> 3.225583 | AZ27: =AR27-AV27 -> 800926 | BA27: =IF(ISERROR(AR27/AV27),"",AR27/AV27) -> 1.6802589
A28: 事務用消耗品費 | B28: =[2]本部!$I$28 -> 643140 | C28: =IF(ISERR(B28/$B$11),"",B28/$B$11) | D28: =[2]本部!$L$28 -> 1020466 | E28: =IF(ISERR(D28/$D$11),"",D28/$D$11) | F28: =[2]本社営業!$I$28 -> 102131 | G28: =IF(ISERR(F28/$F$11),"",F28/$F$11) -> 0.00019631187 | H28: =[2]本社営業!$L$28 -> 207025 | I28: =IF(ISERR(H28/$H$11),"",H28/$H$11) -> 0.00019623199 | J28: =[2]東大阪!$I$28 -> 11362 | K28: =IF(ISERR(J28/$J$11),"",J28/$J$11) -> 0.001211253 | L28: =[2]東大阪!$L$28 -> 15482 | M28: =IF(ISERR(L28/$L$11),"",L28/$L$11) -> 0.00084794642 | N28: =[2]南港工場!$I$28 -> 0 | O28: =IF(ISERR(N28/$N$11),"",N28/$N$11) -> 0 | P28: =[2]南港工場!$L$28 -> 0 | Q28: =IF(ISERR(P28/$P$11),"",P28/$P$11) -> 0 | R28: =[2]南港事務!$I$28 -> 42210 | S28: =IF(ISERR(R28/$R$11),"",R28/$R$11) | T28: =[2]南港事務!$L$28 -> 46318 | U28: =IF(ISERR(T28/$T$11),"",T28/$T$11) | V28: =N28+R28 -> 42210 | W28: =IF(ISERR(V28/$V$11),"",V28/$V$11) -> 0.0015174458 | X28: =P28+T28 -> 46318 | Y28: =IF(ISERR(X28/$X$11),"",X28/$X$11) -> 0.00082653225 | Z28: =F28+J28+N28+R28 -> 155703 | AA28: =IF(ISERR(Z28/$Z$11),"",Z28/$Z$11) -> 0.00027931516 | AB28: =H28+L28+P28+T28 -> 268825 | AC28: =IF(ISERR(AB28/$AB$11),"",AB28/$AB$11) -> 0.00023804602 | AD28: =[2]東京事務!$I$28 -> 14236 | AE28: =IF(ISERR(AD28/$AD$11),"",AD28/$AD$11) -> 5.8742308e-05 | AF28: =[2]東京事務!$L$28 -> 14236 | AG28: =IF(ISERR(AF28/$AF$11),"",AF28/$AF$11) -> 2.9133457e-05 | AH28: =[2]東京工場!$I$28 -> 15663 | AI28: =IF(ISERR(AH28/$AH$11),"",AH28/$AH$11) -> 0.0014827211 | AJ28: =[2]東京工場!$L$28 -> 15663 | AK28: =IF(ISERR(AJ28/$AJ$11),"",AJ28/$AJ$11) -> 0.00076878446 | AL28: =AD28+AH28 -> 29899 | AM28: =IF(ISERR(AL28/$AL$11),"",AL28/AL$11) -> 0.00011821978 | AN28: =AF28+AJ28 -> 29899 | AO28: =IF(ISERR(AN28/$AN$11),"",AN28/$AN$11) -> 5.8738183e-05 | AP28: =B28+Z28+AL28 -> 828742 | AQ28: =IF(ISERR(AP28/$AP$11),"",AP28/$AP$11) -> 0.0010226889 | AR28: =D28+AB28+AN28 -> 1319190 | AS28: =IF(ISERR(AR28/$AR$11),"",AR28/$AR$11) -> 0.000805209 | AT28: =[2]全社合計!$G$28 -> 733256 | AU28: =IF(ISERR(AT28/$AT$11),"",AT28/$AT$11) -> 0.00078590907 | AV28: =[2]全社合計!$N$28 -> 1101070 | AW28: =IF(ISERR(AV28/$AV$11),"",AV28/$AV$11) -> 0.00057947655 | AX28: =AP28-AT28 -> 95486 | AY28: =IF(ISERROR(AP28/AT28),"",AP28/AT28) -> 1.1302219 | AZ28: =AR28-AV28 -> 218120 | BA28: =IF(ISERROR(AR28/AV28),"",AR28/AV28) -> 1.1980982
