Workbook

Sheet 商品マスタ
A1: 商品マスタ
A2: ※材料費(円/kg)と単重(kg/個)を入力すると材料原価・粗利が自動計算されます。グループを設定すると月別計画実績のグループが自動入力されます。商品名は変更・削除禁止（廃番の場合はJ列に「廃番」と記入）。
A3: 商品名 | B3: グループ | C3: 単位 | D3: 売値 (円) | E3: 材料費 (円/kg) | F3: 単重 (kg/個) | G3: 材料原価 (円) 自動 | H3: 粗利/枚 (円) 自動 | I3: 粗利率 (%) 自動 | J3: 廃番 フラグ | K3: 備考
A4: 57mm上 | B4: 缶バッジ | C4: 個 | D4: 4.8 | G4: =IF(AND(E4<>"",F4<>""),E4*F4,4.36) -> 4.36 | H4: =D4-G4 -> 0.44 | I4: =IFERROR(H4/D4,0) -> 0.091666667 | J4: 有効
A5: 56Φ上蓋 | B5: 缶バッジ | C5: 個 | D5: 3.72 | G5: =IF(AND(E5<>"",F5<>""),E5*F5,3.38) -> 3.38 | H5: =D5-G5 -> 0.34 | I5: =IFERROR(H5/D5,0) -> 0.091397849 | J5: 有効
A6: 38mm上 | B6: 缶バッジ | C6: 個 | D6: 4.77 | G6: =IF(AND(E6<>"",F6<>""),E6*F6,4.34) -> 4.34 | H6: =D6-G6 -> 0.43 | I6: =IFERROR(H6/D6,0) -> 0.090146751 | J6: 有効
A7: 32mm上 | B7: 缶バッジ | C7: 個 | D7: 3.34 | G7: =IF(AND(E7<>"",F7<>""),E7*F7,3.04) -> 3.04 | H7: =D7-G7 -> 0.3 | I7: =IFERROR(H7/D7,0) -> 0.089820359 | J7: 有効
A8: 44mm上 | B8: 缶バッジ | C8: 個 | D8: 3.11 | G8: =IF(AND(E8<>"",F8<>""),E8*F8,2.83) -> 2.83 | H8: =D8-G8 -> 0.28 | I8: =IFERROR(H8/D8,0) -> 0.090032154 | J8: 有効
A9: 長方形ﾊﾞｯｼﾞ上蓋 | B9: 缶バッジ | C9: 個 | D9: 5.51 | G9: =IF(AND(E9<>"",F9<>""),E9*F9,5.01) -> 5.01 | H9: =D9-G9 -> 0.5 | I9: =IFERROR(H9/D9,0) -> 0.090744102 | J9: 有効
A10: 76mm上 | B10: 缶バッジ | C10: 個 | D10: 6.8 | G10: =IF(AND(E10<>"",F10<>""),E10*F10,6.18) -> 6.18 | H10: =D10-G10 -> 0.62 | I10: =IFERROR(H10/D10,0) -> 0.091176471 | J10: 有効
A11: 44x70丸角長方形上 | B11: 缶バッジ | C11: 個 | D11: 5.69 | G11: =IF(AND(E11<>"",F11<>""),E11*F11,5.17) -> 5.17 | H11: =D11-G11 -> 0.52 | I11: =IFERROR(H11/D11,0) -> 0.091388401 | J11: 有効
A12: 長方形53ｘ78mm用 | B12: 缶バッジ | C12: 個 | D12: 7.84 | G12: =IF(AND(E12<>"",F12<>""),E12*F12,7.13) -> 7.13 | H12: =D12-G12 -> 0.71 | I12: =IFERROR(H12/D12,0) -> 0.090561224 | J12: 有効
A13: 57mmﾂﾒ下ﾋﾟﾝ付き | B13: 缶バッジ | C13: 個 | D13: 12.55 | G13: =IF(AND(E13<>"",F13<>""),E13*F13,11.41) -> 11.41 | H13: =D13-G13 -> 1.14 | I13: =IFERROR(H13/D13,0) -> 0.090836653 | J13: 有効
A14: 54Φ下蓋 | B14: 缶バッジ | C14: 個 | D14: 3.72 | G14: =IF(AND(E14<>"",F14<>""),E14*F14,3.38) -> 3.38 | H14: =D14-G14 -> 0.34 | I14: =IFERROR(H14/D14,0) -> 0.091397849 | J14: 有効
A15: 56Φ下蓋 | B15: 缶バッジ | C15: 個 | D15: 3.72 | G15: =IF(AND(E15<>"",F15<>""),E15*F15,3.38) -> 3.38 | H15: =D15-G15 -> 0.34 | I15: =IFERROR(H15/D15,0) -> 0.091397849 | J15: 有効
A16: 32mm穴下 | B16: 缶バッジ | C16: 個 | D16: 3.83 | G16: =IF(AND(E16<>"",F16<>""),E16*F16,3.48) -> 3.48 | H16: =D16-G16 -> 0.35 | I16: =IFERROR(H16/D16,0) -> 0.091383812 | J16: 有効
A17: 75Φ下蓋 | B17: 缶バッジ | C17: 個 | D17: 5.28 | G17: =IF(AND(E17<>"",F17<>""),E17*F17,4.8) -> 4.8 | H17: =D17-G17 -> 0.48 | I17: =IFERROR(H17/D17,0) -> 0.090909091 | J17: 有効
A18: 57mm穴下 | B18: 缶バッジ | C18: 個 | D18: 6.02 | G18: =IF(AND(E18<>"",F18<>""),E18*F18,5.47) -> 5.47 | H18: =D18-G18 -> 0.55 | I18: =IFERROR(H18/D18,0) -> 0.091362126 | J18: 有効
A19: 57mmﾂﾒ下 | B19: 缶バッジ | C19: 個 | D19: 6.02 | G19: =IF(AND(E19<>"",F19<>""),E19*F19,5.47) -> 5.47 | H19: =D19-G19 -> 0.55 | I19: =IFERROR(H19/D19,0) -> 0.091362126 | J19: 有効
A20: 32mmﾂﾒ下ﾋﾟﾝ付き | B20: 缶バッジ | C20: 個 | D20: 14.87 | G20: =IF(AND(E20<>"",F20<>""),E20*F20,13.52) -> 13.52 | H20: =D20-G20 -> 1.35 | I20: =IFERROR(H20/D20,0) -> 0.090786819 | J20: 有効
A21: 32mm穴下ﾋﾟﾝ付き | B21: 缶バッジ | C21: 個 | D21: 14.87 | G21: =IF(AND(E21<>"",F21<>""),E21*F21,13.52) -> 13.52 | H21: =D21-G21 -> 1.35 | I21: =IFERROR(H21/D21,0) -> 0.090786819 | J21: 有効
A22: 44mm穴下ﾋﾟﾝ付き | B22: 缶バッジ | C22: 個 | D22: 18.42 | G22: =IF(AND(E22<>"",F22<>""),E22*F22,16.75) -> 16.75 | H22: =D22-G22 -> 1.67 | I22: =IFERROR(H22/D22,0) -> 0.090662324 | J22: 有効
A23: 44mmﾂﾒ下ﾋﾟﾝ付き | B23: 缶バッジ | C23: 個 | D23: 18.42 | G23: =IF(AND(E23<>"",F23<>""),E23*F23,16.75) -> 16.75 | H23: =D23-G23 -> 1.67 | I23: =IFERROR(H23/D23,0) -> 0.090662324 | J23: 有効
A24: 38mmﾂﾒ下ﾋﾟﾝ付き | B24: 缶バッジ | C24: 個 | D24: 10.56 | G24: =IF(AND(E24<>"",F24<>""),E24*F24,9.6) -> 9.6 | H24: =D24-G24 -> 0.96 | I24: =IFERROR(H24/D24,0) -> 0.090909091 | J24: 有効
A25: 76mmﾂﾒ下 | B25: 缶バッジ | C25: 個 | D25: 9.6 | G25: =IF(AND(E25<>"",F25<>""),E25*F25,8.73) -> 8.73 | H25: =D25-G25 -> 0.87 | I25: =IFERROR(H25/D25,0) -> 0.090625 | J25: 有効
A26: 44mmﾂﾒ下 | B26: 缶バッジ | C26: 個 | D26: 5.24 | G26: =IF(AND(E26<>"",F26<>""),E26*F26,4.76) -> 4.76 | H26: =D26-G26 -> 0.48 | I26: =IFERROR(H26/D26,0) -> 0.091603053 | J26: 有効
A27: 44x70丸角長方形下 | B27: 缶バッジ | C27: 個 | D27: 6.92 | G27: =IF(AND(E27<>"",F27<>""),E27*F27,6.29) -> 6.29 | H27: =D27-G27 -> 0.63 | I27: =IFERROR(H27/D27,0) -> 0.091040462 | J27: 有効
A28: 38mm穴下 | B28: 缶バッジ | C28: 個 | D28: 7.44 | G28: =IF(AND(E28<>"",F28<>""),E28*F28,6.76) -> 6.76 | H28: =D28-G28 -> 0.68 | I28: =IFERROR(H28/D28,0) -> 0.091397849 | J28: 有効
A29: 32mmﾂﾒ下 | B29: 缶バッジ | C29: 個 | D29: 4.58 | G29: =IF(AND(E29<>"",F29<>""),E29*F29,4.16) -> 4.16 | H29: =D29-G29 -> 0.42 | I29: =IFERROR(H29/D29,0) -> 0.091703057 | J29: 有効
A30: 57mm穴下ﾋﾟﾝ付き | B30: 缶バッジ | C30: 個 | D30: 20.68 | G30: =IF(AND(E30<>"",F30<>""),E30*F30,18.8) -> 18.8 | H30: =D30-G30 -> 1.88 | I30: =IFERROR(H30/D30,0) -> 0.090909091 | J30: 有効
A31: 76mmﾂﾒ下ﾋﾟﾝ付き | B31: 缶バッジ | C31: 個 | D31: 28.75 | G31: =IF(AND(E31<>"",F31<>""),E31*F31,26.14) -> 26.14 | H31: =D31-G31 -> 2.61 | I31: =IFERROR(H31/D31,0) -> 0.090782609 | J31: 有効
A32: ハート穴下 | B32: 缶バッジ | C32: 個 | D32: 12.77 | G32: =IF(AND(E32<>"",F32<>""),E32*F32,11.61) -> 11.61 | H32: =D32-G32 -> 1.16 | I32: =IFERROR(H32/D32,0) -> 0.090837901 | J32: 有効
A33: 57㎜ﾂﾒ下ﾋﾟﾝ付き(ｸﾘｱ) | B33: 缶バッジ | C33: 個 | D33: 22.44 | G33: =IF(AND(E33<>"",F33<>""),E33*F33,20.4) -> 20.4 | H33: =D33-G33 -> 2.04 | I33: =IFERROR(H33/D33,0) -> 0.090909091 | J33: 有効
A34: 57mm バックパーツ | B34: 缶バッジ | C34: 個 | D34: 3.72 | G34: =IF(AND(E34<>"",F34<>""),E34*F34,3.38) -> 3.38 | H34: =D34-G34 -> 0.34 | I34: =IFERROR(H34/D34,0) -> 0.091397849 | J34: 有効
A35: 76mm バックパーツ | B35: 缶バッジ | C35: 個 | D35: 5.28 | G35: =IF(AND(E35<>"",F35<>""),E35*F35,4.8) -> 4.8 | H35: =D35-G35 -> 0.48 | I35: =IFERROR(H35/D35,0) -> 0.090909091 | J35: 有効
A36: 44mm バックパーツ | B36: 缶バッジ | C36: 個 | D36: 3.11 | G36: =IF(AND(E36<>"",F36<>""),E36*F36,2.83) -> 2.83 | H36: =D36-G36 -> 0.28 | I36: =IFERROR(H36/D36,0) -> 0.090032154 | J36: 有効
A37: 38㎜ バックパーツ | B37: 缶バッジ | C37: 個 | D37: 2.85 | G37: =IF(AND(E37<>"",F37<>""),E37*F37,2.59) -> 2.59 | H37: =D37-G37 -> 0.26 | I37: =IFERROR(H37/D37,0) -> 0.09122807 | J37: 有効
A38: 57mm シェル | B38: 缶バッジ | C38: 個 | D38: 3.72 | G38: =IF(AND(E38<>"",F38<>""),E38*F38,3.38) -> 3.38 | H38: =D38-G38 -> 0.34 | I38: =IFERROR(H38/D38,0) -> 0.091397849 | J38: 有効
A39: 57mm バックパーツ | B39: 缶バッジ | C39: 個 | D39: 3.72 | G39: =IF(AND(E39<>"",F39<>""),E39*F39,3.38) -> 3.38 | H39: =D39-G39 -> 0.34 | I39: =IFERROR(H39/D39,0) -> 0.091397849 | J39: 有効
A40: 76㎜ シェルパーツ | B40: 缶バッジ | C40: 個 | D40: 5.28 | G40: =IF(AND(E40<>"",F40<>""),E40*F40,4.8) -> 4.8 | H40: =D40-G40 -> 0.48 | I40: =IFERROR(H40/D40,0) -> 0.090909091 | J40: 有効
A41: 32mm バックパーツ | B41: 缶バッジ | C41: 個 | D41: 2.6 | G41: =IF(AND(E41<>"",F41<>""),E41*F41,2.36) -> 2.36 | H41: =D41-G41 -> 0.24 | I41: =IFERROR(H41/D41,0) -> 0.092307692 | J41: 有効
A42: 38mm NEW safetypins | B42: 缶バッジ | C42: 個 | D42: 4.08 | G42: =IF(AND(E42<>"",F42<>""),E42*F42,3.71) -> 3.71 | H42: =D42-G42 -> 0.37 | I42: =IFERROR(H42/D42,0) -> 0.090686275 | J42: 有効
A43: 44mm NEW safetypins | B43: 缶バッジ | C43: 個 | D43: 4.35 | G43: =IF(AND(E43<>"",F43<>""),E43*F43,3.95) -> 3.95 | H43: =D43-G43 -> 0.4 | I43: =IFERROR(H43/D43,0) -> 0.091954023 | J43: 有効
A44: 57mm NEW safetypins | B44: 缶バッジ | C44: 個 | D44: 4.95 | G44: =IF(AND(E44<>"",F44<>""),E44*F44,4.5) -> 4.5 | H44: =D44-G44 -> 0.45 | I44: =IFERROR(H44/D44,0) -> 0.090909091 | J44: 有効
A45: 57mmﾌｨﾙﾑ | B45: 缶バッジ | C45: 個 | D45: 1.58 | G45: =IF(AND(E45<>"",F45<>""),E45*F45,1.44) -> 1.44 | H45: =D45-G45 -> 0.14 | I45: =IFERROR(H45/D45,0) -> 0.088607595 | J45: 有効
A46: 44mmﾌｨﾙﾑ | B46: 缶バッジ | C46: 個 | D46: 2.38 | G46: =IF(AND(E46<>"",F46<>""),E46*F46,2.16) -> 2.16 | H46: =D46-G46 -> 0.22 | I46: =IFERROR(H46/D46,0) -> 0.092436975 | J46: 有効
A47: 32mmﾌｨﾙﾑ | B47: 缶バッジ | C47: 個 | D47: 2.38 | G47: =IF(AND(E47<>"",F47<>""),E47*F47,2.16) -> 2.16 | H47: =D47-G47 -> 0.22 | I47: =IFERROR(H47/D47,0) -> 0.092436975 | J47: 有効
A48: 57mmﾎﾛｸﾞﾗﾑﾌｨﾙﾑ | B48: 缶バッジ | C48: 個 | D48: 17.23 | G48: =IF(AND(E48<>"",F48<>""),E48*F48,15.66) -> 15.66 | H48: =D48-G48 -> 1.57 | I48: =IFERROR(H48/D48,0) -> 0.091120139 | J48: 有効
A49: Ｏプランジャー | B49: 昭和以外 | C49: 個 | D49: 6.55 | G49: =IF(AND(E49<>"",F49<>""),E49*F49,5.95) -> 5.95 | H49: =D49-G49 -> 0.6 | I49: =IFERROR(H49/D49,0) -> 0.091603053 | J49: 有効
A50: ＨＢプランジャー | B50: 昭和以外 | C50: 個 | D50: 6.98 | G50: =IF(AND(E50<>"",F50<>""),E50*F50,6.35) -> 6.35 | H50: =D50-G50 -> 0.63 | I50: =IFERROR(H50/D50,0) -> 0.09025788 | J50: 有効
A51: ＯⅡプランジャー端曲 | B51: 昭和以外 | C51: 個 | D51: 9.09 | G51: =IF(AND(E51<>"",F51<>""),E51*F51,8.26) -> 8.26 | H51: =D51-G51 -> 0.83 | I51: =IFERROR(H51/D51,0) -> 0.091309131 | J51: 有効
A52: Ｓ－１プランジャー | B52: 昭和以外 | C52: 個 | D52: 8.23 | G52: =IF(AND(E52<>"",F52<>""),E52*F52,7.48) -> 7.48 | H52: =D52-G52 -> 0.75 | I52: =IFERROR(H52/D52,0) -> 0.091130012 | J52: 有効
A53: ５０Φ底板 | B53: 昭和以外 | C53: 個 | D53: 12.85 | G53: =IF(AND(E53<>"",F53<>""),E53*F53,11.68) -> 11.68 | H53: =D53-G53 -> 1.17 | I53: =IFERROR(H53/D53,0) -> 0.091050584 | J53: 有効
A54: ５０Φリング金具 | B54: 昭和以外 | C54: 個 | D54: 8.1 | G54: =IF(AND(E54<>"",F54<>""),E54*F54,7.36) -> 7.36 | H54: =D54-G54 -> 0.74 | I54: =IFERROR(H54/D54,0) -> 0.091358025 | J54: 有効
A55: Ｓ－２プランジャー | B55: 昭和以外 | C55: 個 | D55: 8.23 | G55: =IF(AND(E55<>"",F55<>""),E55*F55,7.48) -> 7.48 | H55: =D55-G55 -> 0.75 | I55: =IFERROR(H55/D55,0) -> 0.091130012 | J55: 有効
A56: 大型ﾌﾞﾘｷﾌﾟﾗﾝｼﾞｬｰ | B56: 昭和以外 | C56: 個 | D56: 17.35 | G56: =IF(AND(E56<>"",F56<>""),E56*F56,15.77) -> 15.77 | H56: =D56-G56 -> 1.58 | I56: =IFERROR(H56/D56,0) -> 0.091066282 | J56: 有効
A57: ＢＨＫスプリング | B57: 昭和以外 | C57: 個 | D57: 6.4 | G57: =IF(AND(E57<>"",F57<>""),E57*F57,5.82) -> 5.82 | H57: =D57-G57 -> 0.58 | I57: =IFERROR(H57/D57,0) -> 0.090625 | J57: 有効
A58: １００Φ底金具 | B58: 昭和以外 | C58: 個 | D58: 16.09 | G58: =IF(AND(E58<>"",F58<>""),E58*F58,14.63) -> 14.63 | H58: =D58-G58 -> 1.46 | I58: =IFERROR(H58/D58,0) -> 0.09073959 | J58: 有効
A59: １００Φリング金具 | B59: 昭和以外 | C59: 個 | D59: 17.16 | G59: =IF(AND(E59<>"",F59<>""),E59*F59,15.6) -> 15.6 | H59: =D59-G59 -> 1.56 | I59: =IFERROR(H59/D59,0) -> 0.090909091 | J59: 有効
A60: １００Φ底板 | B60: 昭和以外 | C60: 個 | D60: 57.2 | G60: =IF(AND(E60<>"",F60<>""),E60*F60,52) -> 52 | H60: =D60-G60 -> 5.2 | I60: =IFERROR(H60/D60,0) -> 0.090909091 | J60: 有効
A61: ５０Φ底板 | B61: 昭和以外 | C61: 個 | D61: 12.85 | G61: =IF(AND(E61<>"",F61<>""),E61*F61,11.68) -> 11.68 | H61: =D61-G61 -> 1.17 | I61: =IFERROR(H61/D61,0) -> 0.091050584 | J61: 有効
A62: Ｎ－６ Ｊリング | B62: 昭和以外 | C62: 個 | D62: 11.74 | G62: =IF(AND(E62<>"",F62<>""),E62*F62,10.67) -> 10.67 | H62: =D62-G62 -> 1.07 | I62: =IFERROR(H62/D62,0) -> 0.091141397 | J62: 有効
A63: S-211ｽﾌﾟﾘﾝｸﾞ受け座 | B63: 昭和以外 | C63: 個 | D63: 39.48 | G63: =IF(AND(E63<>"",F63<>""),E63*F63,35.89) -> 35.89 | H63: =D63-G63 -> 3.59 | I63: =IFERROR(H63/D63,0) -> 0.090932118 | J63: 有効
A64: ネジ金具 | B64: 昭和 | C64: 個 | D64: 8.14 | G64: =IF(AND(E64<>"",F64<>""),E64*F64,7.4) -> 7.4 | H64: =D64-G64 -> 0.74 | I64: =IFERROR(H64/D64,0) -> 0.090909091 | J64: 有効
A65: バルク用金具５Ｒ | B65: 昭和 | C65: 個 | D65: 13.43 | G65: =IF(AND(E65<>"",F65<>""),E65*F65,12.21) -> 12.21 | H65: =D65-G65 -> 1.22 | I65: =IFERROR(H65/D65,0) -> 0.0908414 | J65: 有効
A66: 段付ネジ | B66: 昭和 | C66: 個 | D66: 8.14 | G66: =IF(AND(E66<>"",F66<>""),E66*F66,7.4) -> 7.4 | H66: =D66-G66 -> 0.74 | I66: =IFERROR(H66/D66,0) -> 0.090909091 | J66: 有効
A67: 大型ネジ金具 | B67: 昭和 | C67: 個 | D67: 24.13 | G67: =IF(AND(E67<>"",F67<>""),E67*F67,21.94) -> 21.94 | H67: =D67-G67 -> 2.19 | I67: =IFERROR(H67/D67,0) -> 0.090758392 | J67: 有効
A68: ｶﾞｲﾄﾞ JN951565-H01 | B68: その他 | C68: 個 | D68: 76.49 | G68: =IF(AND(E68<>"",F68<>""),E68*F68,69.54) -> 69.54 | H68: =D68-G68 -> 6.95 | I68: =IFERROR(H68/D68,0) -> 0.090861551 | J68: 有効
A69: アングル支持金具 | B69: その他 | C69: 個 | D69: 30.94 | G69: =IF(AND(E69<>"",F69<>""),E69*F69,28.13) -> 28.13 | H69: =D69-G69 -> 2.81 | I69: =IFERROR(H69/D69,0) -> 0.090820944 | J69: 有効
A70: PEM3-146遮断器用架台 | B70: その他 | C70: 個 | D70: 29.88 | G70: =IF(AND(E70<>"",F70<>""),E70*F70,27.16) -> 27.16 | H70: =D70-G70 -> 2.72 | I70: =IFERROR(H70/D70,0) -> 0.09103079 | J70: 有効
A71: ロット棒受け金具 | B71: その他 | C71: 個 | D71: 29.88 | G71: =IF(AND(E71<>"",F71<>""),E71*F71,27.16) -> 27.16 | H71: =D71-G71 -> 2.72 | I71: =IFERROR(H71/D71,0) -> 0.09103079 | J71: 有効
A72: ST-14電線止め金具 | B72: その他 | C72: 個 | D72: 76.81 | G72: =IF(AND(E72<>"",F72<>""),E72*F72,69.83) -> 69.83 | H72: =D72-G72 -> 6.98 | I72: =IFERROR(H72/D72,0) -> 0.090873584 | J72: 有効
A73: ST-23電線止め金具 | B73: その他 | C73: 個 | D73: 97.1 | G73: =IF(AND(E73<>"",F73<>""),E73*F73,88.27) -> 88.27 | H73: =D73-G73 -> 8.83 | I73: =IFERROR(H73/D73,0) -> 0.090937178 | J73: 有効
A74: PEM3-236遮断器用架台 | B74: その他 | C74: 個 | D74: 56.55 | G74: =IF(AND(E74<>"",F74<>""),E74*F74,51.41) -> 51.41 | H74: =D74-G74 -> 5.14 | I74: =IFERROR(H74/D74,0) -> 0.090893015 | J74: 有効
A75: PEM3-196遮断器用架台 | B75: その他 | C75: 個 | D75: 48.02 | G75: =IF(AND(E75<>"",F75<>""),E75*F75,43.65) -> 43.65 | H75: =D75-G75 -> 4.37 | I75: =IFERROR(H75/D75,0) -> 0.091003748 | J75: 有効
A76: ｸﾗﾝﾌﾟ N678121-H01 | B76: その他 | C76: 個 | D76: 56.75 | G76: =IF(AND(E76<>"",F76<>""),E76*F76,51.59) -> 51.59 | H76: =D76-G76 -> 5.16 | I76: =IFERROR(H76/D76,0) -> 0.09092511 | J76: 有効
A77: ｴﾎﾟｷｼ硝子取付金具 | B77: その他 | C77: 個 | D77: 61.89 | G77: =IF(AND(E77<>"",F77<>""),E77*F77,56.26) -> 56.26 | H77: =D77-G77 -> 5.63 | I77: =IFERROR(H77/D77,0) -> 0.090967846 | J77: 有効
A78: PEM3-106遮断器用架台 | B78: その他 | C78: 個 | D78: 22.41 | G78: =IF(AND(E78<>"",F78<>""),E78*F78,20.37) -> 20.37 | H78: =D78-G78 -> 2.04 | I78: =IFERROR(H78/D78,0) -> 0.09103079 | J78: 有効
A79: ｶﾞｲﾄﾞ JN951565-H03 | B79: その他 | C79: 個 | D79: 74.58 | G79: =IF(AND(E79<>"",F79<>""),E79*F79,67.8) -> 67.8 | H79: =D79-G79 -> 6.78 | I79: =IFERROR(H79/D79,0) -> 0.090909091 | J79: 有効
A80: PEM3-82遮断器用架台 | B80: その他 | C80: 個 | D80: 18.14 | G80: =IF(AND(E80<>"",F80<>""),E80*F80,16.49) -> 16.49 | H80: =D80-G80 -> 1.65 | I80: =IFERROR(H80/D80,0) -> 0.090959206 | J80: 有効
A81: 計器取付金具 Ｍ | B81: その他 | C81: 個 | D81: 37.35 | G81: =IF(AND(E81<>"",F81<>""),E81*F81,33.95) -> 33.95 | H81: =D81-G81 -> 3.4 | I81: =IFERROR(H81/D81,0) -> 0.09103079 | J81: 有効
A82: ｵｻｴｲﾀ JN677996-H05 | B82: その他 | C82: 個 | D82: 29.85 | G82: =IF(AND(E82<>"",F82<>""),E82*F82,27.14) -> 27.14 | H82: =D82-G82 -> 2.71 | I82: =IFERROR(H82/D82,0) -> 0.09078727 | J82: 有効
A83: ｸﾗﾝﾌﾟ JN678122-H01 | B83: その他 | C83: 個 | D83: 57.31 | G83: =IF(AND(E83<>"",F83<>""),E83*F83,52.1) -> 52.1 | H83: =D83-G83 -> 5.21 | I83: =IFERROR(H83/D83,0) -> 0.090909091 | J83: 有効
A84: ST-35電線止め金具 | B84: その他 | C84: 個 | D84: 165.39 | G84: =IF(AND(E84<>"",F84<>""),E84*F84,150.35) -> 150.35 | H84: =D84-G84 -> 15.04 | I84: =IFERROR(H84/D84,0) -> 0.090936574 | J84: 有効
A85: PEM3-86遮断器用架台 | B85: その他 | C85: 個 | D85: 19.21 | G85: =IF(AND(E85<>"",F85<>""),E85*F85,17.46) -> 17.46 | H85: =D85-G85 -> 1.75 | I85: =IFERROR(H85/D85,0) -> 0.091098386 | J85: 有効
A86: PEM3-176遮断器用架台 | B86: その他 | C86: 個 | D86: 42.68 | G86: =IF(AND(E86<>"",F86<>""),E86*F86,38.8) -> 38.8 | H86: =D86-G86 -> 3.88 | I86: =IFERROR(H86/D86,0) -> 0.090909091 | J86: 有効
A87: 9 片サドル | B87: その他 | C87: 個 | D87: 3.09 | G87: =IF(AND(E87<>"",F87<>""),E87*F87,2.81) -> 2.81 | H87: =D87-G87 -> 0.28 | I87: =IFERROR(H87/D87,0) -> 0.090614887 | J87: 有効
A88: ｸﾗﾝﾌﾟ JN678123-H01 | B88: その他 | C88: 個 | D88: 79.57 | G88: =IF(AND(E88<>"",F88<>""),E88*F88,72.34) -> 72.34 | H88: =D88-G88 -> 7.23 | I88: =IFERROR(H88/D88,0) -> 0.090863391 | J88: 有効
A89: RH015-1Tr据付ﾍﾞｰｽ | B89: その他 | C89: 個 | D89: 84.28 | G89: =IF(AND(E89<>"",F89<>""),E89*F89,76.62) -> 76.62 | H89: =D89-G89 -> 7.66 | I89: =IFERROR(H89/D89,0) -> 0.090887518 | J89: 有効
A90: ｵｻｴｲﾀ JN677997-H04 | B90: その他 | C90: 個 | D90: 33.57 | G90: =IF(AND(E90<>"",F90<>""),E90*F90,30.52) -> 30.52 | H90: =D90-G90 -> 3.05 | I90: =IFERROR(H90/D90,0) -> 0.09085493 | J90: 有効
A91: TPW-1 ﾚﾊﾞｰ(メッキ無) | B91: その他 | C91: 個 | D91: 32.01 | G91: =IF(AND(E91<>"",F91<>""),E91*F91,29.1) -> 29.1 | H91: =D91-G91 -> 2.91 | I91: =IFERROR(H91/D91,0) -> 0.090909091 | J91: 有効
A92: 7 片サドル | B92: その他 | C92: 個 | D92: 2.98 | G92: =IF(AND(E92<>"",F92<>""),E92*F92,2.71) -> 2.71 | H92: =D92-G92 -> 0.27 | I92: =IFERROR(H92/D92,0) -> 0.090604027 | J92: 有効
A93: 12 片サドル | B93: その他 | C93: 個 | D93: 3.3 | G93: =IF(AND(E93<>"",F93<>""),E93*F93,3) -> 3 | H93: =D93-G93 -> 0.3 | I93: =IFERROR(H93/D93,0) -> 0.090909091 | J93: 有効
A94: ELTPIU ﾏﾙｻﾞ軸 | B94: その他 | C94: 個 | D94: 8.54 | G94: =IF(AND(E94<>"",F94<>""),E94*F94,7.76) -> 7.76 | H94: =D94-G94 -> 0.78 | I94: =IFERROR(H94/D94,0) -> 0.091334895 | J94: 有効
A95: RH041-1Tr据付ﾍﾞｰｽ | B95: その他 | C95: 個 | D95: 69.36 | G95: =IF(AND(E95<>"",F95<>""),E95*F95,63.05) -> 63.05 | H95: =D95-G95 -> 6.31 | I95: =IFERROR(H95/D95,0) -> 0.090974625 | J95: 有効

Sheet 月別計画実績
A1: 三幸プロダクツ株式会社 42期 月別計画実績（2026年6月〜2027年5月）
A2: 【入力方法】D列=商品名をドロップダウンから選択 → B列グループ・E/F列単価が自動入力 → 各月の計画数量・実績数量を入力 → 売上・粗利が自動計算されます。 実績は「-」入力で0円取引、空白は未入力扱い。
A3: 工場 | B3: グループ | C3: 取引先 | D3: 商品名 | E3: 売値 (円) | F3: 粗利/枚 (円) | G3: 年間計画 | J3: 年間実績 | M3: 達成率 売上 | N3: 達成率 粗利 | O3: 6月 | R3: 6月 | U3: 7月 | X3: 7月 | AA3: 8月 | AD3: 8月 | AG3: 9月 | AJ3: 9月 | AM3: 10月 | AP3: 10月 | AS3: 11月 | AV3: 11月 | AY3: 12月 | BB3: 12月 | BE3: 1月 | BH3: 1月 | BK3: 2月 | BN3: 2月 | BQ3: 3月 | BT3: 3月 | BW3: 4月 | BZ3: 4月 | CC3: 5月 | CF3: 5月
G4: 計画 数量 | H4: 計画 売上 | I4: 計画 粗利 | J4: 実績 数量 | K4: 実績 売上 | L4: 実績 粗利 | O4: 計画 数量 | P4: 計画 売上 | Q4: 計画 粗利 | R4: 実績 数量 | S4: 実績 売上 | T4: 実績 粗利 | U4: 計画 数量 | V4: 計画 売上 | W4: 計画 粗利 | X4: 実績 数量 | Y4: 実績 売上 | Z4: 実績 粗利 | AA4: 計画 数量 | AB4: 計画 売上 | AC4: 計画 粗利 | AD4: 実績 数量 | AE4: 実績 売上 | AF4: 実績 粗利 | AG4: 計画 数量 | AH4: 計画 売上 | AI4: 計画 粗利 | AJ4: 実績 数量 | AK4: 実績 売上 | AL4: 実績 粗利 | AM4: 計画 数量 | AN4: 計画 売上 | AO4: 計画 粗利 | AP4: 実績 数量 | AQ4: 実績 売上 | AR4: 実績 粗利 | AS4: 計画 数量 | AT4: 計画 売上 | AU4: 計画 粗利 | AV4: 実績 数量 | AW4: 実績 売上 | AX4: 実績 粗利 | AY4: 計画 数量 | AZ4: 計画 売上 | BA4: 計画 粗利 | BB4: 実績 数量 | BC4: 実績 売上 | BD4: 実績 粗利 | BE4: 計画 数量 | BF4: 計画 売上 | BG4: 計画 粗利 | BH4: 実績 数量 | BI4: 実績 売上 | BJ4: 実績 粗利 | BK4: 計画 数量 | BL4: 計画 売上 | BM4: 計画 粗利 | BN4: 実績 数量 | BO4: 実績 売上 | BP4: 実績 粗利 | BQ4: 計画 数量 | BR4: 計画 売上 | BS4: 計画 粗利 | BT4: 実績 数量 | BU4: 実績 売上 | BV4: 実績 粗利 | BW4: 計画 数量 | BX4: 計画 売上 | BY4: 計画 粗利 | BZ4: 実績 数量 | CA4: 実績 売上 | CB4: 実績 粗利 | CC4: 計画 数量 | CD4: 計画 売上 | CE4: 計画 粗利 | CF4: 実績 数量 | CG4: 実績 売上 | CH4: 実績 粗利
A5: 東大阪 | B5: =IF(D5="","",IFERROR(VLOOKUP(D5,商品マスタ!$A:$K,2,FALSE),"昭和")) -> 昭和 | C5: 昭和プロダクツ | D5: 金具・ネジ類 | E5: =IF(D5="","",IFERROR(VLOOKUP(D5,商品マスタ!$A:$K,4,FALSE),8.14)) -> 8.14 | F5: =IF(D5="","",IFERROR(VLOOKUP(D5,商品マスタ!$A:$K,8,FALSE),0)) -> 0 | G5: =SUM(O5,U5,AA5,AG5,AM5,AS5,AY5,BE5,BK5,BQ5,BW5,CC5) -> 10 | H5: =SUM(P5,V5,AB5,AH5,AN5,AT5,AZ5,BF5,BL5,BR5,BX5,CD5) -> 81.4 | I5: =SUM(Q5,W5,AC5,AI5,AO5,AU5,BA5,BG5,BM5,BS5,BY5,CE5) -> 0 | J5: =SUM(R5,X5,AD5,AJ5,AP5,AV5,BB5,BH5,BN5,BT5,BZ5,CF5) -> 0 | K5: =SUM(S5,Y5,AE5,AK5,AQ5,AW5,BC5,BI5,BO5,BU5,CA5,CG5) -> 0 | L5: =SUM(T5,Z5,AF5,AL5,AR5,AX5,BD5,BJ5,BP5,BV5,CB5,CH5) -> 0 | M5: =IFERROR(K5/CI5,"") | N5: =IFERROR(L5/CJ5,"") | O5: 10 | P5: =IF(O5="","",O5*$E5) -> 81.4 | Q5: =IF(O5="","",O5*$F5) -> 0 | S5: =IF(R5="","",R5*$E5) | T5: =IF(R5="","",R5*$F5) | V5: =IF(U5="","",U5*$E5) | W5: =IF(U5="","",U5*$F5) | Y5: =IF(X5="","",X5*$E5) | Z5: =IF(X5="","",X5*$F5) | AB5: =IF(AA5="","",AA5*$E5) | AC5: =IF(AA5="","",AA5*$F5) | AE5: =IF(AD5="","",AD5*$E5) | AF5: =IF(AD5="","",AD5*$F5) | AH5: =IF(AG5="","",AG5*$E5) | AI5: =IF(AG5="","",AG5*$F5) | AK5: =IF(AJ5="","",AJ5*$E5) | AL5: =IF(AJ5="","",AJ5*$F5) | AN5: =IF(AM5="","",AM5*$E5) | AO5: =IF(AM5="","",AM5*$F5) | AQ5: =IF(AP5="","",AP5*$E5) | AR5: =IF(AP5="","",AP5*$F5) | AT5: =IF(AS5="","",AS5*$E5) | AU5: =IF(AS5="","",AS5*$F5) | AW5: =IF(AV5="","",AV5*$E5) | AX5: =IF(AV5="","",AV5*$F5) | AZ5: =IF(AY5="","",AY5*$E5) | BA5: =IF(AY5="","",AY5*$F5) | BC5: =IF(BB5="","",BB5*$E5) | BD5: =IF(BB5="","",BB5*$F5) | BF5: =IF(BE5="","",BE5*$E5) | BG5: =IF(BE5="","",BE5*$F5) | BI5: =IF(BH5="","",BH5*$E5) | BJ5: =IF(BH5="","",BH5*$F5) | BL5: =IF(BK5="","",BK5*$E5) | BM5: =IF(BK5="","",BK5*$F5) | BO5: =IF(BN5="","",BN5*$E5) | BP5: =IF(BN5="","",BN5*$F5) | BR5: =IF(BQ5="","",BQ5*$E5) | BS5: =IF(BQ5="","",BQ5*$F5) | BU5: =IF(BT5="","",BT5*$E5) | BV5: =IF(BT5="","",BT5*$F5) | BX5: =IF(BW5="","",BW5*$E5) | BY5: =IF(BW5="","",BW5*$F5) | CA5: =IF(BZ5="","",BZ5*$E5) | CB5: =IF(BZ5="","",BZ5*$F5) | CD5: =IF(CC5="","",CC5*$E5) | CE5: =IF(CC5="","",CC5*$F5) | CG5: =IF(CF5="","",CF5*$E5) | CH5: =IF(CF5="","",CF5*$F5) | CI5: =IF(R5>0,P5,0) + IF(X5>0,V5,0) + IF(AD5>0,AB5,0) + IF(AJ5>0,AH5,0) + IF(AP5>0,AN5,0) + IF(AV5>0,AT5,0) + IF(BB5>0,AZ5,0) + IF(BH5>0,BF5,0) + IF(BN5>0,BL5,0) + IF(BT5>0,BR5,0) + IF(BZ5>0,BX5,0) + IF(CF5>0,CD5,0) -> 0 | CJ5: =IF(R5>0,Q5,0) + IF(X5>0,W5,0) + IF(AD5>0,AC5,0) + IF(AJ5>0,AI5,0) + IF(AP5>0,AO5,0) + IF(AV5>0,AU5,0) + IF(BB5>0,BA5,0) + IF(BH5>0,BG5,0) + IF(BN5>0,BM5,0) + IF(BT5>0,BS5,0) + IF(BZ5>0,BY5,0) + IF(CF5>0,CE5,0) -> 0
A6: 東大阪 | B6: =IF(D6="","",IFERROR(VLOOKUP(D6,商品マスタ!$A:$K,2,FALSE),"昭和")) -> 昭和 | C6: 昭和丸筒 | D6: 金具・ネジ類 | E6: =IF(D6="","",IFERROR(VLOOKUP(D6,商品マスタ!$A:$K,4,FALSE),8.14)) -> 8.14 | F6: =IF(D6="","",IFERROR(VLOOKUP(D6,商品マスタ!$A:$K,8,FALSE),0)) -> 0 | G6: =SUM(O6,U6,AA6,AG6,AM6,AS6,AY6,BE6,BK6,BQ6,BW6,CC6) -> 0 | H6: =SUM(P6,V6,AB6,AH6,AN6,AT6,AZ6,BF6,BL6,BR6,BX6,CD6) -> 0 | I6: =SUM(Q6,W6,AC6,AI6,AO6,AU6,BA6,BG6,BM6,BS6,BY6,CE6) -> 0 | J6: =SUM(R6,X6,AD6,AJ6,AP6,AV6,BB6,BH6,BN6,BT6,BZ6,CF6) -> 0 | K6: =SUM(S6,Y6,AE6,AK6,AQ6,AW6,BC6,BI6,BO6,BU6,CA6,CG6) -> 0 | L6: =SUM(T6,Z6,AF6,AL6,AR6,AX6,BD6,BJ6,BP6,BV6,CB6,CH6) -> 0 | M6: =IFERROR(K6/CI6,"") | N6: =IFERROR(L6/CJ6,"") | P6: =IF(O6="","",O6*$E6) | Q6: =IF(O6="","",O6*$F6) | S6: =IF(R6="","",R6*$E6) | T6: =IF(R6="","",R6*$F6) | V6: =IF(U6="","",U6*$E6) | W6: =IF(U6="","",U6*$F6) | Y6: =IF(X6="","",X6*$E6) | Z6: =IF(X6="","",X6*$F6) | AB6: =IF(AA6="","",AA6*$E6) | AC6: =IF(AA6="","",AA6*$F6) | AE6: =IF(AD6="","",AD6*$E6) | AF6: =IF(AD6="","",AD6*$F6) | AH6: =IF(AG6="","",AG6*$E6) | AI6: =IF(AG6="","",AG6*$F6) | AK6: =IF(AJ6="","",AJ6*$E6) | AL6: =IF(AJ6="","",AJ6*$F6) | AN6: =IF(AM6="","",AM6*$E6) | AO6: =IF(AM6="","",AM6*$F6) | AQ6: =IF(AP6="","",AP6*$E6) | AR6: =IF(AP6="","",AP6*$F6) | AT6: =IF(AS6="","",AS6*$E6) | AU6: =IF(AS6="","",AS6*$F6) | AW6: =IF(AV6="","",AV6*$E6) | AX6: =IF(AV6="","",AV6*$F6) | AZ6: =IF(AY6="","",AY6*$E6) | BA6: =IF(AY6="","",AY6*$F6) | BC6: =IF(BB6="","",BB6*$E6) | BD6: =IF(BB6="","",BB6*$F6) | BF6: =IF(BE6="","",BE6*$E6) | BG6: =IF(BE6="","",BE6*$F6) | BI6: =IF(BH6="","",BH6*$E6) | BJ6: =IF(BH6="","",BH6*$F6) | BL6: =IF(BK6="","",BK6*$E6) | BM6: =IF(BK6="","",BK6*$F6) | BO6: =IF(BN6="","",BN6*$E6) | BP6: =IF(BN6="","",BN6*$F6) | BR6: =IF(BQ6="","",BQ6*$E6) | BS6: =IF(BQ6="","",BQ6*$F6) | BU6: =IF(BT6="","",BT6*$E6) | BV6: =IF(BT6="","",BT6*$F6) | BX6: =IF(BW6="","",BW6*$E6) | BY6: =IF(BW6="","",BW6*$F6) | CA6: =IF(BZ6="","",BZ6*$E6) | CB6: =IF(BZ6="","",BZ6*$F6) | CD6: =IF(CC6="","",CC6*$E6) | CE6: =IF(CC6="","",CC6*$F6) | CG6: =IF(CF6="","",CF6*$E6) | CH6: =IF(CF6="","",CF6*$F6) | CI6: =IF(R6>0,P6,0) + IF(X6>0,V6,0) + IF(AD6>0,AB6,0) + IF(AJ6>0,AH6,0) + IF(AP6>0,AN6,0) + IF(AV6>0,AT6,0) + IF(BB6>0,AZ6,0) + IF(BH6>0,BF6,0) + IF(BN6>0,BL6,0) + IF(BT6>0,BR6,0) + IF(BZ6>0,BX6,0) + IF(CF6>0,CD6,0) -> 0 | CJ6: =IF(R6>0,Q6,0) + IF(X6>0,W6,0) + IF(AD6>0,AC6,0) + IF(AJ6>0,AI6,0) + IF(AP6>0,AO6,0) + IF(AV6>0,AU6,0) + IF(BB6>0,BA6,0) + IF(BH6>0,BG6,0) + IF(BN6>0,BM6,0) + IF(BT6>0,BS6,0) + IF(BZ6>0,BY6,0) + IF(CF6>0,CE6,0) -> 0
A7: 東大阪 | B7: =IF(D7="","",IFERROR(VLOOKUP(D7,商品マスタ!$A:$K,2,FALSE),"昭和")) -> 昭和 | C7: 昭和化成工業 | D7: その他 | E7: =IF(D7="","",IFERROR(VLOOKUP(D7,商品マスタ!$A:$K,4,FALSE),0)) -> 0 | F7: =IF(D7="","",IFERROR(VLOOKUP(D7,商品マスタ!$A:$K,8,FALSE),0)) -> 0 | G7: =SUM(O7,U7,AA7,AG7,AM7,AS7,AY7,BE7,BK7,BQ7,BW7,CC7) -> 0 | H7: =SUM(P7,V7,AB7,AH7,AN7,AT7,AZ7,BF7,BL7,BR7,BX7,CD7) -> 0 | I7: =SUM(Q7,W7,AC7,AI7,AO7,AU7,BA7,BG7,BM7,BS7,BY7,CE7) -> 0 | J7: =SUM(R7,X7,AD7,AJ7,AP7,AV7,BB7,BH7,BN7,BT7,BZ7,CF7) -> 0 | K7: =SUM(S7,Y7,AE7,AK7,AQ7,AW7,BC7,BI7,BO7,BU7,CA7,CG7) -> 0 | L7: =SUM(T7,Z7,AF7,AL7,AR7,AX7,BD7,BJ7,BP7,BV7,CB7,CH7) -> 0 | M7: =IFERROR(K7/CI7,"") | N7: =IFERROR(L7/CJ7,"") | P7: =IF(O7="","",O7*$E7) | Q7: =IF(O7="","",O7*$F7) | S7: =IF(R7="","",R7*$E7) | T7: =IF(R7="","",R7*$F7) | V7: =IF(U7="","",U7*$E7) | W7: =IF(U7="","",U7*$F7) | Y7: =IF(X7="","",X7*$E7) | Z7: =IF(X7="","",X7*$F7) | AB7: =IF(AA7="","",AA7*$E7) | AC7: =IF(AA7="","",AA7*$F7) | AE7: =IF(AD7="","",AD7*$E7) | AF7: =IF(AD7="","",AD7*$F7) | AH7: =IF(AG7="","",AG7*$E7) | AI7: =IF(AG7="","",AG7*$F7) | AK7: =IF(AJ7="","",AJ7*$E7) | AL7: =IF(AJ7="","",AJ7*$F7) | AN7: =IF(AM7="","",AM7*$E7) | AO7: =IF(AM7="","",AM7*$F7) | AQ7: =IF(AP7="","",AP7*$E7) | AR7: =IF(AP7="","",AP7*$F7) | AT7: =IF(AS7="","",AS7*$E7) | AU7: =IF(AS7="","",AS7*$F7) | AW7: =IF(AV7="","",AV7*$E7) | AX7: =IF(AV7="","",AV7*$F7) | AZ7: =IF(AY7="","",AY7*$E7) | BA7: =IF(AY7="","",AY7*$F7) | BC7: =IF(BB7="","",BB7*$E7) | BD7: =IF(BB7="","",BB7*$F7) | BF7: =IF(BE7="","",BE7*$E7) | BG7: =IF(BE7="","",BE7*$F7) | BI7: =IF(BH7="","",BH7*$E7) | BJ7: =IF(BH7="","",BH7*$F7) | BL7: =IF(BK7="","",BK7*$E7) | BM7: =IF(BK7="","",BK7*$F7) | BO7: =IF(BN7="","",BN7*$E7) | BP7: =IF(BN7="","",BN7*$F7) | BR7: =IF(BQ7="","",BQ7*$E7) | BS7: =IF(BQ7="","",BQ7*$F7) | BU7: =IF(BT7="","",BT7*$E7) | BV7: =IF(BT7="","",BT7*$F7) | BX7: =IF(BW7="","",BW7*$E7) | BY7: =IF(BW7="","",BW7*$F7) | CA7: =IF(BZ7="","",BZ7*$E7) | CB7: =IF(BZ7="","",BZ7*$F7) | CD7: =IF(CC7="","",CC7*$E7) | CE7: =IF(CC7="","",CC7*$F7) | CG7: =IF(CF7="","",CF7*$E7) | CH7: =IF(CF7="","",CF7*$F7) | CI7: =IF(R7>0,P7,0) + IF(X7>0,V7,0) + IF(AD7>0,AB7,0) + IF(AJ7>0,AH7,0) + IF(AP7>0,AN7,0) + IF(AV7>0,AT7,0) + IF(BB7>0,AZ7,0) + IF(BH7>0,BF7,0) + IF(BN7>0,BL7,0) + IF(BT7>0,BR7,0) + IF(BZ7>0,BX7,0) + IF(CF7>0,CD7,0) -> 0 | CJ7: =IF(R7>0,Q7,0) + IF(X7>0,W7,0) + IF(AD7>0,AC7,0) + IF(AJ7>0,AI7,0) + IF(AP7>0,AO7,0) + IF(AV7>0,AU7,0) + IF(BB7>0,BA7,0) + IF(BH7>0,BG7,0) + IF(BN7>0,BM7,0) + IF(BT7>0,BS7,0) + IF(BZ7>0,BY7,0) + IF(CF7>0,CE7,0) -> 0
A8: 東大阪 | B8: =IF(D8="","",IFERROR(VLOOKUP(D8,商品マスタ!$A:$K,2,FALSE),"昭和以外")) -> 昭和以外 | C8: イワサキ | D8: その他 | E8: =IF(D8="","",IFERROR(VLOOKUP(D8,商品マスタ!$A:$K,4,FALSE),0)) -> 0 | F8: =IF(D8="","",IFERROR(VLOOKUP(D8,商品マスタ!$A:$K,8,FALSE),0)) -> 0 | G8: =SUM(O8,U8,AA8,AG8,AM8,AS8,AY8,BE8,BK8,BQ8,BW8,CC8) -> 0 | H8: =SUM(P8,V8,AB8,AH8,AN8,AT8,AZ8,BF8,BL8,BR8,BX8,CD8) -> 0 | I8: =SUM(Q8,W8,AC8,AI8,AO8,AU8,BA8,BG8,BM8,BS8,BY8,CE8) -> 0 | J8: =SUM(R8,X8,AD8,AJ8,AP8,AV8,BB8,BH8,BN8,BT8,BZ8,CF8) -> 0 | K8: =SUM(S8,Y8,AE8,AK8,AQ8,AW8,BC8,BI8,BO8,BU8,CA8,CG8) -> 0 | L8: =SUM(T8,Z8,AF8,AL8,AR8,AX8,BD8,BJ8,BP8,BV8,CB8,CH8) -> 0 | M8: =IFERROR(K8/CI8,"") | N8: =IFERROR(L8/CJ8,"") | P8: =IF(O8="","",O8*$E8) | Q8: =IF(O8="","",O8*$F8) | S8: =IF(R8="","",R8*$E8) | T8: =IF(R8="","",R8*$F8) | V8: =IF(U8="","",U8*$E8) | W8: =IF(U8="","",U8*$F8) | Y8: =IF(X8="","",X8*$E8) | Z8: =IF(X8="","",X8*$F8) | AB8: =IF(AA8="","",AA8*$E8) | AC8: =IF(AA8="","",AA8*$F8) | AE8: =IF(AD8="","",AD8*$E8) | AF8: =IF(AD8="","",AD8*$F8) | AH8: =IF(AG8="","",AG8*$E8) | AI8: =IF(AG8="","",AG8*$F8) | AK8: =IF(AJ8="","",AJ8*$E8) | AL8: =IF(AJ8="","",AJ8*$F8) | AN8: =IF(AM8="","",AM8*$E8) | AO8: =IF(AM8="","",AM8*$F8) | AQ8: =IF(AP8="","",AP8*$E8) | AR8: =IF(AP8="","",AP8*$F8) | AT8: =IF(AS8="","",AS8*$E8) | AU8: =IF(AS8="","",AS8*$F8) | AW8: =IF(AV8="","",AV8*$E8) | AX8: =IF(AV8="","",AV8*$F8) | AZ8: =IF(AY8="","",AY8*$E8) | BA8: =IF(AY8="","",AY8*$F8) | BC8: =IF(BB8="","",BB8*$E8) | BD8: =IF(BB8="","",BB8*$F8) | BF8: =IF(BE8="","",BE8*$E8) | BG8: =IF(BE8="","",BE8*$F8) | BI8: =IF(BH8="","",BH8*$E8) | BJ8: =IF(BH8="","",BH8*$F8) | BL8: =IF(BK8="","",BK8*$E8) | BM8: =IF(BK8="","",BK8*$F8) | BO8: =IF(BN8="","",BN8*$E8) | BP8: =IF(BN8="","",BN8*$F8) | BR8: =IF(BQ8="","",BQ8*$E8) | BS8: =IF(BQ8="","",BQ8*$F8) | BU8: =IF(BT8="","",BT8*$E8) | BV8: =IF(BT8="","",BT8*$F8) | BX8: =IF(BW8="","",BW8*$E8) | BY8: =IF(BW8="","",BW8*$F8) | CA8: =IF(BZ8="","",BZ8*$E8) | CB8: =IF(BZ8="","",BZ8*$F8) | CD8: =IF(CC8="","",CC8*$E8) | CE8: =IF(CC8="","",CC8*$F8) | CG8: =IF(CF8="","",CF8*$E8) | CH8: =IF(CF8="","",CF8*$F8) | CI8: =IF(R8>0,P8,0) + IF(X8>0,V8,0) + IF(AD8>0,AB8,0) + IF(AJ8>0,AH8,0) + IF(AP8>0,AN8,0) + IF(AV8>0,AT8,0) + IF(BB8>0,AZ8,0) + IF(BH8>0,BF8,0) + IF(BN8>0,BL8,0) + IF(BT8>0,BR8,0) + IF(BZ8>0,BX8,0) + IF(CF8>0,CD8,0) -> 0 | CJ8: =IF(R8>0,Q8,0) + IF(X8>0,W8,0) + IF(AD8>0,AC8,0) + IF(AJ8>0,AI8,0) + IF(AP8>0,AO8,0) + IF(AV8>0,AU8,0) + IF(BB8>0,BA8,0) + IF(BH8>0,BG8,0) + IF(BN8>0,BM8,0) + IF(BT8>0,BS8,0) + IF(BZ8>0,BY8,0) + IF(CF8>0,CE8,0) -> 0
A9: 東大阪 | B9: =IF(D9="","",IFERROR(VLOOKUP(D9,商品マスタ!$A:$K,2,FALSE),"昭和以外")) -> 昭和以外 | C9: 三協丸筒 | D9: 金具・ネジ類 | E9: =IF(D9="","",IFERROR(VLOOKUP(D9,商品マスタ!$A:$K,4,FALSE),8.14)) -> 8.14 | F9: =IF(D9="","",IFERROR(VLOOKUP(D9,商品マスタ!$A:$K,8,FALSE),0)) -> 0 | G9: =SUM(O9,U9,AA9,AG9,AM9,AS9,AY9,BE9,BK9,BQ9,BW9,CC9) -> 0 | H9: =SUM(P9,V9,AB9,AH9,AN9,AT9,AZ9,BF9,BL9,BR9,BX9,CD9) -> 0 | I9: =SUM(Q9,W9,AC9,AI9,AO9,AU9,BA9,BG9,BM9,BS9,BY9,CE9) -> 0 | J9: =SUM(R9,X9,AD9,AJ9,AP9,AV9,BB9,BH9,BN9,BT9,BZ9,CF9) -> 0 | K9: =SUM(S9,Y9,AE9,AK9,AQ9,AW9,BC9,BI9,BO9,BU9,CA9,CG9) -> 0 | L9: =SUM(T9,Z9,AF9,AL9,AR9,AX9,BD9,BJ9,BP9,BV9,CB9,CH9) -> 0 | M9: =IFERROR(K9/CI9,"") | N9: =IFERROR(L9/CJ9,"") | P9: =IF(O9="","",O9*$E9) | Q9: =IF(O9="","",O9*$F9) | S9: =IF(R9="","",R9*$E9) | T9: =IF(R9="","",R9*$F9) | V9: =IF(U9="","",U9*$E9) | W9: =IF(U9="","",U9*$F9) | Y9: =IF(X9="","",X9*$E9) | Z9: =IF(X9="","",X9*$F9) | AB9: =IF(AA9="","",AA9*$E9) | AC9: =IF(AA9="","",AA9*$F9) | AE9: =IF(AD9="","",AD9*$E9) | AF9: =IF(AD9="","",AD9*$F9) | AH9: =IF(AG9="","",AG9*$E9) | AI9: =IF(AG9="","",AG9*$F9) | AK9: =IF(AJ9="","",AJ9*$E9) | AL9: =IF(AJ9="","",AJ9*$F9) | AN9: =IF(AM9="","",AM9*$E9) | AO9: =IF(AM9="","",AM9*$F9) | AQ9: =IF(AP9="","",AP9*$E9) | AR9: =IF(AP9="","",AP9*$F9) | AT9: =IF(AS9="","",AS9*$E9) | AU9: =IF(AS9="","",AS9*$F9) | AW9: =IF(AV9="","",AV9*$E9) | AX9: =IF(AV9="","",AV9*$F9) | AZ9: =IF(AY9="","",AY9*$E9) | BA9: =IF(AY9="","",AY9*$F9) | BC9: =IF(BB9="","",BB9*$E9) | BD9: =IF(BB9="","",BB9*$F9) | BF9: =IF(BE9="","",BE9*$E9) | BG9: =IF(BE9="","",BE9*$F9) | BI9: =IF(BH9="","",BH9*$E9) | BJ9: =IF(BH9="","",BH9*$F9) | BL9: =IF(BK9="","",BK9*$E9) | BM9: =IF(BK9="","",BK9*$F9) | BO9: =IF(BN9="","",BN9*$E9) | BP9: =IF(BN9="","",BN9*$F9) | BR9: =IF(BQ9="","",BQ9*$E9) | BS9: =IF(BQ9="","",BQ9*$F9) | BU9: =IF(BT9="","",BT9*$E9) | BV9: =IF(BT9="","",BT9*$F9) | BX9: =IF(BW9="","",BW9*$E9) | BY9: =IF(BW9="","",BW9*$F9) | CA9: =IF(BZ9="","",BZ9*$E9) | CB9: =IF(BZ9="","",BZ9*$F9) | CD9: =IF(CC9="","",CC9*$E9) | CE9: =IF(CC9="","",CC9*$F9) | CG9: =IF(CF9="","",CF9*$E9) | CH9: =IF(CF9="","",CF9*$F9) | CI9: =IF(R9>0,P9,0) + IF(X9>0,V9,0) + IF(AD9>0,AB9,0) + IF(AJ9>0,AH9,0) + IF(AP9>0,AN9,0) + IF(AV9>0,AT9,0) + IF(BB9>0,AZ9,0) + IF(BH9>0,BF9,0) + IF(BN9>0,BL9,0) + IF(BT9>0,BR9,0) + IF(BZ9>0,BX9,0) + IF(CF9>0,CD9,0) -> 0 | CJ9: =IF(R9>0,Q9,0) + IF(X9>0,W9,0) + IF(AD9>0,AC9,0) + IF(AJ9>0,AI9,0) + IF(AP9>0,AO9,0) + IF(AV9>0,AU9,0) + IF(BB9>0,BA9,0) + IF(BH9>0,BG9,0) + IF(BN9>0,BM9,0) + IF(BT9>0,BS9,0) + IF(BZ9>0,BY9,0) + IF(CF9>0,CE9,0) -> 0
A10: 東大阪 | B10: =IF(D10="","",IFERROR(VLOOKUP(D10,商品マスタ!$A:$K,2,FALSE),"昭和以外")) -> 昭和以外 | C10: 向陽エンジニアリング | D10: その他 | E10: =IF(D10="","",IFERROR(VLOOKUP(D10,商品マスタ!$A:$K,4,FALSE),0)) -> 0 | F10: =IF(D10="","",IFERROR(VLOOKUP(D10,商品マスタ!$A:$K,8,FALSE),0)) -> 0 | G10: =SUM(O10,U10,AA10,AG10,AM10,AS10,AY10,BE10,BK10,BQ10,BW10,CC10) -> 0 | H10: =SUM(P10,V10,AB10,AH10,AN10,AT10,AZ10,BF10,BL10,BR10,BX10,CD10) -> 0 | I10: =SUM(Q10,W10,AC10,AI10,AO10,AU10,BA10,BG10,BM10,BS10,BY10,CE10) -> 0 | J10: =SUM(R10,X10,AD10,AJ10,AP10,AV10,BB10,BH10,BN10,BT10,BZ10,CF10) -> 0 | K10: =SUM(S10,Y10,AE10,AK10,AQ10,AW10,BC10,BI10,BO10,BU10,CA10,CG10) -> 0 | L10: =SUM(T10,Z10,AF10,AL10,AR10,AX10,BD10,BJ10,BP10,BV10,CB10,CH10) -> 0 | M10: =IFERROR(K10/CI10,"") | N10: =IFERROR(L10/CJ10,"") | P10: =IF(O10="","",O10*$E10) | Q10: =IF(O10="","",O10*$F10) | S10: =IF(R10="","",R10*$E10) | T10: =IF(R10="","",R10*$F10) | V10: =IF(U10="","",U10*$E10) | W10: =IF(U10="","",U10*$F10) | Y10: =IF(X10="","",X10*$E10) | Z10: =IF(X10="","",X10*$F10) | AB10: =IF(AA10="","",AA10*$E10) | AC10: =IF(AA10="","",AA10*$F10) | AE10: =IF(AD10="","",AD10*$E10) | AF10: =IF(AD10="","",AD10*$F10) | AH10: =IF(AG10="","",AG10*$E10) | AI10: =IF(AG10="","",AG10*$F10) | AK10: =IF(AJ10="","",AJ10*$E10) | AL10: =IF(AJ10="","",AJ10*$F10) | AN10: =IF(AM10="","",AM10*$E10) | AO10: =IF(AM10="","",AM10*$F10) | AQ10: =IF(AP10="","",AP10*$E10) | AR10: =IF(AP10="","",AP10*$F10) | AT10: =IF(AS10="","",AS10*$E10) | AU10: =IF(AS10="","",AS10*$F10) | AW10: =IF(AV10="","",AV10*$E10) | AX10: =IF(AV10="","",AV10*$F10) | AZ10: =IF(AY10="","",AY10*$E10) | BA10: =IF(AY10="","",AY10*$F10) | BC10: =IF(BB10="","",BB10*$E10) | BD10: =IF(BB10="","",BB10*$F10) | BF10: =IF(BE10="","",BE10*$E10) | BG10: =IF(BE10="","",BE10*$F10) | BI10: =IF(BH10="","",BH10*$E10) | BJ10: =IF(BH10="","",BH10*$F10) | BL10: =IF(BK10="","",BK10*$E10) | BM10: =IF(BK10="","",BK10*$F10) | BO10: =IF(BN10="","",BN10*$E10) | BP10: =IF(BN10="","",BN10*$F10) | BR10: =IF(BQ10="","",BQ10*$E10) | BS10: =IF(BQ10="","",BQ10*$F10) | BU10: =IF(BT10="","",BT10*$E10) | BV10: =IF(BT10="","",BT10*$F10) | BX10: =IF(BW10="","",BW10*$E10) | BY10: =IF(BW10="","",BW10*$F10) | CA10: =IF(BZ10="","",BZ10*$E10) | CB10: =IF(BZ10="","",BZ10*$F10) | CD10: =IF(CC10="","",CC10*$E10) | CE10: =IF(CC10="","",CC10*$F10) | CG10: =IF(CF10="","",CF10*$E10) | CH10: =IF(CF10="","",CF10*$F10) | CI10: =IF(R10>0,P10,0) + IF(X10>0,V10,0) + IF(AD10>0,AB10,0) + IF(AJ10>0,AH10,0) + IF(AP10>0,AN10,0) + IF(AV10>0,AT10,0) + IF(BB10>0,AZ10,0) + IF(BH10>0,BF10,0) + IF(BN10>0,BL10,0) + IF(BT10>0,BR10,0) + IF(BZ10>0,BX10,0) + IF(CF10>0,CD10,0) -> 0 | CJ10: =IF(R10>0,Q10,0) + IF(X10>0,W10,0) + IF(AD10>0,AC10,0) + IF(AJ10>0,AI10,0) + IF(AP10>0,AO10,0) + IF(AV10>0,AU10,0) + IF(BB10>0,BA10,0) + IF(BH10>0,BG10,0) + IF(BN10>0,BM10,0) + IF(BT10>0,BS10,0) + IF(BZ10>0,BY10,0) + IF(CF10>0,CE10,0) -> 0
A11: 東大阪 | B11: =IF(D11="","",IFERROR(VLOOKUP(D11,商品マスタ!$A:$K,2,FALSE),"昭和以外")) -> 昭和以外 | C11: 晶立工作所 | D11: プランジャー・スプリング | E11: =IF(D11="","",IFERROR(VLOOKUP(D11,商品マスタ!$A:$K,4,FALSE),6.55)) -> 6.55 | F11: =IF(D11="","",IFERROR(VLOOKUP(D11,商品マスタ!$A:$K,8,FALSE),0.599999999999999)) -> 0.6 | G11: =SUM(O11,U11,AA11,AG11,AM11,AS11,AY11,BE11,BK11,BQ11,BW11,CC11) -> 0 | H11: =SUM(P11,V11,AB11,AH11,AN11,AT11,AZ11,BF11,BL11,BR11,BX11,CD11) -> 0 | I11: =SUM(Q11,W11,AC11,AI11,AO11,AU11,BA11,BG11,BM11,BS11,BY11,CE11) -> 0 | J11: =SUM(R11,X11,AD11,AJ11,AP11,AV11,BB11,BH11,BN11,BT11,BZ11,CF11) -> 0 | K11: =SUM(S11,Y11,AE11,AK11,AQ11,AW11,BC11,BI11,BO11,BU11,CA11,CG11) -> 0 | L11: =SUM(T11,Z11,AF11,AL11,AR11,AX11,BD11,BJ11,BP11,BV11,CB11,CH11) -> 0 | M11: =IFERROR(K11/CI11,"") | N11: =IFERROR(L11/CJ11,"") | P11: =IF(O11="","",O11*$E11) | Q11: =IF(O11="","",O11*$F11) | S11: =IF(R11="","",R11*$E11) | T11: =IF(R11="","",R11*$F11) | V11: =IF(U11="","",U11*$E11) | W11: =IF(U11="","",U11*$F11) | Y11: =IF(X11="","",X11*$E11) | Z11: =IF(X11="","",X11*$F11) | AB11: =IF(AA11="","",AA11*$E11) | AC11: =IF(AA11="","",AA11*$F11) | AE11: =IF(AD11="","",AD11*$E11) | AF11: =IF(AD11="","",AD11*$F11) | AH11: =IF(AG11="","",AG11*$E11) | AI11: =IF(AG11="","",AG11*$F11) | AK11: =IF(AJ11="","",AJ11*$E11) | AL11: =IF(AJ11="","",AJ11*$F11) | AN11: =IF(AM11="","",AM11*$E11) | AO11: =IF(AM11="","",AM11*$F11) | AQ11: =IF(AP11="","",AP11*$E11) | AR11: =IF(AP11="","",AP11*$F11) | AT11: =IF(AS11="","",AS11*$E11) | AU11: =IF(AS11="","",AS11*$F11) | AW11: =IF(AV11="","",AV11*$E11) | AX11: =IF(AV11="","",AV11*$F11) | AZ11: =IF(AY11="","",AY11*$E11) | BA11: =IF(AY11="","",AY11*$F11) | BC11: =IF(BB11="","",BB11*$E11) | BD11: =IF(BB11="","",BB11*$F11) | BF11: =IF(BE11="","",BE11*$E11) | BG11: =IF(BE11="","",BE11*$F11) | BI11: =IF(BH11="","",BH11*$E11) | BJ11: =IF(BH11="","",BH11*$F11) | BL11: =IF(BK11="","",BK11*$E11) | BM11: =IF(BK11="","",BK11*$F11) | BO11: =IF(BN11="","",BN11*$E11) | BP11: =IF(BN11="","",BN11*$F11) | BR11: =IF(BQ11="","",BQ11*$E11) | BS11: =IF(BQ11="","",BQ11*$F11) | BU11: =IF(BT11="","",BT11*$E11) | BV11: =IF(BT11="","",BT11*$F11) | BX11: =IF(BW11="","",BW11*$E11) | BY11: =IF(BW11="","",BW11*$F11) | CA11: =IF(BZ11="","",BZ11*$E11) | CB11: =IF(BZ11="","",BZ11*$F11) | CD11: =IF(CC11="","",CC11*$E11) | CE11: =IF(CC11="","",CC11*$F11) | CG11: =IF(CF11="","",CF11*$E11) | CH11: =IF(CF11="","",CF11*$F11) | CI11: =IF(R11>0,P11,0) + IF(X11>0,V11,0) + IF(AD11>0,AB11,0) + IF(AJ11>0,AH11,0) + IF(AP11>0,AN11,0) + IF(AV11>0,AT11,0) + IF(BB11>0,AZ11,0) + IF(BH11>0,BF11,0) + IF(BN11>0,BL11,0) + IF(BT11>0,BR11,0) + IF(BZ11>0,BX11,0) + IF(CF11>0,CD11,0) -> 0 | CJ11: =IF(R11>0,Q11,0) + IF(X11>0,W11,0) + IF(AD11>0,AC11,0) + IF(AJ11>0,AI11,0) + IF(AP11>0,AO11,0) + IF(AV11>0,AU11,0) + IF(BB11>0,BA11,0) + IF(BH11>0,BG11,0) + IF(BN11>0,BM11,0) + IF(BT11>0,BS11,0) + IF(BZ11>0,BY11,0) + IF(CF11>0,CE11,0) -> 0
A12: 東大阪 | B12: =IF(D12="","",IFERROR(VLOOKUP(D12,商品マスタ!$A:$K,2,FALSE),"昭和以外")) -> 昭和以外 | C12: 製作工房タケダ | D12: その他 | E12: =IF(D12="","",IFERROR(VLOOKUP(D12,商品マスタ!$A:$K,4,FALSE),0)) -> 0 | F12: =IF(D12="","",IFERROR(VLOOKUP(D12,商品マスタ!$A:$K,8,FALSE),0)) -> 0 | G12: =SUM(O12,U12,AA12,AG12,AM12,AS12,AY12,BE12,BK12,BQ12,BW12,CC12) -> 0 | H12: =SUM(P12,V12,AB12,AH12,AN12,AT12,AZ12,BF12,BL12,BR12,BX12,CD12) -> 0 | I12: =SUM(Q12,W12,AC12,AI12,AO12,AU12,BA12,BG12,BM12,BS12,BY12,CE12) -> 0 | J12: =SUM(R12,X12,AD12,AJ12,AP12,AV12,BB12,BH12,BN12,BT12,BZ12,CF12) -> 0 | K12: =SUM(S12,Y12,AE12,AK12,AQ12,AW12,BC12,BI12,BO12,BU12,CA12,CG12) -> 0 | L12: =SUM(T12,Z12,AF12,AL12,AR12,AX12,BD12,BJ12,BP12,BV12,CB12,CH12) -> 0 | M12: =IFERROR(K12/CI12,"") | N12: =IFERROR(L12/CJ12,"") | P12: =IF(O12="","",O12*$E12) | Q12: =IF(O12="","",O12*$F12) | S12: =IF(R12="","",R12*$E12) | T12: =IF(R12="","",R12*$F12) | V12: =IF(U12="","",U12*$E12) | W12: =IF(U12="","",U12*$F12) | Y12: =IF(X12="","",X12*$E12) | Z12: =IF(X12="","",X12*$F12) | AB12: =IF(AA12="","",AA12*$E12) | AC12: =IF(AA12="","",AA12*$F12) | AE12: =IF(AD12="","",AD12*$E12) | AF12: =IF(AD12="","",AD12*$F12) | AH12: =IF(AG12="","",AG12*$E12) | AI12: =IF(AG12="","",AG12*$F12) | AK12: =IF(AJ12="","",AJ12*$E12) | AL12: =IF(AJ12="","",AJ12*$F12) | AN12: =IF(AM12="","",AM12*$E12) | AO12: =IF(AM12="","",AM12*$F12) | AQ12: =IF(AP12="","",AP12*$E12) | AR12: =IF(AP12="","",AP12*$F12) | AT12: =IF(AS12="","",AS12*$E12) | AU12: =IF(AS12="","",AS12*$F12) | AW12: =IF(AV12="","",AV12*$E12) | AX12: =IF(AV12="","",AV12*$F12) | AZ12: =IF(AY12="","",AY12*$E12) | BA12: =IF(AY12="","",AY12*$F12) | BC12: =IF(BB12="","",BB12*$E12) | BD12: =IF(BB12="","",BB12*$F12) | BF12: =IF(BE12="","",BE12*$E12) | BG12: =IF(BE12="","",BE12*$F12) | BI12: =IF(BH12="","",BH12*$E12) | BJ12: =IF(BH12="","",BH12*$F12) | BL12: =IF(BK12="","",BK12*$E12) | BM12: =IF(BK12="","",BK12*$F12) | BO12: =IF(BN12="","",BN12*$E12) | BP12: =IF(BN12="","",BN12*$F12) | BR12: =IF(BQ12="","",BQ12*$E12) | BS12: =IF(BQ12="","",BQ12*$F12) | BU12: =IF(BT12="","",BT12*$E12) | BV12: =IF(BT12="","",BT12*$F12) | BX12: =IF(BW12="","",BW12*$E12) | BY12: =IF(BW12="","",BW12*$F12) | CA12: =IF(BZ12="","",BZ12*$E12) | CB12: =IF(BZ12="","",BZ12*$F12) | CD12: =IF(CC12="","",CC12*$E12) | CE12: =IF(CC12="","",CC12*$F12) | CG12: =IF(CF12="","",CF12*$E12) | CH12: =IF(CF12="","",CF12*$F12) | CI12: =IF(R12>0,P12,0) + IF(X12>0,V12,0) + IF(AD12>0,AB12,0) + IF(AJ12>0,AH12,0) + IF(AP12>0,AN12,0) + IF(AV12>0,AT12,0) + IF(BB12>0,AZ12,0) + IF(BH12>0,BF12,0) + IF(BN12>0,BL12,0) + IF(BT12>0,BR12,0) + IF(BZ12>0,BX12,0) + IF(CF12>0,CD12,0) -> 0 | CJ12: =IF(R12>0,Q12,0) + IF(X12>0,W12,0) + IF(AD12>0,AC12,0) + IF(AJ12>0,AI12,0) + IF(AP12>0,AO12,0) + IF(AV12>0,AU12,0) + IF(BB12>0,BA12,0) + IF(BH12>0,BG12,0) + IF(BN12>0,BM12,0) + IF(BT12>0,BS12,0) + IF(BZ12>0,BY12,0) + IF(CF12>0,CE12,0) -> 0
A13: 東大阪 | B13: =IF(D13="","",IFERROR(VLOOKUP(D13,商品マスタ!$A:$K,2,FALSE),"缶バッジ")) -> 缶バッジ | C13: ダイキ | D13: 下蓋・穴下・ツメ下 | E13: =IF(D13="","",IFERROR(VLOOKUP(D13,商品マスタ!$A:$K,4,FALSE),12.55)) -> 12.55 | F13: =IF(D13="","",IFERROR(VLOOKUP(D13,商品マスタ!$A:$K,8,FALSE),1.14)) -> 1.14 | G13: =SUM(O13,U13,AA13,AG13,AM13,AS13,AY13,BE13,BK13,BQ13,BW13,CC13) -> 0 | H13: =SUM(P13,V13,AB13,AH13,AN13,AT13,AZ13,BF13,BL13,BR13,BX13,CD13) -> 0 | I13: =SUM(Q13,W13,AC13,AI13,AO13,AU13,BA13,BG13,BM13,BS13,BY13,CE13) -> 0 | J13: =SUM(R13,X13,AD13,AJ13,AP13,AV13,BB13,BH13,BN13,BT13,BZ13,CF13) -> 0 | K13: =SUM(S13,Y13,AE13,AK13,AQ13,AW13,BC13,BI13,BO13,BU13,CA13,CG13) -> 0 | L13: =SUM(T13,Z13,AF13,AL13,AR13,AX13,BD13,BJ13,BP13,BV13,CB13,CH13) -> 0 | M13: =IFERROR(K13/CI13,"") | N13: =IFERROR(L13/CJ13,"") | P13: =IF(O13="","",O13*$E13) | Q13: =IF(O13="","",O13*$F13) | S13: =IF(R13="","",R13*$E13) | T13: =IF(R13="","",R13*$F13) | V13: =IF(U13="","",U13*$E13) | W13: =IF(U13="","",U13*$F13) | Y13: =IF(X13="","",X13*$E13) | Z13: =IF(X13="","",X13*$F13) | AB13: =IF(AA13="","",AA13*$E13) | AC13: =IF(AA13="","",AA13*$F13) | AE13: =IF(AD13="","",AD13*$E13) | AF13: =IF(AD13="","",AD13*$F13) | AH13: =IF(AG13="","",AG13*$E13) | AI13: =IF(AG13="","",AG13*$F13) | AK13: =IF(AJ13="","",AJ13*$E13) | AL13: =IF(AJ13="","",AJ13*$F13) | AN13: =IF(AM13="","",AM13*$E13) | AO13: =IF(AM13="","",AM13*$F13) | AQ13: =IF(AP13="","",AP13*$E13) | AR13: =IF(AP13="","",AP13*$F13) | AT13: =IF(AS13="","",AS13*$E13) | AU13: =IF(AS13="","",AS13*$F13) | AW13: =IF(AV13="","",AV13*$E13) | AX13: =IF(AV13="","",AV13*$F13) | AZ13: =IF(AY13="","",AY13*$E13) | BA13: =IF(AY13="","",AY13*$F13) | BC13: =IF(BB13="","",BB13*$E13) | BD13: =IF(BB13="","",BB13*$F13) | BF13: =IF(BE13="","",BE13*$E13) | BG13: =IF(BE13="","",BE13*$F13) | BI13: =IF(BH13="","",BH13*$E13) | BJ13: =IF(BH13="","",BH13*$F13) | BL13: =IF(BK13="","",BK13*$E13) | BM13: =IF(BK13="","",BK13*$F13) | BO13: =IF(BN13="","",BN13*$E13) | BP13: =IF(BN13="","",BN13*$F13) | BR13: =IF(BQ13="","",BQ13*$E13) | BS13: =IF(BQ13="","",BQ13*$F13) | BU13: =IF(BT13="","",BT13*$E13) | BV13: =IF(BT13="","",BT13*$F13) | BX13: =IF(BW13="","",BW13*$E13) | BY13: =IF(BW13="","",BW13*$F13) | CA13: =IF(BZ13="","",BZ13*$E13) | CB13: =IF(BZ13="","",BZ13*$F13) | CD13: =IF(CC13="","",CC13*$E13) | CE13: =IF(CC13="","",CC13*$F13) | CG13: =IF(CF13="","",CF13*$E13) | CH13: =IF(CF13="","",CF13*$F13) | CI13: =IF(R13>0,P13,0) + IF(X13>0,V13,0) + IF(AD13>0,AB13,0) + IF(AJ13>0,AH13,0) + IF(AP13>0,AN13,0) + IF(AV13>0,AT13,0) + IF(BB13>0,AZ13,0) + IF(BH13>0,BF13,0) + IF(BN13>0,BL13,0) + IF(BT13>0,BR13,0) + IF(BZ13>0,BX13,0) + IF(CF13>0,CD13,0) -> 0 | CJ13: =IF(R13>0,Q13,0) + IF(X13>0,W13,0) + IF(AD13>0,AC13,0) + IF(AJ13>0,AI13,0) + IF(AP13>0,AO13,0) + IF(AV13>0,AU13,0) + IF(BB13>0,BA13,0) + IF(BH13>0,BG13,0) + IF(BN13>0,BM13,0) + IF(BT13>0,BS13,0) + IF(BZ13>0,BY13,0) + IF(CF13>0,CE13,0) -> 0
A14: 東大阪 | B14: =IF(D14="","",IFERROR(VLOOKUP(D14,商品マスタ!$A:$K,2,FALSE),"缶バッジ")) -> 缶バッジ | C14: ノート | D14: 下蓋・穴下・ツメ下 | E14: =IF(D14="","",IFERROR(VLOOKUP(D14,商品マスタ!$A:$K,4,FALSE),12.55)) -> 12.55 | F14: =IF(D14="","",IFERROR(VLOOKUP(D14,商品マスタ!$A:$K,8,FALSE),1.14)) -> 1.14 | G14: =SUM(O14,U14,AA14,AG14,AM14,AS14,AY14,BE14,BK14,BQ14,BW14,CC14) -> 0 | H14: =SUM(P14,V14,AB14,AH14,AN14,AT14,AZ14,BF14,BL14,BR14,BX14,CD14) -> 0 | I14: =SUM(Q14,W14,AC14,AI14,AO14,AU14,BA14,BG14,BM14,BS14,BY14,CE14) -> 0 | J14: =SUM(R14,X14,AD14,AJ14,AP14,AV14,BB14,BH14,BN14,BT14,BZ14,CF14) -> 0 | K14: =SUM(S14,Y14,AE14,AK14,AQ14,AW14,BC14,BI14,BO14,BU14,CA14,CG14) -> 0 | L14: =SUM(T14,Z14,AF14,AL14,AR14,AX14,BD14,BJ14,BP14,BV14,CB14,CH14) -> 0 | M14: =IFERROR(K14/CI14,"") | N14: =IFERROR(L14/CJ14,"") | P14: =IF(O14="","",O14*$E14) | Q14: =IF(O14="","",O14*$F14) | S14: =IF(R14="","",R14*$E14) | T14: =IF(R14="","",R14*$F14) | V14: =IF(U14="","",U14*$E14) | W14: =IF(U14="","",U14*$F14) | Y14: =IF(X14="","",X14*$E14) | Z14: =IF(X14="","",X14*$F14) | AB14: =IF(AA14="","",AA14*$E14) | AC14: =IF(AA14="","",AA14*$F14) | AE14: =IF(AD14="","",AD14*$E14) | AF14: =IF(AD14="","",AD14*$F14) | AH14: =IF(AG14="","",AG14*$E14) | AI14: =IF(AG14="","",AG14*$F14) | AK14: =IF(AJ14="","",AJ14*$E14) | AL14: =IF(AJ14="","",AJ14*$F14) | AN14: =IF(AM14="","",AM14*$E14) | AO14: =IF(AM14="","",AM14*$F14) | AQ14: =IF(AP14="","",AP14*$E14) | AR14: =IF(AP14="","",AP14*$F14) | AT14: =IF(AS14="","",AS14*$E14) | AU14: =IF(AS14="","",AS14*$F14) | AW14: =IF(AV14="","",AV14*$E14) | AX14: =IF(AV14="","",AV14*$F14) | AZ14: =IF(AY14="","",AY14*$E14) | BA14: =IF(AY14="","",AY14*$F14) | BC14: =IF(BB14="","",BB14*$E14) | BD14: =IF(BB14="","",BB14*$F14) | BF14: =IF(BE14="","",BE14*$E14) | BG14: =IF(BE14="","",BE14*$F14) | BI14: =IF(BH14="","",BH14*$E14) | BJ14: =IF(BH14="","",BH14*$F14) | BL14: =IF(BK14="","",BK14*$E14) | BM14: =IF(BK14="","",BK14*$F14) | BO14: =IF(BN14="","",BN14*$E14) | BP14: =IF(BN14="","",BN14*$F14) | BR14: =IF(BQ14="","",BQ14*$E14) | BS14: =IF(BQ14="","",BQ14*$F14) | BU14: =IF(BT14="","",BT14*$E14) | BV14: =IF(BT14="","",BT14*$F14) | BX14: =IF(BW14="","",BW14*$E14) | BY14: =IF(BW14="","",BW14*$F14) | CA14: =IF(BZ14="","",BZ14*$E14) | CB14: =IF(BZ14="","",BZ14*$F14) | CD14: =IF(CC14="","",CC14*$E14) | CE14: =IF(CC14="","",CC14*$F14) | CG14: =IF(CF14="","",CF14*$E14) | CH14: =IF(CF14="","",CF14*$F14) | CI14: =IF(R14>0,P14,0) + IF(X14>0,V14,0) + IF(AD14>0,AB14,0) + IF(AJ14>0,AH14,0) + IF(AP14>0,AN14,0) + IF(AV14>0,AT14,0) + IF(BB14>0,AZ14,0) + IF(BH14>0,BF14,0) + IF(BN14>0,BL14,0) + IF(BT14>0,BR14,0) + IF(BZ14>0,BX14,0) + IF(CF14>0,CD14,0) -> 0 | CJ14: =IF(R14>0,Q14,0) + IF(X14>0,W14,0) + IF(AD14>0,AC14,0) + IF(AJ14>0,AI14,0) + IF(AP14>0,AO14,0) + IF(AV14>0,AU14,0) + IF(BB14>0,BA14,0) + IF(BH14>0,BG14,0) + IF(BN14>0,BM14,0) + IF(BT14>0,BS14,0) + IF(BZ14>0,BY14,0) + IF(CF14>0,CE14,0) -> 0
A15: 東大阪 | B15: =IF(D15="","",IFERROR(VLOOKUP(D15,商品マスタ!$A:$K,2,FALSE),"缶バッジ")) -> 缶バッジ | C15: ベック | D15: バックパーツ・シェル | E15: =IF(D15="","",IFERROR(VLOOKUP(D15,商品マスタ!$A:$K,4,FALSE),3.72)) -> 3.72 | F15: =IF(D15="","",IFERROR(VLOOKUP(D15,商品マスタ!$A:$K,8,FALSE),0.34)) -> 0.34 | G15: =SUM(O15,U15,AA15,AG15,AM15,AS15,AY15,BE15,BK15,BQ15,BW15,CC15) -> 0 | H15: =SUM(P15,V15,AB15,AH15,AN15,AT15,AZ15,BF15,BL15,BR15,BX15,CD15) -> 0 | I15: =SUM(Q15,W15,AC15,AI15,AO15,AU15,BA15,BG15,BM15,BS15,BY15,CE15) -> 0 | J15: =SUM(R15,X15,AD15,AJ15,AP15,AV15,BB15,BH15,BN15,BT15,BZ15,CF15) -> 0 | K15: =SUM(S15,Y15,AE15,AK15,AQ15,AW15,BC15,BI15,BO15,BU15,CA15,CG15) -> 0 | L15: =SUM(T15,Z15,AF15,AL15,AR15,AX15,BD15,BJ15,BP15,BV15,CB15,CH15) -> 0 | M15: =IFERROR(K15/CI15,"") | N15: =IFERROR(L15/CJ15,"") | P15: =IF(O15="","",O15*$E15) | Q15: =IF(O15="","",O15*$F15) | S15: =IF(R15="","",R15*$E15) | T15: =IF(R15="","",R15*$F15) | V15: =IF(U15="","",U15*$E15) | W15: =IF(U15="","",U15*$F15) | Y15: =IF(X15="","",X15*$E15) | Z15: =IF(X15="","",X15*$F15) | AB15: =IF(AA15="","",AA15*$E15) | AC15: =IF(AA15="","",AA15*$F15) | AE15: =IF(AD15="","",AD15*$E15) | AF15: =IF(AD15="","",AD15*$F15) | AH15: =IF(AG15="","",AG15*$E15) | AI15: =IF(AG15="","",AG15*$F15) | AK15: =IF(AJ15="","",AJ15*$E15) | AL15: =IF(AJ15="","",AJ15*$F15) | AN15: =IF(AM15="","",AM15*$E15) | AO15: =IF(AM15="","",AM15*$F15) | AQ15: =IF(AP15="","",AP15*$E15) | AR15: =IF(AP15="","",AP15*$F15) | AT15: =IF(AS15="","",AS15*$E15) | AU15: =IF(AS15="","",AS15*$F15) | AW15: =IF(AV15="","",AV15*$E15) | AX15: =IF(AV15="","",AV15*$F15) | AZ15: =IF(AY15="","",AY15*$E15) | BA15: =IF(AY15="","",AY15*$F15) | BC15: =IF(BB15="","",BB15*$E15) | BD15: =IF(BB15="","",BB15*$F15) | BF15: =IF(BE15="","",BE15*$E15) | BG15: =IF(BE15="","",BE15*$F15) | BI15: =IF(BH15="","",BH15*$E15) | BJ15: =IF(BH15="","",BH15*$F15) | BL15: =IF(BK15="","",BK15*$E15) | BM15: =IF(BK15="","",BK15*$F15) | BO15: =IF(BN15="","",BN15*$E15) | BP15: =IF(BN15="","",BN15*$F15) | BR15: =IF(BQ15="","",BQ15*$E15) | BS15: =IF(BQ15="","",BQ15*$F15) | BU15: =IF(BT15="","",BT15*$E15) | BV15: =IF(BT15="","",BT15*$F15) | BX15: =IF(BW15="","",BW15*$E15) | BY15: =IF(BW15="","",BW15*$F15) | CA15: =IF(BZ15="","",BZ15*$E15) | CB15: =IF(BZ15="","",BZ15*$F15) | CD15: =IF(CC15="","",CC15*$E15) | CE15: =IF(CC15="","",CC15*$F15) | CG15: =IF(CF15="","",CF15*$E15) | CH15: =IF(CF15="","",CF15*$F15) | CI15: =IF(R15>0,P15,0) + IF(X15>0,V15,0) + IF(AD15>0,AB15,0) + IF(AJ15>0,AH15,0) + IF(AP15>0,AN15,0) + IF(AV15>0,AT15,0) + IF(BB15>0,AZ15,0) + IF(BH15>0,BF15,0) + IF(BN15>0,BL15,0) + IF(BT15>0,BR15,0) + IF(BZ15>0,BX15,0) + IF(CF15>0,CD15,0) -> 0 | CJ15: =IF(R15>0,Q15,0) + IF(X15>0,W15,0) + IF(AD15>0,AC15,0) + IF(AJ15>0,AI15,0) + IF(AP15>0,AO15,0) + IF(AV15>0,AU15,0) + IF(BB15>0,BA15,0) + IF(BH15>0,BG15,0) + IF(BN15>0,BM15,0) + IF(BT15>0,BS15,0) + IF(BZ15>0,BY15,0) + IF(CF15>0,CE15,0) -> 0
A16: 松原 | B16: =IF(D16="","",IFERROR(VLOOKUP(D16,商品マスタ!$A:$K,2,FALSE),"缶バッジ")) -> 缶バッジ | C16: よつば | D16: 下蓋・穴下・ツメ下 | E16: =IF(D16="","",IFERROR(VLOOKUP(D16,商品マスタ!$A:$K,4,FALSE),12.55)) -> 12.55 | F16: =IF(D16="","",IFERROR(VLOOKUP(D16,商品マスタ!$A:$K,8,FALSE),1.14)) -> 1.14 | G16: =SUM(O16,U16,AA16,AG16,AM16,AS16,AY16,BE16,BK16,BQ16,BW16,CC16) -> 0 | H16: =SUM(P16,V16,AB16,AH16,AN16,AT16,AZ16,BF16,BL16,BR16,BX16,CD16) -> 0 | I16: =SUM(Q16,W16,AC16,AI16,AO16,AU16,BA16,BG16,BM16,BS16,BY16,CE16) -> 0 | J16: =SUM(R16,X16,AD16,AJ16,AP16,AV16,BB16,BH16,BN16,BT16,BZ16,CF16) -> 0 | K16: =SUM(S16,Y16,AE16,AK16,AQ16,AW16,BC16,BI16,BO16,BU16,CA16,CG16) -> 0 | L16: =SUM(T16,Z16,AF16,AL16,AR16,AX16,BD16,BJ16,BP16,BV16,CB16,CH16) -> 0 | M16: =IFERROR(K16/CI16,"") | N16: =IFERROR(L16/CJ16,"") | P16: =IF(O16="","",O16*$E16) | Q16: =IF(O16="","",O16*$F16) | S16: =IF(R16="","",R16*$E16) | T16: =IF(R16="","",R16*$F16) | V16: =IF(U16="","",U16*$E16) | W16: =IF(U16="","",U16*$F16) | Y16: =IF(X16="","",X16*$E16) | Z16: =IF(X16="","",X16*$F16) | AB16: =IF(AA16="","",AA16*$E16) | AC16: =IF(AA16="","",AA16*$F16) | AE16: =IF(AD16="","",AD16*$E16) | AF16: =IF(AD16="","",AD16*$F16) | AH16: =IF(AG16="","",AG16*$E16) | AI16: =IF(AG16="","",AG16*$F16) | AK16: =IF(AJ16="","",AJ16*$E16) | AL16: =IF(AJ16="","",AJ16*$F16) | AN16: =IF(AM16="","",AM16*$E16) | AO16: =IF(AM16="","",AM16*$F16) | AQ16: =IF(AP16="","",AP16*$E16) | AR16: =IF(AP16="","",AP16*$F16) | AT16: =IF(AS16="","",AS16*$E16) | AU16: =IF(AS16="","",AS16*$F16) | AW16: =IF(AV16="","",AV16*$E16) | AX16: =IF(AV16="","",AV16*$F16) | AZ16: =IF(AY16="","",AY16*$E16) | BA16: =IF(AY16="","",AY16*$F16) | BC16: =IF(BB16="","",BB16*$E16) | BD16: =IF(BB16="","",BB16*$F16) | BF16: =IF(BE16="","",BE16*$E16) | BG16: =IF(BE16="","",BE16*$F16) | BI16: =IF(BH16="","",BH16*$E16) | BJ16: =IF(BH16="","",BH16*$F16) | BL16: =IF(BK16="","",BK16*$E16) | BM16: =IF(BK16="","",BK16*$F16) | BO16: =IF(BN16="","",BN16*$E16) | BP16: =IF(BN16="","",BN16*$F16) | BR16: =IF(BQ16="","",BQ16*$E16) | BS16: =IF(BQ16="","",BQ16*$F16) | BU16: =IF(BT16="","",BT16*$E16) | BV16: =IF(BT16="","",BT16*$F16) | BX16: =IF(BW16="","",BW16*$E16) | BY16: =IF(BW16="","",BW16*$F16) | CA16: =IF(BZ16="","",BZ16*$E16) | CB16: =IF(BZ16="","",BZ16*$F16) | CD16: =IF(CC16="","",CC16*$E16) | CE16: =IF(CC16="","",CC16*$F16) | CG16: =IF(CF16="","",CF16*$E16) | CH16: =IF(CF16="","",CF16*$F16) | CI16: =IF(R16>0,P16,0) + IF(X16>0,V16,0) + IF(AD16>0,AB16,0) + IF(AJ16>0,AH16,0) + IF(AP16>0,AN16,0) + IF(AV16>0,AT16,0) + IF(BB16>0,AZ16,0) + IF(BH16>0,BF16,0) + IF(BN16>0,BL16,0) + IF(BT16>0,BR16,0) + IF(BZ16>0,BX16,0) + IF(CF16>0,CD16,0) -> 0 | CJ16: =IF(R16>0,Q16,0) + IF(X16>0,W16,0) + IF(AD16>0,AC16,0) + IF(AJ16>0,AI16,0) + IF(AP16>0,AO16,0) + IF(AV16>0,AU16,0) + IF(BB16>0,BA16,0) + IF(BH16>0,BG16,0) + IF(BN16>0,BM16,0) + IF(BT16>0,BS16,0) + IF(BZ16>0,BY16,0) + IF(CF16>0,CE16,0) -> 0
A17: 松原 | B17: =IF(D17="","",IFERROR(VLOOKUP(D17,商品マスタ!$A:$K,2,FALSE),"缶バッジ")) -> 缶バッジ | C17: アニキャン | D17: 下蓋・穴下・ツメ下 | E17: =IF(D17="","",IFERROR(VLOOKUP(D17,商品マスタ!$A:$K,4,FALSE),12.55)) -> 12.55 | F17: =IF(D17="","",IFERROR(VLOOKUP(D17,商品マスタ!$A:$K,8,FALSE),1.14)) -> 1.14 | G17: =SUM(O17,U17,AA17,AG17,AM17,AS17,AY17,BE17,BK17,BQ17,BW17,CC17) -> 0 | H17: =SUM(P17,V17,AB17,AH17,AN17,AT17,AZ17,BF17,BL17,BR17,BX17,CD17) -> 0 | I17: =SUM(Q17,W17,AC17,AI17,AO17,AU17,BA17,BG17,BM17,BS17,BY17,CE17) -> 0 | J17: =SUM(R17,X17,AD17,AJ17,AP17,AV17,BB17,BH17,BN17,BT17,BZ17,CF17) -> 0 | K17: =SUM(S17,Y17,AE17,AK17,AQ17,AW17,BC17,BI17,BO17,BU17,CA17,CG17) -> 0 | L17: =SUM(T17,Z17,AF17,AL17,AR17,AX17,BD17,BJ17,BP17,BV17,CB17,CH17) -> 0 | M17: =IFERROR(K17/CI17,"") | N17: =IFERROR(L17/CJ17,"") | P17: =IF(O17="","",O17*$E17) | Q17: =IF(O17="","",O17*$F17) | S17: =IF(R17="","",R17*$E17) | T17: =IF(R17="","",R17*$F17) | V17: =IF(U17="","",U17*$E17) | W17: =IF(U17="","",U17*$F17) | Y17: =IF(X17="","",X17*$E17) | Z17: =IF(X17="","",X17*$F17) | AB17: =IF(AA17="","",AA17*$E17) | AC17: =IF(AA17="","",AA17*$F17) | AE17: =IF(AD17="","",AD17*$E17) | AF17: =IF(AD17="","",AD17*$F17) | AH17: =IF(AG17="","",AG17*$E17) | AI17: =IF(AG17="","",AG17*$F17) | AK17: =IF(AJ17="","",AJ17*$E17) | AL17: =IF(AJ17="","",AJ17*$F17) | AN17: =IF(AM17="","",AM17*$E17) | AO17: =IF(AM17="","",AM17*$F17) | AQ17: =IF(AP17="","",AP17*$E17) | AR17: =IF(AP17="","",AP17*$F17) | AT17: =IF(AS17="","",AS17*$E17) | AU17: =IF(AS17="","",AS17*$F17) | AW17: =IF(AV17="","",AV17*$E17) | AX17: =IF(AV17="","",AV17*$F17) | AZ17: =IF(AY17="","",AY17*$E17) | BA17: =IF(AY17="","",AY17*$F17) | BC17: =IF(BB17="","",BB17*$E17) | BD17: =IF(BB17="","",BB17*$F17) | BF17: =IF(BE17="","",BE17*$E17) | BG17: =IF(BE17="","",BE17*$F17) | BI17: =IF(BH17="","",BH17*$E17) | BJ17: =IF(BH17="","",BH17*$F17) | BL17: =IF(BK17="","",BK17*$E17) | BM17: =IF(BK17="","",BK17*$F17) | BO17: =IF(BN17="","",BN17*$E17) | BP17: =IF(BN17="","",BN17*$F17) | BR17: =IF(BQ17="","",BQ17*$E17) | BS17: =IF(BQ17="","",BQ17*$F17) | BU17: =IF(BT17="","",BT17*$E17) | BV17: =IF(BT17="","",BT17*$F17) | BX17: =IF(BW17="","",BW17*$E17) | BY17: =IF(BW17="","",BW17*$F17) | CA17: =IF(BZ17="","",BZ17*$E17) | CB17: =IF(BZ17="","",BZ17*$F17) | CD17: =IF(CC17="","",CC17*$E17) | CE17: =IF(CC17="","",CC17*$F17) | CG17: =IF(CF17="","",CF17*$E17) | CH17: =IF(CF17="","",CF17*$F17) | CI17: =IF(R17>0,P17,0) + IF(X17>0,V17,0) + IF(AD17>0,AB17,0) + IF(AJ17>0,AH17,0) + IF(AP17>0,AN17,0) + IF(AV17>0,AT17,0) + IF(BB17>0,AZ17,0) + IF(BH17>0,BF17,0) + IF(BN17>0,BL17,0) + IF(BT17>0,BR17,0) + IF(BZ17>0,BX17,0) + IF(CF17>0,CD17,0) -> 0 | CJ17: =IF(R17>0,Q17,0) + IF(X17>0,W17,0) + IF(AD17>0,AC17,0) + IF(AJ17>0,AI17,0) + IF(AP17>0,AO17,0) + IF(AV17>0,AU17,0) + IF(BB17>0,BA17,0) + IF(BH17>0,BG17,0) + IF(BN17>0,BM17,0) + IF(BT17>0,BS17,0) + IF(BZ17>0,BY17,0) + IF(CF17>0,CE17,0) -> 0
A18: 松原 | B18: =IF(D18="","",IFERROR(VLOOKUP(D18,商品マスタ!$A:$K,2,FALSE),"缶バッジ")) -> 缶バッジ | C18: アンフィニ | D18: 下蓋・穴下・ツメ下 | E18: =IF(D18="","",IFERROR(VLOOKUP(D18,商品マスタ!$A:$K,4,FALSE),12.55)) -> 12.55 | F18: =IF(D18="","",IFERROR(VLOOKUP(D18,商品マスタ!$A:$K,8,FALSE),1.14)) -> 1.14 | G18: =SUM(O18,U18,AA18,AG18,AM18,AS18,AY18,BE18,BK18,BQ18,BW18,CC18) -> 0 | H18: =SUM(P18,V18,AB18,AH18,AN18,AT18,AZ18,BF18,BL18,BR18,BX18,CD18) -> 0 | I18: =SUM(Q18,W18,AC18,AI18,AO18,AU18,BA18,BG18,BM18,BS18,BY18,CE18) -> 0 | J18: =SUM(R18,X18,AD18,AJ18,AP18,AV18,BB18,BH18,BN18,BT18,BZ18,CF18) -> 0 | K18: =SUM(S18,Y18,AE18,AK18,AQ18,AW18,BC18,BI18,BO18,BU18,CA18,CG18) -> 0 | L18: =SUM(T18,Z18,AF18,AL18,AR18,AX18,BD18,BJ18,BP18,BV18,CB18,CH18) -> 0 | M18: =IFERROR(K18/CI18,"") | N18: =IFERROR(L18/CJ18,"") | P18: =IF(O18="","",O18*$E18) | Q18: =IF(O18="","",O18*$F18) | S18: =IF(R18="","",R18*$E18) | T18: =IF(R18="","",R18*$F18) | V18: =IF(U18="","",U18*$E18) | W18: =IF(U18="","",U18*$F18) | Y18: =IF(X18="","",X18*$E18) | Z18: =IF(X18="","",X18*$F18) | AB18: =IF(AA18="","",AA18*$E18) | AC18: =IF(AA18="","",AA18*$F18) | AE18: =IF(AD18="","",AD18*$E18) | AF18: =IF(AD18="","",AD18*$F18) | AH18: =IF(AG18="","",AG18*$E18) | AI18: =IF(AG18="","",AG18*$F18) | AK18: =IF(AJ18="","",AJ18*$E18) | AL18: =IF(AJ18="","",AJ18*$F18) | AN18: =IF(AM18="","",AM18*$E18) | AO18: =IF(AM18="","",AM18*$F18) | AQ18: =IF(AP18="","",AP18*$E18) | AR18: =IF(AP18="","",AP18*$F18) | AT18: =IF(AS18="","",AS18*$E18) | AU18: =IF(AS18="","",AS18*$F18) | AW18: =IF(AV18="","",AV18*$E18) | AX18: =IF(AV18="","",AV18*$F18) | AZ18: =IF(AY18="","",AY18*$E18) | BA18: =IF(AY18="","",AY18*$F18) | BC18: =IF(BB18="","",BB18*$E18) | BD18: =IF(BB18="","",BB18*$F18) | BF18: =IF(BE18="","",BE18*$E18) | BG18: =IF(BE18="","",BE18*$F18) | BI18: =IF(BH18="","",BH18*$E18) | BJ18: =IF(BH18="","",BH18*$F18) | BL18: =IF(BK18="","",BK18*$E18) | BM18: =IF(BK18="","",BK18*$F18) | BO18: =IF(BN18="","",BN18*$E18) | BP18: =IF(BN18="","",BN18*$F18) | BR18: =IF(BQ18="","",BQ18*$E18) | BS18: =IF(BQ18="","",BQ18*$F18) | BU18: =IF(BT18="","",BT18*$E18) | BV18: =IF(BT18="","",BT18*$F18) | BX18: =IF(BW18="","",BW18*$E18) | BY18: =IF(BW18="","",BW18*$F18) | CA18: =IF(BZ18="","",BZ18*$E18) | CB18: =IF(BZ18="","",BZ18*$F18) | CD18: =IF(CC18="","",CC18*$E18) | CE18: =IF(CC18="","",CC18*$F18) | CG18: =IF(CF18="","",CF18*$E18) | CH18: =IF(CF18="","",CF18*$F18) | CI18: =IF(R18>0,P18,0) + IF(X18>0,V18,0) + IF(AD18>0,AB18,0) + IF(AJ18>0,AH18,0) + IF(AP18>0,AN18,0) + IF(AV18>0,AT18,0) + IF(BB18>0,AZ18,0) + IF(BH18>0,BF18,0) + IF(BN18>0,BL18,0) + IF(BT18>0,BR18,0) + IF(BZ18>0,BX18,0) + IF(CF18>0,CD18,0) -> 0 | CJ18: =IF(R18>0,Q18,0) + IF(X18>0,W18,0) + IF(AD18>0,AC18,0) + IF(AJ18>0,AI18,0) + IF(AP18>0,AO18,0) + IF(AV18>0,AU18,0) + IF(BB18>0,BA18,0) + IF(BH18>0,BG18,0) + IF(BN18>0,BM18,0) + IF(BT18>0,BS18,0) + IF(BZ18>0,BY18,0) + IF(CF18>0,CE18,0) -> 0
A19: 松原 | B19: =IF(D19="","",IFERROR(VLOOKUP(D19,商品マスタ!$A:$K,2,FALSE),"缶バッジ")) -> 缶バッジ | C19: イナバ工芸社 | D19: 下蓋・穴下・ツメ下 | E19: =IF(D19="","",IFERROR(VLOOKUP(D19,商品マスタ!$A:$K,4,FALSE),12.55)) -> 12.55 | F19: =IF(D19="","",IFERROR(VLOOKUP(D19,商品マスタ!$A:$K,8,FALSE),1.14)) -> 1.14 | G19: =SUM(O19,U19,AA19,AG19,AM19,AS19,AY19,BE19,BK19,BQ19,BW19,CC19) -> 0 | H19: =SUM(P19,V19,AB19,AH19,AN19,AT19,AZ19,BF19,BL19,BR19,BX19,CD19) -> 0 | I19: =SUM(Q19,W19,AC19,AI19,AO19,AU19,BA19,BG19,BM19,BS19,BY19,CE19) -> 0 | J19: =SUM(R19,X19,AD19,AJ19,AP19,AV19,BB19,BH19,BN19,BT19,BZ19,CF19) -> 0 | K19: =SUM(S19,Y19,AE19,AK19,AQ19,AW19,BC19,BI19,BO19,BU19,CA19,CG19) -> 0 | L19: =SUM(T19,Z19,AF19,AL19,AR19,AX19,BD19,BJ19,BP19,BV19,CB19,CH19) -> 0 | M19: =IFERROR(K19/CI19,"") | N19: =IFERROR(L19/CJ19,"") | P19: =IF(O19="","",O19*$E19) | Q19: =IF(O19="","",O19*$F19) | S19: =IF(R19="","",R19*$E19) | T19: =IF(R19="","",R19*$F19) | V19: =IF(U19="","",U19*$E19) | W19: =IF(U19="","",U19*$F19) | Y19: =IF(X19="","",X19*$E19) | Z19: =IF(X19="","",X19*$F19) | AB19: =IF(AA19="","",AA19*$E19) | AC19: =IF(AA19="","",AA19*$F19) | AE19: =IF(AD19="","",AD19*$E19) | AF19: =IF(AD19="","",AD19*$F19) | AH19: =IF(AG19="","",AG19*$E19) | AI19: =IF(AG19="","",AG19*$F19) | AK19: =IF(AJ19="","",AJ19*$E19) | AL19: =IF(AJ19="","",AJ19*$F19) | AN19: =IF(AM19="","",AM19*$E19) | AO19: =IF(AM19="","",AM19*$F19) | AQ19: =IF(AP19="","",AP19*$E19) | AR19: =IF(AP19="","",AP19*$F19) | AT19: =IF(AS19="","",AS19*$E19) | AU19: =IF(AS19="","",AS19*$F19) | AW19: =IF(AV19="","",AV19*$E19) | AX19: =IF(AV19="","",AV19*$F19) | AZ19: =IF(AY19="","",AY19*$E19) | BA19: =IF(AY19="","",AY19*$F19) | BC19: =IF(BB19="","",BB19*$E19) | BD19: =IF(BB19="","",BB19*$F19) | BF19: =IF(BE19="","",BE19*$E19) | BG19: =IF(BE19="","",BE19*$F19) | BI19: =IF(BH19="","",BH19*$E19) | BJ19: =IF(BH19="","",BH19*$F19) | BL19: =IF(BK19="","",BK19*$E19) | BM19: =IF(BK19="","",BK19*$F19) | BO19: =IF(BN19="","",BN19*$E19) | BP19: =IF(BN19="","",BN19*$F19) | BR19: =IF(BQ19="","",BQ19*$E19) | BS19: =IF(BQ19="","",BQ19*$F19) | BU19: =IF(BT19="","",BT19*$E19) | BV19: =IF(BT19="","",BT19*$F19) | BX19: =IF(BW19="","",BW19*$E19) | BY19: =IF(BW19="","",BW19*$F19) | CA19: =IF(BZ19="","",BZ19*$E19) | CB19: =IF(BZ19="","",BZ19*$F19) | CD19: =IF(CC19="","",CC19*$E19) | CE19: =IF(CC19="","",CC19*$F19) | CG19: =IF(CF19="","",CF19*$E19) | CH19: =IF(CF19="","",CF19*$F19) | CI19: =IF(R19>0,P19,0) + IF(X19>0,V19,0) + IF(AD19>0,AB19,0) + IF(AJ19>0,AH19,0) + IF(AP19>0,AN19,0) + IF(AV19>0,AT19,0) + IF(BB19>0,AZ19,0) + IF(BH19>0,BF19,0) + IF(BN19>0,BL19,0) + IF(BT19>0,BR19,0) + IF(BZ19>0,BX19,0) + IF(CF19>0,CD19,0) -> 0 | CJ19: =IF(R19>0,Q19,0) + IF(X19>0,W19,0) + IF(AD19>0,AC19,0) + IF(AJ19>0,AI19,0) + IF(AP19>0,AO19,0) + IF(AV19>0,AU19,0) + IF(BB19>0,BA19,0) + IF(BH19>0,BG19,0) + IF(BN19>0,BM19,0) + IF(BT19>0,BS19,0) + IF(BZ19>0,BY19,0) + IF(CF19>0,CE19,0) -> 0
A20: 松原 | B20: =IF(D20="","",IFERROR(VLOOKUP(D20,商品マスタ!$A:$K,2,FALSE),"缶バッジ")) -> 缶バッジ | C20: エイチアールシー | D20: 下蓋・穴下・ツメ下 | E20: =IF(D20="","",IFERROR(VLOOKUP(D20,商品マスタ!$A:$K,4,FALSE),12.55)) -> 12.55 | F20: =IF(D20="","",IFERROR(VLOOKUP(D20,商品マスタ!$A:$K,8,FALSE),1.14)) -> 1.14 | G20: =SUM(O20,U20,AA20,AG20,AM20,AS20,AY20,BE20,BK20,BQ20,BW20,CC20) -> 0 | H20: =SUM(P20,V20,AB20,AH20,AN20,AT20,AZ20,BF20,BL20,BR20,BX20,CD20) -> 0 | I20: =SUM(Q20,W20,AC20,AI20,AO20,AU20,BA20,BG20,BM20,BS20,BY20,CE20) -> 0 | J20: =SUM(R20,X20,AD20,AJ20,AP20,AV20,BB20,BH20,BN20,BT20,BZ20,CF20) -> 0 | K20: =SUM(S20,Y20,AE20,AK20,AQ20,AW20,BC20,BI20,BO20,BU20,CA20,CG20) -> 0 | L20: =SUM(T20,Z20,AF20,AL20,AR20,AX20,BD20,BJ20,BP20,BV20,CB20,CH20) -> 0 | M20: =IFERROR(K20/CI20,"") | N20: =IFERROR(L20/CJ20,"") | P20: =IF(O20="","",O20*$E20) | Q20: =IF(O20="","",O20*$F20) | S20: =IF(R20="","",R20*$E20) | T20: =IF(R20="","",R20*$F20) | V20: =IF(U20="","",U20*$E20) | W20: =IF(U20="","",U20*$F20) | Y20: =IF(X20="","",X20*$E20) | Z20: =IF(X20="","",X20*$F20) | AB20: =IF(AA20="","",AA20*$E20) | AC20: =IF(AA20="","",AA20*$F20) | AE20: =IF(AD20="","",AD20*$E20) | AF20: =IF(AD20="","",AD20*$F20) | AH20: =IF(AG20="","",AG20*$E20) | AI20: =IF(AG20="","",AG20*$F20) | AK20: =IF(AJ20="","",AJ20*$E20) | AL20: =IF(AJ20="","",AJ20*$F20) | AN20: =IF(AM20="","",AM20*$E20) | AO20: =IF(AM20="","",AM20*$F20) | AQ20: =IF(AP20="","",AP20*$E20) | AR20: =IF(AP20="","",AP20*$F20) | AT20: =IF(AS20="","",AS20*$E20) | AU20: =IF(AS20="","",AS20*$F20) | AW20: =IF(AV20="","",AV20*$E20) | AX20: =IF(AV20="","",AV20*$F20) | AZ20: =IF(AY20="","",AY20*$E20) | BA20: =IF(AY20="","",AY20*$F20) | BC20: =IF(BB20="","",BB20*$E20) | BD20: =IF(BB20="","",BB20*$F20) | BF20: =IF(BE20="","",BE20*$E20) | BG20: =IF(BE20="","",BE20*$F20) | BI20: =IF(BH20="","",BH20*$E20) | BJ20: =IF(BH20="","",BH20*$F20) | BL20: =IF(BK20="","",BK20*$E20) | BM20: =IF(BK20="","",BK20*$F20) | BO20: =IF(BN20="","",BN20*$E20) | BP20: =IF(BN20="","",BN20*$F20) | BR20: =IF(BQ20="","",BQ20*$E20) | BS20: =IF(BQ20="","",BQ20*$F20) | BU20: =IF(BT20="","",BT20*$E20) | BV20: =IF(BT20="","",BT20*$F20) | BX20: =IF(BW20="","",BW20*$E20) | BY20: =IF(BW20="","",BW20*$F20) | CA20: =IF(BZ20="","",BZ20*$E20) | CB20: =IF(BZ20="","",BZ20*$F20) | CD20: =IF(CC20="","",CC20*$E20) | CE20: =IF(CC20="","",CC20*$F20) | CG20: =IF(CF20="","",CF20*$E20) | CH20: =IF(CF20="","",CF20*$F20) | CI20: =IF(R20>0,P20,0) + IF(X20>0,V20,0) + IF(AD20>0,AB20,0) + IF(AJ20>0,AH20,0) + IF(AP20>0,AN20,0) + IF(AV20>0,AT20,0) + IF(BB20>0,AZ20,0) + IF(BH20>0,BF20,0) + IF(BN20>0,BL20,0) + IF(BT20>0,BR20,0) + IF(BZ20>0,BX20,0) + IF(CF20>0,CD20,0) -> 0 | CJ20: =IF(R20>0,Q20,0) + IF(X20>0,W20,0) + IF(AD20>0,AC20,0) + IF(AJ20>0,AI20,0) + IF(AP20>0,AO20,0) + IF(AV20>0,AU20,0) + IF(BB20>0,BA20,0) + IF(BH20>0,BG20,0) + IF(BN20>0,BM20,0) + IF(BT20>0,BS20,0) + IF(BZ20>0,BY20,0) + IF(CF20>0,CE20,0) -> 0
A21: 松原 | B21: =IF(D21="","",IFERROR(VLOOKUP(D21,商品マスタ!$A:$K,2,FALSE),"缶バッジ")) -> 缶バッジ | C21: エムズカンパニー | D21: 下蓋・穴下・ツメ下 | E21: =IF(D21="","",IFERROR(VLOOKUP(D21,商品マスタ!$A:$K,4,FALSE),12.55)) -> 12.55 | F21: =IF(D21="","",IFERROR(VLOOKUP(D21,商品マスタ!$A:$K,8,FALSE),1.14)) -> 1.14 | G21: =SUM(O21,U21,AA21,AG21,AM21,AS21,AY21,BE21,BK21,BQ21,BW21,CC21) -> 0 | H21: =SUM(P21,V21,AB21,AH21,AN21,AT21,AZ21,BF21,BL21,BR21,BX21,CD21) -> 0 | I21: =SUM(Q21,W21,AC21,AI21,AO21,AU21,BA21,BG21,BM21,BS21,BY21,CE21) -> 0 | J21: =SUM(R21,X21,AD21,AJ21,AP21,AV21,BB21,BH21,BN21,BT21,BZ21,CF21) -> 0 | K21: =SUM(S21,Y21,AE21,AK21,AQ21,AW21,BC21,BI21,BO21,BU21,CA21,CG21) -> 0 | L21: =SUM(T21,Z21,AF21,AL21,AR21,AX21,BD21,BJ21,BP21,BV21,CB21,CH21) -> 0 | M21: =IFERROR(K21/CI21,"") | N21: =IFERROR(L21/CJ21,"") | P21: =IF(O21="","",O21*$E21) | Q21: =IF(O21="","",O21*$F21) | S21: =IF(R21="","",R21*$E21) | T21: =IF(R21="","",R21*$F21) | V21: =IF(U21="","",U21*$E21) | W21: =IF(U21="","",U21*$F21) | Y21: =IF(X21="","",X21*$E21) | Z21: =IF(X21="","",X21*$F21) | AB21: =IF(AA21="","",AA21*$E21) | AC21: =IF(AA21="","",AA21*$F21) | AE21: =IF(AD21="","",AD21*$E21) | AF21: =IF(AD21="","",AD21*$F21) | AH21: =IF(AG21="","",AG21*$E21) | AI21: =IF(AG21="","",AG21*$F21) | AK21: =IF(AJ21="","",AJ21*$E21) | AL21: =IF(AJ21="","",AJ21*$F21) | AN21: =IF(AM21="","",AM21*$E21) | AO21: =IF(AM21="","",AM21*$F21) | AQ21: =IF(AP21="","",AP21*$E21) | AR21: =IF(AP21="","",AP21*$F21) | AT21: =IF(AS21="","",AS21*$E21) | AU21: =IF(AS21="","",AS21*$F21) | AW21: =IF(AV21="","",AV21*$E21) | AX21: =IF(AV21="","",AV21*$F21) | AZ21: =IF(AY21="","",AY21*$E21) | BA21: =IF(AY21="","",AY21*$F21) | BC21: =IF(BB21="","",BB21*$E21) | BD21: =IF(BB21="","",BB21*$F21) | BF21: =IF(BE21="","",BE21*$E21) | BG21: =IF(BE21="","",BE21*$F21) | BI21: =IF(BH21="","",BH21*$E21) | BJ21: =IF(BH21="","",BH21*$F21) | BL21: =IF(BK21="","",BK21*$E21) | BM21: =IF(BK21="","",BK21*$F21) | BO21: =IF(BN21="","",BN21*$E21) | BP21: =IF(BN21="","",BN21*$F21) | BR21: =IF(BQ21="","",BQ21*$E21) | BS21: =IF(BQ21="","",BQ21*$F21) | BU21: =IF(BT21="","",BT21*$E21) | BV21: =IF(BT21="","",BT21*$F21) | BX21: =IF(BW21="","",BW21*$E21) | BY21: =IF(BW21="","",BW21*$F21) | CA21: =IF(BZ21="","",BZ21*$E21) | CB21: =IF(BZ21="","",BZ21*$F21) | CD21: =IF(CC21="","",CC21*$E21) | CE21: =IF(CC21="","",CC21*$F21) | CG21: =IF(CF21="","",CF21*$E21) | CH21: =IF(CF21="","",CF21*$F21) | CI21: =IF(R21>0,P21,0) + IF(X21>0,V21,0) + IF(AD21>0,AB21,0) + IF(AJ21>0,AH21,0) + IF(AP21>0,AN21,0) + IF(AV21>0,AT21,0) + IF(BB21>0,AZ21,0) + IF(BH21>0,BF21,0) + IF(BN21>0,BL21,0) + IF(BT21>0,BR21,0) + IF(BZ21>0,BX21,0) + IF(CF21>0,CD21,0) -> 0 | CJ21: =IF(R21>0,Q21,0) + IF(X21>0,W21,0) + IF(AD21>0,AC21,0) + IF(AJ21>0,AI21,0) + IF(AP21>0,AO21,0) + IF(AV21>0,AU21,0) + IF(BB21>0,BA21,0) + IF(BH21>0,BG21,0) + IF(BN21>0,BM21,0) + IF(BT21>0,BS21,0) + IF(BZ21>0,BY21,0) + IF(CF21>0,CE21,0) -> 0
A22: 松原 | B22: =IF(D22="","",IFERROR(VLOOKUP(D22,商品マスタ!$A:$K,2,FALSE),"缶バッジ")) -> 缶バッジ | C22: オーラルケア | D22: 下蓋・穴下・ツメ下 | E22: =IF(D22="","",IFERROR(VLOOKUP(D22,商品マスタ!$A:$K,4,FALSE),12.55)) -> 12.55 | F22: =IF(D22="","",IFERROR(VLOOKUP(D22,商品マスタ!$A:$K,8,FALSE),1.14)) -> 1.14 | G22: =SUM(O22,U22,AA22,AG22,AM22,AS22,AY22,BE22,BK22,BQ22,BW22,CC22) -> 0 | H22: =SUM(P22,V22,AB22,AH22,AN22,AT22,AZ22,BF22,BL22,BR22,BX22,CD22) -> 0 | I22: =SUM(Q22,W22,AC22,AI22,AO22,AU22,BA22,BG22,BM22,BS22,BY22,CE22) -> 0 | J22: =SUM(R22,X22,AD22,AJ22,AP22,AV22,BB22,BH22,BN22,BT22,BZ22,CF22) -> 0 | K22: =SUM(S22,Y22,AE22,AK22,AQ22,AW22,BC22,BI22,BO22,BU22,CA22,CG22) -> 0 | L22: =SUM(T22,Z22,AF22,AL22,AR22,AX22,BD22,BJ22,BP22,BV22,CB22,CH22) -> 0 | M22: =IFERROR(K22/CI22,"") | N22: =IFERROR(L22/CJ22,"") | P22: =IF(O22="","",O22*$E22) | Q22: =IF(O22="","",O22*$F22) | S22: =IF(R22="","",R22*$E22) | T22: =IF(R22="","",R22*$F22) | V22: =IF(U22="","",U22*$E22) | W22: =IF(U22="","",U22*$F22) | Y22: =IF(X22="","",X22*$E22) | Z22: =IF(X22="","",X22*$F22) | AB22: =IF(AA22="","",AA22*$E22) | AC22: =IF(AA22="","",AA22*$F22) | AE22: =IF(AD22="","",AD22*$E22) | AF22: =IF(AD22="","",AD22*$F22) | AH22: =IF(AG22="","",AG22*$E22) | AI22: =IF(AG22="","",AG22*$F22) | AK22: =IF(AJ22="","",AJ22*$E22) | AL22: =IF(AJ22="","",AJ22*$F22) | AN22: =IF(AM22="","",AM22*$E22) | AO22: =IF(AM22="","",AM22*$F22) | AQ22: =IF(AP22="","",AP22*$E22) | AR22: =IF(AP22="","",AP22*$F22) | AT22: =IF(AS22="","",AS22*$E22) | AU22: =IF(AS22="","",AS22*$F22) | AW22: =IF(AV22="","",AV22*$E22) | AX22: =IF(AV22="","",AV22*$F22) | AZ22: =IF(AY22="","",AY22*$E22) | BA22: =IF(AY22="","",AY22*$F22) | BC22: =IF(BB22="","",BB22*$E22) | BD22: =IF(BB22="","",BB22*$F22) | BF22: =IF(BE22="","",BE22*$E22) | BG22: =IF(BE22="","",BE22*$F22) | BI22: =IF(BH22="","",BH22*$E22) | BJ22: =IF(BH22="","",BH22*$F22) | BL22: =IF(BK22="","",BK22*$E22) | BM22: =IF(BK22="","",BK22*$F22) | BO22: =IF(BN22="","",BN22*$E22) | BP22: =IF(BN22="","",BN22*$F22) | BR22: =IF(BQ22="","",BQ22*$E22) | BS22: =IF(BQ22="","",BQ22*$F22) | BU22: =IF(BT22="","",BT22*$E22) | BV22: =IF(BT22="","",BT22*$F22) | BX22: =IF(BW22="","",BW22*$E22) | BY22: =IF(BW22="","",BW22*$F22) | CA22: =IF(BZ22="","",BZ22*$E22) | CB22: =IF(BZ22="","",BZ22*$F22) | CD22: =IF(CC22="","",CC22*$E22) | CE22: =IF(CC22="","",CC22*$F22) | CG22: =IF(CF22="","",CF22*$E22) | CH22: =IF(CF22="","",CF22*$F22) | CI22: =IF(R22>0,P22,0) + IF(X22>0,V22,0) + IF(AD22>0,AB22,0) + IF(AJ22>0,AH22,0) + IF(AP22>0,AN22,0) + IF(AV22>0,AT22,0) + IF(BB22>0,AZ22,0) + IF(BH22>0,BF22,0) + IF(BN22>0,BL22,0) + IF(BT22>0,BR22,0) + IF(BZ22>0,BX22,0) + IF(CF22>0,CD22,0) -> 0 | CJ22: =IF(R22>0,Q22,0) + IF(X22>0,W22,0) + IF(AD22>0,AC22,0) + IF(AJ22>0,AI22,0) + IF(AP22>0,AO22,0) + IF(AV22>0,AU22,0) + IF(BB22>0,BA22,0) + IF(BH22>0,BG22,0) + IF(BN22>0,BM22,0) + IF(BT22>0,BS22,0) + IF(BZ22>0,BY22,0) + IF(CF22>0,CE22,0) -> 0
A23: 松原 | B23: =IF(D23="","",IFERROR(VLOOKUP(D23,商品マスタ!$A:$K,2,FALSE),"缶バッジ")) -> 缶バッジ | C23: キャラバン | D23: 下蓋・穴下・ツメ下 | E23: =IF(D23="","",IFERROR(VLOOKUP(D23,商品マスタ!$A:$K,4,FALSE),12.55)) -> 12.55 | F23: =IF(D23="","",IFERROR(VLOOKUP(D23,商品マスタ!$A:$K,8,FALSE),1.14)) -> 1.14 | G23: =SUM(O23,U23,AA23,AG23,AM23,AS23,AY23,BE23,BK23,BQ23,BW23,CC23) -> 0 | H23: =SUM(P23,V23,AB23,AH23,AN23,AT23,AZ23,BF23,BL23,BR23,BX23,CD23) -> 0 | I23: =SUM(Q23,W23,AC23,AI23,AO23,AU23,BA23,BG23,BM23,BS23,BY23,CE23) -> 0 | J23: =SUM(R23,X23,AD23,AJ23,AP23,AV23,BB23,BH23,BN23,BT23,BZ23,CF23) -> 0 | K23: =SUM(S23,Y23,AE23,AK23,AQ23,AW23,BC23,BI23,BO23,BU23,CA23,CG23) -> 0 | L23: =SUM(T23,Z23,AF23,AL23,AR23,AX23,BD23,BJ23,BP23,BV23,CB23,CH23) -> 0 | M23: =IFERROR(K23/CI23,"") | N23: =IFERROR(L23/CJ23,"") | P23: =IF(O23="","",O23*$E23) | Q23: =IF(O23="","",O23*$F23) | S23: =IF(R23="","",R23*$E23) | T23: =IF(R23="","",R23*$F23) | V23: =IF(U23="","",U23*$E23) | W23: =IF(U23="","",U23*$F23) | Y23: =IF(X23="","",X23*$E23) | Z23: =IF(X23="","",X23*$F23) | AB23: =IF(AA23="","",AA23*$E23) | AC23: =IF(AA23="","",AA23*$F23) | AE23: =IF(AD23="","",AD23*$E23) | AF23: =IF(AD23="","",AD23*$F23) | AH23: =IF(AG23="","",AG23*$E23) | AI23: =IF(AG23="","",AG23*$F23) | AK23: =IF(AJ23="","",AJ23*$E23) | AL23: =IF(AJ23="","",AJ23*$F23) | AN23: =IF(AM23="","",AM23*$E23) | AO23: =IF(AM23="","",AM23*$F23) | AQ23: =IF(AP23="","",AP23*$E23) | AR23: =IF(AP23="","",AP23*$F23) | AT23: =IF(AS23="","",AS23*$E23) | AU23: =IF(AS23="","",AS23*$F23) | AW23: =IF(AV23="","",AV23*$E23) | AX23: =IF(AV23="","",AV23*$F23) | AZ23: =IF(AY23="","",AY23*$E23) | BA23: =IF(AY23="","",AY23*$F23) | BC23: =IF(BB23="","",BB23*$E23) | BD23: =IF(BB23="","",BB23*$F23) | BF23: =IF(BE23="","",BE23*$E23) | BG23: =IF(BE23="","",BE23*$F23) | BI23: =IF(BH23="","",BH23*$E23) | BJ23: =IF(BH23="","",BH23*$F23) | BL23: =IF(BK23="","",BK23*$E23) | BM23: =IF(BK23="","",BK23*$F23) | BO23: =IF(BN23="","",BN23*$E23) | BP23: =IF(BN23="","",BN23*$F23) | BR23: =IF(BQ23="","",BQ23*$E23) | BS23: =IF(BQ23="","",BQ23*$F23) | BU23: =IF(BT23="","",BT23*$E23) | BV23: =IF(BT23="","",BT23*$F23) | BX23: =IF(BW23="","",BW23*$E23) | BY23: =IF(BW23="","",BW23*$F23) | CA23: =IF(BZ23="","",BZ23*$E23) | CB23: =IF(BZ23="","",BZ23*$F23) | CD23: =IF(CC23="","",CC23*$E23) | CE23: =IF(CC23="","",CC23*$F23) | CG23: =IF(CF23="","",CF23*$E23) | CH23: =IF(CF23="","",CF23*$F23) | CI23: =IF(R23>0,P23,0) + IF(X23>0,V23,0) + IF(AD23>0,AB23,0) + IF(AJ23>0,AH23,0) + IF(AP23>0,AN23,0) + IF(AV23>0,AT23,0) + IF(BB23>0,AZ23,0) + IF(BH23>0,BF23,0) + IF(BN23>0,BL23,0) + IF(BT23>0,BR23,0) + IF(BZ23>0,BX23,0) + IF(CF23>0,CD23,0) -> 0 | CJ23: =IF(R23>0,Q23,0) + IF(X23>0,W23,0) + IF(AD23>0,AC23,0) + IF(AJ23>0,AI23,0) + IF(AP23>0,AO23,0) + IF(AV23>0,AU23,0) + IF(BB23>0,BA23,0) + IF(BH23>0,BG23,0) + IF(BN23>0,BM23,0) + IF(BT23>0,BS23,0) + IF(BZ23>0,BY23,0) + IF(CF23>0,CE23,0) -> 0
A24: 松原 | B24: =IF(D24="","",IFERROR(VLOOKUP(D24,商品マスタ!$A:$K,2,FALSE),"缶バッジ")) -> 缶バッジ | C24: クリエイト | D24: 下蓋・穴下・ツメ下 | E24: =IF(D24="","",IFERROR(VLOOKUP(D24,商品マスタ!$A:$K,4,FALSE),12.55)) -> 12.55 | F24: =IF(D24="","",IFERROR(VLOOKUP(D24,商品マスタ!$A:$K,8,FALSE),1.14)) -> 1.14 | G24: =SUM(O24,U24,AA24,AG24,AM24,AS24,AY24,BE24,BK24,BQ24,BW24,CC24) -> 0 | H24: =SUM(P24,V24,AB24,AH24,AN24,AT24,AZ24,BF24,BL24,BR24,BX24,CD24) -> 0 | I24: =SUM(Q24,W24,AC24,AI24,AO24,AU24,BA24,BG24,BM24,BS24,BY24,CE24) -> 0 | J24: =SUM(R24,X24,AD24,AJ24,AP24,AV24,BB24,BH24,BN24,BT24,BZ24,CF24) -> 0 | K24: =SUM(S24,Y24,AE24,AK24,AQ24,AW24,BC24,BI24,BO24,BU24,CA24,CG24) -> 0 | L24: =SUM(T24,Z24,AF24,AL24,AR24,AX24,BD24,BJ24,BP24,BV24,CB24,CH24) -> 0 | M24: =IFERROR(K24/CI24,"") | N24: =IFERROR(L24/CJ24,"") | P24: =IF(O24="","",O24*$E24) | Q24: =IF(O24="","",O24*$F24) | S24: =IF(R24="","",R24*$E24) | T24: =IF(R24="","",R24*$F24) | V24: =IF(U24="","",U24*$E24) | W24: =IF(U24="","",U24*$F24) | Y24: =IF(X24="","",X24*$E24) | Z24: =IF(X24="","",X24*$F24) | AB24: =IF(AA24="","",AA24*$E24) | AC24: =IF(AA24="","",AA24*$F24) | AE24: =IF(AD24="","",AD24*$E24) | AF24: =IF(AD24="","",AD24*$F24) | AH24: =IF(AG24="","",AG24*$E24) | AI24: =IF(AG24="","",AG24*$F24) | AK24: =IF(AJ24="","",AJ24*$E24) | AL24: =IF(AJ24="","",AJ24*$F24) | AN24: =IF(AM24="","",AM24*$E24) | AO24: =IF(AM24="","",AM24*$F24) | AQ24: =IF(AP24="","",AP24*$E24) | AR24: =IF(AP24="","",AP24*$F24) | AT24: =IF(AS24="","",AS24*$E24) | AU24: =IF(AS24="","",AS24*$F24) | AW24: =IF(AV24="","",AV24*$E24) | AX24: =IF(AV24="","",AV24*$F24) | AZ24: =IF(AY24="","",AY24*$E24) | BA24: =IF(AY24="","",AY24*$F24) | BC24: =IF(BB24="","",BB24*$E24) | BD24: =IF(BB24="","",BB24*$F24) | BF24: =IF(BE24="","",BE24*$E24) | BG24: =IF(BE24="","",BE24*$F24) | BI24: =IF(BH24="","",BH24*$E24) | BJ24: =IF(BH24="","",BH24*$F24) | BL24: =IF(BK24="","",BK24*$E24) | BM24: =IF(BK24="","",BK24*$F24) | BO24: =IF(BN24="","",BN24*$E24) | BP24: =IF(BN24="","",BN24*$F24) | BR24: =IF(BQ24="","",BQ24*$E24) | BS24: =IF(BQ24="","",BQ24*$F24) | BU24: =IF(BT24="","",BT24*$E24) | BV24: =IF(BT24="","",BT24*$F24) | BX24: =IF(BW24="","",BW24*$E24) | BY24: =IF(BW24="","",BW24*$F24) | CA24: =IF(BZ24="","",BZ24*$E24) | CB24: =IF(BZ24="","",BZ24*$F24) | CD24: =IF(CC24="","",CC24*$E24) | CE24: =IF(CC24="","",CC24*$F24) | CG24: =IF(CF24="","",CF24*$E24) | CH24: =IF(CF24="","",CF24*$F24) | CI24: =IF(R24>0,P24,0) + IF(X24>0,V24,0) + IF(AD24>0,AB24,0) + IF(AJ24>0,AH24,0) + IF(AP24>0,AN24,0) + IF(AV24>0,AT24,0) + IF(BB24>0,AZ24,0) + IF(BH24>0,BF24,0) + IF(BN24>0,BL24,0) + IF(BT24>0,BR24,0) + IF(BZ24>0,BX24,0) + IF(CF24>0,CD24,0) -> 0 | CJ24: =IF(R24>0,Q24,0) + IF(X24>0,W24,0) + IF(AD24>0,AC24,0) + IF(AJ24>0,AI24,0) + IF(AP24>0,AO24,0) + IF(AV24>0,AU24,0) + IF(BB24>0,BA24,0) + IF(BH24>0,BG24,0) + IF(BN24>0,BM24,0) + IF(BT24>0,BS24,0) + IF(BZ24>0,BY24,0) + IF(CF24>0,CE24,0) -> 0
A25: 松原 | B25: =IF(D25="","",IFERROR(VLOOKUP(D25,商品マスタ!$A:$K,2,FALSE),"缶バッジ")) -> 缶バッジ | C25: グラビティ | D25: 下蓋・穴下・ツメ下 | E25: =IF(D25="","",IFERROR(VLOOKUP(D25,商品マスタ!$A:$K,4,FALSE),12.55)) -> 12.55 | F25: =IF(D25="","",IFERROR(VLOOKUP(D25,商品マスタ!$A:$K,8,FALSE),1.14)) -> 1.14 | G25: =SUM(O25,U25,AA25,AG25,AM25,AS25,AY25,BE25,BK25,BQ25,BW25,CC25) -> 0 | H25: =SUM(P25,V25,AB25,AH25,AN25,AT25,AZ25,BF25,BL25,BR25,BX25,CD25) -> 0 | I25: =SUM(Q25,W25,AC25,AI25,AO25,AU25,BA25,BG25,BM25,BS25,BY25,CE25) -> 0 | J25: =SUM(R25,X25,AD25,AJ25,AP25,AV25,BB25,BH25,BN25,BT25,BZ25,CF25) -> 0 | K25: =SUM(S25,Y25,AE25,AK25,AQ25,AW25,BC25,BI25,BO25,BU25,CA25,CG25) -> 0 | L25: =SUM(T25,Z25,AF25,AL25,AR25,AX25,BD25,BJ25,BP25,BV25,CB25,CH25) -> 0 | M25: =IFERROR(K25/CI25,"") | N25: =IFERROR(L25/CJ25,"") | P25: =IF(O25="","",O25*$E25) | Q25: =IF(O25="","",O25*$F25) | S25: =IF(R25="","",R25*$E25) | T25: =IF(R25="","",R25*$F25) | V25: =IF(U25="","",U25*$E25) | W25: =IF(U25="","",U25*$F25) | Y25: =IF(X25="","",X25*$E25) | Z25: =IF(X25="","",X25*$F25) | AB25: =IF(AA25="","",AA25*$E25) | AC25: =IF(AA25="","",AA25*$F25) | AE25: =IF(AD25="","",AD25*$E25) | AF25: =IF(AD25="","",AD25*$F25) | AH25: =IF(AG25="","",AG25*$E25) | AI25: =IF(AG25="","",AG25*$F25) | AK25: =IF(AJ25="","",AJ25*$E25) | AL25: =IF(AJ25="","",AJ25*$F25) | AN25: =IF(AM25="","",AM25*$E25) | AO25: =IF(AM25="","",AM25*$F25) | AQ25: =IF(AP25="","",AP25*$E25) | AR25: =IF(AP25="","",AP25*$F25) | AT25: =IF(AS25="","",AS25*$E25) | AU25: =IF(AS25="","",AS25*$F25) | AW25: =IF(AV25="","",AV25*$E25) | AX25: =IF(AV25="","",AV25*$F25) | AZ25: =IF(AY25="","",AY25*$E25) | BA25: =IF(AY25="","",AY25*$F25) | BC25: =IF(BB25="","",BB25*$E25) | BD25: =IF(BB25="","",BB25*$F25) | BF25: =IF(BE25="","",BE25*$E25) | BG25: =IF(BE25="","",BE25*$F25) | BI25: =IF(BH25="","",BH25*$E25) | BJ25: =IF(BH25="","",BH25*$F25) | BL25: =IF(BK25="","",BK25*$E25) | BM25: =IF(BK25="","",BK25*$F25) | BO25: =IF(BN25="","",BN25*$E25) | BP25: =IF(BN25="","",BN25*$F25) | BR25: =IF(BQ25="","",BQ25*$E25) | BS25: =IF(BQ25="","",BQ25*$F25) | BU25: =IF(BT25="","",BT25*$E25) | BV25: =IF(BT25="","",BT25*$F25) | BX25: =IF(BW25="","",BW25*$E25) | BY25: =IF(BW25="","",BW25*$F25) | CA25: =IF(BZ25="","",BZ25*$E25) | CB25: =IF(BZ25="","",BZ25*$F25) | CD25: =IF(CC25="","",CC25*$E25) | CE25: =IF(CC25="","",CC25*$F25) | CG25: =IF(CF25="","",CF25*$E25) | CH25: =IF(CF25="","",CF25*$F25) | CI25: =IF(R25>0,P25,0) + IF(X25>0,V25,0) + IF(AD25>0,AB25,0) + IF(AJ25>0,AH25,0) + IF(AP25>0,AN25,0) + IF(AV25>0,AT25,0) + IF(BB25>0,AZ25,0) + IF(BH25>0,BF25,0) + IF(BN25>0,BL25,0) + IF(BT25>0,BR25,0) + IF(BZ25>0,BX25,0) + IF(CF25>0,CD25,0) -> 0 | CJ25: =IF(R25>0,Q25,0) + IF(X25>0,W25,0) + IF(AD25>0,AC25,0) + IF(AJ25>0,AI25,0) + IF(AP25>0,AO25,0) + IF(AV25>0,AU25,0) + IF(BB25>0,BA25,0) + IF(BH25>0,BG25,0) + IF(BN25>0,BM25,0) + IF(BT25>0,BS25,0) + IF(BZ25>0,BY25,0) + IF(CF25>0,CE25,0) -> 0
A26: 松原 | B26: =IF(D26="","",IFERROR(VLOOKUP(D26,商品マスタ!$A:$K,2,FALSE),"缶バッジ")) -> 缶バッジ | C26: グラフィック機材 | D26: 下蓋・穴下・ツメ下 | E26: =IF(D26="","",IFERROR(VLOOKUP(D26,商品マスタ!$A:$K,4,FALSE),12.55)) -> 12.55 | F26: =IF(D26="","",IFERROR(VLOOKUP(D26,商品マスタ!$A:$K,8,FALSE),1.14)) -> 1.14 | G26: =SUM(O26,U26,AA26,AG26,AM26,AS26,AY26,BE26,BK26,BQ26,BW26,CC26) -> 0 | H26: =SUM(P26,V26,AB26,AH26,AN26,AT26,AZ26,BF26,BL26,BR26,BX26,CD26) -> 0 | I26: =SUM(Q26,W26,AC26,AI26,AO26,AU26,BA26,BG26,BM26,BS26,BY26,CE26) -> 0 | J26: =SUM(R26,X26,AD26,AJ26,AP26,AV26,BB26,BH26,BN26,BT26,BZ26,CF26) -> 0 | K26: =SUM(S26,Y26,AE26,AK26,AQ26,AW26,BC26,BI26,BO26,BU26,CA26,CG26) -> 0 | L26: =SUM(T26,Z26,AF26,AL26,AR26,AX26,BD26,BJ26,BP26,BV26,CB26,CH26) -> 0 | M26: =IFERROR(K26/CI26,"") | N26: =IFERROR(L26/CJ26,"") | P26: =IF(O26="","",O26*$E26) | Q26: =IF(O26="","",O26*$F26) | S26: =IF(R26="","",R26*$E26) | T26: =IF(R26="","",R26*$F26) | V26: =IF(U26="","",U26*$E26) | W26: =IF(U26="","",U26*$F26) | Y26: =IF(X26="","",X26*$E26) | Z26: =IF(X26="","",X26*$F26) | AB26: =IF(AA26="","",AA26*$E26) | AC26: =IF(AA26="","",AA26*$F26) | AE26: =IF(AD26="","",AD26*$E26) | AF26: =IF(AD26="","",AD26*$F26) | AH26: =IF(AG26="","",AG26*$E26) | AI26: =IF(AG26="","",AG26*$F26) | AK26: =IF(AJ26="","",AJ26*$E26) | AL26: =IF(AJ26="","",AJ26*$F26) | AN26: =IF(AM26="","",AM26*$E26) | AO26: =IF(AM26="","",AM26*$F26) | AQ26: =IF(AP26="","",AP26*$E26) | AR26: =IF(AP26="","",AP26*$F26) | AT26: =IF(AS26="","",AS26*$E26) | AU26: =IF(AS26="","",AS26*$F26) | AW26: =IF(AV26="","",AV26*$E26) | AX26: =IF(AV26="","",AV26*$F26) | AZ26: =IF(AY26="","",AY26*$E26) | BA26: =IF(AY26="","",AY26*$F26) | BC26: =IF(BB26="","",BB26*$E26) | BD26: =IF(BB26="","",BB26*$F26) | BF26: =IF(BE26="","",BE26*$E26) | BG26: =IF(BE26="","",BE26*$F26) | BI26: =IF(BH26="","",BH26*$E26) | BJ26: =IF(BH26="","",BH26*$F26) | BL26: =IF(BK26="","",BK26*$E26) | BM26: =IF(BK26="","",BK26*$F26) | BO26: =IF(BN26="","",BN26*$E26) | BP26: =IF(BN26="","",BN26*$F26) | BR26: =IF(BQ26="","",BQ26*$E26) | BS26: =IF(BQ26="","",BQ26*$F26) | BU26: =IF(BT26="","",BT26*$E26) | BV26: =IF(BT26="","",BT26*$F26) | BX26: =IF(BW26="","",BW26*$E26) | BY26: =IF(BW26="","",BW26*$F26) | CA26: =IF(BZ26="","",BZ26*$E26) | CB26: =IF(BZ26="","",BZ26*$F26) | CD26: =IF(CC26="","",CC26*$E26) | CE26: =IF(CC26="","",CC26*$F26) | CG26: =IF(CF26="","",CF26*$E26) | CH26: =IF(CF26="","",CF26*$F26) | CI26: =IF(R26>0,P26,0) + IF(X26>0,V26,0) + IF(AD26>0,AB26,0) + IF(AJ26>0,AH26,0) + IF(AP26>0,AN26,0) + IF(AV26>0,AT26,0) + IF(BB26>0,AZ26,0) + IF(BH26>0,BF26,0) + IF(BN26>0,BL26,0) + IF(BT26>0,BR26,0) + IF(BZ26>0,BX26,0) + IF(CF26>0,CD26,0) -> 0 | CJ26: =IF(R26>0,Q26,0) + IF(X26>0,W26,0) + IF(AD26>0,AC26,0) + IF(AJ26>0,AI26,0) + IF(AP26>0,AO26,0) + IF(AV26>0,AU26,0) + IF(BB26>0,BA26,0) + IF(BH26>0,BG26,0) + IF(BN26>0,BM26,0) + IF(BT26>0,BS26,0) + IF(BZ26>0,BY26,0) + IF(CF26>0,CE26,0) -> 0
A27: 松原 | B27: =IF(D27="","",IFERROR(VLOOKUP(D27,商品マスタ!$A:$K,2,FALSE),"缶バッジ")) -> 缶バッジ | C27: グランサンク | D27: 下蓋・穴下・ツメ下 | E27: =IF(D27="","",IFERROR(VLOOKUP(D27,商品マスタ!$A:$K,4,FALSE),12.55)) -> 12.55 | F27: =IF(D27="","",IFERROR(VLOOKUP(D27,商品マスタ!$A:$K,8,FALSE),1.14)) -> 1.14 | G27: =SUM(O27,U27,AA27,AG27,AM27,AS27,AY27,BE27,BK27,BQ27,BW27,CC27) -> 0 | H27: =SUM(P27,V27,AB27,AH27,AN27,AT27,AZ27,BF27,BL27,BR27,BX27,CD27) -> 0 | I27: =SUM(Q27,W27,AC27,AI27,AO27,AU27,BA27,BG27,BM27,BS27,BY27,CE27) -> 0 | J27: =SUM(R27,X27,AD27,AJ27,AP27,AV27,BB27,BH27,BN27,BT27,BZ27,CF27) -> 0 | K27: =SUM(S27,Y27,AE27,AK27,AQ27,AW27,BC27,BI27,BO27,BU27,CA27,CG27) -> 0 | L27: =SUM(T27,Z27,AF27,AL27,AR27,AX27,BD27,BJ27,BP27,BV27,CB27,CH27) -> 0 | M27: =IFERROR(K27/CI27,"") | N27: =IFERROR(L27/CJ27,"") | P27: =IF(O27="","",O27*$E27) | Q27: =IF(O27="","",O27*$F27) | S27: =IF(R27="","",R27*$E27) | T27: =IF(R27="","",R27*$F27) | V27: =IF(U27="","",U27*$E27) | W27: =IF(U27="","",U27*$F27) | Y27: =IF(X27="","",X27*$E27) | Z27: =IF(X27="","",X27*$F27) | AB27: =IF(AA27="","",AA27*$E27) | AC27: =IF(AA27="","",AA27*$F27) | AE27: =IF(AD27="","",AD27*$E27) | AF27: =IF(AD27="","",AD27*$F27) | AH27: =IF(AG27="","",AG27*$E27) | AI27: =IF(AG27="","",AG27*$F27) | AK27: =IF(AJ27="","",AJ27*$E27) | AL27: =IF(AJ27="","",AJ27*$F27) | AN27: =IF(AM27="","",AM27*$E27) | AO27: =IF(AM27="","",AM27*$F27) | AQ27: =IF(AP27="","",AP27*$E27) | AR27: =IF(AP27="","",AP27*$F27) | AT27: =IF(AS27="","",AS27*$E27) | AU27: =IF(AS27="","",AS27*$F27) | AW27: =IF(AV27="","",AV27*$E27) | AX27: =IF(AV27="","",AV27*$F27) | AZ27: =IF(AY27="","",AY27*$E27) | BA27: =IF(AY27="","",AY27*$F27) | BC27: =IF(BB27="","",BB27*$E27) | BD27: =IF(BB27="","",BB27*$F27) | BF27: =IF(BE27="","",BE27*$E27) | BG27: =IF(BE27="","",BE27*$F27) | BI27: =IF(BH27="","",BH27*$E27) | BJ27: =IF(BH27="","",BH27*$F27) | BL27: =IF(BK27="","",BK27*$E27) | BM27: =IF(BK27="","",BK27*$F27) | BO27: =IF(BN27="","",BN27*$E27) | BP27: =IF(BN27="","",BN27*$F27) | BR27: =IF(BQ27="","",BQ27*$E27) | BS27: =IF(BQ27="","",BQ27*$F27) | BU27: =IF(BT27="","",BT27*$E27) | BV27: =IF(BT27="","",BT27*$F27) | BX27: =IF(BW27="","",BW27*$E27) | BY27: =IF(BW27="","",BW27*$F27) | CA27: =IF(BZ27="","",BZ27*$E27) | CB27: =IF(BZ27="","",BZ27*$F27) | CD27: =IF(CC27="","",CC27*$E27) | CE27: =IF(CC27="","",CC27*$F27) | CG27: =IF(CF27="","",CF27*$E27) | CH27: =IF(CF27="","",CF27*$F27) | CI27: =IF(R27>0,P27,0) + IF(X27>0,V27,0) + IF(AD27>0,AB27,0) + IF(AJ27>0,AH27,0) + IF(AP27>0,AN27,0) + IF(AV27>0,AT27,0) + IF(BB27>0,AZ27,0) + IF(BH27>0,BF27,0) + IF(BN27>0,BL27,0) + IF(BT27>0,BR27,0) + IF(BZ27>0,BX27,0) + IF(CF27>0,CD27,0) -> 0 | CJ27: =IF(R27>0,Q27,0) + IF(X27>0,W27,0) + IF(AD27>0,AC27,0) + IF(AJ27>0,AI27,0) + IF(AP27>0,AO27,0) + IF(AV27>0,AU27,0) + IF(BB27>0,BA27,0) + IF(BH27>0,BG27,0) + IF(BN27>0,BM27,0) + IF(BT27>0,BS27,0) + IF(BZ27>0,BY27,0) + IF(CF27>0,CE27,0) -> 0
... A50: 松原 | B50: =IF(D50="","",IFERROR(VLOOKUP(D50,商品マスタ!$A:$K,2,FALSE),"缶バッジ")) -> 缶バッジ | C50: ｻｻﾞﾝ･ﾃﾞｨ･ｴｽ･ｸﾘｴｲﾄ | D50: 下蓋・穴下・ツメ下 | E50: =IF(D50="","",IFERROR(VLOOKUP(D50,商品マスタ!$A:$K,4,FALSE),12.55)) -> 12.55 | F50: =IF(D50="","",IFERROR(VLOOKUP(D50,商品マスタ!$A:$K,8,FALSE),1.14)) -> 1.14 | G50: =SUM(O50,U50,AA50,AG50,AM50,AS50,AY50,BE50,BK50,BQ50,BW50,CC50) -> 0 | H50: =SUM(P50,V50,AB50,AH50,AN50,AT50,AZ50,BF50,BL50,BR50,BX50,CD50) -> 0 | I50: =SUM(Q50,W50,AC50,AI50,AO50,AU50,BA50,BG50,BM50,BS50,BY50,CE50) -> 0 | J50: =SUM(R50,X50,AD50,AJ50,AP50,AV50,BB50,BH50,BN50,BT50,BZ50,CF50) -> 0 | K50: =SUM(S50,Y50,AE50,AK50,AQ50,AW50,BC50,BI50,BO50,BU50,CA50,CG50) -> 0 | L50: =SUM(T50,Z50,AF50,AL50,AR50,AX50,BD50,BJ50,BP50,BV50,CB50,CH50) -> 0 | M50: =IFERROR(K50/CI50,"") | N50: =IFERROR(L50/CJ50,"") | P50: =IF(O50="","",O50*$E50) | Q50: =IF(O50="","",O50*$F50) | S50: =IF(R50="","",R50*$E50) | T50: =IF(R50="","",R50*$F50) | V50: =IF(U50="","",U50*$E50) | W50: =IF(U50="","",U50*$F50) | Y50: =IF(X50="","",X50*$E50) | Z50: =IF(X50="","",X50*$F50) | AB50: =IF(AA50="","",AA50*$E50) | AC50: =IF(AA50="","",AA50*$F50) | AE50: =IF(AD50="","",AD50*$E50) | AF50: =IF(AD50="","",AD50*$F50) | AH50: =IF(AG50="","",AG50*$E50) | AI50: =IF(AG50="","",AG50*$F50) | AK50: =IF(AJ50="","",AJ50*$E50) | AL50: =IF(AJ50="","",AJ50*$F50) | AN50: =IF(AM50="","",AM50*$E50) | AO50: =IF(AM50="","",AM50*$F50) | AQ50: =IF(AP50="","",AP50*$E50) | AR50: =IF(AP50="","",AP50*$F50) | AT50: =IF(AS50="","",AS50*$E50) | AU50: =IF(AS50="","",AS50*$F50) | AW50: =IF(AV50="","",AV50*$E50) | AX50: =IF(AV50="","",AV50*$F50) | AZ50: =IF(AY50="","",AY50*$E50) | BA50: =IF(AY50="","",AY50*$F50) | BC50: =IF(BB50="","",BB50*$E50) | BD50: =IF(BB50="","",BB50*$F50) | BF50: =IF(BE50="","",BE50*$E50) | BG50: =IF(BE50="","",BE50*$F50) | BI50: =IF(BH50="","",BH50*$E50) | BJ50: =IF(BH50="","",BH50*$F50) | BL50: =IF(BK50="","",BK50*$E50) | BM50: =IF(BK50="","",BK50*$F50) | BO50: =IF(BN50="","",BN50*$E50) | BP50: =IF(BN50="","",BN50*$F50) | BR50: =IF(BQ50="","",BQ50*$E50) | BS50: =IF(BQ50="","",BQ50*$F50) | BU50: =IF(BT50="","",BT50*$E50) | BV50: =IF(BT50="","",BT50*$F50) | BX50: =IF(BW50="","",BW50*$E50) | BY50: =IF(BW50="","",BW50*$F50) | CA50: =IF(BZ50="","",BZ50*$E50) | CB50: =IF(BZ50="","",BZ50*$F50) | CD50: =IF(CC50="","",CC50*$E50) | CE50: =IF(CC50="","",CC50*$F50) | CG50: =IF(CF50="","",CF50*$E50) | CH50: =IF(CF50="","",CF50*$F50) | CI50: =IF(R50>0,P50,0) + IF(X50>0,V50,0) + IF(AD50>0,AB50,0) + IF(AJ50>0,AH50,0) + IF(AP50>0,AN50,0) + IF(AV50>0,AT50,0) + IF(BB50>0,AZ50,0) + IF(BH50>0,BF50,0) + IF(BN50>0,BL50,0) + IF(BT50>0,BR50,0) + IF(BZ50>0,BX50,0) + IF(CF50>0,CD50,0) -> 0 | CJ50: =IF(R50>0,Q50,0) + IF(X50>0,W50,0) + IF(AD50>0,AC50,0) + IF(AJ50>0,AI50,0) + IF(AP50>0,AO50,0) + IF(AV50>0,AU50,0) + IF(BB50>0,BA50,0) + IF(BH50>0,BG50,0) + IF(BN50>0,BM50,0) + IF(BT50>0,BS50,0) + IF(BZ50>0,BY50,0) + IF(CF50>0,CE50,0) -> 0
A51: 松原 | B51: =IF(D51="","",IFERROR(VLOOKUP(D51,商品マスタ!$A:$K,2,FALSE),"その他")) -> その他 | C51: 三菱電機ﾄﾚｰﾃﾞｨﾝｸﾞ | D51: その他 | E51: =IF(D51="","",IFERROR(VLOOKUP(D51,商品マスタ!$A:$K,4,FALSE),0)) -> 0 | F51: =IF(D51="","",IFERROR(VLOOKUP(D51,商品マスタ!$A:$K,8,FALSE),0)) -> 0 | G51: =SUM(O51,U51,AA51,AG51,AM51,AS51,AY51,BE51,BK51,BQ51,BW51,CC51) -> 0 | H51: =SUM(P51,V51,AB51,AH51,AN51,AT51,AZ51,BF51,BL51,BR51,BX51,CD51) -> 0 | I51: =SUM(Q51,W51,AC51,AI51,AO51,AU51,BA51,BG51,BM51,BS51,BY51,CE51) -> 0 | J51: =SUM(R51,X51,AD51,AJ51,AP51,AV51,BB51,BH51,BN51,BT51,BZ51,CF51) -> 0 | K51: =SUM(S51,Y51,AE51,AK51,AQ51,AW51,BC51,BI51,BO51,BU51,CA51,CG51) -> 0 | L51: =SUM(T51,Z51,AF51,AL51,AR51,AX51,BD51,BJ51,BP51,BV51,CB51,CH51) -> 0 | M51: =IFERROR(K51/CI51,"") | N51: =IFERROR(L51/CJ51,"") | P51: =IF(O51="","",O51*$E51) | Q51: =IF(O51="","",O51*$F51) | S51: =IF(R51="","",R51*$E51) | T51: =IF(R51="","",R51*$F51) | V51: =IF(U51="","",U51*$E51) | W51: =IF(U51="","",U51*$F51) | Y51: =IF(X51="","",X51*$E51) | Z51: =IF(X51="","",X51*$F51) | AB51: =IF(AA51="","",AA51*$E51) | AC51: =IF(AA51="","",AA51*$F51) | AE51: =IF(AD51="","",AD51*$E51) | AF51: =IF(AD51="","",AD51*$F51) | AH51: =IF(AG51="","",AG51*$E51) | AI51: =IF(AG51="","",AG51*$F51) | AK51: =IF(AJ51="","",AJ51*$E51) | AL51: =IF(AJ51="","",AJ51*$F51) | AN51: =IF(AM51="","",AM51*$E51) | AO51: =IF(AM51="","",AM51*$F51) | AQ51: =IF(AP51="","",AP51*$E51) | AR51: =IF(AP51="","",AP51*$F51) | AT51: =IF(AS51="","",AS51*$E51) | AU51: =IF(AS51="","",AS51*$F51) | AW51: =IF(AV51="","",AV51*$E51) | AX51: =IF(AV51="","",AV51*$F51) | AZ51: =IF(AY51="","",AY51*$E51) | BA51: =IF(AY51="","",AY51*$F51) | BC51: =IF(BB51="","",BB51*$E51) | BD51: =IF(BB51="","",BB51*$F51) | BF51: =IF(BE51="","",BE51*$E51) | BG51: =IF(BE51="","",BE51*$F51) | BI51: =IF(BH51="","",BH51*$E51) | BJ51: =IF(BH51="","",BH51*$F51) | BL51: =IF(BK51="","",BK51*$E51) | BM51: =IF(BK51="","",BK51*$F51) | BO51: =IF(BN51="","",BN51*$E51) | BP51: =IF(BN51="","",BN51*$F51) | BR51: =IF(BQ51="","",BQ51*$E51) | BS51: =IF(BQ51="","",BQ51*$F51) | BU51: =IF(BT51="","",BT51*$E51) | BV51: =IF(BT51="","",BT51*$F51) | BX51: =IF(BW51="","",BW51*$E51) | BY51: =IF(BW51="","",BW51*$F51) | CA51: =IF(BZ51="","",BZ51*$E51) | CB51: =IF(BZ51="","",BZ51*$F51) | CD51: =IF(CC51="","",CC51*$E51) | CE51: =IF(CC51="","",CC51*$F51) | CG51: =IF(CF51="","",CF51*$E51) | CH51: =IF(CF51="","",CF51*$F51) | CI51: =IF(R51>0,P51,0) + IF(X51>0,V51,0) + IF(AD51>0,AB51,0) + IF(AJ51>0,AH51,0) + IF(AP51>0,AN51,0) + IF(AV51>0,AT51,0) + IF(BB51>0,AZ51,0) + IF(BH51>0,BF51,0) + IF(BN51>0,BL51,0) + IF(BT51>0,BR51,0) + IF(BZ51>0,BX51,0) + IF(CF51>0,CD51,0) -> 0 | CJ51: =IF(R51>0,Q51,0) + IF(X51>0,W51,0) + IF(AD51>0,AC51,0) + IF(AJ51>0,AI51,0) + IF(AP51>0,AO51,0) + IF(AV51>0,AU51,0) + IF(BB51>0,BA51,0) + IF(BH51>0,BG51,0) + IF(BN51>0,BM51,0) + IF(BT51>0,BS51,0) + IF(BZ51>0,BY51,0) + IF(CF51>0,CE51,0) -> 0
A52: 松原 | B52: =IF(D52="","",IFERROR(VLOOKUP(D52,商品マスタ!$A:$K,2,FALSE),"その他")) -> その他 | C52: 京都プレス工業 | D52: 電設資材 | E52: =IF(D52="","",IFERROR(VLOOKUP(D52,商品マスタ!$A:$K,4,FALSE),76.49)) -> 76.49 | F52: =IF(D52="","",IFERROR(VLOOKUP(D52,商品マスタ!$A:$K,8,FALSE),0)) -> 0 | G52: =SUM(O52,U52,AA52,AG52,AM52,AS52,AY52,BE52,BK52,BQ52,BW52,CC52) -> 0 | H52: =SUM(P52,V52,AB52,AH52,AN52,AT52,AZ52,BF52,BL52,BR52,BX52,CD52) -> 0 | I52: =SUM(Q52,W52,AC52,AI52,AO52,AU52,BA52,BG52,BM52,BS52,BY52,CE52) -> 0 | J52: =SUM(R52,X52,AD52,AJ52,AP52,AV52,BB52,BH52,BN52,BT52,BZ52,CF52) -> 0 | K52: =SUM(S52,Y52,AE52,AK52,AQ52,AW52,BC52,BI52,BO52,BU52,CA52,CG52) -> 0 | L52: =SUM(T52,Z52,AF52,AL52,AR52,AX52,BD52,BJ52,BP52,BV52,CB52,CH52) -> 0 | M52: =IFERROR(K52/CI52,"") | N52: =IFERROR(L52/CJ52,"") | P52: =IF(O52="","",O52*$E52) | Q52: =IF(O52="","",O52*$F52) | S52: =IF(R52="","",R52*$E52) | T52: =IF(R52="","",R52*$F52) | V52: =IF(U52="","",U52*$E52) | W52: =IF(U52="","",U52*$F52) | Y52: =IF(X52="","",X52*$E52) | Z52: =IF(X52="","",X52*$F52) | AB52: =IF(AA52="","",AA52*$E52) | AC52: =IF(AA52="","",AA52*$F52) | AE52: =IF(AD52="","",AD52*$E52) | AF52: =IF(AD52="","",AD52*$F52) | AH52: =IF(AG52="","",AG52*$E52) | AI52: =IF(AG52="","",AG52*$F52) | AK52: =IF(AJ52="","",AJ52*$E52) | AL52: =IF(AJ52="","",AJ52*$F52) | AN52: =IF(AM52="","",AM52*$E52) | AO52: =IF(AM52="","",AM52*$F52) | AQ52: =IF(AP52="","",AP52*$E52) | AR52: =IF(AP52="","",AP52*$F52) | AT52: =IF(AS52="","",AS52*$E52) | AU52: =IF(AS52="","",AS52*$F52) | AW52: =IF(AV52="","",AV52*$E52) | AX52: =IF(AV52="","",AV52*$F52) | AZ52: =IF(AY52="","",AY52*$E52) | BA52: =IF(AY52="","",AY52*$F52) | BC52: =IF(BB52="","",BB52*$E52) | BD52: =IF(BB52="","",BB52*$F52) | BF52: =IF(BE52="","",BE52*$E52) | BG52: =IF(BE52="","",BE52*$F52) | BI52: =IF(BH52="","",BH52*$E52) | BJ52: =IF(BH52="","",BH52*$F52) | BL52: =IF(BK52="","",BK52*$E52) | BM52: =IF(BK52="","",BK52*$F52) | BO52: =IF(BN52="","",BN52*$E52) | BP52: =IF(BN52="","",BN52*$F52) | BR52: =IF(BQ52="","",BQ52*$E52) | BS52: =IF(BQ52="","",BQ52*$F52) | BU52: =IF(BT52="","",BT52*$E52) | BV52: =IF(BT52="","",BT52*$F52) | BX52: =IF(BW52="","",BW52*$E52) | BY52: =IF(BW52="","",BW52*$F52) | CA52: =IF(BZ52="","",BZ52*$E52) | CB52: =IF(BZ52="","",BZ52*$F52) | CD52: =IF(CC52="","",CC52*$E52) | CE52: =IF(CC52="","",CC52*$F52) | CG52: =IF(CF52="","",CF52*$E52) | CH52: =IF(CF52="","",CF52*$F52) | CI52: =IF(R52>0,P52,0) + IF(X52>0,V52,0) + IF(AD52>0,AB52,0) + IF(AJ52>0,AH52,0) + IF(AP52>0,AN52,0) + IF(AV52>0,AT52,0) + IF(BB52>0,AZ52,0) + IF(BH52>0,BF52,0) + IF(BN52>0,BL52,0) + IF(BT52>0,BR52,0) + IF(BZ52>0,BX52,0) + IF(CF52>0,CD52,0) -> 0 | CJ52: =IF(R52>0,Q52,0) + IF(X52>0,W52,0) + IF(AD52>0,AC52,0) + IF(AJ52>0,AI52,0) + IF(AP52>0,AO52,0) + IF(AV52>0,AU52,0) + IF(BB52>0,BA52,0) + IF(BH52>0,BG52,0) + IF(BN52>0,BM52,0) + IF(BT52>0,BS52,0) + IF(BZ52>0,BY52,0) + IF(CF52>0,CE52,0) -> 0
A53: 松原 | B53: =IF(D53="","",IFERROR(VLOOKUP(D53,商品マスタ!$A:$K,2,FALSE),"その他")) -> その他 | C53: 吉田商事 | D53: 電設資材 | E53: =IF(D53="","",IFERROR(VLOOKUP(D53,商品マスタ!$A:$K,4,FALSE),76.49)) -> 76.49 | F53: =IF(D53="","",IFERROR(VLOOKUP(D53,商品マスタ!$A:$K,8,FALSE),0)) -> 0 | G53: =SUM(O53,U53,AA53,AG53,AM53,AS53,AY53,BE53,BK53,BQ53,BW53,CC53) -> 0 | H53: =SUM(P53,V53,AB53,AH53,AN53,AT53,AZ53,BF53,BL53,BR53,BX53,CD53) -> 0 | I53: =SUM(Q53,W53,AC53,AI53,AO53,AU53,BA53,BG53,BM53,BS53,BY53,CE53) -> 0 | J53: =SUM(R53,X53,AD53,AJ53,AP53,AV53,BB53,BH53,BN53,BT53,BZ53,CF53) -> 0 | K53: =SUM(S53,Y53,AE53,AK53,AQ53,AW53,BC53,BI53,BO53,BU53,CA53,CG53) -> 0 | L53: =SUM(T53,Z53,AF53,AL53,AR53,AX53,BD53,BJ53,BP53,BV53,CB53,CH53) -> 0 | M53: =IFERROR(K53/CI53,"") | N53: =IFERROR(L53/CJ53,"") | P53: =IF(O53="","",O53*$E53) | Q53: =IF(O53="","",O53*$F53) | S53: =IF(R53="","",R53*$E53) | T53: =IF(R53="","",R53*$F53) | V53: =IF(U53="","",U53*$E53) | W53: =IF(U53="","",U53*$F53) | Y53: =IF(X53="","",X53*$E53) | Z53: =IF(X53="","",X53*$F53) | AB53: =IF(AA53="","",AA53*$E53) | AC53: =IF(AA53="","",AA53*$F53) | AE53: =IF(AD53="","",AD53*$E53) | AF53: =IF(AD53="","",AD53*$F53) | AH53: =IF(AG53="","",AG53*$E53) | AI53: =IF(AG53="","",AG53*$F53) | AK53: =IF(AJ53="","",AJ53*$E53) | AL53: =IF(AJ53="","",AJ53*$F53) | AN53: =IF(AM53="","",AM53*$E53) | AO53: =IF(AM53="","",AM53*$F53) | AQ53: =IF(AP53="","",AP53*$E53) | AR53: =IF(AP53="","",AP53*$F53) | AT53: =IF(AS53="","",AS53*$E53) | AU53: =IF(AS53="","",AS53*$F53) | AW53: =IF(AV53="","",AV53*$E53) | AX53: =IF(AV53="","",AV53*$F53) | AZ53: =IF(AY53="","",AY53*$E53) | BA53: =IF(AY53="","",AY53*$F53) | BC53: =IF(BB53="","",BB53*$E53) | BD53: =IF(BB53="","",BB53*$F53) | BF53: =IF(BE53="","",BE53*$E53) | BG53: =IF(BE53="","",BE53*$F53) | BI53: =IF(BH53="","",BH53*$E53) | BJ53: =IF(BH53="","",BH53*$F53) | BL53: =IF(BK53="","",BK53*$E53) | BM53: =IF(BK53="","",BK53*$F53) | BO53: =IF(BN53="","",BN53*$E53) | BP53: =IF(BN53="","",BN53*$F53) | BR53: =IF(BQ53="","",BQ53*$E53) | BS53: =IF(BQ53="","",BQ53*$F53) | BU53: =IF(BT53="","",BT53*$E53) | BV53: =IF(BT53="","",BT53*$F53) | BX53: =IF(BW53="","",BW53*$E53) | BY53: =IF(BW53="","",BW53*$F53) | CA53: =IF(BZ53="","",BZ53*$E53) | CB53: =IF(BZ53="","",BZ53*$F53) | CD53: =IF(CC53="","",CC53*$E53) | CE53: =IF(CC53="","",CC53*$F53) | CG53: =IF(CF53="","",CF53*$E53) | CH53: =IF(CF53="","",CF53*$F53) | CI53: =IF(R53>0,P53,0) + IF(X53>0,V53,0) + IF(AD53>0,AB53,0) + IF(AJ53>0,AH53,0) + IF(AP53>0,AN53,0) + IF(AV53>0,AT53,0) + IF(BB53>0,AZ53,0) + IF(BH53>0,BF53,0) + IF(BN53>0,BL53,0) + IF(BT53>0,BR53,0) + IF(BZ53>0,BX53,0) + IF(CF53>0,CD53,0) -> 0 | CJ53: =IF(R53>0,Q53,0) + IF(X53>0,W53,0) + IF(AD53>0,AC53,0) + IF(AJ53>0,AI53,0) + IF(AP53>0,AO53,0) + IF(AV53>0,AU53,0) + IF(BB53>0,BA53,0) + IF(BH53>0,BG53,0) + IF(BN53>0,BM53,0) + IF(BT53>0,BS53,0) + IF(BZ53>0,BY53,0) + IF(CF53>0,CE53,0) -> 0
A54: 松原 | B54: =IF(D54="","",IFERROR(VLOOKUP(D54,商品マスタ!$A:$K,2,FALSE),"その他")) -> その他 | C54: 日本ﾄﾞｱｰﾁｴｯｸ製造 | D54: プランジャー・スプリング | E54: =IF(D54="","",IFERROR(VLOOKUP(D54,商品マスタ!$A:$K,4,FALSE),6.55)) -> 6.55 | F54: =IF(D54="","",IFERROR(VLOOKUP(D54,商品マスタ!$A:$K,8,FALSE),0.599999999999999)) -> 0.6 | G54: =SUM(O54,U54,AA54,AG54,AM54,AS54,AY54,BE54,BK54,BQ54,BW54,CC54) -> 0 | H54: =SUM(P54,V54,AB54,AH54,AN54,AT54,AZ54,BF54,BL54,BR54,BX54,CD54) -> 0 | I54: =SUM(Q54,W54,AC54,AI54,AO54,AU54,BA54,BG54,BM54,BS54,BY54,CE54) -> 0 | J54: =SUM(R54,X54,AD54,AJ54,AP54,AV54,BB54,BH54,BN54,BT54,BZ54,CF54) -> 0 | K54: =SUM(S54,Y54,AE54,AK54,AQ54,AW54,BC54,BI54,BO54,BU54,CA54,CG54) -> 0 | L54: =SUM(T54,Z54,AF54,AL54,AR54,AX54,BD54,BJ54,BP54,BV54,CB54,CH54) -> 0 | M54: =IFERROR(K54/CI54,"") | N54: =IFERROR(L54/CJ54,"") | P54: =IF(O54="","",O54*$E54) | Q54: =IF(O54="","",O54*$F54) | S54: =IF(R54="","",R54*$E54) | T54: =IF(R54="","",R54*$F54) | V54: =IF(U54="","",U54*$E54) | W54: =IF(U54="","",U54*$F54) | Y54: =IF(X54="","",X54*$E54) | Z54: =IF(X54="","",X54*$F54) | AB54: =IF(AA54="","",AA54*$E54) | AC54: =IF(AA54="","",AA54*$F54) | AE54: =IF(AD54="","",AD54*$E54) | AF54: =IF(AD54="","",AD54*$F54) | AH54: =IF(AG54="","",AG54*$E54) | AI54: =IF(AG54="","",AG54*$F54) | AK54: =IF(AJ54="","",AJ54*$E54) | AL54: =IF(AJ54="","",AJ54*$F54) | AN54: =IF(AM54="","",AM54*$E54) | AO54: =IF(AM54="","",AM54*$F54) | AQ54: =IF(AP54="","",AP54*$E54) | AR54: =IF(AP54="","",AP54*$F54) | AT54: =IF(AS54="","",AS54*$E54) | AU54: =IF(AS54="","",AS54*$F54) | AW54: =IF(AV54="","",AV54*$E54) | AX54: =IF(AV54="","",AV54*$F54) | AZ54: =IF(AY54="","",AY54*$E54) | BA54: =IF(AY54="","",AY54*$F54) | BC54: =IF(BB54="","",BB54*$E54) | BD54: =IF(BB54="","",BB54*$F54) | BF54: =IF(BE54="","",BE54*$E54) | BG54: =IF(BE54="","",BE54*$F54) | BI54: =IF(BH54="","",BH54*$E54) | BJ54: =IF(BH54="","",BH54*$F54) | BL54: =IF(BK54="","",BK54*$E54) | BM54: =IF(BK54="","",BK54*$F54) | BO54: =IF(BN54="","",BN54*$E54) | BP54: =IF(BN54="","",BN54*$F54) | BR54: =IF(BQ54="","",BQ54*$E54) | BS54: =IF(BQ54="","",BQ54*$F54) | BU54: =IF(BT54="","",BT54*$E54) | BV54: =IF(BT54="","",BT54*$F54) | BX54: =IF(BW54="","",BW54*$E54) | BY54: =IF(BW54="","",BW54*$F54) | CA54: =IF(BZ54="","",BZ54*$E54) | CB54: =IF(BZ54="","",BZ54*$F54) | CD54: =IF(CC54="","",CC54*$E54) | CE54: =IF(CC54="","",CC54*$F54) | CG54: =IF(CF54="","",CF54*$E54) | CH54: =IF(CF54="","",CF54*$F54) | CI54: =IF(R54>0,P54,0) + IF(X54>0,V54,0) + IF(AD54>0,AB54,0) + IF(AJ54>0,AH54,0) + IF(AP54>0,AN54,0) + IF(AV54>0,AT54,0) + IF(BB54>0,AZ54,0) + IF(BH54>0,BF54,0) + IF(BN54>0,BL54,0) + IF(BT54>0,BR54,0) + IF(BZ54>0,BX54,0) + IF(CF54>0,CD54,0) -> 0 | CJ54: =IF(R54>0,Q54,0) + IF(X54>0,W54,0) + IF(AD54>0,AC54,0) + IF(AJ54>0,AI54,0) + IF(AP54>0,AO54,0) + IF(AV54>0,AU54,0) + IF(BB54>0,BA54,0) + IF(BH54>0,BG54,0) + IF(BN54>0,BM54,0) + IF(BT54>0,BS54,0) + IF(BZ54>0,BY54,0) + IF(CF54>0,CE54,0) -> 0
A55: 松原 | B55: =IF(D55="","",IFERROR(VLOOKUP(D55,商品マスタ!$A:$K,2,FALSE),"その他")) -> その他 | C55: 楠田金属 | D55: その他 | E55: =IF(D55="","",IFERROR(VLOOKUP(D55,商品マスタ!$A:$K,4,FALSE),0)) -> 0 | F55: =IF(D55="","",IFERROR(VLOOKUP(D55,商品マスタ!$A:$K,8,FALSE),0)) -> 0 | G55: =SUM(O55,U55,AA55,AG55,AM55,AS55,AY55,BE55,BK55,BQ55,BW55,CC55) -> 0 | H55: =SUM(P55,V55,AB55,AH55,AN55,AT55,AZ55,BF55,BL55,BR55,BX55,CD55) -> 0 | I55: =SUM(Q55,W55,AC55,AI55,AO55,AU55,BA55,BG55,BM55,BS55,BY55,CE55) -> 0 | J55: =SUM(R55,X55,AD55,AJ55,AP55,AV55,BB55,BH55,BN55,BT55,BZ55,CF55) -> 0 | K55: =SUM(S55,Y55,AE55,AK55,AQ55,AW55,BC55,BI55,BO55,BU55,CA55,CG55) -> 0 | L55: =SUM(T55,Z55,AF55,AL55,AR55,AX55,BD55,BJ55,BP55,BV55,CB55,CH55) -> 0 | M55: =IFERROR(K55/CI55,"") | N55: =IFERROR(L55/CJ55,"") | P55: =IF(O55="","",O55*$E55) | Q55: =IF(O55="","",O55*$F55) | S55: =IF(R55="","",R55*$E55) | T55: =IF(R55="","",R55*$F55) | V55: =IF(U55="","",U55*$E55) | W55: =IF(U55="","",U55*$F55) | Y55: =IF(X55="","",X55*$E55) | Z55: =IF(X55="","",X55*$F55) | AB55: =IF(AA55="","",AA55*$E55) | AC55: =IF(AA55="","",AA55*$F55) | AE55: =IF(AD55="","",AD55*$E55) | AF55: =IF(AD55="","",AD55*$F55) | AH55: =IF(AG55="","",AG55*$E55) | AI55: =IF(AG55="","",AG55*$F55) | AK55: =IF(AJ55="","",AJ55*$E55) | AL55: =IF(AJ55="","",AJ55*$F55) | AN55: =IF(AM55="","",AM55*$E55) | AO55: =IF(AM55="","",AM55*$F55) | AQ55: =IF(AP55="","",AP55*$E55) | AR55: =IF(AP55="","",AP55*$F55) | AT55: =IF(AS55="","",AS55*$E55) | AU55: =IF(AS55="","",AS55*$F55) | AW55: =IF(AV55="","",AV55*$E55) | AX55: =IF(AV55="","",AV55*$F55) | AZ55: =IF(AY55="","",AY55*$E55) | BA55: =IF(AY55="","",AY55*$F55) | BC55: =IF(BB55="","",BB55*$E55) | BD55: =IF(BB55="","",BB55*$F55) | BF55: =IF(BE55="","",BE55*$E55) | BG55: =IF(BE55="","",BE55*$F55) | BI55: =IF(BH55="","",BH55*$E55) | BJ55: =IF(BH55="","",BH55*$F55) | BL55: =IF(BK55="","",BK55*$E55) | BM55: =IF(BK55="","",BK55*$F55) | BO55: =IF(BN55="","",BN55*$E55) | BP55: =IF(BN55="","",BN55*$F55) | BR55: =IF(BQ55="","",BQ55*$E55) | BS55: =IF(BQ55="","",BQ55*$F55) | BU55: =IF(BT55="","",BT55*$E55) | BV55: =IF(BT55="","",BT55*$F55) | BX55: =IF(BW55="","",BW55*$E55) | BY55: =IF(BW55="","",BW55*$F55) | CA55: =IF(BZ55="","",BZ55*$E55) | CB55: =IF(BZ55="","",BZ55*$F55) | CD55: =IF(CC55="","",CC55*$E55) | CE55: =IF(CC55="","",CC55*$F55) | CG55: =IF(CF55="","",CF55*$E55) | CH55: =IF(CF55="","",CF55*$F55) | CI55: =IF(R55>0,P55,0) + IF(X55>0,V55,0) + IF(AD55>0,AB55,0) + IF(AJ55>0,AH55,0) + IF(AP55>0,AN55,0) + IF(AV55>0,AT55,0) + IF(BB55>0,AZ55,0) + IF(BH55>0,BF55,0) + IF(BN55>0,BL55,0) + IF(BT55>0,BR55,0) + IF(BZ55>0,BX55,0) + IF(CF55>0,CD55,0) -> 0 | CJ55: =IF(R55>0,Q55,0) + IF(X55>0,W55,0) + IF(AD55>0,AC55,0) + IF(AJ55>0,AI55,0) + IF(AP55>0,AO55,0) + IF(AV55>0,AU55,0) + IF(BB55>0,BA55,0) + IF(BH55>0,BG55,0) + IF(BN55>0,BM55,0) + IF(BT55>0,BS55,0) + IF(BZ55>0,BY55,0) + IF(CF55>0,CE55,0) -> 0
A56: 松原 | B56: =IF(D56="","",IFERROR(VLOOKUP(D56,商品マスタ!$A:$K,2,FALSE),"その他")) -> その他 | C56: 西谷精巧舎 | D56: その他 | E56: =IF(D56="","",IFERROR(VLOOKUP(D56,商品マスタ!$A:$K,4,FALSE),0)) -> 0 | F56: =IF(D56="","",IFERROR(VLOOKUP(D56,商品マスタ!$A:$K,8,FALSE),0)) -> 0 | G56: =SUM(O56,U56,AA56,AG56,AM56,AS56,AY56,BE56,BK56,BQ56,BW56,CC56) -> 0 | H56: =SUM(P56,V56,AB56,AH56,AN56,AT56,AZ56,BF56,BL56,BR56,BX56,CD56) -> 0 | I56: =SUM(Q56,W56,AC56,AI56,AO56,AU56,BA56,BG56,BM56,BS56,BY56,CE56) -> 0 | J56: =SUM(R56,X56,AD56,AJ56,AP56,AV56,BB56,BH56,BN56,BT56,BZ56,CF56) -> 0 | K56: =SUM(S56,Y56,AE56,AK56,AQ56,AW56,BC56,BI56,BO56,BU56,CA56,CG56) -> 0 | L56: =SUM(T56,Z56,AF56,AL56,AR56,AX56,BD56,BJ56,BP56,BV56,CB56,CH56) -> 0 | M56: =IFERROR(K56/CI56,"") | N56: =IFERROR(L56/CJ56,"") | P56: =IF(O56="","",O56*$E56) | Q56: =IF(O56="","",O56*$F56) | S56: =IF(R56="","",R56*$E56) | T56: =IF(R56="","",R56*$F56) | V56: =IF(U56="","",U56*$E56) | W56: =IF(U56="","",U56*$F56) | Y56: =IF(X56="","",X56*$E56) | Z56: =IF(X56="","",X56*$F56) | AB56: =IF(AA56="","",AA56*$E56) | AC56: =IF(AA56="","",AA56*$F56) | AE56: =IF(AD56="","",AD56*$E56) | AF56: =IF(AD56="","",AD56*$F56) | AH56: =IF(AG56="","",AG56*$E56) | AI56: =IF(AG56="","",AG56*$F56) | AK56: =IF(AJ56="","",AJ56*$E56) | AL56: =IF(AJ56="","",AJ56*$F56) | AN56: =IF(AM56="","",AM56*$E56) | AO56: =IF(AM56="","",AM56*$F56) | AQ56: =IF(AP56="","",AP56*$E56) | AR56: =IF(AP56="","",AP56*$F56) | AT56: =IF(AS56="","",AS56*$E56) | AU56: =IF(AS56="","",AS56*$F56) | AW56: =IF(AV56="","",AV56*$E56) | AX56: =IF(AV56="","",AV56*$F56) | AZ56: =IF(AY56="","",AY56*$E56) | BA56: =IF(AY56="","",AY56*$F56) | BC56: =IF(BB56="","",BB56*$E56) | BD56: =IF(BB56="","",BB56*$F56) | BF56: =IF(BE56="","",BE56*$E56) | BG56: =IF(BE56="","",BE56*$F56) | BI56: =IF(BH56="","",BH56*$E56) | BJ56: =IF(BH56="","",BH56*$F56) | BL56: =IF(BK56="","",BK56*$E56) | BM56: =IF(BK56="","",BK56*$F56) | BO56: =IF(BN56="","",BN56*$E56) | BP56: =IF(BN56="","",BN56*$F56) | BR56: =IF(BQ56="","",BQ56*$E56) | BS56: =IF(BQ56="","",BQ56*$F56) | BU56: =IF(BT56="","",BT56*$E56) | BV56: =IF(BT56="","",BT56*$F56) | BX56: =IF(BW56="","",BW56*$E56) | BY56: =IF(BW56="","",BW56*$F56) | CA56: =IF(BZ56="","",BZ56*$E56) | CB56: =IF(BZ56="","",BZ56*$F56) | CD56: =IF(CC56="","",CC56*$E56) | CE56: =IF(CC56="","",CC56*$F56) | CG56: =IF(CF56="","",CF56*$E56) | CH56: =IF(CF56="","",CF56*$F56) | CI56: =IF(R56>0,P56,0) + IF(X56>0,V56,0) + IF(AD56>0,AB56,0) + IF(AJ56>0,AH56,0) + IF(AP56>0,AN56,0) + IF(AV56>0,AT56,0) + IF(BB56>0,AZ56,0) + IF(BH56>0,BF56,0) + IF(BN56>0,BL56,0) + IF(BT56>0,BR56,0) + IF(BZ56>0,BX56,0) + IF(CF56>0,CD56,0) -> 0 | CJ56: =IF(R56>0,Q56,0) + IF(X56>0,W56,0) + IF(AD56>0,AC56,0) + IF(AJ56>0,AI56,0) + IF(AP56>0,AO56,0) + IF(AV56>0,AU56,0) + IF(BB56>0,BA56,0) + IF(BH56>0,BG56,0) + IF(BN56>0,BM56,0) + IF(BT56>0,BS56,0) + IF(BZ56>0,BY56,0) + IF(CF56>0,CE56,0) -> 0

Sheet 取引先別年間計画
A1: 三幸プロダクツ株式会社 42期 取引先別年間計画
A2: 参考期間: 2025年4月〜2026年3月（41期実績） ／ 計画期間: 42期 2026年6月〜2027年5月 ※42期実績は月別計画実績シートの実績入力から自動集計
A3: 工場/グループ/取引先 | D3: 41期 実績 | G3: 42期 計画 | J3: 42期 実績（自動集計） | M3: 達成率 | O3: 計画比差異
A4: 工場 | B4: グループ | C4: 取引先 | D4: 41期実績 数量(個) | E4: 41期実績 売上(円) | F4: 41期実績 粗利(円) | G4: 42期計画 数量(個) | H4: 42期計画 売上(円) | I4: 42期計画 粗利(円) | J4: 42期実績 数量(個) | K4: 42期実績 売上(円) | L4: 42期実績 粗利(円) | M4: 達成率 売上 | N4: 達成率 粗利 | O4: 差異額 (実績-計画) | P4: 差異率
A5: 東大阪 | B5: 昭和 | C5: 昭和プロダクツ | D5: 22371847 | E5: 218752361 | F5: 19687712 | G5: 22371847 | H5: 0 | I5: 0 | J5: 0 | K5: 0 | L5: 0 | O5: 0
A6: 東大阪 | B6: 昭和 | C6: 昭和化成工業 | D6: 30000 | E6: 352110 | F6: 31689.9 | G6: 30000 | H6: 0 | I6: 0 | J6: 0 | K6: 0 | L6: 0 | O6: 0
A7: 東大阪 | B7: 昭和 | C7: 昭和丸筒 | D7: 8005 | E7: 116248 | F7: 10462.32 | G7: 8005 | H7: 0 | I7: 0 | J7: 0 | K7: 0 | L7: 0 | O7: 0
A8: 東大阪 | B8: 昭和以外 | C8: 晶立工作所 | D8: 813420 | E8: 16031970 | F8: 1442877.3 | G8: 813420 | H8: 0 | I8: 0 | J8: 0 | K8: 0 | L8: 0 | O8: 0
A9: 東大阪 | B9: 昭和以外 | C9: 三協丸筒 | D9: 151440 | E9: 1235647 | F9: 111208.23 | G9: 151440 | H9: 0 | I9: 0 | J9: 0 | K9: 0 | L9: 0 | O9: 0
A10: 東大阪 | B10: 昭和以外 | C10: 製作工房タケダ | D10: 100780 | E10: 364723 | F10: 32825.07 | G10: 100780 | H10: 0 | I10: 0 | J10: 0 | K10: 0 | L10: 0 | O10: 0
A11: 東大阪 | B11: 昭和以外 | C11: 向陽エンジニアリング | D11: 11200 | E11: 345574 | F11: 31101.66 | G11: 11200 | H11: 0 | I11: 0 | J11: 0 | K11: 0 | L11: 0 | O11: 0
A12: 東大阪 | B12: 昭和以外 | C12: イワサキ | D12: 2000 | E12: 53295 | F12: 4796.55 | G12: 2000 | H12: 0 | I12: 0 | J12: 0 | K12: 0 | L12: 0 | O12: 0
A13: 東大阪 | B13: 缶バッジ | C13: ダイキ | D13: 27988493 | E13: 110607247 | F13: 9954652.2 | G13: 0 | H13: 0 | I13: 0 | J13: 0 | K13: 0 | L13: 0 | O13: 0
A14: 東大阪 | B14: 缶バッジ | C14: ベック | D14: 18940001 | E14: 68095720 | F14: 6128614.8 | G14: 18940001 | H14: 0 | I14: 0 | J14: 0 | K14: 0 | L14: 0 | O14: 0
A15: 東大阪 | B15: 缶バッジ | C15: ノート | D15: 4523500 | E15: 17880902 | F15: 1609281.2 | G15: 4523500 | H15: 0 | I15: 0 | J15: 0 | K15: 0 | L15: 0 | O15: 0
A16: 東大阪 | B16: 缶バッジ | C16: ノート | D16: 3779865 | E16: 17375750 | F16: 1563817.5 | G16: 3779865 | H16: 0 | I16: 0 | J16: 0 | K16: 0 | L16: 0 | O16: 0
... A55: 松原 | B55: その他 | C55: 西谷精巧舎 | D55: 8153 | E55: 122981 | F55: 11068.29 | G55: 8153 | H55: 0 | I55: 0 | J55: 0 | K55: 0 | L55: 0 | O55: 0
A56: 松原 | B56: その他 | C56: 京都プレス工業 | D56: 1474 | E56: 85521 | F56: =IFERROR(E56*0.09,0) -> 7696.89 | G56: 1474 | H56: 0 | I56: =IFERROR(H56*0.09,0) -> 0 | J56: =SUMIFS(月別計画実績!$J:$J,月別計画実績!$C:$C,C56) -> 0 | K56: =SUMIFS(月別計画実績!$K:$K,月別計画実績!$C:$C,C56) -> 0 | L56: =SUMIFS(月別計画実績!$L:$L,月別計画実績!$C:$C,C56) -> 0 | M56: =IFERROR(K56/H56,"") | N56: =IFERROR(L56/I56,"") | O56: =K56-H56 -> 0 | P56: =IFERROR(O56/H56,"")
A58: 【合計】 | D58: =SUM(D5:D57) -> 104277392 | E58: =SUM(E5:E57) -> 641315227 | F58: =SUM(F5:F57) -> 57718370 | G58: =SUM(G5:G57) -> 76288899 | H58: =SUM(H5:H57) -> 0 | I58: =SUM(I5:I57) -> 0 | J58: =SUM(J5:J57) -> 0 | K58: =SUM(K5:K57) -> 0 | L58: =SUM(L5:L57) -> 0 | O58: =SUM(O5:O57) -> 0
A60: ↓ 新規取引先はここから追記（A列=工場、B列=グループ、C列=取引先名）
